Workbook

Sheet Data Summary
A1: Bulletin Reports Summary for Apr-19
A2: Report Name | B2: Data Status
A3: Table 1: SEBI Registered Market Intermediaries/Institutions | B3: Data Available
A4: Table 2: Company-Wise Capital Raised through Public and Rights Issues (Equity) | B4: Data Available
A5: Table 3: Open Offers under SEBI Takeover Code closed | B5: Data Available
A6: Table 4: Substantial Acquisition of Shares and Takeovers | B6: Data Available
A7: Table 5: Capital Raised from the Primary Market through though Public and Rights Issues | B7: Data Available
A8: Table 6: Issues Listed on SME Platform | B8: Data Available
A9: Table 7: Industry-wise Classification of Capital Raised through Public and Rights Issues | B9: Data Available
A10: Table 8: Sector-wise and Region-wise Distribution of Capital Mobilised through Public and Rights Issues | B10: Data Available
A11: Table 9: Size-wise Classification of Capital Raised through Public and Rights Issues | B11: Data Available
A12: Table 10: Capital Raised by Listed Companies from the Primary Market through QIPs | B12: Data Available
A13: Table 11: Preferential Allotments Listed at BSE and NSE | B13: Data Available
... A76: Table 74: Macro Economic Indicators | B76: Data Available

Sheet 1
A1: Table 1: SEBI Registered Market Intermediaries/Institutions
A2: Market Intermediaries | B2: 2018-19 | C2: 2019-20$
A3: Stock Exchanges (Cash Segment) | B3: 5 | C3: 5
A4: Stock Exchanges (Equity Derivatives Segment) | B4: 3 | C4: 3
A5: Stock Exchanges (Currency Derivatives Segment) | B5: 3 | C5: 3
A6: Stock Exchanges (Commodity Derivatives Segment) | B6: 5 | C6: 5
A7: Brokers (Cash Segment) | B7: 2315 | C7: 2282
A8: Brokers (Equity Derivatives Segment) | B8: 2435 | C8: 2435
A9: Brokers (Currency Derivatives Segment) | B9: 2110 | C9: 2092
A10: Brokers (Debt Segment) | B10: 173 | C10: 173
A11: Brokers (Commodity Derivatives Segment) | B11: 1708 | C11: 1703
A12: Corporate Brokers(Cash Segment) | B12: 2004 | C12: 1975
A13: Foreign Portfolio Investors (FPIs) | B13: 9390 | C13: 9385
A14: Custodians | B14: 20 | C14: 20
... A37: STP Service Providers | B37: 2 | C37: 2
A38: Notes:
A39: $ indicates as on April 30,2019
A40: Source: SEBI, NSDL.

Sheet 2
A1: Table 2: Company-Wise Capital Raised through Public and Rights Issues (Equity)
A2: Sl.No. | B2: Name of the Issuer/Company | C2: Date of Opening | D2: Type of Issue | E2: Type of Instrument | F2: No. of Shares Issued | G2: Face Value (`) | H2: Premium Value (`) | I2: Issue Price (`) | J2: Size of Issue (` Crore)
A3: 1 | B3: Vodafone Idea Limited | C3: 43579 | D3: Rights | E3: Equity | F3: 19999830911 | G3: 10 | H3: 2.5 | I3: 12.5 | J3: 24999.788
A4: 2 | B4: Polycab India Limited | C4: 43564 | D4: IPO | E4: Equity | F4: 25022067 | G4: 10 | H4: 528 | I4: 538 | J4: 1345.26
A5: 3 | B5: Metropolis Healthcare Limited | C5: 43560 | D5: IPO | E5: Equity | F5: 13685095 | G5: 2 | H5: 878 | I5: 880 | J5: 1204.29
A6: 4 | B6: Rail Vikas Nigam Limited | C6: 43558 | D6: IPO | E6: Equity | F6: 253457280 | G6: 10 | H6: 9 | I6: 19 | J6: 477.11
A7: 5 | B7: Jinaam's Dress Limited | C7: 43570 | D7: SME IPO | E7: Equity | F7: 7200000 | G7: 10 | H7: 49 | I7: 59 | J7: 42.48
A8: 6 | B8: Bharat Gears Ltd | C8: 43585 | D8: Rights | E8: Equity | F8: 1163262 | G8: 10 | H8: 95 | I8: 105 | J8: 12.21
A9: 7 | B9: KHFM Hospitality and Facility Management Serv Ltd | C9: 43551 | D9: SME IPO | E9: Equity | F9: 2949000 | G9: 10 | H9: 26 | I9: 36 | J9: 10.62
A10: 8 | B10: G.K.P. Printing & Packaging Limited | C10: 43581 | D10: SME IPO | E10: Equity | F10: 2056000 | G10: 10 | H10: 22 | I10: 32 | J10: 6.58
A11: 9 | B11: V R Films & Studios Limited | C11: 43573 | D11: SME IPO | E11: Equity | F11: 372000 | G11: 10 | H11: 51 | I11: 61 | J11: 2.27
A12: 10 | B12: Neogen Chemicals Limited | C12: 43581 | D12: IPO | E12: Equity | F12: 6155813 | G12: 10 | H12: 205 | I12: 215 | J12: 132.35
A13: Note: All the issues are compiled from the Prospectus of Issuer Companies filed with SEBI.
A14: Source: SEBI.

Sheet 3
A1: Table 3: Open Offers under SEBI Takeover Code closed during Mar-19
A2: Sl.No | B2: Target Company | C2: Acquirer | D2: Offer Opening Date | E2: Offer Closing Date | F2: Offer Size | H2: Offer Price (`) per share | I2: Offer Size (` Crore)
F3: No. of Shares | G3: Percent of Equity Capital
A4: 1 | B4: HATHWAY BHAWANI CABLETEL AND DATACOM LIMITED | C4: JIO CONTENT DISTRIBUTION HOLDINGS PVT LTD, JIO INTERNET DISTRIBUTION HOLDINGS PVT. LTD., JIO CABLE A | D4: 43546 | E4: 43559 | F4: 2106000 | G4: 26 | H4: 2.46 | I4: 0.52
A5: Source: SEBI.

Sheet 4
A1: Table 4: Substantial Acquisition of Shares and Takeovers
A2: Year / Month | B2: Open Offers
B3: Objectives | H3: Total
B4: Change in Control of Management | D4: Consolidation of Holdings | F4: Substantial Acquisition | H4: No. of Offers | I4: Amount (` crore)
B5: No. of Offers | C5: Amount (` crore) | D5: No. of Offers | E5: Amount (` crore) | F5: No. of Offers | G5: Amount (` crore)
A6: 2018-19 | B6: 63 | C6: 23015.99 | D6: 4 | E6: 4636.33 | F6: 4 | G6: 941.23 | H6: 71 | I6: 28593.55
A7: 2019-20$ | B7: 3 | C7: 24.55 | D7: 1 | E7: 31.82 | F7: 0 | G7: 0 | H7: 4 | I7: 56.37
A8: Apr-19 | B8: 3 | C8: 24.55 | D8: 1 | E8: 31.82 | F8: 0 | G8: 0 | H8: 4 | I8: 56.37
A9: $ indicates as on April 30, 2019
A10: Source: SEBI.

Sheet 5
A1: Table 5: Capital Raised from the Primary Market through though Public and Rights Issues
A2: Year / Month | B2: Total | D2: Category-Wise | H2: Issue-Type | L2: Instrument-Wise
D3: Public | F3: Rights | H3: Listed | J3: IPOs | L3: Equities | P3: CCPS/FCDs* | R3: Debt
L4: At Par | N4: At Premium
B5: No. of issues | C5: Amount (` crore) | D5: No. of issues | E5: Amount (` crore) | F5: No. of issues | G5: Amount (` crore) | H5: No. of issues | I5: Amount (` crore) | J5: No. of issues | K5: Amount (` crore) | L5: No. of issues | M5: Amount (` crore) | N5: No. of issues | O5: Amount (` crore) | P5: No. of issues | Q5: Amount (` crore) | R5: No. of issues | S5: Amount (` crore)
A6: 2018-19 | B6: 158 | C6: 54914.58 | D6: 148 | E6: 52765.93 | F6: 10 | G6: 2148.65 | H6: 35 | I6: 38828.04 | J6: 123 | K6: 16086.54 | L6: 6 | M6: 512.57 | N6: 127 | O6: 17722.62 | P6: 0 | Q6: 0 | R6: 25 | S6: 36679.39
A7: 2019-20$ | B7: 12 | C7: 29349.68 | D7: 10 | E7: 4337.68 | F7: 2 | G7: 25012 | H7: 4 | I7: 26128.72 | J7: 8 | K7: 3220.96 | L7: 0 | M7: 0 | N7: 10 | O7: 28232.96 | P7: 0 | Q7: 0 | R7: 2 | S7: 1116.72
A8: Apr-19 | B8: 12 | C8: 29349.68 | D8: 10 | E8: 4337.68 | F8: 2 | G8: 25012 | H8: 4 | I8: 26128.72 | J8: 8 | K8: 3220.96 | L8: 0 | M8: 0 | N8: 10 | O8: 28232.96 | P8: 0 | Q8: 0 | R8: 2 | S8: 1116.72
A9: Notes: 1. The total provides category-wise total of any of the three sub-categories viz. public plus rights or issuer-type(listed plus IPOs) or instrument-wise(equities plus CCPS/FCDs plus debt). 2. Amount for public debt issue for last two months is provisional and may get updated 3. All the Issues are compiled from the Prospectus. of Issuer Companies filed with SEBI. 4. * CCPS: Compulsory Convertible Preference Shares, FCDs: Fully Convertible Debentures.
A10: 5. Equity public issues also includes issues listed on SME platform.
A11: 6. Since April 2018, both the equity and debt issues are categorised based on their respective closing dates. Prior to April 2018, the equity issues were classified based on opening date of the issue, while debt issues were classfied based on closing date of the issue.
A12: $ indicates as on April 30,2019
A13: Source: SEBI.

Sheet 6
A1: Table 6: Issues Listed on SME Platform
A2: Year/ Month | B2: Total
B3: No. of issue | C3: Amount (`crore)
A4: 2018-19 | B4: 110 | C4: 1844
A5: 2019-20$ | B5: 3 | C5: 51.3292
A6: Apr-19 | B6: 3 | C6: 51.3292
A7: $ indicates as on April 30,2019
A8: Source: SEBI

Sheet 7
A1: Table 7: Industry-wise Classification of Capital Raised through Public and Rights Issues
A2: Industry | B2: 2019-20$ | D2: Apr-19
B3: No. of issues | C3: Amount (`crore) | D3: No. of issues | E3: Amount (` crore)
A4: Airlines | B4: 0 | C4: 0 | D4: 0 | E4: 0
A5: Automobiles | B5: 1 | C5: 12.21 | D5: 1 | E5: 12.21
A6: Banks/FIs | B6: 0 | C6: 0 | D6: 0 | E6: 0
A7: Cement/ Constructions | B7: 0 | C7: 0 | D7: 0 | E7: 0
A8: Chemical | B8: 1 | C8: 132.35 | D8: 1 | E8: 132.35
A9: Consumer Services | B9: 0 | C9: 0 | D9: 0 | E9: 0
A10: Electronic Equipments/ Products | B10: 1 | C10: 1345.26 | D10: 1 | E10: 1345.26
A11: Engineering | B11: 1 | C11: 477.11 | D11: 1 | E11: 477.11
A12: Entertainment | B12: 1 | C12: 2.27 | D12: 1 | E12: 2.27
A13: Finance | B13: 2 | C13: 1116.72 | D13: 2 | E13: 1116.72
A14: Food processing | B14: 0 | C14: 0 | D14: 0 | E14: 0
A15: Healthcare | B15: 1 | C15: 1204.29 | D15: 1 | E15: 1204.29
... A27: Total | B27: 12 | C27: 29349.68 | D27: 12 | E27: 29349.68
A28: $ indicates as on April 30,2019
A29: Source: SEBI.

Sheet 8
A1: Table 8: Sector-wise and Region-wise Distribution of Capital Mobilised through Public and Rights Issues
A2: Year / Month | B2: Total | D2: Sector-wise | H2: Region-wise
D3: Private | F3: Public | H3: Northern | J3: Eastern | L3: Western | N3: Southern | P3: Central | R3: Foreign
B4: No. of Issue | C4: Amount (`Crores) | D4: No. of Issue | E4: Amount (` Crores) | F4: No. of Issue | G4: Amount (` Crores) | H4: No. of Issue | I4: Amount (` Crores) | J4: No. of Issue | K4: Amount (` Crores) | L4: No. of Issue | M4: Amount (` Crores) | N4: No. of Issue | O4: Amount (` Crores) | P4: No. of Issue | Q4: Amount (` Crores) | R4: No. of Issue | S4: Amount (` Crores)
A5: 2018-19 | B5: 158 | C5: 54916.58 | D5: 154 | E5: 53434.74 | F5: 4 | G5: 1481.84 | H5: 24 | I5: 3338.36 | J5: 8 | K5: 1155.2095 | L5: 85 | M5: 35717.24 | N5: 20 | O5: 12175.42 | P5: 4 | Q5: 115.7 | R5: 0 | S5: 0
A6: 2019-20$ | B6: 12 | C6: 29349.68 | D6: 11 | E6: 28872.57 | F6: 1 | G6: 477.11 | H6: 3 | I6: 1834.58 | J6: 0 | K6: 0 | L6: 8 | M6: 27398.38 | N6: 1 | O6: 116.72 | P6: 0 | Q6: 0 | R6: 0 | S6: 0
A7: Apr-19 | B7: 12 | C7: 29349.68 | D7: 11 | E7: 28872.57 | F7: 1 | G7: 477.11 | H7: 3 | I7: 1834.58 | J7: 0 | K7: 0 | L7: 8 | M7: 27398.38 | N7: 1 | O7: 116.72 | P7: 0 | Q7: 0 | R7: 0 | S7: 0
A8: $ indicates as on April 30,2019
A9: Source: SEBI.

Sheet 9
A1: Table 9: Size-wise Classification of Capital Raised through Public and Rights Issues
A2: Year / Month | B2: Total | D2: < 5 crore | F2: ≥ 5crore - < 10crore | H2: ≥ 10 crore - < 50 crore | J2: ≥ 50 crore - < 100 crore | L2: ≥ 100 crore
B3: No. of issue | C3: Amount (` crore) | D3: No. of issue | E3: Amount (` crore) | F3: No. of issue | G3: Amount (` crore) | H3: No. of issue | I3: Amount (` crore) | J3: No. of issue | K3: Amount (` crore) | L3: No. of issue | M3: Amount (` crore)
A4: 2018-19 | B4: 158 | C4: 54916.6 | D4: 20 | E4: 68.41 | F4: 29 | G4: 212.75 | H4: 61 | I4: 1355.19 | J4: 6 | K4: 437.52 | L4: 42 | M4: 52842.73
A5: 2019-20$ | B5: 12 | C5: 29349.68 | D5: 1 | E5: 2.27 | F5: 1 | G5: 6.58 | H5: 3 | I5: 65.31 | J5: 0 | K5: 0 | L5: 7 | M5: 29275.52
A6: Apr-19 | B6: 12 | C6: 29349.68 | D6: 1 | E6: 2.27 | F6: 1 | G6: 6.58 | H6: 3 | I6: 65.31 | J6: 0 | K6: 0 | L6: 7 | M6: 29275.52
A7: $ indicates as on April 30,2019
A8: Source: SEBI.

Sheet 10
A1: Table 10: Capital Raised by Listed Companies from the Primary Market through QIPs
A2: Year / Month | B2: Only BSE | D2: Only NSE | F2: Only MSEI | H2: Both NSE and BSE | J2: Total
B3: No. of issues | C3: Amount (` Crores) | D3: No. of issues | E3: Amount (` Crores) | F3: No. of issues | G3: Amount (` Crores) | H3: No. of issues | I3: Amount (` Crores) | J3: No. of issues | K3: Amount (` Crores)
A4: 2018-19 | B4: 1 | C4: 113.25139 | D4: 0 | E4: 0 | F4: 0 | G4: 0 | H4: 13 | I4: 8565.0668 | J4: 14 | K4: 8678.3182
A5: 2019-20$ | B5: 0 | C5: 0 | D5: 0 | E5: 0 | F5: 0 | G5: 0 | H5: 1 | I5: 3172.82 | J5: 1 | K5: 3172.82
A6: Apr-19 | B6: 0 | C6: 0 | D6: 0 | E6: 0 | F6: 0 | G6: 0 | H6: 1 | I6: 3172.82 | J6: 1 | K6: 3172.82
A7: Notes: 1. The above data includes both "no. of issues" and "Amount" raised on conversion of convertible securities issued on QIP basis. 2. 2017-18, Includes one issue of Institutional Placement Programme (Issue Size of Rs. 873.92 crore).
A8: $ indicates as on April 30,2019
A9: Source: BSE, NSE and MSEI.

Sheet 11
A1: Table 11: Preferential Allotments Listed at BSE and NSE
A2: Year/Month | B2: Only BSE | D2: Only NSE | F2: Only MSEI | H2: Both NSE and BSE | J2: Total
B3: No. of issues | C3: Amount (` Crores) | D3: No. of issues | E3: Amount (` Crores) | F3: No. of issues | G3: Amount (`Crores) | H3: No. of issues | I3: Amount ` Crores) | J3: No. of issues | K3: Amount (`Crores)
A4: 2018-19 | B4: 208 | C4: 10824.71 | D4: 20 | E4: 8032.005 | F4: 4 | G4: 23.59 | H4: 171 | I4: 191281.42 | J4: 403 | K4: 210161.72
A5: 2019-20$ | B5: 7 | C5: 21.53 | D5: 0 | E5: 0 | F5: 0 | G5: 0 | H5: 16 | I5: 35806.25 | J5: 23 | K5: 35827.78
A6: Apr-19 | B6: 7 | C6: 21.53 | D6: 0 | E6: 0 | F6: 0 | G6: 0 | H6: 16 | I6: 35806.25 | J6: 23 | K6: 35827.78
A7: $ indicates as on April 30,2019
A8: Source: BSE, NSE and MSEI.

Sheet 12
A1: Table 12: Private Placement of Corporate Debt Reported to BSE and NSE
A2: Year/Month | B2: Only BSE | D2: Only NSE | F2: Both NSE and BSE | H2: TOTAL
B3: No. of Issues | C3: Amount (`Crores) | D3: No. of Issues | E3: Amount (` Crores) | F3: No. of Issues | G3: Amount (` Crores) | H3: No. of Issues | I3: Amount (` Crores)
A4: 2018-19 | B4: 479 | C4: 177592.59 | D4: 1703 | E4: 247190.35 | F4: 176 | G4: 185274.02 | H4: 2358 | I4: 579424.55
A5: 2019-20$ | B5: 39 | C5: 26394.183 | D5: 174 | E5: 31434.83 | F5: 11 | G5: 12235.204 | H5: 224 | I5: 70064.217
A6: Apr-19 | B6: 39 | C6: 26394.183 | D6: 174 | E6: 31434.83 | F6: 11 | G6: 12235.204 | H6: 224 | I6: 70064.217
A7: $ indicates as on April 30, 2019
A8: Source: BSE and NSE

Sheet 13
A1: Table 13: Trading in the Corporate Debt Market
A2: Year / Month | B2: BSE | D2: NSE | F2: MSEI | H2: Total
B3: No. of Trades | C3: Traded Value (` crore) | D3: No. of Trades | E3: Traded Value (` crore) | F3: No. of Trades | G3: Traded Value (` crore) | H3: No. of Trades | I3: Traded Value (` crore)
A4: 2018-19 | B4: 43157 | C4: 631252.22 | D4: 60370 | E4: 1168407.7 | F4: 0 | G4: 0 | H4: 103527 | I4: 1799659.9
A5: 2019-20$ | B5: 3944 | C5: 53755.86 | D5: 5380 | E5: 90747.82 | F5: 0 | G5: 0 | H5: 9324 | I5: 144503.68
A6: Apr-19 | B6: 3944 | C6: 53755.86 | D6: 5380 | E6: 90747.82 | F6: 0 | G6: 0 | H6: 9324 | I6: 144503.68
A7: $ indicates as on April 30, 2019
A8: Source: BSE, NSE and MSEI.

Sheet 14
A1: Table 14: Ratings Assigned for Long-term Corporate Debt Securities (Maturity ≥ 1 year)
A2: Grade | B2: Investment Grade | J2: Non-Investment Grade | L2: Total
B3: Highest Safety (AAA) | D3: High Safety (AA) | F3: Adequate Safety (A) | H3: Moderate Safety (BBB)
A4: Period | B4: No. of issue | C4: Amount (`crore) | D4: No. of issue | E4: Amount (` crore) | F4: No. of issue | G4: Amount (` crore) | H4: No. of issue | I4: Amount (` crore) | J4: No. of issue | K4: Amount (` crore) | L4: No. of issue | M4: Amount (` crore)
A5: 2018-19 | B5: 279 | C5: 2080535.8 | D5: 400 | E5: 324988.84 | F5: 349 | G5: 104665.52 | H5: 241 | I5: 20878.506 | J5: 57 | K5: 12738.1 | L5: 1326 | M5: 2543806.7
A6: 2019-20$ | B6: 8 | C6: 105452 | D6: 4 | E6: 2850 | F6: 6 | G6: 1482.5 | H6: 1 | I6: 495 | J6: 7 | K6: 3072 | L6: 26 | M6: 113351.5
A7: Apr-19 | B7: 8 | C7: 105452 | D7: 4 | E7: 2850 | F7: 6 | G7: 1482.5 | H7: 1 | I7: 495 | J7: 7 | K7: 3072 | L7: 26 | M7: 113351.5
A8: $ indicates as on April 30,2019
A9: Source: Credit Rating Agencies.

Sheet 15
A1: Table 15: Review of Accepted Ratings of Corporate Debt Securities (Maturity ≥ 1 year)
A2: Grade | B2: Upgraded | D2: Downgraded | F2: Reaffirmed | H2: Rating Watch | J2: Withdrawn/ Suspended | L2: Total
A3: Period | B3: No. of issue | C3: Amount (`crore) | D3: No. of issue | E3: Amount (`crore) | F3: No. of issue | G3: Amount (`crore) | H3: No. of issue | I3: Amount (`crore) | J3: No. of issue | K3: Amount (`crore) | L3: No. of issue | M3: Amount (`crore)
A4: 2018-19 | B4: 711 | C4: 314241.22 | D4: 892 | E4: 913562.25 | F4: 5489 | G4: 12252045 | H4: 494 | I4: 1124407.7 | J4: 1101 | K4: 475759.98 | L4: 8687 | M4: 15079016
A5: 2019-20$ | B5: 4 | C5: 21200 | D5: 148 | E5: 186753.51 | F5: 62 | G5: 71602.33 | H5: 136 | I5: 226341.18 | J5: 29 | K5: 2545 | L5: 379 | M5: 508442.02
A6: Apr-19 | B6: 4 | C6: 21200 | D6: 148 | E6: 186753.51 | F6: 62 | G6: 71602.33 | H6: 136 | I6: 226341.18 | J6: 29 | K6: 2545 | L6: 379 | M6: 508442.02
A7: $ indicates as on April 30,2019
A8: Source: Credit Rating Agencies.

Sheet 16
A1: Table 16: Distribution of Turnover on Cash Segments of Stock Exchanges (`crore)
A2: Stock Exchanges | B2: 2018-19 | C2: 2019-20$ | D2: Apr-19
A3: BSE | B3: 775590.08 | C3: 55867.81 | D3: 55867.81
A4: MSEI | B4: 30.29325 | C4: 7.4556996 | D4: 7.4556996
A5: NSE | B5: 7949004.3 | C5: 640115.39 | D5: 640115.39
A6: $ indicates as on April 30, 2019
A7: Source: BSE, NSE and MSEI.

Sheet 17
A1: Table 17: Trends in Cash Segment of BSE
A2: Year / Month | B2: No. of Companies Listed | C2: No. of Companies Permitted* | D2: No. of companies traded | E2: No. of Trading Days | F2: No. of Trades (Lakh) | G2: Traded Quantity (Lakh) | H2: Turnover (` crore) | I2: Average Daily Turnover (` crore) | J2: Average Trade Size (`) | K2: Demat Securities Traded (Lakh) | L2: Demat Turnover (` crore) | M2: Market Capitalisation (` crore) | N2: S&P BSE Sensex
N3: High | O3: Low | P3: Close
A4: 2018-19 | B4: 5262 | C4: 36 | D4: 4086 | E4: 248 | F4: 3145.25 | G4: 518103.44 | H4: 775590.08 | I4: 3127.3794 | J4: 24659.092 | K4: 518103.44 | L4: 775589.97 | M4: 15108711 | N4: 38989.65 | O4: 32972.56 | P4: 38672.91
A5: 2019-20$ | B5: 5282 | C5: 36 | D5: 3580 | E5: 19 | F5: 254.6 | G5: 76938.82 | H5: 55867.81 | I5: 2940.4111 | J5: 21943.366 | K5: 76938.82 | L5: 55867.81 | M5: 15254028 | N5: 39487.45 | O5: 38460.25 | P5: 39031.55
A6: Apr-19 | B6: 5282 | C6: 36 | D6: 3580 | E6: 19 | F6: 254.6 | G6: 76938.82 | H6: 55867.81 | I6: 2940.4111 | J6: 21943.366 | K6: 76938.82 | L6: 55867.81 | M6: 15254028 | N6: 39487.45 | O6: 38460.25 | P6: 39031.55
A7: $ indicates as on April 30,2019
A8: Source: BSE .

Sheet 18
A1: Table 18: Trends in Cash Segment of NSE
A2: Year / Month | B2: No. of Companies Listed | C2: No. of Companies Permitted* | D2: No. of companies traded | E2: No. of Trading Days | F2: No. of Trades (Lakh) | G2: Traded Quantity (Lakh) | H2: Turnover (` crore) | I2: Average Daily Turnover (` crore) | J2: Average Trade Size (`) | K2: Demat Securities Traded (Lakh) | L2: Demat Turnover (` crore) | M2: Market Capitalisation (` crore) | N2: Nifty 50 Index
N3: High | O3: Low | P3: Close
A4: 2018-19 | B4: 1931 | C4: 4 | D4: 1922 | E4: 248 | F4: 28531.564 | G4: 3749975.9 | H4: 7949004.3 | I4: 32052.437 | J4: 27860.387 | K4: 3749975.9 | L4: 7949004.3 | M4: 14934227 | N4: 11760.2 | O4: 10004.55 | P4: 11623.9
A5: 2019-20$ | B5: 1938 | C5: 4 | D5: 1856 | E5: 19 | F5: 2147.241 | G5: 308635.83 | H5: 640115.39 | I5: 33690.284 | J5: 29811.064 | K5: 308635.83 | L5: 640115.39 | M5: 15043276 | N5: 11856.15 | O5: 11549.1 | P5: 11748.15
A6: Apr-19 | B6: 1938 | C6: 4 | D6: 1856 | E6: 19 | F6: 2147.241 | G6: 308635.83 | H6: 640115.39 | I6: 33690.284 | J6: 29811.064 | K6: 308635.83 | L6: 640115.39 | M6: 15043276 | N6: 11856.15 | O6: 11549.1 | P6: 11748.15
A7: Turnover Data compiled for all markets except auction market
A8: $ indicates as on April 30,2019
A9: Source: NSE

Sheet 19
A1: Table 19: Trends in Cash Segment of MSEI
A2: Year/Month | B2: No. of Companies Listed | C2: No. of Companies Permitted # | D2: No. of Companies Traded | E2: No. of Trading Days | F2: No. of Trades (Lakh) | G2: Traded Quantity (Lakh) | H2: Turnover (₹ crore) | I2: Average Daily Turnover (₹ crore) | J2: Average Trade Size (`) | K2: Demat Securities Traded (Lakh) | L2: Demat Turnover (₹ crore) | M2: Market Capitalisation (₹ crore) | N2: SX 50 Index
N3: High | O3: Low | P3: Close
A4: 2018-19 | B4: 287 | C4: 1309 | D4: 8 | E4: 248 | F4: 0.01911 | G4: 14.16864 | H4: 30.29325 | I4: 0.1221502 | J4: 158520.41 | K4: 14.16853 | L4: 30.288544 | M4: 14751584 | N4: 22872.75 | O4: 19644.59 | P4: 22743.31
A5: 2019-20$ | B5: 286 | C5: 1308 | D5: 6 | E5: 19 | F5: 0.00227 | G5: 3.82974 | H5: 7.4556996 | I5: 0.39240524 | J5: 328444.92 | K5: 3.82974 | L5: 7.4557 | M5: 14842661 | N5: 23072 | O5: 22659.08 | P5: 23000.87
A6: Apr-19 | B6: 286 | C6: 1308 | D6: 6 | E6: 19 | F6: 0.00227 | G6: 3.82974 | H6: 7.4556996 | I6: 0.39240524 | J6: 328444.92 | K6: 3.82974 | L6: 7.4557 | M6: 14842661 | N6: 23072 | O6: 22659.08 | P6: 23000.87
A7: $ indicates as on April 30, 2019
A8: Source: MSEI

Sheet 20
A1: Table 20: City-wise Distribution of Turnover on Cash Segments of BSE and NSE
A2: (Percentage share in Turnover)
A3: S.No | B3: City | C3: BSE | E3: NSE | G3: MSEI
C4: 2018-19 | D4: Apr-19 | E4: 2018-19 | F4: Apr-19 | G4: 2018-19 | H4: Apr-19
A5: 1 | B5: Ahmedabad | C5: 2.540772 | D5: 2.1284174 | E5: 2.24 | F5: 1.9 | G5: 0 | H5: 0
A6: 2 | B6: Bengaluru | C6: 0.453121 | D6: 0.9583561 | E6: 3.84 | F6: 3 | G6: 0 | H6: 0
A7: 3 | B7: Vadodra | C7: 0.907871 | D7: 0.94489403 | E7: 0.3 | F7: 0.24 | G7: 0 | H7: 0
A8: 4 | B8: Bhubneshwar | C8: 0.019895 | D8: 0.014461141 | E8: 0 | F8: 0 | G8: 0 | H8: 0
A9: 5 | B9: Chennai | C9: 1.090857 | D9: 1.2186534 | E9: 0.86 | F9: 0.82 | G9: 0 | H9: 0
A10: 6 | B10: Ernakulum | C10: 0.104662 | D10: 0.088157028 | E10: 0.75 | F10: 0.8 | G10: 0 | H10: 0
A11: 7 | B11: Coimbatore | C11: 0.042661 | D11: 0.03940365 | E11: 0.05 | F11: 0.04 | G11: 0 | H11: 0
A12: 8 | B12: New Delhi | C12: 1.604574 | D12: 1.3625655 | E12: 6.34 | F12: 6.57 | G12: 29.35 | H12: 49.36
A13: 9 | B13: Guwahati | C13: 0.046059 | D13: 0.032742056 | E13: 0 | F13: 0 | G13: 0 | H13: 0
A14: 10 | B14: Hyderabad | C14: 0.428016 | D14: 0.79549534 | E14: 3.36 | F14: 3.17 | G14: 0.08 | H14: 0
A15: 11 | B15: Indore | C15: 0.350443 | D15: 0.35068354 | E15: 0.44 | F15: 0.32 | G15: 0 | H15: 0
A16: 12 | B16: Jaipur | C16: 0.558991 | D16: 0.5517098 | E16: 0.32 | F16: 0.3 | G16: 0.09 | H16: 0
... A25: 21 | B25: Others | C25: 30.59857 | D25: 32.283089 | E25: 10.84 | F25: 11.38 | G25: 29.82 | H25: 35.51
B26: Total | C26: 100 | D26: 100 | E26: 100.02 | F26: 100 | G26: 100 | H26: 100
A27: Notes:
A28: 1. The city-wise distribution of turnover is based on the cities uploaded in the UCC database of the Exchange for clientele trades and members registered office city for proprietary trades.
A29: Source: BSE, NSE and MSEI.

Sheet 21
A1: Table 21: Category-wise Share of Turnover in Cash Segment of BSE
A2: Year / Month | B2: Percentage Share in Turnover
B3: Proprietary | C3: FPIs | D3: Mutual Funds | E3: Banks | F3: Others
A4: 2018-19 | B4: 22.3525 | C4: 12.430833 | D4: 7.94 | E4: 0.051666667 | F4: 57.224167
A5: 2019-20$ | B5: 22.47 | C5: 7.12 | D5: 6.77 | E5: 0.04 | F5: 63.59
A6: Apr-19 | B6: 22.47 | C6: 7.12 | D6: 6.77 | E6: 0.04 | F6: 63.59
A7: $ indicates as on April 30,2019
A8: Source: BSE.

Sheet 22
A1: Table 22: Category-wise Share of Turnover in Cash Segment of NSE
A2: Year /Month | B2: Percentage Share in Turnover
B3: Proprietary | C3: FPIs | D3: Mutual Funds | E3: Banks | F3: Others
A4: 2018-19 | B4: 21.53 | C4: 15.1 | D4: 7.49 | E4: 0.22 | F4: 55.66
A5: 2019-20$ | B5: 22.66 | C5: 14.33 | D5: 6.69 | E5: 0.15 | F5: 56.17
A6: Apr-19 | B6: 22.66 | C6: 14.33 | D6: 6.69 | E6: 0.15 | F6: 56.17
A7: $ indicates as on April 30,2019
A8: Source: NSE.

Sheet 23
A1: Table 23: Category-wise Share of Turnover in Cash Segment of MSEI
A2: Year / Month | B2: Percentage Share in Turnover
B3: Proprietary | C3: FPIs | D3: Mutual Funds | E3: Banks | F3: Others
A4: 2018-19 | B4: 0 | C4: 0 | D4: 0 | E4: 0 | F4: 100
A5: 2019-20$ | B5: 0 | C5: 0 | D5: 0 | E5: 0 | F5: 100
A6: Apr-19 | B6: 0 | C6: 0 | D6: 0 | E6: 0 | F6: 100
A7: $ indicates as on April 30, 2019
A8: Source: MSEI.

Sheet 24
A1: Table 24: Component Stocks: S&P BSE Sensex during Apr-19
A2: Sl.No | B2: Name of Security | C2: Issued Capital (` crore) | D2: Free Float Market Capitalisation (` crore) | E2: Weightage (Percent) | F2: Beta | G2: R 2 | H2: Daily Volatility (Percent) | I2: Monthly Return (Percent) | J2: Impact Cost (Percent)
A3: 1 | B3: HDFC BANK | C3: 545.01 | D3: 497038.06 | E3: 12.518176 | F3: 0.71 | G3: 0.306229 | H3: 0.99 | I3: -0.043168 | J3: 0.04
A4: 2 | B4: RELIANCE | C4: 6338.75 | D4: 449532.35 | E4: 11.321719 | F4: 1.5 | G4: 0.463172 | H4: 1.72 | I4: 2.10924 | J4: 0.02
A5: 3 | B5: HDFC | C5: 344.29 | D5: 342760.03 | E5: 8.6325995 | F5: 1.23 | G5: 0.45009 | H5: 1.42 | I5: 1.428353 | J5: 0.04
A6: 4 | B6: INFOSYS LTD | C6: 2184.47 | D6: 285007.74 | E6: 7.1780764 | F6: 0.84 | G6: 0.021125 | H6: 4.5 | I6: 1.03058 | J6: 0.04
A7: 5 | B7: ICICI BANK | C7: 1289.42 | D7: 261553.48 | E7: 6.5873679 | F7: 1.33 | G7: 0.309523 | H7: 1.86 | I7: 2.231415 | J7: 0.06
A8: 6 | B8: ITC LTD. | C8: 1225.86 | D8: 257017.5 | E8: 6.4731267 | F8: 0.93 | G8: 0.32215 | H8: 1.27 | I8: 1.634647 | J8: 0.06
A9: 7 | B9: TCS LTD. | C9: 375.24 | D9: 236920.34 | E9: 5.9669686 | F9: -0.01 | G9: 2e-06 | H9: 4.71 | I9: 12.724955 | J9: 0.03
A10: 8 | B10: LARSEN & TOU | C10: 280.55 | D10: 164219.97 | E10: 4.1359701 | F10: 0.91 | G10: 0.28799 | H10: 1.31 | I10: -2.622737 | J10: 0.03
A11: 9 | B11: KOTAK MAH.BK | C11: 954.42 | D11: 163701.41 | E11: 4.1229099 | F11: 0.97 | G11: 0.23906 | H11: 1.54 | I11: 3.840539 | J11: 0.03
A12: 10 | B12: AXIS BANK | C12: 514.47 | D12: 135670.53 | E12: 3.4169367 | F12: 1.16 | G12: 0.284649 | H12: 1.68 | I12: -1.185414 | J12: 0.03
A13: 11 | B13: HIND UNI LT | C13: 216.47 | D13: 125279.99 | E13: 3.1552453 | F13: 0.72 | G13: 0.181606 | H13: 1.31 | I13: 2.702307 | J13: 0.04
A14: 12 | B14: STATE BANK | C14: 892.46 | D14: 116273.1 | E14: 2.9284019 | F14: 1.33 | G14: 0.330687 | H14: 1.8 | I14: -3.304239 | J14: 0.04
... A33: 31 | B33: TATAMTRTDVR | C33: 101.7 | D33: 5196.8904 | E33: 0.13 | F33: 1.38 | G33: 0.178426 | H33: 2.53 | I33: 19.114219 | J33: 0.12
A34: Notes: 1. Beta & R2 are calculated for the trailing 12 months. Beta measures the degree to which any portfolio of stocks is affected as compared to the effect on the market as a whole.
A35: 2. The coefficient of determination (R2) measures the strength of relationship between two variables the return on a security versus that of the market.
A36: 3. Volatility is the standard deviation of the daily returns for the trailing 12 months.
A37: 4. Impact cost is calculated as the difference between actual buy price and ideal buy price, divided by ideal buy price, multiplied by 100. Hence ideal price is calculated as (best buy + best sell)/2.
A38: 5. The above is calculated for a month for the portfolio size of ` 5 lakh. It is calculated for the current month.
A39: Source: BSE.

Sheet 25
A1: Table 25: Component Stocks: Nifty 50 Index during Apr-19
A2: Sl. No | B2: Name of Security | C2: Issued Capital (`Crore) | D2: Free Float Market Capitalisation (` crore) | E2: Weightage (Percent) | F2: Beta | G2: R 2 | H2: Daily Volatility (Percent) | I2: Monthly Return (Percent) | J2: Impact Cost (Percent)
A3: 1 | B3: HDFC Bank Ltd. | C3: 544.66 | D3: 498579.03 | E3: 10.53 | F3: 0.68 | G3: 0.28 | H3: 1 | I3: -0.06 | J3: 0.02
A4: 2 | B4: Reliance Industries Ltd. | C4: 6338.69 | D4: 476740.68 | E4: 10.07 | F4: 1.46 | G4: 0.45 | H4: 1.42 | I4: 2.17 | J4: 0.02
A5: 3 | B5: Housing Development Finance Corporation Ltd. | C5: 343.74 | D5: 329173.86 | E5: 6.95 | F5: 1.22 | G5: 0.43 | H5: 1.28 | I5: 1.36 | J5: 0.01
A6: 4 | B6: Infosys Ltd. | C6: 2184.47 | D6: 285585.91 | E6: 6.03 | F6: 0.59 | G6: 0.1 | H6: 1.21 | I6: 1.01 | J6: 0.02
A7: 5 | B7: ICICI Bank Ltd. | C7: 1288.92 | D7: 262617.28 | E7: 5.55 | F7: 1.31 | G7: 0.3 | H7: 1.58 | I7: 1.75 | J7: 0.03
A8: 6 | B8: ITC Ltd. | C8: 1225.39 | D8: 258490.02 | E8: 5.46 | F8: 0.9 | G8: 0.3 | H8: 0.99 | I8: 1.38 | J8: 0.02
A9: 7 | B9: Tata Consultancy Services Ltd. | C9: 375.24 | D9: 237487.68 | E9: 5.01 | F9: 0.48 | G9: 0.06 | H9: 1.72 | I9: 12.92 | J9: 0.02
A10: 8 | B10: Kotak Mahindra Bank Ltd. | C10: 954.02 | D10: 185190.92 | E10: 3.91 | F10: 0.94 | G10: 0.23 | H10: 0.87 | I10: 3.9 | J10: 0.02
A11: 9 | B11: Larsen & Toubro Ltd. | C11: 280.52 | D11: 166452.82 | E11: 3.51 | F11: 0.92 | G11: 0.3 | H11: 0.89 | I11: -2.65 | J11: 0.02
A12: 10 | B12: Axis Bank Ltd. | C12: 514.25 | D12: 149852.78 | E12: 3.16 | F12: 1.16 | G12: 0.29 | H12: 1.11 | I12: -1.34 | J12: 0.02
A13: 11 | B13: Hindustan Unilever Ltd. | C13: 216.47 | D13: 125559.85 | E13: 2.65 | F13: 0.72 | G13: 0.18 | H13: 0.61 | I13: 2.98 | J13: 0.02
A14: 12 | B14: State Bank of India | C14: 892.46 | D14: 116179.7 | E14: 2.45 | F14: 1.34 | G14: 0.33 | H14: 1.34 | I14: -3.37 | J14: 0.02
... A52: 50 | B52: Bharti Infratel Ltd. | C52: 1849.61 | D52: 22338.27 | E52: 0.47 | F52: 0.29 | G52: 0.01 | H52: 2.68 | I52: -16.23 | J52: 0.03
A53: Notes: 1. Beta & R2 are calculated for the the trailing 12 months. Beta measures the degree to which any portfolio of stocks is affected as compared to the effect on the market as a whole.
A54: 2. The coefficient of determination (R2) measures the strength of relationship between two variables the return on a security versus that of the market.
A55: 3. Volatility is the standard deviation of the daily returns for the the trailing 12 months.
A56: 4. Impact cost is calculated as the difference between actual buy price and ideal buy price, divided by ideal buy price, multiplied by 100. Hence ideal price is calculated as (best buy + best sell)/2.
A57: 5. Impact Cost for Nifty 50 is for a portfolio of Rs. 50 Lakhs and is weightage average impact cost.
A58: Source: NSE.

Sheet 26
A1: Table 26: Component Stocks: SX40 Index
A2: S.No. | B2: Name of Security | C2: Issued Capital (₹ crore) | D2: Free Float Market Capitalisation (₹ crore) | E2: Weightage (Percent) | F2: Beta | G2: R2 | H2: Daily Volatility (Percent) | I2: Monthly Return (Percent) | J2: Impact Cost (Percent) *
A3: 1 | B3: HDFCBANK | C3: 545.00883 | D3: 496164.58 | E3: 11.35 | F3: 0.67 | G3: 0.26 | H3: 0.92 | I3: -0.06 | J3: Na
A4: 2 | B4: RELIANCE | C4: 6338.7505 | D4: 451352 | E4: 10.33 | F4: 1.5 | G4: 0.46 | H4: 1.51 | I4: 2.12 | J4: Na
A5: 3 | B5: HDFC | C5: 344.27049 | D5: 330584.28 | E5: 7.56 | F5: 1.21 | G5: 0.42 | H5: 1.12 | I5: 1.34 | J5: Na
A6: 4 | B6: INFY | C6: 2182.6847 | D6: 284614.34 | E6: 6.51 | F6: 0.67 | G6: 0.12 | H6: 1.19 | I6: 1 | J6: Na
A7: 5 | B7: ICICIBANK | C7: 1289.2879 | D7: 262591.01 | E7: 6.01 | F7: 1.29 | G7: 0.28 | H7: 1.47 | I7: 1.72 | J7: Na
A8: 6 | B8: ITC | C8: 1225.4194 | D8: 260059.87 | E8: 5.95 | F8: 0.92 | G8: 0.31 | H8: 1.01 | I8: 1.36 | J8: Na
A9: 7 | B9: TCS | C9: 375.23847 | D9: 254296.88 | E9: 5.82 | F9: 0.56 | G9: 0.08 | H9: 1.56 | I9: 11.45 | J9: Na
A10: 8 | B10: KOTAKBANK | C10: 954.41781 | D10: 172530.44 | E10: 3.95 | F10: 0.93 | G10: 0.22 | H10: 1.2 | I10: 3.75 | J10: Na
A11: 9 | B11: LT | C11: 280.49146 | D11: 165901.87 | E11: 3.8 | F11: 0.94 | G11: 0.3 | H11: 1.17 | I11: -2.73 | J11: Na
A12: 10 | B12: AXISBANK | C12: 514.18478 | D12: 151474.75 | E12: 3.47 | F12: 1.16 | G12: 0.28 | H12: 1.26 | I12: -1.36 | J12: Na
A13: 11 | B13: HINDUNILVR | C13: 216.47044 | D13: 124842.24 | E13: 2.86 | F13: 0.73 | G13: 0.18 | H13: 0.77 | I13: 2.9 | J13: Na
A14: 12 | B14: SBIN | C14: 892.46115 | D14: 116877 | E14: 2.67 | F14: 1.32 | G14: 0.31 | H14: 1.52 | I14: -3.48 | J14: Na
... A42: 40 | B42: ZEEL | C42: 96.04665 | D42: 24256.154 | E42: 0.55 | F42: 0.78 | G42: 0.04 | H42: 3 | I42: -2.98 | J42: Na
A43: Notes:
A44: 1. Market Cap, Beta & R2 as on the last day of the month
A45: 2. Beta & R2 are calculated for the trailing 12 months
A46: 3. Volatility for the current month
A47: 4. *Since there is no trading in the SX40 constituents, the Impact Cost for the given stocks is NIL.
A48: Source: MSEI.

Sheet 27
A1: Table 27: Advances/Declines in Cash Segment of BSE, NSE and MSEI
A2: Year/ Month | B2: BSE | E2: NSE | H2: MSEI
B3: Advances | C3: Declines | D3: Advance/Decline Ratio | E3: Advances | F3: Declines | G3: Advance/Decline Ratio | H3: Advances | I3: Declines | J3: Advance/Decline Ratio
A4: 2018-19 | B4: 1156 | C4: 2730 | D4: 0.42344322 | E4: 585 | F4: 1294 | G4: 0.45 | H4: 2 | I4: 5 | J4: 0.4
A5: 2019-20$ | B5: 930 | C5: 2621 | D5: 0.3548264 | E5: 353 | F5: 1434 | G5: 0.25 | H5: 2 | I5: 2 | J5: 1
A6: Apr-19 | B6: 1541 | C6: 1921 | D6: 0.80218636 | E6: 879 | F6: 1040 | G6: 0.85 | H6: 2 | I6: 2 | J6: 1
A7: Note: Advance/Decline is calculated based on the average price methodology.
A8: $ indicates as on April 30, 2019
A9: Source: BSE, NSE and MSEI.

Sheet 28
A1: Table 28: Trading Frequency in Cash Segment of BSE, NSE and MSEI
A2: Month | B2: BSE | E2: NSE | H2: MSEI
B3: No. of Companies Listed | C3: No. of Companies Traded | D3: Percent of Traded to Listed | E3: No. of Companies Listed | F3: No. of Companies Traded | G3: Percent of Traded to Listed | H3: No. of Companies Listed | I3: No. of Companies Traded | J3: Percent of Traded to Listed
A4: 2018-19 | B4: 5262 | C4: 4086 | D4: 77.651083 | E4: 1931 | F4: 1922 | G4: 99.53392 | H4: 287 | I4: 8 | J4: 2.7874564
A5: 2019-20$ | B5: 5282 | C5: 3580 | D5: 67.777357 | E5: 1938 | F5: 1856 | G5: 95.768834 | H5: 286 | I5: 6 | J5: 2.0979021
A6: Apr-19 | B6: 5282 | C6: 3580 | D6: 67.777357 | E6: 1938 | F6: 1856 | G6: 95.768834 | H6: 286 | I6: 6 | J6: 2.0979021
A7: $ indicates as on April 30,2019
A8: Source: BSE, NSE and MSEI.

Sheet 29
A1: Table 29: Daily Volatility of Major Indices (percent)
A2: Year / Month | B2: BSE Sensex | C2: BSE 100 | D2: BSE 500 | E2: Nifty 50 | F2: Nifty Next 50 | G2: Nifty 500 | H2: SX40
A3: 2018-19 | B3: 0.76505508 | C3: 0.79260673 | D3: 0.80214609 | E3: 0.78237731 | F3: 1.0209709 | G3: 0.80626923 | H3: 0.77
A4: 2019-20$ | B4: 0.68796438 | C4: 0.64456652 | D4: 0.61263988 | E4: 0.66285354 | F4: 0.57229388 | G4: 0.60203805 | H4: 0.71
A5: Apr-19 | B5: 0.68796438 | C5: 0.64456652 | D5: 0.61263988 | E5: 0.66285354 | F5: 0.57229388 | G5: 0.60203805 | H5: 0.71
A6: Note: Volatility is calculated as the standard deviation of the natural log of daily returns in indices for the respective period.
A7: $ indicates as on April 30,2019
A8: Source: BSE, MSEI and NSE.

Sheet 30
A1: Table 30: Percentage Share of Top ‘N’ Securities/Members in Turnover of Cash Segment (percent)
A2: Year/ Month | B2: BSE | G2: NSE | L2: MSEI
A3: Top | B3: 5 | C3: 10 | D3: 25 | E3: 50 | F3: 100 | G3: 5 | H3: 10 | I3: 25 | J3: 50 | K3: 100 | L3: 5 | M3: 10 | N3: 25 | O3: 50 | P3: 100
A4: Securities
A5: 2018-19 | B5: 9.529 | C5: 16.1709 | D5: 31.0552 | E5: 44.2911 | F5: 60.2394 | G5: 11.68 | H5: 20.43 | I5: 36.67 | J5: 52.57 | K5: 70.93 | L5: 98.9 | M5: 100 | N5: 100 | O5: 100 | P5: 100
A6: 2019-20$ | B6: 16.79 | C6: 26.8901 | D6: 42.9178 | E6: 56.3117 | F6: 70.2505 | G6: 14.92 | H6: 24.97 | I6: 43 | J6: 59.47 | K6: 76.69 | L6: 99.47 | M6: 100 | N6: 100 | O6: 100 | P6: 100
A7: Apr-19 | B7: 16.79 | C7: 26.8901 | D7: 42.9178 | E7: 56.3117 | F7: 70.2505 | G7: 14.92 | H7: 24.97 | I7: 43 | J7: 59.47 | K7: 76.69 | L7: 99.47 | M7: 100 | N7: 100 | O7: 100 | P7: 100
A8: Members
A9: 2018-19 | B9: 24.2 | C9: 38.4 | D9: 61 | E9: 73.5 | F9: 84.5 | G9: 22.47 | H9: 34.34 | I9: 54.6 | J9: 72.37 | K9: 85.69 | L9: 94.71 | M9: 100 | N9: 100 | O9: 100 | P9: Na
A10: 2019-20$ | B10: 31.24 | C10: 46.01 | D10: 62.89 | E10: 74.51 | F10: 84.49 | G10: 24.97 | H10: 37.18 | I10: 57.29 | J10: 74.1 | K10: 86.64 | L10: 88.28 | M10: 100 | N10: 100 | O10: 100 | P10: Na
A11: Apr-19 | B11: 31.24 | C11: 46.01 | D11: 62.89 | E11: 74.51 | F11: 84.49 | G11: 24.97 | H11: 37.18 | I11: 57.29 | J11: 74.1 | K11: 86.64 | L11: 88.28 | M11: 100 | N11: 100 | O11: 100 | P11: Na
A12: Notes: 1. Data for Top N scrips has been compiled for all markets except Auction market & Retail Debt Market and includes series EQ, BE,BT, BL and IL.
A13: 2. During the month only 57 members were permitted to trade.
A14: $ indicates as on April 30,2019
A15: Source: BSE, NSE and MSEI.

Sheet 31
A1: Table 31: Settlement Statistics for Cash Segment of BSE
A2: Year / Month | B2: No. of Trades(Lakh) | C2: Traded Quantity (Lakh) | D2: Delivered Quantity (Lakh) | E2: Percent of Delivered Quantity to Traded Quantity | F2: Turnover (` crore) | G2: Delivered Value (` crore) | H2: Percent of Delivered Value to Total Turnover | I2: Delivered Quantity in Demat Mode (Lakh) | J2: Percent of Demat Delivered Quantity to Total Delivered Quantity | K2: Delivered Value in Demat Mode (` crore) | L2: Percent of Demat Delivered Value to Total Delivered Value | M2: Short Delivery (Auctioned quantity) (Lakh) | N2: Percent of Short Delivery to Delivery Quantity | O2: Funds Pay-in (` crore) | P2: Securities Pay-in (` crore) | Q2: Settlement Guarantee Fund (`crore)
A3: 2018-19 | B3: 3145.2411 | C3: 518108 | D3: 195611.7 | E3: 37.528772 | F3: 775589.75 | G3: 261208.29 | H3: 33.097801 | I3: 195277.89 | J3: 99.814042 | K3: 261207.8 | L3: 99.994167 | M3: 458.18739 | N3: 0.22265529 | O3: 109583.71 | P3: 194997.75 | Q3: 207.14
A4: 2019-20$ | B4: 254.76076 | C4: 59515 | D4: 49993.686 | E4: 84.001825 | F4: 56860.88 | G4: 19548.391 | H4: 34.379333 | I4: 16965.053 | J4: 33.934392 | K4: 19191.226 | L4: 98.172918 | M4: 30.62797 | N4: 0.18053565 | O4: 10404.408 | P4: 19570.154 | Q4: 208.35
A5: Apr-19 | B5: 254.76076 | C5: 59515 | D5: 49993.686 | E5: 84.001825 | F5: 56860.88 | G5: 19548.391 | H5: 34.379333 | I5: 16965.053 | J5: 33.934392 | K5: 19191.226 | L5: 98.172918 | M5: 30.62797 | N5: 0.18053565 | O5: 10404.408 | P5: 19570.154 | Q5: 208.35
A6: $ indicates as on April 30,2019
A7: Source: BSE.

Sheet 32
A1: Table 32: Settlement Statistics for Cash Segment of NSE
A2: Year / Month | B2: No. of Trades(Lakh) | C2: Traded Quantity (Lakh) | D2: Delivered Quantity (Lakh) | E2: Percent of Delivered Quantity to Traded Quantity | F2: Turnover (` crore) | G2: Delivered Value (` crore) | H2: Percent of Delivered Value to Total Turnover | I2: Delivered Quantity in Demat Mode (Lakh) | J2: Percent of Demat Delivered Quantity to Total Delivered Quantity | K2: Delivered Value in Demat Mode (` crore) | L2: Percent of Demat Delivered Value to Total Delivered Value | M2: Short Delivery (Auctioned quantity) (Lakh) | N2: Percent of Short Delivery to Delivery Quantity | O2: Funds Pay-in (` crore) | P2: Securities Pay-in (` crore) | Q2: Settlement Guarantee Fund (`crore)
A3: 2018-19 | B3: 28452.85 | C3: 3668649.1 | D3: 845400.34 | E3: 23.04 | F3: 7912284.5 | G3: 1950906.3 | H3: 24.66 | I3: 844261.48 | J3: 100 | K3: 1949508.1 | L3: 100 | M3: 1138.86 | N3: 0.13 | O3: 533294.54 | P3: 1950906.3 | Q3: 270.69
A4: 2019-20$ | B4: 2178.6753 | C4: 318767.13 | D4: 83715.624 | E4: 26.262314 | F4: 660248.73 | G4: 164990.23 | H4: 24.989102 | I4: 83612.943 | J4: 100 | K4: 164854.61 | L4: 100 | M4: 102.68078 | N4: 0.12265426 | O4: 43313.93 | P4: 164990.23 | Q4: 273.14
A5: Apr-19 | B5: 2178.6753 | C5: 318767.13 | D5: 83715.624 | E5: 26.262314 | F5: 660248.73 | G5: 164990.23 | H5: 24.989102 | I5: 83612.943 | J5: 100 | K5: 164854.61 | L5: 100 | M5: 102.68078 | N5: 0.12265426 | O5: 43313.93 | P5: 164990.23 | Q5: 273.14
A6: Settlement Statistics for settlement type N, excluding CM Series IL & BL
A7: $ indicates as on April 30,2019
A8: Source: NSE.

Sheet 33
A1: Table 33: Settlement Statistics for Cash Segment of MSEI
A2: Month Sorting | B2: No. of Trades(Lakh) | C2: Traded Quantity (Lakh) | D2: Delivered Quantity (Lakh) | E2: Percent of Delivered Quantity to Traded Quantity | F2: Turnover (₹ crore) | G2: Delivered Value (₹ crore) | H2: Percent of Delivered Value to Total Turnover | I2: Delivered Quantity in Demat Mode (Lakh) | J2: Percent of Demat Delivered Quantity to Total Delivered Quantity | K2: Delivered Value in Demat Mode (₹ crore) | L2: Percent of Demat Delivered Value to Total Delivered Value | M2: Funds Pay-in (₹ crore) | N2: Securities Pay-in (₹ crore) | O2: Settlement Guarantee Fund(₹ crore)
A3: 2018-19 | B3: 0.01915 | C3: 14.16864 | D3: 14.16864 | E3: 100 | F3: 30.293252 | G3: 30.293252 | H3: 100 | I3: 14.16864 | J3: 100 | K3: 30.293252 | L3: 100 | M3: 30.293252 | N3: 30.293252 | O3: 0.32
A4: 2019-20$ | B4: 0.00227 | C4: 3.82974 | D4: 3.82974 | E4: 100 | F4: 7.4556996 | G4: 7.4556996 | H4: 100 | I4: 3.82974 | J4: 100 | K4: 7.4556996 | L4: 100 | M4: 7.4556996 | N4: 7.4556996 | O4: 0.32
A5: Apr-19 | B5: 0.00227 | C5: 3.82974 | D5: 3.82974 | E5: 100 | F5: 7.4556996 | G5: 7.4556996 | H5: 100 | I5: 3.82974 | J5: 100 | K5: 7.4556996 | L5: 100 | M5: 7.4556996 | N5: 7.4556996 | O5: 0.32
A6: $ indicates as on April 30, 2019
A7: Source: MSEI.

Sheet 34
A1: Table 34: Trends in Equity Derivatives Segment at BSE (Turnover in Notional Value)
A2: Year/ Month | B2: No. of Trading Days | C2: Index Futures | E2: Stock Futures | G2: Index Options | K2: Stock Options | O2: Total | Q2: Open Interest at the end of Month
G3: Call | I3: Put | K3: Call | M3: Put
C4: No. of Contracts | D4: Turnover (` crore) | E4: No. of Contracts | F4: Turnover (` crore) | G4: No. of Contracts | H4: Turnover (` crore) | I4: No. of Contracts | J4: Turnover (` crore) | K4: No. of Contracts | L4: Turnover (` crore) | M4: No. of Contracts | N4: Turnover (` crore) | O4: No. of Contracts | P4: Turnover (` crore) | Q4: No. of contracts | R4: Turnover (` crore)
A5: 2018-19 | B5: 248 | C5: 438 | D5: 39.15837 | E5: 271 | F5: 17.779123 | G5: 19158 | H5: 1308.5017 | I5: 11298 | J5: 884.62804 | K5: 2 | L5: 0.07568 | M5: 0 | N5: 0 | O5: 31167 | P5: 2250.1429 | Q5: 9 | R5: 0.67341037
A6: 2019-20$ | B6: 19 | C6: 7 | D6: 0.68431138 | E6: 51 | F6: 3.5252402 | G6: 0 | H6: 0 | I6: 0 | J6: 0 | K6: 0 | L6: 0 | M6: 0 | N6: 0 | O6: 58 | P6: 4.2095516 | Q6: 6 | R6: 0.47
A7: Apr-19 | B7: 19 | C7: 7 | D7: 0.68431138 | E7: 51 | F7: 3.5252402 | G7: 0 | H7: 0 | I7: 0 | J7: 0 | K7: 0 | L7: 0 | M7: 0 | N7: 0 | O7: 58 | P7: 4.2095516 | Q7: 6 | R7: 0.47
A8: Note: 1. Notional Turnover = (Strike Price + Premium) * Quantity.
A9: $ indicates as on April 30,2019
A10: Source: BSE.

Sheet 35
A1: Table 35: Trends in Equity Derivatives Segment at NSE (Turnover in Notional Value)
A2: Year/ Month | B2: No. of Trading Days | C2: Index Futures | E2: Stock Futures | G2: Index Options | K2: Stock Options | O2: Total | Q2: Open Interest at the end of Month
G3: Call | I3: Put | K3: Call | M3: Put
C4: No. of Contracts | D4: Turnover (` crore) | E4: No. of Contracts | F4: Turnover (` crore) | G4: No. of Contracts | H4: Turnover (` crore) | I4: No. of Contracts | J4: Turnover (` crore) | K4: No. of Contracts | L4: Turnover (` crore) | M4: No. of Contracts | N4: Turnover (` crore) | O4: No. of Contracts | P4: Turnover (` crore) | Q4: No. of Contracts | R4: Turnover (` crore)
A5: 2018-19 | B5: 248 | C5: 69824522 | D5: 5568914.4 | E5: 255533869 | F5: 16147011 | G5: 1391027617 | H5: 1.0772633e+08 | I5: 1261429870 | J5: 95576078 | K5: 123510308 | L5: 8517920.5 | M5: 63476234 | N5: 4064454.4 | O5: 3164802420 | P5: 237600705 | Q5: 4038916 | R5: 286402.85
A6: 2019-20$ | B6: 19 | C6: 5521413 | D6: 406219.34 | E6: 18819091 | F6: 1159128.2 | G6: 161093858 | H6: 10860276 | I6: 137719004 | J6: 9170370.4 | K6: 9936612 | L6: 651294.77 | M6: 5037643 | N6: 307998.01 | O6: 338127621 | P6: 22555286 | Q6: 4397035 | R6: 300027.62
A7: Apr-19 | B7: 19 | C7: 5521413 | D7: 406219.34 | E7: 18819091 | F7: 1159128.2 | G7: 161093858 | H7: 10860276 | I7: 137719004 | J7: 9170370.4 | K7: 9936612 | L7: 651294.77 | M7: 5037643 | N7: 307998.01 | O7: 338127621 | P7: 22555286 | Q7: 4397035 | R7: 300027.62
A8: Note: 1. Notional Turnover = (Strike Price + Premium) * Quantity.
A9: $ indicates as on April 30,2019
A10: Source: NSE.

Sheet 36
A1: Table 36: Settlement Statistics in Equity Derivatives Segment at BSE and NSE (` crore)
A2: Year/ Month | B2: BSE | H2: NSE
B3: Index/Stock Futures | D3: Index/Stock Options | F3: Total | G3: Settlement Gurantee Fund | H3: Index/Stock Futures | J3: Index/Stock Options | L3: Total | M3: Settlement Gurantee Fund
B4: MTM Settlement | C4: Final Settlement | D4: Premium Settlement | E4: Exercise Settlement | H4: MTM Settlement | I4: Final Settlement | J4: Premium Settlement | K4: Exercise Settlement
A5: 2018-19 | B5: 0.98 | C5: 0.08 | D5: 8.67 | E5: 0.05 | F5: 9.78 | G5: 19.43 | H5: 136640.06 | I5: 2754.22 | J5: 19252.85 | K5: 2534.91 | L5: 161182.04 | M5: 1911.63
A6: 2019-20$ | B6: 0.15 | C6: 0.02 | D6: 0 | E6: 0 | F6: 0.17 | G6: 19.54 | H6: 7864.19 | I6: 114.9 | J6: 1522.91 | K6: 93.85 | L6: 9595.85 | M6: 1936.43
A7: Apr-19 | B7: 0.15 | C7: 0.02 | D7: 0 | E7: 0 | F7: 0.17 | G7: 19.54 | H7: 7864.19 | I7: 114.9 | J7: 1522.91 | K7: 93.85 | L7: 9595.85 | M7: 1936.43
A8: $ indicates as on April 30,2019
A9: Source: BSE and NSE

Sheet 37
A1: Table 37: Category-wise Share of Turnover & Open Interest in Equity Derivative Segment of BSE
A2: Year/Month | B2: Percentage Share in Turnover | G2: Percentage Share in Open Interest
B3: Pro | C3: FPI | D3: Mutual Funds | E3: Banks | F3: Others | G3: Pro | H3: FPI | I3: Mutual Funds | J3: Banks | K3: Others
A4: 2018-19 | B4: 2 | C4: 0 | D4: 0 | E4: 0 | F4: 98 | G4: 0 | H4: 0 | I4: 0 | J4: 0 | K4: 100
A5: 2019-20$ | B5: 16.26 | C5: 0 | D5: 0 | E5: 0 | F5: 83.74 | G5: 0 | H5: 0 | I5: 0 | J5: 0 | K5: 100
A6: Apr-19 | B6: 16.26 | C6: 0 | D6: 0 | E6: 0 | F6: 83.74 | G6: 0 | H6: 0 | I6: 0 | J6: 0 | K6: 100
A7: $ indicates as on April 30,2019
A8: Source: BSE.

Sheet 38
A1: Table 38: Category-wise Share of Turnover & Open Interest in Equity Derivative Segment of NSE
A2: Year/Month | B2: Percentage Share in Turnover | G2: Percentage Share in Open Interest
B3: Pro | C3: FPIs | D3: Mutual Funds | E3: Banks | F3: Others | G3: Pro | H3: FPIs | I3: Mutual Funds | J3: Banks | K3: Others
A4: 2018-19 | B4: 37.84 | C4: 13.58 | D4: 0.42 | E4: 0 | F4: 48.16 | G4: 13.72 | H4: 29.83 | I4: 13.19 | J4: 0 | K4: 43.25
A5: 2019-20$ | B5: 32.86 | C5: 19.28 | D5: 0.34 | E5: 0 | F5: 47.52 | G5: 13.53 | H5: 26.86 | I5: 12.8 | J5: 0 | K5: 46.81
A6: Apr-19 | B6: 32.86 | C6: 19.28 | D6: 0.34 | E6: 0 | F6: 47.52 | G6: 13.53 | H6: 26.86 | I6: 12.8 | J6: 0 | K6: 46.81
A7: $ indicates as on April 30,2019
A8: Source: NSE.

Sheet 39
A1: Table 39: Instrument-wise Turnover in Index Derivatives at BSE
A2: Turnover (in Percentage)
A3: Year/Month | B3: BSE 30 SENSEX | C3: BSE SENSEX 50 | D3: BSE BANKEX | E3: BSE OIL & GAS INDEX | F3: BSE TECK INDEX | G3: BSE100 | H3: HANG SENG Index Futures | I3: MICEX Index Futures | J3: FTSE/JSE Top 40 Futures | K3: IBOVESPA Futures
A4: 2018-19 | B4: 41.32 | C4: 0 | D4: 58.68 | E4: 0 | F4: 0 | G4: 0 | H4: 0 | I4: 0 | J4: 0 | K4: 0
A5: 2019-20$ | B5: 100 | C5: 0 | D5: 0 | E5: 0 | F5: 0 | G5: 0 | H5: 0 | I5: 0 | J5: 0 | K5: 0
A6: Apr-19 | B6: 100 | C6: 0 | D6: 0 | E6: 0 | F6: 0 | G6: 0 | H6: 0 | I6: 0 | J6: 0 | K6: 0
A7: $ indicates as on April 30,2019
A8: Source: BSE.

Sheet 40
A1: Table 40: Instrument-wise Turnover in Index Derivatives at NSE
A2: Turnover (in Percentage)
A3: Year/Month | B3: NIFTY | C3: NIFTYIT | D3: BANKNIFTY | E3: NIFTYMID50 | F3: NIFTYPSE | G3: NIFTYINFRA | H3: FTSE100 | I3: S&P500 | J3: DJIA | K3: India VIX | L3: NIFTYCPSE
A4: 2018-19 | B4: 26.234649 | C4: 0.003855915 | D4: 73.75893 | E4: 0.002828893 | F4: 1e-06 | G4: 0 | H4: 8.5e-08 | I4: 0 | J4: 0 | K4: 0 | L4: 4.01e-07
A5: 2019-20$ | B5: 32.68824 | C5: 0.002977 | D5: 67.308783 | E5: 0 | F5: 0 | G5: 0 | H5: 0 | I5: 0 | J5: 0 | K5: 0 | L5: 0
A6: Apr-19 | B6: 32.68824 | C6: 0.002977 | D6: 67.308783 | E6: 0 | F6: 0 | G6: 0 | H6: 0 | I6: 0 | J6: 0 | K6: 0 | L6: 0
A7: $ indicates as on April 30,2019
A8: Source: NSE.

Sheet 41
A1: Table 41: Trends in Currency Derivatives Segment at BSE
A2: Year/ Month | B2: No. of Trading Days | C2: Currency Futures | E2: Currency Options | I2: Total | K2: Open Interest at the end of the Month
E3: Call | G3: Put
C4: No. of Contracts | D4: Turnover (` crore) | E4: No. of Contracts | F4: Turnover (` crore) | G4: No. of Contracts | H4: Turnover (` crore) | I4: No. of Contracts | J4: Turnover (` crore) | K4: No. of Contracts | L4: Value (` crore)
A5: 2018-19 | B5: 243 | C5: 456884165 | D5: 3206488.6 | E5: 241869262 | F5: 1719119.9 | G5: 353698730 | H5: 2426665.9 | I5: 1052452157 | J5: 7352274.4 | K5: 712162 | L5: 4929.4031
A6: 2019-20$ | B6: 18 | C6: 28454552 | D6: 198227.25 | E6: 27648067 | F6: 196542.51 | G6: 27200048 | H6: 185922.52 | I6: 83302667 | J6: 580692.29 | K6: 1277029 | L6: 8920.27
A7: Apr-19 | B7: 18 | C7: 28454552 | D7: 198227.25 | E7: 27648067 | F7: 196542.51 | G7: 27200048 | H7: 185922.52 | I7: 83302667 | J7: 580692.29 | K7: 1277029 | L7: 8920.27
A8: $ indicates as on April 30,2019
A9: Source: BSE

Sheet 42
A1: Table 42: Trends in Currency Derivatives Segment at NSE
A2: Year/ Month | B2: No. of Trading Days | C2: Currency Futures | E2: Currency Options | I2: Total | K2: Open Interest at the end of Month
C3: No. of Contracts | D3: Turnover (` crore) | E3: Call | G3: Put | I3: No. of Contracts | J3: Turnover (` crore) | K3: No. of Contracts | L3: Value (` crore)
E4: No. of Contracts | F4: Turnover (` crore) | G4: No. of Contracts | H4: Turnover (` crore)
A5: 2018-19 | B5: 243 | C5: 650024870 | D5: 4654927.1 | E5: 275919964 | F5: 1956019.7 | G5: 272439387 | H5: 1907404.5 | I5: 1198384221 | J5: 8518351.2 | K5: 4205566 | L5: 29351.446
A6: 2019-20$ | B6: 18 | C6: 50944880 | D6: 361284.9 | E6: 25110750 | F6: 175702.56 | G6: 25140409 | H6: 174367.63 | I6: 101196039 | J6: 711355.08 | K6: 5062681 | L6: 35527.744
A7: Apr-19 | B7: 18 | C7: 50944880 | D7: 361284.9 | E7: 25110750 | F7: 175702.56 | G7: 25140409 | H7: 174367.63 | I7: 101196039 | J7: 711355.08 | K7: 5062681 | L7: 35527.744
A8: Notes: 1. Trading Value :- For Futures, Value of contract = Traded Qty*Traded Price. 2. For Options, Value of contract = Traded Qty*(Strike Price+Traded Premium)
A9: $ indicates as on April 30,2019
A10: Source: NSE.

Sheet 43
A1: Table 43: Trends in Currency Derivatives Segment at MSEI
A2: Year/ Month | B2: No. of Trading Days | C2: Currency Futures | E2: Currency Options | I2: Total | K2: Open Interest at the end of Month
C3: No. of Contracts | D3: Turnover (` crore) | E3: Call | G3: Put | I3: No. of Contracts | J3: Turnover (` crore) | K3: No. of Contracts | L3: Value (` crore)
E4: No. of Contracts | F4: Turnover (` crore) | G4: No. of Contracts | H4: Turnover (` crore)
A5: 2018-19 | B5: 243 | C5: 5499701 | D5: 38194.64 | E5: 574634 | F5: 4082.9041 | G5: 697331 | H5: 4960.9747 | I5: 6771666 | J5: 47238.518 | K5: 18715 | L5: 130.15286
A6: 2019-20$ | B6: 18 | C6: 243494 | D6: 1704.5449 | E6: 62239 | F6: 444.06509 | G6: 90537 | H6: 631.72794 | I6: 396270 | J6: 2780.3379 | K6: 19412 | L6: 141.17954
A7: Apr-19 | B7: 18 | C7: 243494 | D7: 1704.5449 | E7: 62239 | F7: 444.06509 | G7: 90537 | H7: 631.72794 | I7: 396270 | J7: 2780.3379 | K7: 19412 | L7: 141.17954
A8: $ indicates as on April 30,2019
A9: Source: MSEI

Sheet 44
A1: Table 44: Settlement Statistics of Currency Derivatives Segment (` crore)
A2: Year/ Month | B2: BSE | F2: Total | G2: NSE | K2: Total | L2: MSEI | P2: Total
B3: Currency Futures | D3: Currency Options | G3: Currency Futures | I3: Currency Options | L3: Currency Futures | N3: Currency Options
B4: MTM Settlement | C4: Final Settlement | D4: Premium Settlement | E4: Exercise Settlement | G4: MTM Settlement | H4: Final Settlement | I4: Premium Settlement | J4: Exercise Settlement | L4: MTM Settlement | M4: Final Settlement | N4: Premium Settlement | O4: Exercise Settlement
A5: 2018-19 | B5: 5970.05 | C5: 191.46 | D5: 3565.27 | E5: 154.97 | F5: 9881.75 | G5: 8260.464 | H5: 292.40325 | I5: 1286.8978 | J5: 643.41508 | K5: 10483.18 | L5: 125.37569 | M5: 6.8401983 | N5: 0.555969 | O5: 0.68199744 | P5: 133.45385
A6: 2019-20$ | B6: 363.16 | C6: 6.08 | D6: 403.39 | E6: 6.8 | F6: 779.43 | G6: 512.90147 | H6: 6.432021 | I6: 102.97739 | J6: 25.654563 | K6: 647.96544 | L6: 14.89 | M6: 0.22280344 | N6: 0.01516775 | O6: 0.0010549 | P6: 15.129026
A7: Apr-19 | B7: 363.16 | C7: 6.08 | D7: 403.39 | E7: 6.8 | F7: 779.43 | G7: 512.90147 | H7: 6.432021 | I7: 102.97739 | J7: 25.654563 | K7: 647.96544 | L7: 14.89 | M7: 0.22280344 | N7: 0.01516775 | O7: 0.0010549 | P7: 15.129026
A8: $ indicates as on April 30,2019
A9: Source: BSE, NSE and MSEI.

Sheet 45
A1: Table 45: Instrument-wise Turnover in Currency Derivative Segment of BSE
A2: Year/Month | B2: Turnover (` crore) | I2: Open Interest as on last day of the month (in lots)
B3: USDINR | C3: EURINR | D3: GBPINR | E3: JPYINR | F3: EURUSD | G3: GBPUSD | H3: USDJPY | I3: USDINR | J3: EURINR | K3: GBPINR | L3: JPYINR | M3: EURUSD | N3: GBPUSD | O3: USDJPY
A4: 2018-2019 | B4: 7336635.9 | C4: 5354.2229 | D4: 4940.5534 | E4: 1322.2592 | F4: 2712.9962 | G4: 1275.3717 | H4: 33.1141 | I4: 709594 | J4: 873 | K4: 1332 | L4: 354 | M4: 0 | N4: 9 | O4: 0
A5: 2019-20$ | B5: 580467.68 | C5: 46.114839 | D5: 138.95065 | E5: 39.54 | F5: 0 | G5: 0 | H5: 0 | I5: 1275372 | J5: 308 | K5: 946 | L5: 403 | M5: 0 | N5: 0 | O5: 0
A6: Apr-19 | B6: 580467.68 | C6: 46.114839 | D6: 138.95065 | E6: 39.54 | F6: 0 | G6: 0 | H6: 0 | I6: 1275372 | J6: 308 | K6: 946 | L6: 403 | M6: 0 | N6: 0 | O6: 0
A7: 1. USDINR includes Futures and options both other currencys have only futures till February 26, 2018.
A8: 2. All Products include both Futures & options from February 27, 2018 onwards.
A9: 3. EURUSD, GBPUSD, USDJPY wer launched in Feb 2018
A10: $ indicates as on April 30,2019
A11: Source: BSE

Sheet 46
A1: Table 46: Instrument-wise Turnover in Currency Derivatives of NSE
A2: Year/Month | B2: Turnover ( ` crore) | I2: Open Interest as on last day of the month ( in lots)
B3: USDINR | C3: EURINR | D3: GBPINR | E3: JPYINR | F3: EURUSD | G3: GBPUSD | H3: USDJPY | I3: USDINR | J3: EURINR | K3: GBPINR | L3: JPYINR | M3: EURUSD | N3: GBPUSD | O3: USDJPY
A4: 2018-19$ | B4: 7978933.8 | C4: 176061.27 | D4: 226751.72 | E4: 59106.091 | F4: 42661.716 | G4: 33643.822 | H4: 1192.8246 | I4: 4059718 | J4: 50501 | K4: 37698 | L4: 21801 | M4: 33796 | N4: 1978 | O4: 74
A5: 2019-20 | B5: 673980.52 | C5: 10092.261 | D5: 21981.23 | E5: 3519.8798 | F5: 897.44538 | G5: 872.66995 | H5: 11.079929 | I5: 4911962 | J5: 49395 | K5: 32413 | L5: 23666 | M5: 42550 | N5: 2631 | O5: 64
A6: Apr-19 | B6: 673980.52 | C6: 10092.261 | D6: 21981.23 | E6: 3519.8798 | F6: 897.44538 | G6: 872.66995 | H6: 11.079929 | I6: 4911962 | J6: 49395 | K6: 32413 | L6: 23666 | M6: 42550 | N6: 2631 | O6: 64
A7: 1. Cross Currency was introduced wef Feb 27, 2018
A8: 2. Options contracts on EURINR,GBPINR,JPYINR were introduced wef Feb 27, 2018
A9: $ indicates as on April 30,2019
A10: Source: NSE.

Sheet 47
A1: Table 47: Instrument-wise Turnover in Currency Derivative Segment of MSEI
A2: Year/Month | B2: Turnover (` crore) | F2: Open Interest as on last day of the month (in lots)
B3: USDINR | C3: EURINR | D3: GBPINR | E3: JPYINR | F3: USDINR | G3: EURINR | H3: GBPINR | I3: JPYINR
A4: 2018-19 | B4: 45388.394 | C4: 682.56191 | D4: 1144.1231 | E4: 21.812767 | F4: 18649 | G4: 53 | H4: 7 | I4: 6
A5: 2019-20$ | B5: 2659.6614 | C5: 60.362018 | D5: 59.801301 | E5: 0.5131315 | F5: 16184 | G5: 1593 | H5: 1629 | I5: 6
A6: Apr-19 | B6: 2659.6614 | C6: 60.362018 | D6: 59.801301 | E6: 0.5131315 | F6: 16184 | G6: 1593 | H6: 1629 | I6: 6
A7: Data includes Notional Value for Options
A8: Excludes data of Interest Rate Futures
A9: $ indicates as on April 30,2019
A10: Source: MSEI

Sheet 48
A1: Table 48: Maturity-wise Turnover in Currency Derivative Segment of BSE (` crore)
A2: Year/Month | B2: Currency Futures | F2: Currency Options
B3: 1 Month | C3: 2 Month | D3: 3 Month | E3: > 3 Months | F3: 1 Month | G3: 2 Month | H3: 3 Month | I3: > 3 Months
A4: 2018-19 | B4: 2821842.2 | C4: 328321.59 | D4: 9826.4511 | E4: 1918.3599 | F4: 3701091.9 | G4: 315307.15 | H4: 1160.0513 | I4: 127.1642
A5: 2019-20$ | B5: 169144.15 | C5: 24434.401 | D5: 317.7254 | E5: 10.6563 | F5: 327257.38 | G5: 27355.288 | H5: 3.9959 | I5: 0
A6: Apr-19 | B6: 169144.15 | C6: 24434.401 | D6: 317.7254 | E6: 10.6563 | F6: 327257.38 | G6: 27355.288 | H6: 3.9959 | I6: 0
A7: $ indicates as on April 30,2019
A8: Source: BSE

Sheet 49
A1: Table 49: Maturity-wise Turnover in Currency Derivative Segment of NSE (` crore)
A2: Year/Month | B2: Currency Future | F2: Currency Options
B3: 1 Month | C3: 2 Month | D3: 3 Month | E3: > 3 Months | F3: 1 Month | G3: 2 Month | H3: 3 Month | I3: > 3 Months
A4: 2018-19 | B4: 3719230 | C4: 828483.43 | D4: 70716.607 | E4: 36497.054 | F4: 2646030.7 | G4: 578570.97 | H4: 242227.87 | I4: 396594.59
A5: 2019-20$ | B5: 277112.52 | C5: 74400.989 | D5: 6549.2537 | E5: 3222.1359 | F5: 189409.03 | G5: 47929.714 | H5: 42277.963 | I5: 70453.478
A6: Apr-19 | B6: 277112.52 | C6: 74400.989 | D6: 6549.2537 | E6: 3222.1359 | F6: 189409.03 | G6: 47929.714 | H6: 42277.963 | I6: 70453.478
A7: $ indicates as on April 30,2019
A8: Source: NSE.

Sheet 50
A1: Table 50: Maturity-wise Turnover in Currency Derivative Segment of MSEI (` crore)
A2: Year/Month | B2: Currency Future | F2: Currency Options
B3: 1 Month | C3: 2 Month | D3: 3 Month | E3: > 3 Months | F3: 1 Month | G3: 2 Month | H3: 3 Month | I3: > 3 Months
A4: 2018-19 | B4: 33138.897 | C4: 4977.6412 | D4: 55.156287 | E4: 22.945404 | F4: 5702.8547 | G4: 3164.6336 | H4: 176.3905 | I4: 0
A5: 2019-20$ | B5: 1612.0491 | C5: 92.481732 | D5: 0.01407 | E5: 0 | F5: 1048.2721 | G5: 27.520913 | H5: 0 | I5: 0
A6: Apr-19 | B6: 1612.0491 | C6: 92.481732 | D6: 0.01407 | E6: 0 | F6: 1048.2721 | G6: 27.520913 | H6: 0 | I6: 0
A7: $ indicates as on April 30,2019
A8: Source: MSEI

Sheet 51
A1: Table 51: Trading Statistics of Interest Rate Futures at BSE, NSE and MSEI
A2: Year/ Month | B2: No. of Trading Days | C2: BSE | G2: NSE | K2: MSEI
C3: Interest Rate Futures | E3: Open Interest at the end of | G3: Interest Rate Futures | I3: Open Interest at the end of | K3: Interest RateFutures | M3: Open Interest at the end of
C4: No. of Contracts | D4: Traded Value (` crore) | E4: No. of Contracts | F4: Traded Value (` crore) | G4: No. of Contracts | H4: Traded Value (` crore) | I4: No. of Contracts | J4: Value (` crore) | K4: No. of Contracts | L4: Traded Value (` crore) | M4: No. of Contracts | N4: Value (` crore)
A5: 2018-19 | B5: 243 | C5: 5901468 | D5: 111222.29 | E5: 60205 | F5: 1214.2243 | G5: 12764150 | H5: 245407.18 | I5: 103589 | J5: 2054.4424 | K5: 0 | L5: 0 | M5: 0 | N5: 0
A6: 2019-20$ | B6: 18 | C6: 246140 | D6: 4738.1118 | E6: 66107 | F6: 1319.5983 | G6: 1232112 | H6: 24097.958 | I6: 122799 | J6: 2431.93 | K6: 0 | L6: 0 | M6: 0 | N6: 0
A7: Apr-19 | B7: 18 | C7: 246140 | D7: 4738.1118 | E7: 66107 | F7: 1319.5983 | G7: 1232112 | H7: 24097.958 | I7: 122799 | J7: 2431.93 | K7: 0 | L7: 0 | M7: 0 | N7: 0
A8: $ indicates as on April 30,2019
A9: Source: BSE, NSE and MSEI

Sheet 52
A1: Table 52: Settlement Statistics in Interest Rate Futures at BSE, NSE and MSEI (` crore)
A2: Year/ Month | B2: BSE | D2: NSE | F2: MSEI
B3: MTM Settlement | C3: Physical Delivery Settlement | D3: MTM Settlement | E3: Physical Delivery Settlement | F3: MTM Settlement | G3: Physical Delivery Settlement
A4: 2018-19 | B4: 308.58898 | C4: 13.792949 | D4: 634.57266 | E4: 13.227393 | F4: 0.0504 | G4: 0
A5: 2019-20$ | B5: 58.395731 | C5: 0.944379 | D5: 63.695625 | E5: 1.6079706 | F5: 0 | G5: 0
A6: Apr-19 | B6: 58.395731 | C6: 0.944379 | D6: 63.695625 | E6: 1.6079706 | F6: 0 | G6: 0
A7: $ indicates as on April 30,2019
A8: Source: NSE, BSE and MSEI

Sheet 53
A1: Table 53: Trends in Foreign Portfolio Investment
A2: Year/Month | B2: Gross Purchase (` crore) | C2: Gross Sales (` crores) | D2: Net Investment (` crores) | E2: Net Investment (US' $ mn.) | F2: Cumulative Net Investment (US $ mn.)
A3: 2018-19 | B3: 1640809.7 | C3: 1679740.8 | D3: -38931.12 | E3: -5498.74 | F3: 248154.18
A4: 2019-20$ | B4: 135799.91 | C4: 119072.05 | D4: 16727.86 | E4: 2406.9 | F4: 250561.08
A5: Apr-19 | B5: 135799.91 | C5: 119072.05 | D5: 16727.86 | E5: 2406.9 | F5: 250561.08
A6: $ indicates as on April 30,2019
A7: Source: NSDL, CDSL

Sheet 54
A1: Table 54: Notional Value of Offshore Derivative Instruments (ODIs) compared to Assets Under Custody (AUC) of FPIs/Deemed FPIs (` crore)
A2: Year/ Month | B2: Notional value of ODIs on Equity, Debt & Derivatives | C2: Notional value of ODIs on Equity & Debt excluding Derivatives | D2: Assets Under Custody of FPIs/Deemed FPIs | E2: Notional value of ODIs on Equity, Debt & Derivatives as % of Assets Under Custody of FPIs/Deemed FPIs | F2: Notional value of ODIs on Equity & Debt excluding Derivatives as % of Assets Under Custody of FPIs/Deemed FPIs
A3: 2018-19 | B3: 78110 | C3: 77287 | D3: 3342680 | E3: 2.3 | F3: 2.3
A4: 2019-20$ | B4: 81220 | C4: 80362 | D4: 3355045 | E4: 2.4 | F4: 2.4
A5: Apr-19 | B5: 81220 | C5: 80362 | D5: 3355045 | E5: 2.4 | F5: 2.4
A6: Notes: 1. Figures are compiled based on reports submitted by FPIs/deemed FPIs issuing ODIs. 2. Column 4 Figures are compiled on the basis of reports submitted by custodians & does not includes positions taken by FPIs/deemed FPIs in derivatives. 3. The total value of ODIs excludes the unhedged positions & portfolio hedging positions taken by the FPIs/deemed FPIs issuing ODIs.
A7: $ indicates as on April 30,2019
A8: Source: SEBI.

Sheet 55
A1: Table 55: Assets under the Custody of Custodians
A2: Type of Client | B2: FPIs | D2: Foreign Depositories | F2: FDI Investments | H2: Foreign Venture Capital Investments | J2: OCBs | L2: NRIs | N2: Mutual Funds | P2: Corporates | R2: Banks | T2: Insurance Companies | V2: Local Pension Funds | X2: Financial Institutions | Z2: Others | AB2: Total
B3: No. | C3: Amount (` crore) | D3: No. | E3: Amount (`crore) | F3: No. | G3: Amount (`crore) | H3: No. | I3: Amount (`crore) | J3: No. | K3: Amount (`crore) | L3: No. | M3: Amount (`crore) | N3: No. | O3: Amount (`crore) | P3: No. | Q3: Amount (`crore) | R3: No. | S3: Amount (`crore) | T3: No. | U3: Amount (`crore) | V3: No. | W3: Amount (`crore) | X3: No. | Y3: Amount (`crore) | Z3: No. | AA3: Amount (`crore) | AB3: No. | AC3: Amount (`crore)
A4: 2018-19 | B4: 9556 | C4: 3342680.3 | D4: 64 | E4: 354339.64 | F4: 1867 | G4: 802859.99 | H4: 201 | I4: 37261.17 | J4: 24 | K4: 1948.99 | L4: 547 | M4: 3485.82 | N4: 1755 | O4: 2278220.4 | P4: 499 | Q4: 104563.22 | R4: 117 | S4: 320444.7 | T4: 781 | U4: 1732889 | V4: 120 | W4: 422316.79 | X4: 25 | Y4: 60865.9 | Z4: 19018 | AA4: 791087.54 | AB4: 34574 | AC4: 10252963
A5: 2019-20$ | B5: 9518 | C5: 3355044.8 | D5: 64 | E5: 354291.66 | F5: 1895 | G5: 813049.09 | H5: 201 | I5: 37267.92 | J5: 24 | K5: 1967.08 | L5: 554 | M5: 3477.48 | N5: 1739 | O5: 2323169.1 | P5: 499 | Q5: 102763.88 | R5: 117 | S5: 329869.38 | T5: 783 | U5: 1738754.5 | V5: 126 | W5: 427419.72 | X5: 25 | Y5: 61094.24 | Z5: 19296 | AA5: 795703.08 | AB5: 34841 | AC5: 10343872
A6: Apr-19 | B6: 9518 | C6: 3355044.8 | D6: 64 | E6: 354291.66 | F6: 1895 | G6: 813049.09 | H6: 201 | I6: 37267.92 | J6: 24 | K6: 1967.08 | L6: 554 | M6: 3477.48 | N6: 1739 | O6: 2323169.1 | P6: 499 | Q6: 102763.88 | R6: 117 | S6: 329869.38 | T6: 783 | U6: 1738754.5 | V6: 126 | W6: 427419.72 | X6: 25 | Y6: 61094.24 | Z6: 19296 | AA6: 795703.08 | AB6: 34841 | AC6: 10343872
A7: Notes: 1. With the commencement of FPI Regime from June 1, 2014, the erstwhile FIIs, Sub Accounts and QFIs are merged into a new investor class termed as .Foreign Portfolio Investors (FPIs)..
A8: 2. "Others" include Portfolio manager, partnership firm, trusts, depository receipts, AIFs, FCCB, HUFs, Brokers etc.
A9: $ indicates as on April 30,2019
A10: Source: Custodians.

Sheet 56
A1: Table 56: Trends in Resource Mobilization by Mutual Funds (` crore)
A2: Year / Month | B2: Gross Mobilisation | E2: Redemption | H2: Net Inflow/ Outflow | K2: Assets at the End of Period
B3: Pvt. Sector | C3: Public Sector | D3: Total | E3: Pvt. Sector | F3: Public Sector | G3: Total | H3: Pvt. Sector | I3: Public Sector | J3: Total
A4: 2018-19 | B4: 19652989 | C4: 4741373.7 | D4: 24394362 | E4: 19591483 | F4: 4693177.6 | G4: 24284661 | H4: 61505.297 | I4: 48196.106 | J4: 109701.4 | K4: 2379662.9
A5: 2019-20$ | B5: 1507089.1 | C5: 366427.04 | D5: 1873516.1 | E5: 1441199.1 | F5: 331857.31 | G5: 1773056.4 | H5: 65890.008 | I5: 34569.723 | J5: 100459.73 | K5: 2478756.9
A6: Apr-19 | B6: 1507089.1 | C6: 366427.04 | D6: 1873516.1 | E6: 1441199.1 | F6: 331857.31 | G6: 1773056.4 | H6: 65890.008 | I6: 34569.723 | J6: 100459.73 | K6: 2478756.9
A7: $ indicates as on April 30,2019
A8: Source: SEBI.

Sheet 57
A1: Table 57: Status of Mutual Funds Industry in India (` crore)
I2: Rs. in crore
A3: Sr. No. | B3: Scheme Category | C3: No. of schemes as on April 30, 2019 | D3: No. of Folios as on April 30, 2019 | E3: Funds mobilized for the period (Since April 01, 2019 to April 30, 2019) | F3: Repurchase/ Redemption for the period (Since April 01, 2019 to April 30, 2019) | G3: Net Inflow (+ve)/ Outflow (-ve) for the period (Since April 01, 2019 to April 30, 2019) | H3: Net Assets Under Management as on (Since April 01, 2019 to April 30, 2019) | I3: Average Net Assets under Management for the month April 2019
A4: A | B4: Open ended Schemes
A5: I | B5: Income/Debt Oriented Schemes
A6: 1 | B6: Overnight Fund | C6: 16 | D6: 21363 | E6: 31582.996 | F6: 31487.26 | G6: 95.73558 | H6: 11309.754 | I6: 11566.842
A7: 2 | B7: Liquid Fund | C7: 40 | D7: 1451293 | E7: 1741122.9 | F7: 1651344.4 | G7: 89778.434 | H7: 477842.96 | I7: 510923.83
A8: 3 | B8: Ultra Short Duration Fund | C8: 25 | D8: 591392 | E8: 21187.243 | F8: 10149.981 | G8: 11037.262 | H8: 87144.674 | I8: 86203.309
A9: 4 | B9: Low Duration Fund | C9: 26 | D9: 922455 | E9: 13428.886 | F9: 8515.5389 | G9: 4913.3473 | H9: 89821.938 | I9: 90672.654
A10: 5 | B10: Money Market Fund | C10: 16 | D10: 284325 | E10: 14309.151 | F10: 7890.6311 | G10: 6418.52 | H10: 59017.647 | I10: 59200.304
A11: 6 | B11: Short Duration Fund | C11: 29 | D11: 263140 | E11: 5214.5393 | F11: 2443.9649 | G11: 2770.5744 | H11: 80720.93 | I11: 80722.693
A12: 7 | B12: Medium Duration Fund | C12: 17 | D12: 243389 | E12: 698.44444 | F12: 1229.3361 | G12: -530.8917 | H12: 36556.277 | I12: 37329.081
A13: 8 | B13: Medium to Long Duration Fund | C13: 13 | D13: 103875 | E13: 465.77118 | F13: 201.62716 | G13: 264.14402 | H13: 10127.504 | I13: 10034.242
A14: 9 | B14: Long Duration Fund | C14: 2 | D14: 18687 | E14: 21.645728 | F14: 13.58488 | G14: 8.0608479 | H14: 1130.4137 | I14: 1125.2904
A15: 10 | B15: Dynamic Bond Fund | C15: 28 | D15: 212622 | E15: 984.87354 | F15: 572.90204 | G15: 411.9715 | H15: 19861.099 | I15: 19881.428
A16: 11 | B16: Corporate Bond Fund | C16: 21 | D16: 193906 | E16: 6078.4448 | F16: 2204.0461 | G16: 3874.3986 | H16: 61329.495 | I16: 60431.668
A17: 12 | B17: Credit Risk Fund | C17: 20 | D17: 576015 | E17: 994.87666 | F17: 2248.1601 | G17: -1253.2835 | H17: 79643.89 | I17: 80756.804
... A21: 16 | B21: Floater Fund | C21: 7 | D21: 133693 | E21: 2068.572 | F21: 1720.8436 | G21: 347.72836 | H21: 30058.009 | I21: 30140.441
B22: Sub total - I (1+2+3+4+5+6+7+8+9+10+11+12+13+14+15+16) | C22: 303 | D22: 5176072 | E22: 1841848.7 | F22: 1720928.3 | G22: 120920.4 | H22: 1088340.1 | I22: 1121697.2
A24: II | B24: Growth/Equity Oriented Schemes
A25: 17 | B25: Multi Cap Fund | C25: 34 | D25: 8718034 | E25: 4371.4139 | F25: 2498.3518 | G25: 1873.0622 | H25: 152056.4 | I25: 151782.16
A26: 18 | B26: Large Cap Fund | C26: 29 | D26: 8179430 | E26: 2627.1116 | F26: 2578.8414 | G26: 48.270207 | H26: 126595.93 | I26: 126132.41
A27: 19 | B27: Large & Mid Cap Fund | C27: 24 | D27: 4352083 | E27: 1179.3823 | F27: 1199.8863 | G27: -20.504 | H27: 51426.529 | I27: 51506.078
A28: 20 | B28: Mid Cap Fund | C28: 24 | D28: 6128989 | E28: 2060.4613 | F28: 1569.4228 | G28: 491.03849 | H28: 75058.47 | I28: 75976.242
A29: 21 | B29: Small Cap Fund | C29: 20 | D29: 4946766 | E29: 1772.5988 | F29: 816.77181 | G29: 955.82696 | H29: 43872.109 | I29: 44279.323
A30: 22 | B30: Dividend Yield Fund | C30: 6 | D30: 505530 | E30: 27.888808 | F30: 59.921406 | G30: -32.032598 | H30: 4825.604 | I30: 4839.7036
A31: 23 | B31: Value Fund/Contra Fund | C31: 18 | D31: 4465360 | E31: 1131.5975 | F31: 1091.9108 | G31: 39.686678 | H31: 58196.251 | I31: 58522.089
A32: 24 | B32: Focused Fund | C32: 18 | D32: 2865887 | E32: 1086.2126 | F32: 858.64284 | G32: 227.56978 | H32: 37392.525 | I32: 37121.877
A33: 25 | B33: Sectoral/Thematic Funds | C33: 91 | D33: 6317911 | E33: 1829.1224 | F33: 1261.9505 | G33: 567.17191 | H33: 62082.454 | I33: 62238.717
A34: 26 | B34: ELSS | C34: 43 | D34: 11484832 | E34: 1353.7479 | F34: 895.0965 | G34: 458.65144 | H34: 92043.505 | I34: 91930.224
B35: Sub total - II (17+18+19+20+21+22+23+24+25+26) | C35: 307 | D35: 57964822 | E35: 17439.537 | F35: 12830.796 | G35: 4608.741 | H35: 703549.78 | I35: 704328.83
A37: III | B37: Hybrid Schemes
A38: 27 | B38: Conservative Hybrid Fund | C38: 22 | D38: 439456 | E38: 124.59366 | F38: 363.99489 | G38: -239.40123 | H38: 15227.816 | I38: 15401.514
A39: 28 | B39: Balanced Hybrid Fund/Aggressive Hybrid Fund | C39: 31 | D39: 5526783 | E39: 2215.6637 | F39: 4337.0736 | G39: -2121.4099 | H39: 146292.12 | I39: 148599.3
A40: 29 | B40: Dynamic Asset Allocation/Balanced Advantage | C40: 20 | D40: 2458452 | E40: 2036.3633 | F40: 1881.7099 | G40: 154.65336 | H40: 92832.567 | I40: 93265.247
A41: 30 | B41: Multi Asset Allocation | C41: 8 | D41: 614524 | E41: 276.17557 | F41: 505.79878 | G41: -229.6232 | H41: 12610.236 | I41: 12904.687
A42: 31 | B42: Arbitrage Fund | C42: 23 | D42: 252394 | E42: 5327.3794 | F42: 3798.3361 | G42: 1529.0433 | H42: 50494.587 | I42: 50839.106
A43: 32 | B43: Equity Savings Fund | C43: 22 | D43: 364908 | E43: 278.90688 | F43: 986.99841 | G43: -708.09154 | H43: 18749.294 | I43: 19258.736
B44: Sub total - III (27+28+29+30+31+32) | C44: 126 | D44: 9656517 | E44: 10259.082 | F44: 11873.912 | G44: -1614.8292 | H44: 336206.62 | I44: 340268.6
A46: IV | B46: Solution Oriented Schemes
A47: 33 | B47: Retirement Fund | C47: 21 | D47: 2497702 | E47: 184.44736 | F47: 58.590132 | G47: 125.85722 | H47: 8376.1914 | I47: 8360.391
A48: 34 | B48: Childrens' Fund | C48: 9 | D48: 2790432 | E48: 72.557509 | F48: 41.120086 | G48: 31.437423 | H48: 8101.5763 | I48: 8130.675
B49: Sub total - IV (33+34) | C49: 30 | D49: 5288134 | E49: 257.00486 | F49: 99.710218 | G49: 157.29465 | H49: 16477.768 | I49: 16491.066
A51: V | B51: Other Schemes
A52: 35 | B52: Index Funds | C52: 25 | D52: 288137 | E52: 261.65696 | F52: 243.72354 | G52: 17.933421 | H52: 5286.3403 | I52: 5255.2655
A53: 36 | B53: GOLD ETFs | C53: 12 | D53: 319863 | E53: 4.5288897 | F53: 14.232663 | G53: -9.7037733 | H53: 4594.0642 | I53: 4479.9182
A54: 37 | B54: Other ETFs | C54: 67 | D54: 906290 | E54: 3007.1218 | F54: 7266.4152 | G54: -4259.2933 | H54: 131188.71 | I54: 132591.42
A55: 38 | B55: Fund of funds investing overseas | C55: 29 | D55: 125594 | E55: 53.930245 | F55: 33.307301 | G55: 20.622945 | H55: 1951.049 | I55: 1913.0906
B56: Sub total - V (35+36+37+38) | C56: 133 | D56: 1639884 | E56: 3327.2379 | F56: 7557.6787 | G56: -4230.4407 | H56: 143020.16 | I56: 144239.7
B58: Total A-Open ended Schemes | C58: 899 | D58: 79725429 | E58: 1873131.5 | F58: 1753290.4 | G58: 119841.16 | H58: 2287594.4 | I58: 2327025.4
A60: B | B60: Close Ended Schemes
A61: I | B61: Income/Debt Oriented Schemes
A62: i | B62: Fixed Term Plan | C62: 800 | D62: 916839 | E62: 384.45072 | F62: 18028.866 | G62: -17644.415 | H62: 141170.58 | I62: 149375.47
A63: ii | B63: Capital Protection Oriented Schemes | C63: 41 | D63: 147978 | E63: 0 | F63: 607.66936 | G63: -607.66936 | H63: 5572.4235 | I63: 5771.1244
A64: iii | B64: Infrastructure Debt Fund | C64: 9 | D64: 89 | E64: 0 | F64: 314.72243 | G64: -314.72243 | H64: 2348.6472 | I64: 2661.9668
A65: iv | B65: Other Debt | C65: 62 | D65: 134275 | E65: 0 | F65: 382.94808 | G65: -382.94808 | H65: 5509.7463 | I65: 5841.5843
B66: Sub total (i+ii+iii+iv) | C66: 912 | D66: 1199181 | E66: 384.45072 | F66: 19334.206 | G66: -18949.755 | H66: 154601.4 | I66: 163650.15
A68: II | B68: Growth/Equity Oriented Schemes
A69: i | B69: ELSS | C69: 26 | D69: 504150 | E69: 0 | F69: 48.085688 | G69: -48.085688 | H69: 4506.0372 | I69: 4564.4685
A70: ii | B70: Others | C70: 102 | D70: 1290925 | E70: -1e-05 | F70: 331.1787 | G70: -331.17871 | H70: 29654.46 | I70: 29919.166
B71: Sub total (i+ii) | C71: 128 | D71: 1795075 | E71: -1e-05 | F71: 379.26438 | G71: -379.26439 | H71: 34160.497 | I71: 34483.634
A73: III | B73: Other Schemes | C73: 0 | D73: 0 | E73: 0 | F73: 0 | G73: 0 | H73: 0 | I73: 0
B75: Total B -Close ended Schemes | C75: 1040 | D75: 2994256 | E75: 384.45071 | F75: 19713.47 | G75: -19329.02 | H75: 188761.89 | I75: 198133.78
A77: C | B77: Interval Schemes
A78: I | B78: Income/Debt Oriented Schemes | C78: 27 | D78: 4636 | E78: 0.14799549 | F78: 52.561961 | G78: -52.413965 | H78: 1919.1724 | I78: 1992.8325
A80: II | B80: Growth/Equity Oriented Schemes | C80: 1 | D80: 12018 | E80: 0 | F80: 0 | G80: 0 | H80: 481.46959 | I80: 480.74746
A82: III | B82: Other Schemes | C82: 0 | D82: 0 | E82: 0 | F82: 0 | G82: 0 | H82: 0 | I82: 0
B84: Total C -Interval Schemes | C84: 28 | D84: 16654 | E84: 0.14799549 | F84: 52.561961 | G84: -52.413965 | H84: 2400.642 | I84: 2473.58
B86: Grand Total (A+B+C) | C86: 1967 | D86: 82736339 | E86: 1873516.1 | F86: 1773056.4 | G86: 100459.73 | H86: 2478756.9 | I86: 2527632.8
B88: Fund of Funds Scheme (Domestic) | C88: 42 | D88: 438895 | E88: 572.76837 | F88: 80.745484 | G88: 492.02288 | H88: 4794.628 | I88: 4604.5907
B90: No.of schemes also includes serial plans.
A91: Notes: | B91: #AAUM of the mutual fund is the average of the daily AUM of the Mutual Fund for the month.
B92: Inter scheme investments are excluded from the above data

Sheet 58
A1: Table 58: Trends in Transactions on Stock Exchanges by Mutual Funds (`crore)
A2: Year/ Month | B2: Equity | E2: Debt | H2: Total
B3: Gross Purchases | C3: Gross Sales | D3: Net Purchases /Sales | E3: Gross Purchases | F3: Gross Sales | G3: Net Purchases /Sales | H3: Gross Purchases | I3: Gross Sales | J3: Net purchases /Sale
A4: 2018-19 | B4: 708991.25 | C4: 621112.49 | D4: 87878.76 | E4: 2267415.5 | F4: 1877490.3 | G4: 418096.31 | H4: 2976406.8 | I4: 2498602.8 | J4: 505975.07
A5: 2019-20$ | B5: 46931.89 | C5: 51531.55 | D5: -4599.66 | E5: 226460.99 | F5: 175640.89 | G5: 50820.1 | H5: 273392.88 | I5: 227172.44 | J5: 46220.44
A6: Apr-19 | B6: 46931.89 | C6: 51531.55 | D6: -4599.66 | E6: 226460.99 | F6: 175640.89 | G6: 50820.1 | H6: 273392.88 | I6: 227172.44 | J6: 46220.44
A7: $ indicates as on April 30,2019
A8: Source: SEBI

Sheet 59
A1: Table 59: Assets Under Management by Portfolio Managers
A2: Year / Month | B2: 2018-19 | C2: 2018-19 | D2: 2018-19 | E2: 2019-20$ | F2: 2019-20$ | G2: 2019-20$
A3: Particulars | B3: Discretionary | C3: Non-Discretionary | D3: Advisory | E3: Discretionary | F3: Non-Discretionary | G3: Advisory
A4: No. of Clients | B4: 138829 | C4: 6853 | D4: 4038 | E4: 140583 | F4: 7025 | G4: 4010
A5: AUM (` crore)
A6: Listed Equity | B6: 111995.61 | C6: 18477.08 | D6: 193620 | E6: 111043.03 | F6: 18587.98 | G6: 184606.81
A7: Unlisted Equity | B7: 458.85 | C7: 74.69 | E7: 481.8 | F7: 78.29
A8: Plain Debt | B8: 1160856.7 | C8: 74701.85 | E8: 1041125.6 | F8: 76272.67
A9: Structured Debt | B9: 752.86 | C9: 530.57 | E9: 1014.51 | F9: 578.67
A10: Equity Derivatives | B10: 466.12 | C10: -1.24 | E10: 461.83 | F10: -1.26
A11: Mutual Funds | B11: 14112.76 | C11: 13856.15 | E11: 11108.57 | F11: 13737.02
A12: Others | B12: 14498.29 | C12: 1392.08 | E12: 9755.16 | F12: 1503.66
A13: Total | B13: 1303141.2 | C13: 109031.18 | E13: 1174990.5 | F13: 110757.03
A14: Notes:1. *Value of Assets for which Advisory Services are being given.2.�#Of the above AUM�Rs. 1035966.99 Crore�is contributed by funds from EPFO/PFs.3. The above data is based on the monthly reports received from portfolio managers.
A15: $ indicates as on April 30,2019
A16: Source: SEBI.

Sheet 60
A1: Table 60: Progress Report of NSDL & CDSL as on end of Apr-19 (Listed Companies)
A2: Parameter | B2: Unit | C2: NSDL | H2: CDSL
C3: Apr-19 | D3: Mar-19 | E3: Apr-18 | F3: % Change during the year | G3: % Change during the month | H3: Apr-19 | I3: Mar-19 | J3: Apr-18 | K3: % Change during the year | L3: % Change during the month
A4: Number of companies signed up to make their shares available for dematerialization | B4: Number | C4: 6168 | D4: 6150 | E4: 5949 | F4: 3.681291 | G4: 0.29268293 | H4: 5763 | I4: 6407 | J4: 6766 | K4: -14.82 | L4: -10.05 | N4: Number of companies signed up to make their shares available for dematerialization
A5: Number of Depository Participants (registered) | B5: Number | C5: 278 | D5: 277 | E5: 277 | F5: 0.36101083 | G5: 0.36101083 | H5: 598 | I5: 597 | J5: 601 | K5: -0.49 | L5: 0.17 | N5: Number of Depository Participants (registered)
A6: Number of Stock Exchanges (connected) | B6: Number | C6: 3 | D6: 3 | E6: 3 | F6: 0 | G6: 0 | H6: 3 | I6: 3 | J6: 3 | K6: 0 | L6: 0 | N6: Number of Stock Exchanges (connected)
A7: Number of Investors Accounts | B7: Lakh | C7: 185.99864 | D7: 185.22418 | E7: 171.51831 | F7: 8.4424398 | G7: 0.41812036 | H7: 175.75 | I7: 173.86 | J7: 149.9 | K7: 17.24 | L7: 1.09 | N7: Number of Investors Accounts
A8: Quantity of Shares dematerialized | B8: Crore | C8: 53170.958 | D8: 53156.456 | E8: 50265.097 | F8: 5.7810704 | G8: 0.027282241 | H8: 18747.95 | I8: 17660.03 | J8: 15778.1 | K8: 18.82 | L8: 6.16 | N8: Quantity of Shares dematerialized
A9: Value of Shares dematerialized | B9: Crore | C9: 13188180 | D9: 13113010 | E9: 13199167 | F9: -0.083241868 | G9: 0.57324644 | H9: 1753987.9 | I9: 1757785.2 | J9: 1863506.4 | K9: -5.88 | L9: -0.22 | N9: Value of Shares dematerialized
A10: Quantity of Securities dematerialized # | B10: Crore | C10: 57157.107 | D10: 57208.252 | E10: 53628.809 | F10: 6.5791096 | G10: -0.089402082 | H10: 20397.73 | I10: 19301.26 | J10: 16958.69 | K10: 20.28 | L10: 5.68 | N10: Quantity of Securities dematerialized #
A11: Value of Securities dematerialized # | B11: Crore | C11: 16011891 | D11: 15895016 | E11: 15771880 | F11: 1.5217635 | G11: 0.73529657 | H11: 1881605.2 | I11: 1882388.2 | J11: 1960970.3 | K11: -4.05 | L11: -0.04 | N11: Value of Securities dematerialized #
A12: Quantity of shares settled during the month | B12: Crore | C12: 1026.0136 | D12: 1183.802 | E12: 938.01224 | F12: 9.3816892 | G12: -13.328946 | H12: 577.45 | I12: 669.37 | J12: 654.44 | K12: -11.76 | L12: -13.73 | N12: Quantity of shares settled during the month
A13: Average Quantity of shares settled daily (quantity of shares settled during the month (divided by 30)) | B13: Crore | C13: 57.000757 | D13: 62.305366 | E13: 49.369065 | F13: 15.45845 | G13: -8.5138875 | H13: 19.25 | I13: 21.59 | J13: 21.81 | K13: -11.76 | L13: -10.86 | N13: Average Quantity of shares settled daily (quantity of shares settled during the month (divided by 30))
A14: Value of shares settled during the month in dematerialized form | B14: Crore | C14: 255007.72 | D14: 298773.53 | E14: 243371.86 | F14: 4.7811052 | G14: -14.648488 | H14: 54026.42 | I14: 67847.91 | J14: 69659.41 | K14: -22.44 | L14: -20.37 | N14: Value of shares settled during the month in dematerialized form
A15: Average Value of shares settled daily (value of shares settled during the month (divided by 30)) | B15: Crore | C15: 14167.096 | D15: 15724.923 | E15: 12809.045 | F15: 10.602278 | G15: -9.9067373 | H15: 1800.88 | I15: 2188.64 | J15: 2321.98 | K15: -22.44 | L15: -17.72 | N15: Average Value of shares settled daily (value of shares settled during the month (divided by 30))
... A17: The ratio of dematerialized equity shares to the total outstanding shares market value | B17: Percent | C17: 86.769889 | D17: 86.575852 | E17: 86.833108 | F17: -0.072804636 | G17: 0.22412372 | H17: 11.48 | I17: 11.57 | J17: 12.87 | K17: -10.8 | L17: -0.78 | N17: The ratio of dematerialized equity shares to the total outstanding shares (market value)
A18: Notes: 1. Shares includes only equity shares. 2. Securities include common equity shares, preference shares, debenture, MF units, etc. 3. No. of days taken for calculating Daily Average is 30 days instead of Actual settlement days. 4. Quantity and value of shares mentioned are single sided. 5. #Source for listed securities information: Issuer/ NSE/BSE.
A19: Source: NSDL and CDSL.

Sheet 61
A1: Table 61: Progress of Dematerialisation at NSDL and CDSL (Listed and Unlisted Companies)
A2: Year/ Month | B2: NSDL | G2: CDSL
B3: Companies Live | C3: DPs Live | D3: DPs Locations | E3: Demat Quantity (million securities) | F3: Demat Value (` crore) | G3: Companies Live | H3: DPs Live | I3: DPs Locations | J3: Demat Quantity (million securities) | K3: Demat Value (` crore)
A4: 2018-19 | B4: 25233 | C4: 277 | D4: 30741 | E4: 1867407.6 | F4: 18680372 | G4: 12757 | H4: 597 | I4: 19460 | J4: 361876.12 | K4: 2079693.5
A5: 2019-20$ | B5: 25841 | C5: 278 | D5: 30898 | E5: 1898007 | F5: 18846586 | G5: 13009 | H5: 598 | I5: 19461 | J5: 373897.06 | K5: 2079779.4
A6: Apr-19 | B6: 25841 | C6: 278 | D6: 30898 | E6: 1898007 | F6: 18846586 | G6: 13009 | H6: 598 | I6: 19461 | J6: 373897.06 | K6: 2079779.4
A7: Notes : 1. For CDSL, the current and historical data of Companies Live has been revised to exclude MF schemes count. 2. The Companies Live figure includes only the number of mutual fund companies and not the mutual fund schemes. 3. DPs Locations represents the total live (main DPs and branch DPs as well as non-live (back office connected collection centres).
A8: * Includes Nine Participants which are under closure/termination process and SEBI registration is not yet cancelled/suspended
A9: Source: NSDL and CDSL.

Sheet 62
A1: Table 62: Depository Statistics as on Apr-19
A2: Particulars | B2: Unit | C2: Debt | E2: Equity | G2: Others | I2: Total
C3: Listed | D3: Unlisted | E3: Listed | F3: Unlisted | G3: Listed | H3: Unlisted | I3: Listed | J3: Unlisted
A4: NSDL
A5: No.of issuers debt/Companies(equity) | B5: (numbers) | C5: 717 | D5: 1848 | E5: 6168 | F5: 16302 | G5: 74 | H5: 4725 | I5: 6959 | J5: 22875
A6: No.of Active Instruments | B6: (numbers) | C6: 10568 | D6: 6293 | E6: 12532 | F6: 16984 | G6: 8466 | H6: 33024 | I6: 31566 | J6: 56301
A7: Demat Quantity | B7: (lakhs) | C7: 115001.1 | D7: 469550.04 | E7: 5317095.8 | F7: 8611035.3 | G7: 283613.79 | H7: 4183774.5 | I7: 5715710.7 | J7: 13264360
A8: Demat Value | B8: (Rs.Crore) | C8: 2616898.7 | D8: 492034.57 | E8: 13188180 | F8: 877736.35 | G8: 206812.46 | H8: 1464924.5 | I8: 16011891 | J8: 2834695.4
A9: Quantity settled during the month | B9: (Lakh) | C9: 14633.835 | D9: 9593.1078 | E9: 102601.36 | F9: 41.12482 | G9: 8344.4069 | H9: 1111.0535 | I9: 125579.6 | J9: 10745.286
A10: Value Settled during the month | B10: (Rs.Crores) | C10: 566545.25 | D10: 14579.056 | E10: 255007.72 | F10: 50.317951 | G10: 3555.6968 | H10: 288.16463 | I10: 825108.67 | J10: 14917.539
A11: CDSL
A12: No. of Issuers (Debt) / Companies (Equity) | B12: (numbers) | C12: 558 | D12: 404 | E12: 5763 | F12: 6167 | G12: 2472 | H12: 558 | I12: 8793 | J12: 7129
A13: No. of Active Instruments | B13: (numbers) | C13: 8092 | D13: 2238 | E13: 5898 | F13: 6413 | G13: 19500 | H13: 1976 | I13: 33490 | J13: 10627
A14: Demat Quantity | B14: (lakh) | C14: 2981.36 | D14: 97214.01 | E14: 1874795.1 | F14: 1440957.4 | G14: 161996.79 | H14: 161026.03 | I14: 2039773.2 | J14: 1699197.4
A15: Demat Value | B15: (Rs.crore) | C15: 63183.01 | D15: 33668.61 | E15: 1753987.9 | F15: 139703.88 | G15: 64434.25 | H15: 24801.77 | I15: 1881605.2 | J15: 198174.27
A16: Quantity settled during the month | B16: (lakh) | C16: 30.3 | D16: 0 | E16: 57744.94 | F16: 0 | G16: 22217.69 | H16: 0 | I16: 79992.92 | J16: 0
A17: Value Settled during the month | B17: (Rs.crore) | C17: 2436.23 | D17: 0 | E17: 54026.42 | F17: 0 | G17: 12497.81 | H17: 0 | I17: 68960.46 | J17: 0
A18: Note: The categories included in Others are Preference Shares, Mutual Fund Units, Warrants, PTCs, Treasury Bills, CPs, CDs and Government Securities.
A19: Source: NSDL and CDSL.

Sheet 63
A1: Table 63: Number of commodities permitted and traded at exchanges
A2: Exchanges | B2: Particulars | C2: Futures | H2: Options
C3: Agriculture | D3: Metals other than bullion | E3: Bullion | F3: Energy | G3: Gems and Stones | H3: Agriculture | I3: Metals other than bullion | J3: Bullion | K3: Energy
A4: NCDEX | B4: Permitted for trading | C4: 18 | D4: 2 | E4: 1 | F4: 1 | G4: 0 | H4: 5 | I4: 0 | J4: 0 | K4: 0
B5: Contracts floated | C5: 18 | D5: 0 | E5: 0 | F5: 0 | G5: 0 | H5: 5 | I5: 0 | J5: 0 | K5: 0
B6: Traded | C6: 15 | D6: 0 | E6: 0 | F6: 0 | G6: 0 | H6: 2 | I6: 0 | J6: 0 | K6: 0
A7: MCX | B7: Permitted for trading | C7: 8 | D7: 6 | E7: 3 | F7: 2 | G7: 0 | H7: 0 | I7: 2 | J7: 2 | K7: 1
B8: Contracts floated | C8: 7 | D8: 6 | E8: 2 | F8: 2 | G8: 0 | H8: 0 | I8: 2 | J8: 2 | K8: 1
B9: Traded | C9: 4 | D9: 5 | E9: 2 | F9: 2 | G9: 0 | H9: 0 | I9: 2 | J9: 2 | K9: 1
A10: ICEX | B10: Permitted for trading | C10: 12 | D10: 1 | E10: 0 | F10: 0 | G10: 1 | H10: 0 | I10: 0 | J10: 0 | K10: 0
B11: Contracts floated | C11: 11 | D11: 1 | E11: 0 | F11: 0 | G11: 1 | H11: 0 | I11: 0 | J11: 0 | K11: 0
B12: Traded | C12: 2 | D12: 1 | E12: 0 | F12: 0 | G12: 1 | H12: 0 | I12: 0 | J12: 0 | K12: 0
A13: BSE | B13: Permitted for trading | C13: 3 | D13: 1 | E13: 2 | F13: 1 | G13: 0 | H13: 0 | I13: 0 | J13: 0 | K13: 0
B14: Contracts floated | C14: 3 | D14: 1 | E14: 2 | F14: 1 | G14: 0 | H14: 0 | I14: 0 | J14: 0 | K14: 0
B15: Traded | C15: 2 | D15: 1 | E15: 2 | F15: 0 | G15: 0 | H15: 0 | I15: 0 | J15: 0 | K15: 0
A16: NSE | B16: Permitted for trading | C16: 0 | D16: 1 | E16: 2 | F16: 1 | G16: 0 | H16: 0 | I16: 0 | J16: 0 | K16: 0
B17: Contracts floated | C17: 0 | D17: 0 | E17: 2 | F17: 1 | G17: 0 | H17: 0 | I17: 0 | J17: 0 | K17: 0
B18: Traded | C18: 0 | D18: 0 | E18: 2 | F18: 1 | G18: 0 | H18: 0 | I18: 0 | J18: 0 | K18: 0
A19: Source: NCDEX, MCX, ICEX, BSE and NSE

Sheet 64
A1: Table 64: Trends in commodity indices
A2: Year/ Month | B2: MCX Comdex | F2: NCDEX Dhaanya
B3: Open | C3: High | D3: Low | E3: Close | F3: Open | G3: High | H3: Low | I3: Close
A4: 2018-19 | B4: 3662.99 | C4: 4172 | D4: 3312 | E4: 3739 | F4: 3051.23 | G4: 3590 | H4: 2838 | I4: 3414
A5: 2019-20$ | B5: 3742.4 | C5: 3839.61 | D5: 3742.4 | E5: =E6 -> 3769.31 | F5: 3450.3 | G5: 3604.18 | H5: 3450.33 | I5: =I6 -> 3500.82
A6: 43556 | B6: 3742.4 | C6: 3839.61 | D6: 3742.4 | E6: 3769.31 | F6: 3450.3 | G6: 3604.18 | H6: 3450.33 | I6: 3500.82
A7: ='[1]1'!A8 -> $ indicates as on April 30, 2019
A8: Source: MCX and NCDEX

Sheet 65
A1: Table 65: Trends in commodity derivatives at MCX
A2: FUTURES
A3: Year/ Month | B3: No.of Trading days | C3: Agriculture | F3: Metals | I3: Bullion | L3: Energy | O3: Total | Q3: Open interest at the end of the period
C4: Volume ('000 tonnes) | D4: No. of contracts traded | E4: Turnover (₹ crore) | F4: Volume ('000 tonnes) | G4: No. of contracts traded | H4: Turnover (₹ crore) | I4: Volume ('000 tonnes) | J4: No. of contracts traded | K4: Turnover (₹ crore) | L4: Volume ('000 tonnes)* | M4: No. of contracts traded | N4: Turnover (₹ crore) | O4: No. of contracts traded | P4: Turnover (₹ crore) | Q4: No. of contracts | R4: Value (₹ crore)
A5: 2018-19 | B5: 257 | C5: 9662.0727 | D5: 1828722 | E5: 101232.76 | F5: 111474.84 | G5: 78835865 | H5: 2525601.2 | I5: 168.65428 | J5: 28837833 | K5: 1513817.3 | L5: 671698.23 | M5: 136946607 | N5: 2450777.1 | O5: 246449027 | P5: 6591428.4 | Q5: 313641 | R5: 14243.599
A6: 2019-20$ | B6: 20 | C6: 991.38809 | D6: 196632 | E6: 10805.72 | F6: 7029.8468 | G6: 5565142 | H6: 172972.52 | I6: 15.129268 | J6: 2516285 | K6: 129663.01 | L6: 62102.357 | M6: 12417788 | N6: 213671.81 | O6: 20695847 | P6: 527113.06 | Q6: 318726 | R6: =R7 -> 13840.079
A7: 43556 | B7: 20 | C7: 991.38809 | D7: 196632 | E7: 10805.72 | F7: 7029.8468 | G7: 5565142 | H7: 172972.52 | I7: 15.129268 | J7: 2516285 | K7: 129663.01 | L7: 62102.357 | M7: 12417788 | N7: 213671.81 | O7: 20695847 | P7: 527113.06 | Q7: 318726 | R7: 13840.079
A8: OPTIONS
A9: Year / Month | B9: No.of Trading days | C9: Metals | G9: Bullion | K9: Energy | O9: Total | Q9: Open interest at the end of the period
C10: Call Options | E10: Put Options | G10: Call Options | I10: Put Options | K10: Call Options | M10: Put Options | O10: No. of contracts | P10: Turnover (₹ crore) | Q10: No. of contracts | R10: Notional Value (₹ crore)
C11: No. of contracts | D11: Turnover (₹ crore) | E11: No. of contracts | F11: Turnover (₹ crore) | G11: No. of contracts | H11: Turnover (₹ crore) | I11: No. of contracts | J11: Turnover (₹ crore) | K11: No. of contracts | L11: Turnover (₹ crore) | M11: No. of contracts | N11: Turnover (₹ crore)
A12: 2018-19 | B12: 257 | C12: 69152 | D12: 3701.0513 | E12: 54509 | F12: 2791.6585 | G12: 265487 | H12: 75209.556 | I12: 207148 | J12: 60490.5 | K12: 480193 | L12: 20896.828 | M12: 418758 | N12: 17854.906 | O12: 1495517 | P12: 180944.5 | Q12: 9471 | R12: 802.06
A13: 2019-20$ | B13: 20 | C13: 4633 | D13: 324.85 | E13: 5480 | F13: 417.92 | G13: 11545 | H13: 2283.17 | I13: 6547 | J13: 1510.86 | K13: 42154 | L13: 1919.28 | M13: 51136 | N13: 2229.16 | O13: 121495 | P13: 8685.25 | Q13: 6962 | R13: =R14 -> 907.8
A14: 43556 | B14: 20 | C14: 4633 | D14: 324.85 | E14: 5480 | F14: 417.92 | G14: 11545 | H14: 2283.17 | I14: 6547 | J14: 1510.86 | K14: 42154 | L14: 1919.28 | M14: 51136 | N14: 2229.16 | O14: 121495 | P14: 8685.25 | Q14: 6962 | R14: 907.8
A15: ='[1]1'!A8 -> $ indicates as on April 30, 2019
A16: Note : Natural Gas volume is in Trillion BTU and is not included in volume ('000 tonnes) of energy contracts.
A17: Source: MCX
B22: following is not for publications (verifications):
B23: annual total of TO | D23: Agir | E23: non-agri | F23: Total | H23: futures | I23: options | J23: total | K23: match
B25: Monthly totals of TO | D25: =E5+'66'!E5+'67'!E4+'66'!I5+'66'!K5 -> 647592.88 | E25: =P12+H5+K5+N5+'67'!K4+'67'!H4+'68'!P4+'69'!E4 -> 6730282.6 | F25: =D25+E25 -> 7377875.5 | H25: =P5+'66'!E5+'67'!M4+'68'!P4+'69'!E4 -> 7196756.3 | I25: =P12+'66'!I5+'66'!K5 -> 181118.36 | J25: =H25+I25 -> 7377874.6 | K25: =F25=J25 -> FALSE | M25: ='71'!D27+'71'!D39+'72'!D21+'72'!D28+'73'!D16+'73'!D26+'73'!D37+0.51 -> 593509.22
B26: 43191 | D26: =E7+'66'!E7+'67'!E6+'66'!I7+'66'!K7 -> 58822.545 | E26: =P14+H7+K7+N7+'67'!K6 -> 528669.95 | F26: =D26+E26 -> 587492.5 | H26: =P7+'66'!E7+'67'!M6 -> 579342.86 | I26: =P14+'66'!I7+'66'!K7 -> 8686.03 | J26: =H26+I26 -> 588028.89 | K26: =F26=J26 -> FALSE
B27: 43221 | D27: =#REF!+'66'!#REF!+'67'!#REF!+'66'!#REF!+'66'!#REF! -> #REF! | E27: =#REF!+#REF!+#REF!+#REF!+'67'!#REF! -> #REF! | F27: =D27+E27 -> #REF! | H27: =#REF!+'66'!#REF!+'67'!#REF! -> #REF! | I27: =#REF!+'66'!#REF!+'66'!#REF! -> #REF! | J27: =H27+I27 -> #REF! | K27: =F27=J27 -> #REF!
B28: 43252 | D28: =#REF!+'66'!#REF!+'67'!#REF!+'66'!#REF!+'66'!#REF! -> #REF! | E28: =#REF!+#REF!+#REF!+#REF!+'67'!#REF! -> #REF! | F28: =D28+E28 -> #REF! | H28: =#REF!+'66'!#REF!+'67'!#REF! -> #REF! | I28: =#REF!+'66'!#REF!+'66'!#REF! -> #REF! | J28: =H28+I28 -> #REF! | K28: =F28=J28 -> #REF!
B29: 43282 | D29: =#REF!+'66'!#REF!+'67'!#REF!+'66'!#REF!+'66'!#REF! -> #REF! | E29: =#REF!+#REF!+#REF!+#REF!+'67'!#REF! -> #REF! | F29: =D29+E29 -> #REF! | H29: =#REF!+'66'!#REF!+'67'!#REF! -> #REF! | I29: =#REF!+'66'!#REF!+'66'!#REF! -> #REF! | J29: =H29+I29 -> #REF! | K29: =F29=J29 -> #REF!
B30: 43313 | D30: =#REF!+'66'!#REF!+'67'!#REF!+'66'!#REF!+'66'!#REF! -> #REF! | E30: =#REF!+#REF!+#REF!+#REF!+'67'!#REF!+'67'!#REF! -> #REF! | F30: =D30+E30 -> #REF! | H30: =#REF!+'66'!#REF!+'67'!#REF! -> #REF! | I30: =#REF!+'66'!#REF!+'66'!#REF! -> #REF! | J30: =H30+I30 -> #REF! | K30: =F30=J30 -> #REF!
B31: 43344 | D31: =#REF!+'66'!#REF!+'67'!#REF!+'66'!#REF!+'66'!#REF! -> #REF! | E31: =#REF!+#REF!+#REF!+#REF!+'67'!#REF!+'67'!#REF!+'68'!P4+'69'!E4 -> #REF! | F31: =D31+E31 -> #REF! | H31: =#REF!+'66'!#REF!+'67'!#REF!+'68'!P4+'69'!E4 -> #REF! | I31: =#REF!+'66'!#REF!+'66'!#REF! -> #REF! | J31: =H31+I31 -> #REF! | K31: =F31=J31 -> #REF!
B32: 43380 | D32: =#REF!+'66'!#REF!+'67'!#REF!+'66'!#REF!+'66'!#REF! -> #REF! | E32: =#REF!+#REF!+#REF!+#REF!+'67'!#REF!+'67'!#REF!+'68'!P6+'69'!E6 -> #REF! | F32: =D32+E32 -> #REF! | H32: =#REF!+'66'!#REF!+'67'!#REF!+'68'!P6+'69'!E6 -> #REF! | I32: =#REF!+'66'!#REF!+'66'!#REF! -> #REF! | J32: =H32+I32 -> #REF! | K32: =F32=J32 -> #REF!
B33: 43405 | D33: =#REF!+'66'!#REF!+'67'!#REF!+'66'!#REF!+'66'!#REF! -> #REF! | E33: =#REF!+#REF!+#REF!+#REF!+'67'!#REF!+'67'!#REF!+'68'!#REF!+'69'!#REF! -> #REF! | F33: =D33+E33 -> #REF! | H33: =#REF!+'66'!#REF!+'67'!#REF!+'68'!#REF!+'69'!#REF! -> #REF! | I33: =#REF!+'66'!#REF!+'66'!#REF! -> #REF! | J33: =H33+I33 -> #REF! | K33: =F33=J33 -> #REF!

Sheet 66
A1: Table 66: Trends in commodity derivatives at NCDEX
A2: Year/ Month | B2: No.of Trading days | C2: FUTURES | H2: OPTIONS
C3: Volume ('000 tonnes) | D3: No. of contracts traded | E3: Turnover (₹ crore) | F3: Open interest at the end of the period | H3: Call options | J3: Put options | L3: Open interest at the end of the period
F4: No. of Contracts | G4: Value (₹ crore) | H4: No. of contracts | I4: Turnover (₹ crore) | J4: No. of contracts | K4: Turnover (₹ crore) | L4: No. of contracts | M4: Notional Value (₹ crore)
A5: 2018-19 | B5: 248 | C5: 120124.92 | D5: 14005485 | E5: 531414.1 | F5: 128338.5 | G5: 5328.34 | H5: 3646 | I5: 159.9 | J5: 328 | K5: 13.96 | L5: 6 | M5: 0.27
A6: 2019-20$ | B6: 19 | C6: 9826.457 | D6: 1294409 | E6: 47775.985 | F6: 135463 | G6: =G7 -> 5988.31 | H6: 17 | I6: 0.78 | J6: 0 | K6: 0 | L6: 6 | M6: =M7 -> 0.27
A7: 43556 | B7: 19 | C7: 9826.457 | D7: 1294409 | E7: 47775.985 | F7: 135463 | G7: 5988.31 | H7: 17 | I7: 0.78 | J7: 0 | K7: 0 | L7: 6 | M7: 0.27
A8: ='[1]1'!A8 -> $ indicates as on April 30, 2019
A9: Source: NCDEX

Sheet 67
A1: Table 67: Trends in commodity derivatives at ICEX
A2: Year/ Month | B2: No.of Trading days | C2: Agriculture Futures | F2: Metals Futures | I2: Gems and Stones Futures | L2: Total | N2: Open interest at the end of the period
C3: Volume ('000 tonnes) | D3: No. of contracts traded | E3: Turnover (₹ crore) | F3: Volume ('000 tonnes) | G3: No. of contracts traded | H3: Turnover (₹ crore) | I3: Volume (in cents) | J3: No. of contracts traded | K3: Turnover (₹ crore) | L3: No. of contracts traded | M3: Turnover (₹ crore) | N3: No. of contracts | O3: Value (₹ crore)
A4: 2018-19 | B4: 257 | C4: 3195.8932 | D4: 683893 | E4: 14772.164 | F4: 1155.85 | G4: 115585 | H4: 4062.66 | I4: 55312169 | J4: 55312169 | K4: 18901.567 | L4: 56111647 | M4: 37735.501 | N4: 129291 | O4: 77
A5: 2019-20$ | B5: 20 | C5: 39.5 | D5: 18822 | E5: 240.06 | F5: 157.54 | G5: 15754 | H5: 536.39 | I5: 10661364 | J5: 10661364 | K5: 3677.36 | L5: 10695940 | M5: 4453.81 | N5: 172820 | O5: =O6 -> 80.44
A6: 43556 | B6: 20 | C6: 39.5 | D6: 18822 | E6: 240.06 | F6: 157.54 | G6: 15754 | H6: 536.39 | I6: 10661364 | J6: 10661364 | K6: 3677.36 | L6: 10695940 | M6: 4453.81 | N6: 172820 | O6: 80.44
A7: ='64'!A7 -> $ indicates as on April 30, 2019
A8: Notes : i. Contract size for all diamond futures contract at ICEX is one cent.
A9: ii. Futures trading in steel long contracts commenced from 28th Aug. 2018.
A10: iii. Consequent upon merger of NMCE with ICEX, all contracts of NMCE are transferred to ICEX w.e.f September 24, 2018. The trading data of NMCE is added to agri. segment of ICEX.
A11: Source: ICEX

Sheet 68
A1: Table 68: Trends in commodity derivatives at BSE
A2: Year/ Month | B2: No.of Trading days | C2: Metal Futures | F2: Bullion Futures | I2: Energy Futures | L2: Agriculture | O2: Total | Q2: Open interest at the end of the period
C3: Volume ( tonnes) | D3: No. of contracts traded | E3: Turnover (₹ crore) | F3: Volume ( tonnes) | G3: No. of contracts traded | H3: Turnover (₹ crore) | I3: Volume (Tonnes) | J3: No. of contracts traded | K3: Turnover (₹ crore) | L3: Volume ( tonnes) | M3: No. of contracts traded | N3: Turnover (₹ crore) | O3: No. of contracts traded | P3: Turnover (₹ crore) | Q3: No. of contracts | R3: Value (₹ crore)
A4: 2018-19 | B4: 128 | C4: 21 | D4: 21 | E4: 0.99 | F4: 771.641 | G4: 103678 | H4: 28079.569 | I4: =7700/7.33 -> 1050.4775 | J4: 77 | K4: 4.28514 | L4: 793415.25 | M4: 101429 | N4: 4718.89 | O4: =D4+G4+J4+M4 -> 205205 | P4: 32803.748 | Q4: 1052 | R4: 73.27
A5: 2019-20$ | B5: 20 | C5: 7 | D5: 7 | E5: 0.33 | F5: 109.79 | G5: 10431 | H5: 2217.9 | I5: 0 | J5: 0 | K5: 0 | L5: 416618 | M5: 55862 | N5: 2771.82 | O5: 66300 | P5: 4990.05 | Q5: 1175 | R5: =R6 -> 106.29
A6: 43556 | B6: 20 | C6: 7 | D6: 7 | E6: 0.33 | F6: 109.79 | G6: 10431 | H6: 2217.9 | I6: 0 | J6: 0 | K6: 0 | L6: 416618 | M6: 55862 | N6: 2771.82 | O6: 66300 | P6: 4990.05 | Q6: 1175 | R6: 106.29
A7: ='[1]1'!A8 -> $ indicates as on April 30, 2019
A8: Conversion factors: OMAN Crude Oil (1 Tonne = 7.33Barrels)
A9: Source: BSE | M9: =E6+H6 -> 2218.23

Sheet 69
A1: Table 69: Trends in commodity derivatives at NSE
A2: Year/ Month | B2: No.of Trading days | C2: Bullion Futures | F2: Energy | I2: Total | K2: Open interest at the end of the period
C3: Volume ( tonnes) | D3: No. of contracts traded | E3: Turnover (₹ crore) | F3: Volume ('000 tonnes)* | G3: No. of contracts traded | H3: Turnover (₹ crore) | I3: No. of contracts traded | J3: Turnover (₹ crore) | K3: No. of contracts | L3: Value (₹ crore)
A4: 2018-19 | B4: 120 | C4: 148.7392 | D4: 36315 | E4: 3374.5538 | F4: 10584 | G4: 10584 | H4: 69.264048 | I4: 46899 | J4: 3443.8179 | K4: 159 | L4: 6.59
A5: 2019-20$ | B5: 20 | C5: 6.217 | D5: 12468 | E5: 431.03877 | F5: 8443 | G5: 8443 | H5: 58.747573 | I5: 20911 | J5: 489.78634 | K5: 91 | L5: =L6 -> 4.36
A6: 43556 | B6: 20 | C6: 6.217 | D6: 12468 | E6: 431.03877 | F6: 8443 | G6: 8443 | H6: 58.747573 | I6: 20911 | J6: 489.78634 | K6: 91 | L6: 4.36
A7: ='[1]1'!A8 -> $ indicates as on April 30, 2019
A8: Volume for BR Crude and BR Crude Mini is provided in barrels (absolute figure).
A9: Source: NSE

Sheet 70
A1: Table 70: Participant-wise percentage share of turnover at MCX, NCDEX, ICEX, BSE and NSE
A2: Year/ Month | B2: MCX | F2: NCDEX | I2: ICEX | M2: BSE | Q2: NSE
B3: Agriculture | D3: Non-Agriculture Segment | F3: Agriculture | I3: Agriculture | K3: Non-Agriculture | M3: Non-Agriculture | O3: Agriculture | Q3: Non-Agriculture
B4: Proprietary | C4: Client | D4: Proprietary | E4: Client | F4: Proprietary | G4: Client | H4: Hedgers | I4: Proprietary | J4: Client | K4: Proprietary | L4: Client | M4: Proprietary | N4: Client | O4: Proprietary | P4: Client | Q4: Proprietary | R4: Client
A5: 2018-19 | B5: 38.248436 | C5: 61.751564 | D5: 27.622798 | E5: 72.377202 | F5: 44.124685 | G5: 55.463657 | H5: 0.41165811 | I5: 7.19 | J5: 92.81 | K5: 45.46 | L5: 54.54 | M5: 92.954602 | N5: 7.0453985 | O5: NA | P5: NA | Q5: 83.932337 | R5: 16.067663
A6: 2019-20$ | B6: 39.596508 | C6: 60.403492 | D6: 29.710732 | E6: 70.289268 | F6: 47.493273 | G6: 51.791447 | H6: 0.71527974 | I6: 55.62 | J6: 44.38 | K6: 64.5 | L6: 35 | M6: 47.508401 | N6: 2.4915988 | O6: 36.91368 | P6: 13.08632 | Q6: 50.490495 | R6: 49.509505
A7: 43556 | B7: 39.596508 | C7: 60.403492 | D7: 29.710732 | E7: 70.289268 | F7: 47.493273 | G7: 51.791447 | H7: 0.71527974 | I7: 55.62 | J7: 44.38 | K7: 64.5 | L7: 35 | M7: 47.508401 | N7: 2.4915988 | O7: 36.91368 | P7: 13.08632 | Q7: 50.490495 | R7: 49.509505
A8: ='64'!A7 -> $ indicates as on April 30, 2019
A9: Conserquent to merger of NMCE with ICEX w.e.f. September 24, 2018, data pertaiing to NMCE are merged with ICEX
A10: Source: MCX, NCDEX, ICEX, BSE and NSE

Sheet 71
A1: Table 71: Commodity-wise monthly turnover and trading volume at MCX
A2: Sr.No | B2: Name of the Commodity | C2: 2019-20$ | E2: 43191 | G2: 43525 | I2: 43556
C3: Volume ('000 tonnes) | D3: Value (₹ crore) | E3: Volume ('000 tonnes) | F3: Value (₹ crore) | G3: Volume ('000 tonnes) | H3: Value (₹ crore) | I3: Volume ('000 tonnes) | J3: Value (₹ crore)
A4: Futures
A5: A | B5: Bullion
A6: 1 | B6: Gold | C6: 0.23213101 | D6: 73848.885 | E6: 0.21308275 | F6: 66209.53 | G6: 0.32116162 | H6: 102934.6 | I6: 0.23213101 | J6: 73848.885 | K6: =(J6-H6)/H6*100 -> -28.256502
A7: 2 | B7: Silver | C7: 14.897137 | D7: 55814.127 | E7: 15.222353 | F7: 59630.905 | G7: 12.75699 | H7: 48919.012 | I7: 14.897137 | J7: 55814.127 | K7: =(J7-H7)/H7*100 -> 14.09496
B8: Total for A | C8: =SUM(C6:C7) -> 15.129268 | D8: =SUM(D6:D7) -> 129663.01 | E8: =SUM(E6:E7) -> 15.435436 | F8: =SUM(F6:F7) -> 125840.43 | G8: =SUM(G6:G7) -> 13.078152 | H8: =SUM(H6:H7) -> 151853.61 | I8: =SUM(I6:I7) -> 15.129268 | J8: =SUM(J6:J7) -> 129663.01 | K8: =(J8-H8)/H8*100 -> -14.613154
A9: B | B9: Metals other than Bullion
A10: 1 | B10: Aluminium | C10: 692.326 | D10: 9683.8302 | E10: 4262.54 | F10: 64882.026 | G10: 879.986 | H10: 12225.512 | I10: 692.326 | J10: 9683.8302 | K10: =(J10-H10)/H10*100 -> -20.789983
A11: 2 | B11: Brass | C11: Na | D11: Na | E11: 4.939 | F11: 175.36431 | G11: Na | H11: Na | I11: Na | J11: Na
A12: 3 | B12: Copper | C12: 955.161 | D12: 42859.898 | E12: 1086.724 | F12: 48769.533 | G12: 918.33925 | H12: 41177.238 | I12: 955.161 | J12: 42859.898 | K12: =(J12-H12)/H12*100 -> 4.0863841
A13: 4 | B13: Lead | C13: 1745.603 | D13: 23756.034 | E13: 2054.646 | F13: 31838.552 | G13: 2149.932 | H13: 30822.334 | I13: 1745.603 | J13: 23756.034 | K13: =(J13-H13)/H13*100 -> -22.925906
A14: 5 | B14: Nickel | C14: 256.10085 | D14: 22922.506 | E14: 440.3472 | F14: 41261.817 | G14: 289.2856 | H14: 26408.5 | I14: 256.10085 | J14: 22922.506 | K14: =(J14-H14)/H14*100 -> -13.200273
A15: 6 | B15: Zinc | C15: 3380.656 | D15: 73750.249 | E15: 3145.828 | F15: 66102.643 | G15: 4362.838 | H15: 86539.208 | I15: 3380.656 | J15: 73750.249 | K15: =(J15-H15)/H15*100 -> -14.778224
B16: Total for B | C16: =SUM(C10:C15) -> 7029.8468 | D16: =SUM(D10:D15) -> 172972.52 | E16: =SUM(E10:E15) -> 10995.024 | F16: =SUM(F10:F15) -> 253029.94 | G16: =SUM(G10:G15) -> 8600.3809 | H16: =SUM(H10:H15) -> 197172.79 | I16: =SUM(I10:I15) -> 7029.8468 | J16: =SUM(J10:J15) -> 172972.52 | K16: =(J16-H16)/H16*100 -> -12.273637
A17: C | B17: Agricultural commodities
A18: 1 | B18: Cardamom | C18: 0.0841 | D18: 14.506961 | E18: 0.1831 | F18: 18.373867 | G18: 0.056 | H18: 8.734503 | I18: 0.0841 | J18: 14.506961 | K18: =(J18-H18)/H18*100 -> 66.087996
A19: 2 | B19: Cotton | C19: 594.14575 | D19: 7785.2231 | E19: 264.8345 | F19: 3238.3744 | G19: 519.16725 | H19: 6505.624 | I19: 594.14575 | J19: 7785.2231 | K19: =(J19-H19)/H19*100 -> 19.669122
A20: 3 | B20: CPO | C20: 391.08 | D20: 2119.0546 | E20: 405.17 | F20: 2628.228 | G20: 411.07 | H20: 2183.0701 | I20: 391.08 | J20: 2119.0546 | K20: =(J20-H20)/H20*100 -> -2.9323598
A21: 4 | B21: Mentha Oil | C21: 6.07824 | D21: 886.93573 | E21: 11.1996 | F21: 1497.0987 | G21: 6.21396 | H21: 1009.2882 | I21: 6.07824 | J21: 886.93573 | K21: =(J21-H21)/H21*100 -> -12.12265
B22: Total for C | C22: =SUM(C18:C21) -> 991.38809 | D22: =SUM(D18:D21) -> 10805.72 | E22: =SUM(E18:E21) -> 681.3872 | F22: =SUM(F18:F21) -> 7382.075 | G22: =SUM(G18:G21) -> 936.50721 | H22: =SUM(H18:H21) -> 9706.7169 | I22: =SUM(I18:I21) -> 991.38809 | J22: =SUM(J18:J21) -> 10805.72 | K22: =(J22-H22)/H22*100 -> 11.322094
A23: D | B23: Energy
A24: 1 | B24: Crude Oil | C24: 62102.357 | D24: 202058.66 | E24: 50265.02 | F24: 159948.62 | G24: 68525.514 | H24: 203182.75 | I24: 62102.357 | J24: 202058.66 | K24: =(J24-H24)/H24*100 -> -0.55323997
A25: 2 | B25: Natural Gas (trln. Btu) | C25: 638.53125 | D25: 11613.155 | E25: 875.41375 | F25: 15662.086 | G25: 794.37375 | H25: 15552.202 | I25: 638.53125 | J25: 11613.155 | K25: =(J25-H25)/H25*100 -> -25.327904
B26: Total for D* | C26: =C24 -> 62102.357 | D26: =SUM(D24:D25) -> 213671.81 | E26: =E24 -> 50265.02 | F26: =SUM(F24:F25) -> 175610.71 | G26: =G24 -> 68525.514 | H26: =SUM(H24:H25) -> 218734.95 | I26: =I24 -> 62102.357 | J26: =SUM(J24:J25) -> 213671.81
A27: Grand Total (A+B+C+D) | C27: =C26+C22+C16+C8 -> 70138.721 | D27: =D26+D22+D16+D8 -> 527113.06 | E27: =E26+E22+E16+E8 -> 61956.867 | F27: =F26+F22+F16+F8 -> 561863.15 | G27: =SUM(G8+G16+G22+G26) -> 78075.48 | H27: =H26+H22+H16+H8 -> 577468.07 | I27: =I26+I22+I16+I8 -> 70138.721 | J27: =J26+J22+J16+J8 -> 527113.06 | K27: =(J27-H27)/H27*100 -> -8.7199639
A28: Options
A29: E | B29: Bullion
A30: 1 | B30: Gold | C30: 0.008261 | D30: 2660.1478 | E30: 0.008388 | F30: 2640.4239 | G30: 0.023273 | H30: 7579.6183 | I30: 0.008261 | J30: 2660.1478 | K30: =(J30-H30)/H30*100 -> -64.903934
A31: 2 | B31: Silver | C31: 0.29493 | D31: 1133.8833 | E31: 0 | F31: 0 | G31: 0.1779 | H31: 704.21693 | I31: 0.29493 | J31: 1133.8833 | K31: =(J31-H31)/H31*100 -> 61.01336
B32: Total of E | C32: =SUM(C30:C31) -> 0.303191 | D32: =SUM(D30:D31) -> 3794.0311 | E32: =SUM(E30:E31) -> 0.008388 | F32: =SUM(F30:F31) -> 2640.4239 | G32: =SUM(G30:G31) -> 0.201173 | H32: =SUM(H30:H31) -> 8283.8352 | I32: =SUM(I30:I31) -> 0.303191 | J32: =SUM(J30:J31) -> 3794.0311 | K32: =(J32-H32)/H32*100 -> -54.199582
A33: F | B33: Metals
A34: 1 | B34: Copper | C34: 5.851 | D34: 265.17125 | E34: 0 | F34: 0 | G34: 5.356 | H34: 244.78431 | I34: 5.851 | J34: 265.17125 | K34: =(J34-H34)/H34*100 -> 8.3285331
A35: 2 | B35: Zinc | C35: 21.31 | D35: 477.59881 | E35: 0 | F35: 0 | G35: 20.935 | H35: 419.6646 | I35: 21.31 | J35: 477.59881 | K35: =(J35-H35)/H35*100 -> 13.804883
B36: Total of F | C36: =SUM(C34:C35) -> 27.161 | D36: =SUM(D34:D35) -> 742.77005 | E36: 0 | F36: 0 | G36: =SUM(G34:G35) -> 26.291 | H36: =SUM(H34:H35) -> 664.44891 | I36: =SUM(I34:I35) -> 27.161 | J36: =SUM(J34:J35) -> 742.77005 | K36: =(J36-H36)/H36*100 -> 11.787384
A37: G | B37: Energy
A38: 1 | B38: Crude Oil | C38: 1272.7149 | D38: 4148.4457 | E38: 0 | F38: 0 | G38: 1243.2606 | H38: 3702.7328 | I38: 1272.7149 | J38: 4148.4457 | K38: =(J38-H38)/H38*100 -> 12.037402
A39: Grand Total (E+F+G) | C39: =SUM(C32+C36+C38) -> 1300.1791 | D39: =SUM(D32+D36+D38) -> 8685.2469 | E39: =SUM(E32) -> 0.008388 | F39: =SUM(F32) -> 2640.4239 | G39: =SUM(G32+G36+G38) -> 1269.7528 | H39: =SUM(H32+H36+H38) -> 12651.017 | I39: =SUM(I32+I36+I38) -> 1300.1791 | J39: =SUM(J32+J36+J38) -> 8685.2469 | K39: =(J39-H39)/H39*100 -> -31.347441
A40: ='64'!A7 -> $ indicates as on April 30, 2019
A41: Note : Natural Gas volume is in trillion BTU and is not included in total volume.
A42: Turnover of options contract is notional value.
A43: Conversion factors: Cotton (1 Bale=170 kg), Crude Oil (1 Tonne = 7.33Barrels)
A44: Source : MCX

Sheet 72
A1: Table 72: Commodity-wise monthly turnover and trading volume at NCDEX
A2: Sr.No | B2: Name of Agri. Commodity | C2: 2019-20$ | E2: 43207 | G2: 43525 | I2: 43573
C3: Volume ('000 tonnes) | D3: Value (₹ crore) | E3: Volume ('000 tonnes) | F3: Value (₹ crore) | G3: Volume ('000 tonnes) | H3: Value ( crore) | I3: Volume ('000 tonnes) | J3: Value (₹ crore)
A4: Futures
A5: 1 | B5: Barley | C5: 37.17 | D5: 66.15044 | E5: 60.74 | F5: 84.584085 | G5: 4.45 | H5: 7.535235 | I5: 37.17 | J5: 66.15044 | K5: =(J5-H5)/H5*100 -> 777.88158
A6: 2 | B6: Castorseed | C6: 2096.665 | D6: 12159.881 | E6: 734.48 | F6: 3027.2687 | G6: 889.625 | H6: 4716.957 | I6: 2096.665 | J6: 12159.881 | K6: =(J6-H6)/H6*100 -> 157.7908
A7: 3 | B7: Chana | C7: 1175.83 | D7: 5260.2237 | E7: 1047.25 | F7: 3857.7925 | G7: 682.82 | H7: 2894.3339 | I7: 1175.83 | J7: 5260.2237 | K7: =(J7-H7)/H7*100 -> 81.742116
A8: =A7+1 -> 4 | B8: Cotton seed oil cake | C8: 1499.97 | D8: 3627.2631 | E8: 1808.69 | F8: 2423.8932 | G8: 1416.4 | H8: 3046.0078 | I8: 1499.97 | J8: 3627.2631 | K8: =(J8-H8)/H8*100 -> 19.082529
A9: =A8+1 -> 5 | B9: Coriander | C9: 307.1 | D9: 2215.6226 | E9: 178.02 | F9: 914.9133 | G9: 211.39 | H9: 1385.7471 | I9: 307.1 | J9: 2215.6226 | K9: =(J9-H9)/H9*100 -> 59.88651
A10: =A9+1 -> 6 | B10: Guar seed | C10: 1610.21 | D10: 7140.3029 | E10: 1812.28 | F10: 7420.3335 | G10: 1294.92 | H10: 5602.0324 | I10: 1610.21 | J10: 7140.3029 | K10: =(J10-H10)/H10*100 -> 27.45915
A11: =A10+1 -> 7 | B11: Guargum | C11: 425.59 | D11: 3815.4137 | E11: 420.08 | F11: 3729.24 | G11: 392.985 | H11: 3434.2603 | I11: 425.59 | J11: 3815.4137 | K11: =(J11-H11)/H11*100 -> 11.09856
A12: =A11+1 -> 8 | B12: Jeera | C12: 82.131 | D12: 1359.7782 | E12: 76.326 | F12: 1180.2218 | G12: 55.182 | H12: 857.23291 | I12: 82.131 | J12: 1359.7782 | K12: =(J12-H12)/H12*100 -> 58.624122
A13: =A12+1 -> 9 | B13: Kapas | C13: 172.916 | D13: 1044.2542 | E13: 118.78 | F13: 541.7686 | G13: 266.24 | H13: 1539.8775 | I13: 172.916 | J13: 1044.2542 | K13: =(J13-H13)/H13*100 -> -32.185889
A14: =A13+1 -> 10 | B14: Maize | C14: 8.27 | D14: 15.50183 | E14: 11.65 | F14: 13.91703 | G14: 3.05 | H14: 5.36707 | I14: 8.27 | J14: 15.50183 | K14: =(J14-H14)/H14*100 -> 188.83227
A15: =A14+1 -> 11 | B15: Rmseed | C15: 662.75 | D15: 2517.7129 | E15: 1091.93 | F15: 4293.427 | G15: 334.29 | H15: 1270.0075 | I15: 662.75 | J15: 2517.7129 | K15: =(J15-H15)/H15*100 -> 98.24393
A16: =A15+1 -> 12 | B16: Sugar | C16: Na | D16: Na | E16: 0.02 | F16: 0.059 | G16: Na | H16: Na | I16: Na | J16: Na
A17: =A16+1 -> 13 | B17: Soya bean | C17: 1140.21 | D17: 4305.5646 | E17: 1880.46 | F17: 7171.0707 | G17: 1211.88 | H17: 4484.4546 | I17: 1140.21 | J17: 4305.5646 | K17: =(J17-H17)/H17*100 -> -3.9891141
A18: =A17+1 -> 14 | B18: Soya oil | C18: 449.07 | D18: 3278.9324 | E18: 529.3 | F18: 4109.2774 | G18: 415.67 | H18: 3084.6172 | I18: 449.07 | J18: 3278.9324 | K18: =(J18-H18)/H18*100 -> 6.299493
A19: =A18+1 -> 15 | B19: Turmeric | C19: 144.365 | D19: 942.86902 | E19: 122.605 | F19: 826.78533 | G19: 57.545 | H19: 358.99447 | I19: 144.365 | J19: 942.86902 | K19: =(J19-H19)/H19*100 -> 162.64166
A20: =A19+1 -> 16 | B20: Wheat | C20: 14.21 | D20: 26.51377 | E20: 14.35 | F20: 24.27349 | G20: 0.82 | H20: 1.50388 | I20: 14.21 | J20: 26.51377 | K20: =(J20-H20)/H20*100 -> 1663.0243
B21: Total | C21: =SUM(C5:C20) -> 9826.457 | D21: =SUM(D5:D20) -> 47775.985 | E21: =SUM(E5:E20) -> 9906.961 | F21: =SUM(F5:F20) -> 39618.826 | G21: =SUM(G5:G20) -> 7237.267 | H21: =SUM(H5:H20) -> 32688.929 | I21: =SUM(I5:I20) -> 9826.457 | J21: =SUM(J5:J20) -> 47775.985 | K21: =(J21-H21)/H21*100 -> 46.153412
A22: Options
A23: 1 | B23: Chana | C23: 8 | D23: 0.37 | E23: Na | F23: Na | G23: 0 | H23: 0 | I23: 8 | J23: 0.37
A24: 2 | B24: Guargum | C24: 0 | D24: 0 | E24: Na | F24: Na | G24: 0 | H24: 0 | I24: 0 | J24: 0
A25: 3 | B25: Guarseed | C25: 9 | D25: 0.41 | E25: 4.96 | F25: 21.26 | G25: 1.16 | H25: 5.13 | I25: 9 | J25: 0.41
A26: 4 | B26: Soybean | C26: 0 | D26: 0 | E26: Na | F26: Na | G26: 0 | H26: 0 | I26: 0 | J26: 0
A27: 5 | B27: Ref. Soy Oil | C27: 0 | D27: 0 | E27: Na | F27: Na | G27: 0 | H27: 0 | I27: 0 | J27: 0
B28: Total | C28: =SUM(C23:C27) -> 17 | D28: =SUM(D23:D27) -> 0.78 | E28: =SUM(E23:E27) -> 4.96 | F28: =SUM(F23:F27) -> 21.26 | G28: =SUM(G23:G27) -> 1.16 | H28: =SUM(H23:H27) -> 5.13 | I28: =SUM(I23:I27) -> 17 | J28: =SUM(J23:J27) -> 0.78
A29: ='64'!A7 -> $ indicates as on April 30, 2019
A30: Turnover of options contract is notional value.
A31: Source: NCDEX

Sheet 73
A1: Table 73: Commodity-wise monthly turnover and trading volume at ICEX, BSE and NSE
A2: Sr.No | B2: Name of the Commodity | C2: 2019-20$ | E2: 43218 | G2: 43525 | I2: 43556
C3: Volume ('000 tonnes) | D3: Value (₹ crore) | E3: Volume ('000 tonnes) | F3: Value (₹ crore) | G3: Volume ('000 tonnes) | H3: Value (₹ crore) | I3: Volume ('000 tonnes) | J3: Value (₹ crore)
A4: A. | B4: ICEX
A5: 1 | B5: Castorseed | C5: 0 | D5: 0 | E5: 85.78 | F5: 355.19 | G5: 0 | H5: 0 | I5: 0 | J5: 0
A6: 2 | B6: Guarseed | C6: 0 | D6: 0 | E6: 112.065 | F6: 462.64 | G6: 0 | H6: 0 | I6: 0 | J6: 0
A7: 3 | B7: Isabgulseed | C7: 22.98 | D7: 23.98 | E7: 79.39013 | F7: 660.88 | G7: 0 | H7: 0 | I7: 22.98 | J7: 23.98
A8: 4 | B8: Pepper Mini | C8: 0 | D8: 0 | E8: 0.395 | F8: 1.511359 | G8: 0 | H8: 0 | I8: 0 | J8: 0
A9: 5 | B9: Rape/Mustardseed | C9: 0 | D9: 0 | E9: 230.23 | F9: 805.10658 | G9: 0 | H9: 0 | I9: 0 | J9: 0
A10: 6 | B10: Raw Jute | C10: 0 | D10: 0 | E10: 170.69 | F10: 750.65906 | G10: 0 | H10: 0 | I10: 0 | J10: 0
A11: 7 | B11: Rubber | C11: 165.24 | D11: 216.07 | E11: 10.627 | F11: 130.01715 | G11: 18.31 | H11: 238.73 | I11: 165.24 | J11: 216.07
A12: 8 | B12: Diamond 1 CT | C12: 104815.84 | D12: 3648.72 | E12: 11766.13 | F12: 389.81457 | G12: 112666.05 | H12: 3921.69 | I12: 104815.84 | J12: 3648.72
A13: 9 | B13: Diamond .5 CT | C13: 1797.78 | D13: 28.64 | E13: 5872.77 | F13: 89.4212 | G13: 8793.58 | H13: 140.31 | I13: 1797.78 | J13: 28.64
A14: 10 | B14: Diamond .3 CT | C14: 0.02 | D14: 0.0002 | E14: 2.59 | F14: 0.257 | G14: 0.33 | H14: 0.003646 | I14: 0.02 | J14: 0.0002
A15: 11 | B15: Steel | C15: 157.54 | D15: 536.39 | E15: 0 | F15: 0 | G15: 169.07 | H15: 577.15 | I15: 157.54 | J15: 536.39
B16: Total (ICEX) | C16: =SUM(C5:C15) -> 106959.4 | D16: =SUM(D5:D15) -> 4453.8002 | E16: =SUM(E5:E15) -> 18330.667 | F16: =SUM(F5:F15) -> 3645.4969 | G16: =SUM(G5:G15) -> 121647.34 | H16: =SUM(H5:H15) -> 4877.8836 | I16: =SUM(I5:I15) -> 106959.4 | J16: =SUM(J5:J15) -> 4453.8002
A17: B. | B17: BSE
A18: 1 | B18: Gold | C18: 0.00561 | D18: 1784.5157 | E18: Na | F18: Na | G18: =3.97/1000 -> 0.00397 | H18: 1272.5501 | I18: =5.61/1000 -> 0.00561 | J18: 1784.5157
A19: 2 | B19: Silver | C19: 0.10404 | D19: 390.43662 | E19: Na | F19: Na | G19: =61.29/1000 -> 0.06129 | H19: 235.36856 | I19: =104.04/1000 -> 0.10404 | J19: 390.43662
A20: 3 | B20: OMAN CRUDE * | C20: 0 | D20: 0 | E20: Na | F20: Na | G20: 0 | H20: 0 | I20: 0 | J20: 0
A21: 4 | B21: Copper | C21: 0.007 | D21: 0.328215 | E21: Na | F21: Na | G21: 0 | H21: 0 | I21: =7/1000 -> 0.007 | J21: 0.328215
A22: 5 | B22: Gold M | C22: 0.00014 | D22: 42.945122 | E22: Na | F22: Na | G22: =15.8/1000 -> 0.0158 | H22: 15.824189 | I22: =0.14/1000 -> 0.00014 | J22: 42.945122
A23: 6 | B23: Guar Gum | C23: 0.00014 | D23: 0 | E23: Na | F23: Na | G23: =90/1000 -> 0.09 | H23: 0.77983 | I23: 0.00014 | J23: 0
A24: 7 | B24: Guar Seed | C24: 311.66 | D24: 1388.4051 | E24: Na | F24: Na | G24: =332120/1000 -> 332.12 | H24: 1438.1628 | I24: =311660/1000 -> 311.66 | J24: 1388.4051
A25: 8 | B25: Cotton | C25: 104.958 | D25: 1383.4128 | E25: Na | F25: Na | G25: =117474/1000 -> 117.474 | H25: 1462.3226 | I25: =104958/1000 -> 104.958 | J25: 1383.4128
B26: Total (BSE) | C26: 416.73493 | D26: =SUM(D18:D25) -> 4990.0435 | E26: Na | F26: Na | G26: =SUM(G18:G25) -> 449.76506 | H26: =SUM(H18:H25) -> 4425.008 | I26: =SUM(I18:I25) -> 416.73493 | J26: =SUM(J18:J25) -> 4990.0435
A27: C. | B27: NSE
A28: 1 | B28: Gold | E28: Na | F28: Na | G28: Na | H28: Na
A29: 2 | B29: Silver | E29: Na | F29: Na | G29: Na | H29: Na
B30: Total (NSE) | D30: 696.19 | E30: Na | F30: Na | G30: Na | H30: Na | J30: 696.19
A31: C. | B31: NSE
A32: 1 | B32: Gold | C32: 0.074 | D32: 23.60278 | E32: Na | F32: Na | G32: 0.159 | H32: 50.9628 | I32: 0.074 | J32: 23.60278 | K32: =SUM(J32:J34) -> 431.03877 | L32: =SUM(H32:H34) -> 360.33587 | M32: =(K32-L32)/L32*100 -> 19.621389
A33: 2 | B33: Gold Mini | C33: 1.223 | D33: 389.0143 | E33: Na | F33: Na | G33: 0.8263 | H33: 264.79472 | I33: 1.223 | J33: 389.0143
A34: 3 | B34: Silver | C34: 4.92 | D34: 18.421689 | E34: Na | F34: Na | G34: 11.61 | H34: 44.578344 | I34: 4.92 | J34: 18.421689
A35: 4 | B35: BR Crude | C35: 370 | D35: 18.53172 | E35: Na | F35: Na | G35: 476 | H35: 22.18074 | I35: 370 | J35: 18.53172 | K35: =SUM(J35:J36) -> 58.747573 | L35: =SUM(H35:H36) -> 69.264048 | M35: =(K35-L35)/L35*100 -> -15.183165
A36: 5 | B36: BR Crude Mini | C36: 8073 | D36: 40.215853 | E36: Na | F36: Na | G36: 10108 | H36: 47.083308 | I36: 8073 | J36: 40.215853
B37: Total (NSE) | C37: =SUM(C32:C36) -> 8449.217 | D37: =SUM(D32:D36) -> 489.78634 | E37: Na | F37: Na | G37: =SUM(G32:G36) -> 10596.595 | H37: =SUM(H32:H36) -> 429.59992 | I37: =SUM(I32:I36) -> 8449.217 | J37: =SUM(J32:J36) -> 489.78634
A38: ='64'!A7 -> $ indicates as on April 30, 2019 | I38: =K32/J37*100 -> 88.005469 | J38: =K35/J37*100 -> 11.994531
A39: Note : i) Consequent to merger of NMCE with ICEX, all the contracts of NMCE are transferred to ICEX w.e.f. September 24, 2018. Trading data of NMCE prior to its merger is added to agri. segment of ICEX.
B40: ii) Volume for Diamond 1 CT, 0.5CT & 0.3CT has been given in Carat only (e.g. if volume is 80312.2 i.e. 80312.2 carats) and 1 Carat is equivalent to 100 cents.
B41: iii. Conversion factors: OMAN Crude Oil (1 Tonne = 7.33Barrels)
B42: iv. Volume for BR Crude and BR Crude Mini for NSE is provided in barrels (absolute figure)
A43: Source : ICEX, BSE and NSE

Sheet 74
A1: Table 74: Macro Economic Indicators
A2: I. GDP at constant prices (2011-12 prices) for 2018-19 (` crore)# | E2: 14100119
A3: II. Gross Saving as a percent of Gross national Disposable Income at current market prices in 2017-18! | E3: 30.1
A4: III. Gross Capital Formation as a per cent of GDP at current market prices in 2017-18! | E4: 32.3
A5: IV. Monetary and Banking Indicators | B5: 43435 | C5: 43466 | D5: 43497 | E5: 43525 | F5: 43556
A6: Cash Reserve Ratio (percent) | B6: 4 | C6: 4 | D6: 4 | E6: 4 | F6: 4 | J6: T_5 | K6: https://rbi.org.in/Scripts/BS_ViewWss.aspx
A7: Repo Rate (percent) | B7: 6.5 | C7: 6.5 | D7: 6.25 | E7: 6.25 | F7: 6 | J7: T_5
A8: Money Supply (M3) (₹ crore) | B8: 145515.7 | C8: 147591.9 | D8: 149401 | E8: 150859.3 | F8: 154301.1 | J8: T_6
A9: Aggregate Deposit (₹ crore) | B9: 118182.1 | C9: 119864.6 | D9: 121211.8 | E9: 122262.4 | F9: 125309.8 | J9: T_4
A10: Bank Credit (₹ crore) | B10: 92877.5 | C10: 93316.9 | D10: 94034.9 | E10: 95537.1 | F10: 96450.6 | J10: T_4
A11: V. Interest Rate
A12: Call Money Rate (Weighted Average) | B12: 6.57 | C12: 6.43 | D12: 6.29 | E12: 6.35 | F12: 6.16 | J12: T_5
A13: 91-Day-Treasury Bill (Primary Yield) | B13: 6.65 | C13: 6.6 | D13: 6.4 | E13: 6.31 | F13: 6.4 | J13: T_5
A14: Base rate (percent) | B14: 8.95/9.45 | C14: 8.95/9.45 | D14: 8.95/9.45 | E14: 8.95/9.40 | F14: 8.95/9.40 | J14: T_5
A15: Term Deposit Rate > 1 year (Maximum) | B15: 6.25/7.50 | C15: 6.25/7.50 | D15: 6.25/7.50 | E15: 6.25/7.50 | F15: 6.25/7.50 | J15: T_5
A16: VI. Capital Market Indicators (₹crore)
A17: Equity Cash Turnover (BSE+NSE) | B17: 650399.91 | C17: 727221.33 | D17: 689925.69 | E17: 778201.06 | F17: 695982.81 | K17: bse from bse file (BSE_C_TRD_STAT_TABLE17_DDMMYYYY, col H and M respectivly) and nse from website
A18: Market Cap-BSE | B18: 14448466 | C18: 14099330 | D18: 14041530 | E18: 15108711 | F18: 15254028
A19: Market Cap-NSE | B19: 14279083 | C19: 13916643 | D19: 13871449 | E19: 14934227 | F19: 15043275 | K19: https://www.nseindia.com/products/content/equities/equities/historical_equity_businessgrowth.htm
A20: Net FPI Investment in Equity | B20: -229.91 | C20: -7827.23 | D20: 17219.62 | E20: 33980.56 | F20: 16727.86 | K20: https://www.fpi.nsdl.co.in/web/Reports/Archive.aspx
A21: VII. Exchange Rate and Reserves
A22: Forex Reserves (USD million) | B22: 393404.3 | C22: 398178.4 | D22: 399217.2 | E22: 411905 | F22: 418515.3 | J22: T_2
A23: Re/ Dollar | B23: 69.98 | C23: 71.11 | D23: 71.22 | E23: 69.17 | F23: 70.14
A24: Re/Euro | B24: 80.18 | C24: 80.5 | D24: 80.75 | E24: 77.7 | F24: 78.13
A25: Forward Premia of USD 6-month | B25: 4.09 | C25: 4.11 | D25: 4.16 | E25: 4.16 | F25: 4.28
A26: VIII. Public Borrowing and Inflation
A27: Govt. Market Borrowing-Gross (₹ Billion) 2018-19^ | B27: 4030 | C27: 4510 | D27: 4990 | E27: 5710 | F27: 510 | J27: T_2
A28: Wholesale Price Index (2011-12=100) | B28: 120.1 | C28: 119.2 | D28: 119.5 | E28: 120 | F28: NA | K28: https://eaindustry.nic.in/home.asp
A29: Consumer Price Index (2012 =100) | B29: 140.1 | C29: 139.6 | D29: 139.9 | E29: 140.4 | F29: NA | K29: http://mospi.nic.in/press-release
A30: IX. Index of Industrial Production (y-o-y) percent (Base year 2011-12 = 100)
A31: General | B31: 134 | C31: 134.2 | D31: 127.5 | E31: NA | F31: NA | K31: http://mospi.nic.in/press-release
A32: Mining | B32: 114.4 | C32: 119.2 | D32: 112.3 | E32: NA | F32: NA
A33: Manufacturing | B33: 135.9 | C33: 135.2 | D33: 129.3 | E33: NA | F33: NA
A34: Electricity | B34: 150.3 | C34: 150.9 | D34: 137.7 | E34: NA | F34: NA
A35: X. External Sector Indicators (USD million)
A36: Exports | B36: 27927.72 | C36: 26360.18 | D36: 26667.61 | E36: 32547.97 | F36: NA | K36: http://commerce.gov.in/InnerContent.aspx?Type=TradeStatisticsmenu&Id=254
A37: Imports | B37: 41005.01 | C37: 41085.81 | D37: 36263.02 | E37: 43439.86 | F37: NA
A38: Trade Balance | B38: -13077.29 | C38: -14725.63 | D38: -9595.41 | E38: -10891.89 | F38: NA
A39: Notes:
A40: # Second advance Extimates as per MOSPI press release dated 28.02.2019
A41: ! First revised estimates of national income, consumption expenditure, saving and capital formation for 2017-18 dated, 31.01.2019
A42: ^ cumulative figure value of the respective month for 2018-19
A43: Aggregate Deposit, Bank Credit, Money Supply (M3) and Forex Reserve are updated as per available information on WSS dated 03 May 2019
A44: Data for CPI, WPI, IIP and External sector have been complied based on available information.
A45: Source : RBI, FBIL, MOSPI, Ministry of Commerce & Industry, Office of the Economic Adviser.
