Workbook

Sheet Data Summary
A1: Bulletin Reports Summary for Feb-19
A2: Report Name | B2: Data Status
A3: Table 1: SEBI Registered Market Intermediaries/Institutions | B3: Data Available
A4: Table 2: Company-Wise Capital Raised through Public and Rights Issues (Equity) | B4: Data Available
A5: Table 3: Open Offers under SEBI Takeover Code closed | B5: Data Available
A6: Table 4: Substantial Acquisition of Shares and Takeovers | B6: Data Available
A7: Table 5: Capital Raised from the Primary Market through though Public and Rights Issues | B7: Data Available
A8: Table 6: Issues Listed on SME Platform | B8: Data Available
A9: Table 7: Industry-wise Classification of Capital Raised through Public and Rights Issues | B9: Data Available
A10: Table 8: Sector-wise and Region-wise Distribution of Capital Mobilised through Public and Rights Issues | B10: Data Available
A11: Table 9: Size-wise Classification of Capital Raised through Public and Rights Issues | B11: Data Available
A12: Table 10: Capital Raised by Listed Companies from the Primary Market through QIPs | B12: Data Available
A13: Table 11: Preferential Allotments Listed at BSE and NSE | B13: Data Available
... A78: Table 76: Macro Economic Indicators | B78: Data Available

Sheet 1
A1: Table 1: SEBI Registered Market Intermediaries/Institutions
A2: Market Intermediaries / Institutions | B2: 2017-18 | C2: 2018-19$
A3: Stock Exchanges (Cash Segment) | B3: 5 | C3: 5
A4: Stock Exchanges (Equity Derivatives Segment) | B4: 3 | C4: 3
A5: Stock Exchanges (Currency Derivatives Segment) | B5: 3 | C5: 3
A6: Stock Exchanges (Commodity Derivatives Segment) | B6: 6 | C6: 5
A7: Brokers (Cash Segment) | B7: 3038 | C7: 2549
A8: Brokers (Equity Derivatives Segment) | B8: 2549 | C8: 2502
A9: Brokers (Currency Derivatives Segment) | B9: 2245 | C9: 2162
A10: Brokers (Debt Segment) | B10: 162 | C10: 179
A11: Brokers (Commodity Derivatives Segment) | B11: 1200 | C11: 1670
A12: Corporate Brokers(Cash Segment) | B12: 2647 | C12: 2223
A13: Foreign Portfolio Investors (FPIs) | B13: 9227 | C13: 9410
A14: Custodians | B14: 19 | C14: 20
... A36: STP Service Providers | B36: 2 | C36: 2
A38: $ indicates as on February 28,2019
A39: Source: SEBI, NSDL.

Sheet 2
A1: Table 2: Company-Wise Capital Raised through Public and Rights Issues (Equity)
A2: Sl.No. | B2: Name of the Issuer/Company | C2: Date of Opening | D2: Type of Issue | E2: Type of Instrument | F2: No. of Shares Issued | G2: Face Value (`) | H2: Premium Value (`) | I2: Issue Price (`) | J2: Size of Issue (` Crore)
A3: 1 | B3: Anmol India Limited | C3: 43510 | D3: SME-IPO | E3: Equity | F3: 3100000 | G3: 10 | H3: 23 | I3: 33 | J3: 10.23
A4: 2 | B4: Jonjua Overseas Limited | C4: 43511 | D4: SME-IPO | E4: Equity | F4: 1300000 | G4: 10 | H4: 0 | I4: 10 | J4: 1.3
A5: 3 | B5: Kranti Industries Limited | C5: 43516 | D5: SME-IPO | E5: Equity | F5: 2319000 | G5: 10 | H5: 27 | I5: 37 | J5: 8.5803
A6: 4 | B6: LGB FORGE LIMITED | C6: 43516 | D6: Rights | E6: Equity | F6: 88200912 | G6: 1 | H6: 2 | I6: 3 | J6: 26.46
A7: 5 | B7: Mindpool Technologies Limited | C7: 43516 | D7: SME-IPO | E7: Equity | F7: 1200000 | G7: 10 | H7: 20 | I7: 30 | J7: 3.6
A8: 6 | B8: Gleam Fabmat Limited | C8: 43518 | D8: SME-IPO | E8: Equity | F8: 3120000 | G8: 10 | H8: 0 | I8: 10 | J8: 3.12
A9: All the issues are compiled from the Prospectus of Issuer Companies filed with SEBI.
A10: Source: SEBI.

Sheet 3
A1: Table 3: Open Offers under SEBI Takeover Code closed during Feb-19
A2: Sl.No | B2: Target Company | C2: Acquirer | D2: Offer Opening Date | E2: Offer Closing Date | F2: Offer Size | H2: Offer Price (`) per share | I2: Offer Size (` Crore)
F3: No. of Shares | G3: Percent of Equity Capital
A4: 1 | B4: SHREE DIGVIJAY CEMENT COMPANY LIMITED | C4: NORTH FUND VI LLP | D4: 43487 | E4: 43500 | F4: 35611817 | G4: 25.1 | H4: 23.33 | I4: 83.08
A5: 2 | B5: HATHWAY CABLE AND DATACOM LIMITED | C5: JIO CONTENT DISTRIBUTION HOLDINGS PVT LTD, JIO INTERNET DISTRIBUTION HOLDINGS PVT. LTD., JIO CABLE A | D5: 43496 | E5: 43509 | F5: 460227170 | G5: 26 | H5: 32.35 | I5: 1488.83
A6: 3 | B6: TOURISM FINANCE CORPORATION OF INDIA LIMITED | C6: REDKITE CAPITAL PRIVATE LIMITED | D6: 43501 | E6: 43514 | F6: 20986355 | G6: 26 | H6: 157.2 | I6: 329.91
A7: 4 | B7: DEN NETWORKS LIMITED | C7: JIO FUTURISTIC DIGITAL HOLDINGS PVT LTD, JIO DIDGITAL DISTRIBUTION HOLDINGS PVT. LTD., JIO TELEVISIO | D7: 43504 | E7: 43518 | F7: 122183457 | G7: 25.58 | H7: 72.66 | I7: 887.78
A8: 5 | B8: GTPL HATHWAY LIMITED | C8: JIO CONTENT DISTRIBUTION HOLDINGS PVT LTD, JIO INTERNET DISTRIBUTION HOLDINGS PVT. LTD., JIO CABLE A | D8: 43504 | E8: 43518 | F8: 28840891 | G8: 25.64 | H8: 82.65 | I8: 238.37
A9: Source: SEBI.

Sheet 4
A1: Table 4: Substantial Acquisition of Shares and Takeovers
A2: Year / Month | B2: Open Offers
B3: Objectives | H3: Total
B4: Change in Control of Management | D4: Consolidation of Holdings | F4: Substantial Acquisition | H4: No. of Offers | I4: Amount (` crore)
B5: No. of Offers | C5: Amount (` crore) | D5: No. of Offers | E5: Amount (` crore) | F5: No. of Offers | G5: Amount (` crore)
A6: 2017-18 | B6: 43 | C6: 1510.12 | D6: 3 | E6: 38.27 | F6: 4 | G6: 220.93 | H6: 50 | I6: 1769.22
A7: 2018-19$ | B7: 62 | C7: 22969.03 | D7: 4 | E7: 4636.33 | F7: 4 | G7: 941.23 | H7: 70 | I7: 28546.59
A8: Apr-18 | B8: 13 | C8: 872.94 | D8: 1 | E8: 7.09 | F8: 1 | G8: 934.56 | H8: 15 | I8: 1814.59
A9: May-18 | B9: 7 | C9: 460.71 | D9: 0 | E9: 0 | F9: 1 | G9: 2.78 | H9: 8 | I9: 463.49
A10: Jun-18 | B10: 7 | C10: 32.41 | D10: 2 | E10: 927.24 | F10: 0 | G10: 0 | H10: 9 | I10: 959.65
A11: Jul-18 | B11: 6 | C11: 12.2 | D11: 1 | E11: 3702 | F11: 0 | G11: 0 | H11: 7 | I11: 3714.2
A12: Aug-18 | B12: 0 | C12: 0 | D12: 0 | E12: 0 | F12: 1 | G12: 2.23 | H12: 1 | I12: 2.23
A13: Sep-18 | B13: 3 | C13: 1318.86 | D13: 0 | E13: 0 | F13: 0 | G13: 0 | H13: 3 | I13: 1318.86
A14: Oct-18 | B14: 2 | C14: 70.56 | D14: 0 | E14: 0 | F14: 0 | G14: 0 | H14: 2 | I14: 70.56
A15: Nov-18 | B15: 4 | C15: 651.03 | D15: 0 | E15: 0 | F15: 0 | G15: 0 | H15: 4 | I15: 651.03
A16: Dec-18 | B16: 9 | C16: 43.41 | D16: 0 | E16: 0 | F16: 0 | G16: 0 | H16: 9 | I16: 43.41
A17: Jan-19 | B17: 6 | C17: 16478.94 | D17: 0 | E17: 0 | F17: 1 | G17: 1.66 | H17: 7 | I17: 16480.6
A18: Feb-19 | B18: 5 | C18: 3027.97 | D18: 0 | E18: 0 | F18: 0 | G18: 0 | H18: 5 | I18: 3027.97
A19: $ indicates as on February 28,2019
A20: Source: SEBI.

Sheet 5
A1: Table 5: Capital Raised from the Primary Market through though Public and Rights Issues
A2: Year / Month | B2: Total | D2: Category-Wise | H2: Issue-Type | L2: Instrument-Wise
D3: Public | F3: Rights | H3: Listed | J3: IPOs | L3: Equities | P3: CCPS/FCDs* | R3: Debt
L4: At Par | N4: At Premium
B5: No. of issues | C5: Amount (` crore) | D5: No. of issues | E5: Amount (` crore) | F5: No. of issues | G5: Amount (` crore) | H5: No. of issues | I5: Amount (` crore) | J5: No. of issues | K5: Amount (` crore) | L5: No. of issues | M5: Amount (` crore) | N5: No. of issues | O5: Amount (` crore) | P5: No. of issues | Q5: Amount (` crore) | R5: No. of issues | S5: Amount (` crore)
A6: 2017-18 | B6: 229 | C6: 110359.69 | D6: 208 | E6: 88959.63 | F6: 21 | G6: 21400.06 | H6: 30 | I6: 26585.22 | J6: 199 | K6: 83774.47 | L6: 3 | M6: 10.93 | N6: 218 | O6: 105176.2 | P6: 0 | Q6: 0 | R6: 8 | S6: 5172.56
A7: 2018-19$ | B7: =SUM(B8:B18) -> 144 | C7: =SUM(C8:C18) -> 51182.459 | D7: =SUM(D8:D18) -> 135 | E7: =SUM(E8:E18) -> 49058.627 | F7: =SUM(F8:F18) -> 9 | G7: =SUM(G8:G18) -> 2123.8319 | H7: =SUM(H8:H18) -> 30 | I7: =SUM(I8:I18) -> 35432.329 | ... S7: =SUM(S8:S18) -> 33308.5
A8: Apr-18 | B8: 16 | C8: 3555.31 | D8: 14 | E8: 3405.65 | F8: 2 | G8: 149.66 | H8: 4 | I8: 3363.9267 | J8: 12 | K8: 191.38 | L8: 1 | M8: 3.2 | N8: 13 | O8: 337.84 | P8: 0 | Q8: 0 | R8: 2 | S8: 3214.27
A9: May-18 | B9: 23 | C9: 14429.485 | D9: 23 | E9: 14429.485 | F9: 0 | G9: 0 | H9: 3 | I9: 12204.6 | J9: 20 | K9: 2224.8854 | L9: 0 | M9: 0 | N9: 20 | O9: 2224.8854 | P9: 0 | Q9: 0 | R9: 3 | S9: 12204.6
A10: Jun-18 | B10: 11 | C10: 3151.7067 | D10: 11 | E10: 3151.7067 | F10: 0 | G10: 0 | H10: 0 | I10: 0 | J10: 11 | K10: 3151.7067 | L10: 0 | M10: 0 | N10: 11 | O10: 3151.7067 | P10: 0 | Q10: 0 | R10: 0 | S10: 0
A11: Jul-18 | B11: 15 | C11: 10686.131 | D11: 13 | E11: 9708.3993 | F11: 2 | G11: 977.73191 | H11: 4 | I11: 6607.2519 | J11: 11 | K11: 4078.8793 | L11: 0 | M11: 0 | N11: 13 | O11: 5056.6112 | P11: 0 | Q11: 0 | R11: 2 | S11: 5629.52
A12: Aug-18 | B12: 11 | C12: 1254.11 | D12: 11 | E12: 1254.11 | F12: 0 | G12: 0 | H12: 0 | I12: 0 | J12: 11 | K12: 1254.11 | L12: 1 | M12: 1.35 | N12: 10 | O12: 1252.76 | P12: 0 | Q12: 0 | R12: 0 | S12: 0
A13: Sep-18 | B13: 20 | C13: 8700.7681 | D13: 20 | E13: 8700.7681 | F13: 0 | G13: 0 | H13: 4 | I13: 6284.51 | J13: 16 | K13: 2416.2581 | L13: 0 | M13: 0 | N13: 16 | O13: 2416.26 | P13: 0 | Q13: 0 | R13: 4 | S13: 6284.51
A14: Oct-18 | B14: 17 | C14: 1232.228 | D14: 17 | E14: 1232.228 | F14: 0 | G14: 0 | H14: 2 | I14: 706.79 | J14: 15 | K14: 525.438 | L14: 0 | M14: 0 | N14: 15 | O14: 525.44 | P14: 0 | Q14: 0 | R14: 2 | S14: 706.79
A15: Nov-18 | B15: 6 | C15: 317.52 | D15: 6 | E15: 317.52 | F15: 0 | G15: 0 | H15: 1 | I15: 262.02 | J15: 5 | K15: 55.5 | L15: 0 | M15: 0 | N15: 5 | O15: 55.5 | P15: 0 | Q15: 0 | R15: 1 | S15: 262.02
A16: Dec-18 | B16: 5 | C16: 1028.27 | D16: 3 | E16: 313.02 | F16: 2 | G16: 715.25 | H16: 3 | I16: 978.86 | J16: 2 | K16: 49.41 | L16: 0 | M16: 0 | N16: 4 | O16: 764.66 | P16: 0 | Q16: 0 | R16: 1 | S16: 263.61
A17: Jan-19 | B17: 12 | C17: 5485.17 | D17: 10 | E17: 5230.44 | F17: 2 | G17: 254.73 | H17: 6 | I17: 3709.44 | J17: 6 | K17: 1775.73 | L17: 1 | M17: 5.99 | N17: 7 | O17: 2024.47 | P17: 0 | Q17: 0 | R17: 4 | S17: 3454.71
A18: Feb-19 | B18: 8 | C18: 1341.76 | D18: 7 | E18: 1315.3 | F18: 1 | G18: 26.46 | H18: 3 | I18: 1314.93 | J18: 5 | K18: 26.83 | L18: 2 | M18: 4.45 | N18: 4 | O18: 48.84 | P18: 0 | Q18: 0 | R18: 2 | S18: 1288.47
A19: 1. The total provides category-wise total of any of the three sub-categories viz. public plus rights or issuer-type(listed plus IPOs) or instrument-wise(equities plus CCPS/FCDs plus debt). 2. Amount for public debt issue for last two months is provisional and may get updated 3. All the Issues are compiled from the Prospectus. of Issuer Companies filed with SEBI. 4. * CCPS: Compulsory Convertible Preference Shares, FCDs: Fully Convertible Debentures.
A20: 5. Equity public issues also includes issues listed on SME platform.
A21: $ indicates as on February 28,2019
A22: 6. Since April 2018, both the equity and debt issues are categorised based on their respective closing dates. Prior to April 2018, the equity issues were classified based on opening date of the issue, while debt issues were classfied based on closing date of the issue.
A23: Source: SEBI.

Sheet 6
A1: Table 6: Issues Listed on SME Platform
A2: Year/ Month | B2: Total
B3: No. of issue | C3: Amount (`crore)
A4: 2017-18 | B4: 156 | C4: 2360.8709
A5: 2018-19$ | B5: 102 | C5: 1718.5372
A6: Apr-18 | B6: 12 | C6: 191.3762
A7: May-18 | B7: 19 | C7: 380.88536
A8: Jun-18 | B8: 8 | C8: 135.5554
A9: Jul-18 | B9: 9 | C9: 153.42314
A10: Aug-18 | B10: 10 | C10: 122.9223
A11: Sep-18 | B11: 14 | C11: 309.23812
A12: Oct-18 | B12: 14 | C12: 181.848
A13: Nov-18 | B13: 5 | C13: 55.5004
A14: Dec-18 | B14: 2 | C14: 49.41
A15: Jan-19 | B15: 4 | C15: 111.548
A16: Feb-19 | B16: 5 | C16: 26.8303
A17: $ indicates as on February 28,2019
A18: Source: SEBI

Sheet 7
A1: Table 7: Industry-wise Classification of Capital Raised through Public and Rights Issues
A2: Industry | B2: 2018-19$ | D2: Feb-19
B3: No. of issues | C3: Amount (`crore) | D3: No. of issues | E3: Amount (` crore)
A4: Airlines | B4: 0 | C4: 0 | D4: 0 | E4: 0
A5: Automobiles | B5: 1 | C5: 8.58 | D5: 1 | E5: 8.58
A6: Banks/FIs | B6: 1 | C6: 1131.1876 | D6: 0 | E6: 0
A7: Cement/ Constructions | B7: 4 | C7: 542.1929 | D7: 0 | E7: 0
A8: Chemical | B8: 4 | C8: 621.73783 | D8: 0 | E8: 0
A9: Consumer Services | B9: 1 | C9: 18.7452 | D9: 0 | E9: 0
A10: Electronic Equipments/ Products | B10: 7 | C10: 259.00511 | D10: 0 | E10: 0
A11: Engineering | B11: 9 | C11: 466.7348 | D11: 0 | E11: 0
A12: Entertainment | B12: 1 | C12: 1.35 | D12: 0 | E12: 0
A13: Finance | B13: 26 | C13: 37584.767 | D13: 2 | E13: 1288.47
A14: Food processing | B14: 4 | C14: 90.42232 | D14: 0 | E14: 0
A15: Healthcare | B15: 3 | C15: 58.3014 | D15: 0 | E15: 0
... A27: Total | B27: 145 | C27: 51719.546 | D27: 8 | E27: 1341.76
A28: $ indicates as on February 28,2019
A29: Source: SEBI.

Sheet 8
A1: Table 8: Sector-wise and Region-wise Distribution of Capital Mobilised through Public and Rights Issues
A2: Year / Month | B2: Total | D2: Sector-wise | H2: Region-wise
D3: Private | F3: Public | H3: Northern | J3: Eastern | L3: Western | N3: Southern | P3: Central | R3: Foreign
B4: No. of Issue | C4: Amount (`Crores) | D4: No. of Issue | E4: Amount (` Crores) | F4: No. of Issue | G4: Amount (` Crores) | H4: No. of Issue | I4: Amount (` Crores) | J4: No. of Issue | K4: Amount (` Crores) | L4: No. of Issue | M4: Amount (` Crores) | N4: No. of Issue | O4: Amount (` Crores) | P4: No. of Issue | Q4: Amount (` Crores) | R4: No. of Issue | S4: Amount (` Crores)
A5: 2017-18 | B5: 229 | C5: 110359.69 | D5: 222 | E5: 74118.09 | F5: 7 | G5: 36241.6 | H5: 62 | I5: 13118.88 | J5: 9 | K5: 6628.89 | L5: 129 | M5: 76310.38 | N5: 29 | O5: 14301.53 | P5: 0 | Q5: 0 | R5: 0 | S5: 0
A6: 2018-19$ | B6: 144 | C6: 51182.352 | D6: 141 | E6: 49911.552 | F6: 3 | G6: 1270.8 | H6: 27 | I6: 5342.7705 | J6: 9 | K6: 1165.4395 | L6: 85 | M6: 33603.344 | N6: 19 | O6: 10955.107 | P6: 4 | Q6: 115.7 | R6: 0 | S6: 0
A7: Apr-18 | B7: 16 | C7: 3555.2982 | D7: 16 | E7: 3555.2982 | F7: 0 | G7: 0 | H7: 4 | I7: 90.19618 | J7: 0 | K7: 0 | L7: 8 | M7: 149.12471 | N7: 3 | O7: 3231.382 | P7: 1 | Q7: 84.6 | R7: 0 | S7: 0
A8: May-18 | B8: 23 | C8: 14429.485 | D8: 23 | E8: 14429.485 | F8: 0 | G8: 0 | H8: 4 | I8: 154.6 | J8: 1 | K8: 509.81 | L8: 16 | M8: 13745.875 | N8: 0 | O8: 0 | P8: 2 | Q8: 19.2 | R8: 0 | S8: 0
A9: Jun-18 | B9: 11 | C9: 3151.7067 | D9: 10 | E9: 2691.1967 | F9: 1 | G9: 460.51 | H9: 1 | I9: 460.51 | J9: 0 | K9: 0 | L9: 9 | M9: 2679.2967 | N9: 0 | O9: 0 | P9: 1 | Q9: 11.9 | R9: 0 | S9: 0
A10: Jul-18 | B10: 15 | C10: 10686.03 | D10: 15 | E10: 10686.03 | F10: 0 | G10: 0 | H10: 4 | I10: 1598.2768 | J10: 1 | K10: 60.0075 | L10: 8 | M10: 4851.3931 | N10: 2 | O10: 4176.3538 | P10: 0 | Q10: 0 | R10: 0 | S10: 0
A11: Aug-18 | B11: 11 | C11: 1254.11 | D11: 11 | E11: 1254.11 | F11: 0 | G11: 0 | H11: 2 | I11: 29.8 | J11: 0 | K11: 0 | L11: 8 | M11: 93.12 | N11: 1 | O11: 1131.19 | P11: 0 | Q11: 0 | R11: 0 | S11: 0
A12: Sep-18 | B12: 20 | C12: 8700.7719 | D12: 19 | E12: 8234.0719 | F12: 1 | G12: 466.7 | H12: 4 | I12: 2476.49 | J12: 0 | K12: 0 | L12: 13 | M12: 5262.0945 | N12: 3 | O12: 962.19 | P12: 0 | Q12: 0 | R12: 0 | S12: 0
A13: Oct-18 | B13: 17 | C13: 1232.23 | D13: 16 | E13: 888.64 | F13: 1 | G13: 343.59 | H13: 2 | I13: 7.896 | J13: 4 | K13: 387.072 | L13: 8 | M13: 110.4792 | N13: 3 | O13: 726.7808 | P13: 0 | Q13: 0 | R13: 0 | S13: 0
A14: Nov-18 | B14: 6 | C14: 317.52 | D14: 6 | E14: 317.52 | F14: 0 | G14: 0 | H14: 0 | I14: 0 | J14: 1 | K14: 13.32 | L14: 3 | M14: 10.68 | N14: 2 | O14: 293.52 | P14: 0 | Q14: 0 | R14: 0 | S14: 0
A15: Dec-18 | B15: 5 | C15: 1028.27 | D15: 5 | E15: 1028.27 | F15: 0 | G15: 0 | H15: 1 | I15: 217.67149 | J15: 0 | K15: 0 | L15: 3 | M15: 768.48 | N15: 1 | O15: 42.12 | P15: 0 | Q15: 0 | R15: 0 | S15: 0
A16: Jan-19 | B16: 12 | C16: 5485.17 | D16: 12 | E16: 5485.17 | F16: 0 | G16: 0 | H16: 3 | I16: 302.91 | J16: 1 | K16: 185 | L16: 6 | M16: 4762.05 | N16: 2 | O16: 235.21 | P16: 0 | Q16: 0 | R16: 0 | S16: 0
A17: Feb-19 | B17: 8 | C17: 1341.76 | D17: 8 | E17: 1341.76 | F17: 0 | G17: 0 | H17: 2 | I17: 4.42 | J17: 1 | K17: 10.23 | L17: 3 | M17: 1170.75 | N17: 2 | O17: 156.36 | P17: 0 | Q17: 0 | R17: 0 | S17: 0
A18: $ indicates as on February 28,2019
A19: Source: SEBI.

Sheet 9
A1: Table 9: Size-wise Classification of Capital Raised through Public and Rights Issues
A2: Year / Month | B2: Total | D2: < 5 crore | F2: ≥ 5crore - < 10crore | H2: ≥ 10 crore - < 50 crore | J2: ≥ 50 crore - < 100 crore | L2: ≥ 100 crore
B3: No. of issue | C3: Amount (` crore) | D3: No. of issue | E3: Amount (` crore) | F3: No. of issue | G3: Amount (` crore) | H3: No. of issue | I3: Amount (` crore) | J3: No. of issue | K3: Amount (` crore) | L3: No. of issue | M3: Amount (` crore)
A4: 2017-18 | B4: 229 | C4: 110359.31 | D4: 28 | E4: 108.28 | F4: 41 | G4: 273.58 | H4: 90 | I4: 1848 | J4: 9 | K4: 615.59 | L4: 61 | M4: 107513.86
A5: 2018-19$ | B5: =SUM(B6:B16) -> 144 | C5: =SUM(C6:C16) -> 51182.359 | D5: =SUM(D6:D16) -> 18 | E5: =SUM(E6:E16) -> 62.6668 | F5: =SUM(F6:F16) -> 27 | G5: =SUM(G6:G16) -> 197.3294 | H5: =SUM(H6:H16) -> 56 | I5: =SUM(I6:I16) -> 1226.141 | ... M5: =SUM(M6:M16) -> 49258.706
A6: Apr-18 | B6: 16 | C6: 3555.3 | D6: 3 | E6: 11.9 | F6: 4 | G6: 24.23 | H6: 5 | I6: 120.38 | J6: 2 | K6: 184.52 | L6: 2 | M6: 3214.27
A7: May-18 | B7: 23 | C7: 14429.485 | D7: 1 | E7: 4.44 | F7: 8 | G7: 64.674 | H7: 9 | I7: 233.86136 | J7: 1 | K7: 77.91 | L7: 4 | M7: 14048.6
A8: Jun-18 | B8: 11 | C8: 3151.7054 | D8: 0 | E8: 0 | F8: 2 | G8: 14.164 | H8: 6 | I8: 121.3914 | J8: 0 | K8: 0 | L8: 3 | M8: 3016.15
A9: Jul-18 | B9: 15 | C9: 10686.031 | D9: 1 | E9: 4.5084 | F9: 3 | G9: 22.4534 | H9: 4 | I9: 66.45384 | J9: 1 | K9: 60.0075 | L9: 6 | M9: 10532.608
A10: Aug-18 | B10: 11 | C10: 1254.12 | D10: 2 | E10: 6.13 | F10: 2 | G10: 15.67 | H10: 6 | I10: 101.13 | J10: 0 | K10: 0 | L10: 1 | M10: 1131.19
A11: Sep-18 | B11: 20 | C11: 8700.7681 | D11: 3 | E11: 10.7184 | F11: 2 | G11: 14.268 | H11: 7 | I11: 169.174 | J11: 2 | K11: 115.07772 | L11: 6 | M11: 8391.53
A12: Oct-18 | B12: 17 | C12: 1232.2304 | D12: 3 | E12: 12.78 | F12: 2 | G12: 13.5 | H12: 9 | I12: 155.5704 | J12: 0 | K12: 0 | L12: 3 | M12: 1050.38
A13: Nov-18 | B13: 6 | C13: 317.52 | D13: 2 | E13: 4.17 | F13: 1 | G13: 6.51 | H13: 2 | I13: 44.82 | J13: 0 | K13: 0 | L13: 1 | M13: 262.02
A14: Dec-18 | B14: 5 | C14: 1028.2683 | D14: 0 | E14: 0 | F14: 1 | G14: 7.29 | H14: 1 | I14: 42.12 | J14: 0 | K14: 0 | L14: 3 | M14: 978.85832
A15: Jan-19 | B15: 12 | C15: 5485.17 | D15: 0 | E15: 0 | F15: 1 | G15: 5.99 | H15: 5 | I15: 134.55 | J15: 0 | K15: 0 | L15: 6 | M15: 5344.63
A16: Feb-19 | B16: 8 | C16: 1341.76 | D16: 3 | E16: 8.02 | F16: 1 | G16: 8.58 | H16: 2 | I16: 36.69 | J16: 0 | K16: 0 | L16: 2 | M16: 1288.47
A17: $ indicates as on February 28,2019
A18: Source: SEBI.

Sheet 10
A1: Table 10: Capital Raised by Listed Companies from the Primary Market through QIPs
A2: Year / Month | B2: Only BSE | D2: Only NSE | F2: Only MSEI | H2: Both NSE and BSE | J2: Total
B3: No. of issues | C3: Amount (` Crores) | D3: No. of issues | E3: Amount (` Crores) | F3: No. of issues | G3: Amount (` Crores) | H3: No. of issues | I3: Amount (` Crores) | J3: No. of issues | K3: Amount (` Crores)
A4: 2017-18 | B4: 0 | C4: 0 | D4: 0 | E4: 0 | F4: 0 | G4: 0 | H4: 53 | I4: 67238 | J4: 53 | K4: 67238
A5: 2018-19$ | B5: 0 | C5: 0 | D5: 0 | E5: 0 | F5: 0 | G5: 0 | H5: 12 | I5: 7468.7314 | J5: 12 | K5: 7468.7314
A6: Apr-18 | B6: 0 | C6: 0 | D6: 0 | E6: 0 | F6: 0 | G6: 0 | H6: 3 | I6: 1862 | J6: 3 | K6: 1862
A7: May-18 | B7: 0 | C7: 0 | D7: 0 | E7: 0 | F7: 0 | G7: 0 | H7: 5 | I7: 1008 | J7: 5 | K7: 1008
A8: Jun-18 | B8: 0 | C8: 0 | D8: 0 | E8: 0 | F8: 0 | G8: 0 | H8: 1 | I8: 1200 | J8: 1 | K8: 1200
A9: Jul-18 | B9: 0 | C9: 0 | D9: 0 | E9: 0 | F9: 0 | G9: 0 | H9: 0 | I9: 0 | J9: 0 | K9: 0
A10: Aug-18 | B10: 0 | C10: 0 | D10: 0 | E10: 0 | F10: 0 | G10: 0 | H10: 2 | I10: 2888 | J10: 2 | K10: 2888
A11: Sep-18 | B11: 0 | C11: 0 | D11: 0 | E11: 0 | F11: 0 | G11: 0 | H11: 0 | I11: 0 | J11: 0 | K11: 0
A12: Oct-18 | B12: 0 | C12: 0 | D12: 0 | E12: 0 | F12: 0 | G12: 0 | H12: 0 | I12: 0 | J12: 0 | K12: 0
A13: Nov-18 | B13: 0 | C13: 0 | D13: 0 | E13: 0 | F13: 0 | G13: 0 | H13: 0 | I13: 0 | J13: 0 | K13: 0
A14: Dec-18 | B14: 0 | C14: 0 | D14: 0 | E14: 0 | F14: 0 | G14: 0 | H14: 0 | I14: 0 | J14: 0 | K14: 0
A15: Jan-19 | B15: 0 | C15: 0 | D15: 0 | E15: 0 | F15: 0 | G15: 0 | H15: 1 | I15: 510.79 | J15: 1 | K15: 510.79
A16: Feb-19 | B16: 0 | C16: 0 | D16: 0 | E16: 0 | F16: 0 | G16: 0 | H16: 0 | I16: 0 | J16: 0 | K16: 0
A17: 1. The above data includes both "no. of issues" and "Amount" raised on conversion of convertible securities issued on QIP basis. 2. 2017-18, Includes one issue of Institutional Placement Programme (Issue Size of Rs. 873.92 crore).
A18: $ indicates as on February 28,2019
A19: Source: BSE, NSE and MSEI.

Sheet 11
A1: Table 11: Preferential Allotments Listed at BSE and NSE
A2: Year/Month | B2: Only BSE | D2: Only NSE | F2: Only MSEI | H2: Both NSE and BSE | J2: Total
B3: No. of issues | C3: Amount (` Crores) | D3: No. of issues | E3: Amount (` Crores) | F3: No. of issues | G3: Amount (`Crores) | H3: No. of issues | I3: Amount ` Crores) | J3: No. of issues | K3: Amount (`Crores)
A4: 2017-18 | B4: 189 | C4: 2563.36 | D4: 18 | E4: 715.867 | F4: 8 | G4: 27.73 | H4: 200 | I4: 56193.111 | J4: 407 | K4: 59472.648
A5: 2018-19$ | B5: 200 | C5: 10732.22 | D5: 19 | E5: 8030.59 | F5: 4 | G5: 23.59 | H5: 159 | I5: 164000.5 | J5: 382 | K5: 182786.9
A6: Apr-18 | B6: 17 | C6: 3359.53 | D6: 3 | E6: 1931.55 | F6: 1 | G6: 13.7 | H6: 39 | I6: 67145.29 | J6: 60 | K6: 72450.07
A7: May-18 | B7: 14 | C7: 2131.5 | D7: 1 | E7: 52.43 | F7: 0 | G7: 0 | H7: 10 | I7: 627.91 | J7: 25 | K7: 2811.84
A8: Jun-18 | B8: 23 | C8: 2906.38 | D8: 0 | E8: 0 | F8: 1 | G8: 2.64 | H8: 16 | I8: 21640.46 | J8: 40 | K8: 24549.48
A9: Jul-18 | B9: 30 | C9: 530.4 | D9: 4 | E9: 15 | F9: 0 | G9: 0 | H9: 14 | I9: 10815.83 | J9: 48 | K9: 11361.23
A10: Aug-18 | B10: 17 | C10: 386.8 | D10: 3 | E10: 3272.27 | F10: 0 | G10: 0 | H10: 14 | I10: 579.6 | J10: 34 | K10: 4238.67
A11: Sep-18 | B11: 15 | C11: 261.87 | D11: 2 | E11: 2710.08 | F11: 0 | G11: 0 | H11: 5 | I11: 440.22 | J11: 22 | K11: 3412.17
A12: Oct-18 | B12: 17 | C12: 140.82 | D12: 0 | E12: 0 | F12: 1 | G12: 1.94 | H12: 12 | I12: 3504.63 | J12: 30 | K12: 3647.39
A13: Nov-18 | B13: 14 | C13: 219.02 | D13: 3 | E13: 18.94 | F13: 0 | G13: 0 | H13: 17 | I13: 24021.51 | J13: 34 | K13: 24259.47
A14: Dec-18 | B14: 22 | C14: 425.95 | D14: 0 | E14: 0 | F14: 1 | G14: 5.31 | H14: 13 | I14: 2784.12 | J14: 36 | K14: 3215.38
A15: Jan-19 | B15: 15 | C15: 201.42 | D15: 1 | E15: 7.32 | F15: 0 | G15: 0 | H15: 10 | I15: 19635.74 | J15: 26 | K15: 19844.48
A16: Feb-19 | B16: 16 | C16: 168.53 | D16: 2 | E16: 23 | F16: 0 | G16: 0 | H16: 9 | I16: 12805.19 | J16: 27 | K16: 12996.72
A17: $ indicates as on February 28,2019
A18: Source: BSE, NSE and MSEI.

Sheet 12
A1: Table 12: Private Placement of Corporate Debt Reported to BSE and NSE
A2: Year/Month | B2: Only NSE | D2: Only BSE | F2: Both NSE and BSE | H2: TOTAL
B3: No. of Issues | C3: Amount (`Crores) | D3: No. of Issues | E3: Amount (` Crores) | F3: No. of Issues | G3: Amount (` Crores) | H3: No. of Issues | I3: Amount (` Crores)
A4: 2017-18 | B4: 721 | C4: 170834.77 | D4: 1812 | E4: 234614.24 | F4: 173 | G4: 193698 | H4: 2706 | I4: 599147.01
A5: 2018-19$ | B5: 436 | C5: 152699.99 | D5: 1543 | E5: 202371.48 | F5: 159 | G5: 140928.72 | H5: 2138 | I5: 465367.78
A6: Apr-18 | B6: 42 | C6: 18516.74 | D6: 214 | E6: 31435 | F6: 16 | G6: 16187 | H6: 272 | I6: 66138.74
A7: May-18 | B7: 15 | C7: 1924 | D7: 104 | E7: 7114.98 | F7: 3 | G7: 1500 | H7: 122 | I7: 10538.98
A8: Jun-18 | B8: 33 | C8: 11031.46 | D8: 92 | E8: 7838.36 | F8: 9 | G8: 4863.5 | H8: 134 | I8: 23733.32
A9: Jul-18 | B9: 48 | C9: 11555.75 | D9: 161 | E9: 19076.66 | F9: 12 | G9: 1319.4 | H9: 221 | I9: 1319.4
A10: Aug-18 | B10: 48 | C10: 11382.65 | D10: 159 | E10: 17721.12 | F10: 13 | G10: 7812.3 | H10: 220 | I10: 36916.07
A11: Sep-18 | B11: 45 | C11: 10823.91 | D11: 152 | E11: 19543.6 | F11: 7 | G11: 1434.2 | H11: 204 | I11: 31801.71
A12: Oct-18 | B12: 31 | C12: 11145.59 | D12: 116 | E12: 5589.39 | F12: 8 | G12: 15159 | H12: 155 | I12: 31893.98
A13: Nov-18 | B13: 34 | C13: 16814.55 | D13: 104 | E13: 18366.16 | F13: 20 | G13: 20034.1 | H13: 158 | I13: 55214.81
A14: Dec-18 | B14: 52 | C14: 28334.722 | D14: 109 | E14: 25663.85 | F14: 24 | G14: 30926.5 | H14: 185 | I14: 84925.072
A15: Jan-19 | B15: 59 | C15: 18057 | D15: 192 | E15: 33432.89 | F15: 33 | G15: 32097.328 | H15: 284 | I15: 83587.218
A16: Feb-19 | B16: 29 | C16: 13113.616 | D16: 140 | E16: 16589.472 | F16: 14 | G16: 9595.3945 | H16: 183 | I16: 39298.483
A17: $ indicates as on February 28, 2018
A18: Source: BSE and NSE

Sheet 13
A1: Table 13: Trading in the Corporate Debt Market
A2: Year / Month | B2: BSE | D2: NSE | F2: MSEI | H2: Total
B3: No. of Trades | C3: Traded Value (` crore) | D3: No. of Trades | E3: Traded Value (` crore) | F3: No. of Trades | G3: Traded Value (` crore) | H3: No. of Trades | I3: Traded Value (` crore)
A4: 2017-18 | B4: 30008 | C4: 494674.7 | D4: 61395 | E4: 1303423.4 | F4: 1 | G4: 0.22 | H4: 91404 | I4: 1798098.4 | J4: 152800
A5: 2018-19$ | B5: =SUM(B6:B16) -> 37952 | C5: =SUM(C6:C16) -> 552731.13 | D5: =SUM(D6:D16) -> 52248 | E5: =SUM(E6:E16) -> 992748.44 | F5: =SUM(F6:F16) -> 0 | G5: =SUM(G6:G16) -> 0 | H5: =SUM(H6:H16) -> 90200 | I5: =SUM(I6:J16) -> 1545479.6
A6: Apr-18 | B6: 3442 | C6: 48912.74 | D6: 5588 | E6: 113974.59 | F6: 0 | G6: 0 | H6: 9030 | I6: 162887.33
A7: May-18 | B7: 4470 | C7: 87009.74 | D7: 1770 | E7: 22494.35 | F7: 0 | G7: 0 | H7: 6240 | I7: 109504.09
A8: Jun-18 | B8: 3067 | C8: 53079.63 | D8: 5252 | E8: 103335.67 | F8: 0 | G8: 0 | H8: 8319 | I8: 156415.3
A9: Jul-18 | B9: 3122 | C9: 54314.01 | D9: 4535 | E9: 91539.73 | F9: 0 | G9: 0 | H9: 7657 | I9: 145853.74
A10: Aug-18 | B10: 3534 | C10: 43548.04 | D10: 5036 | E10: 92454.69 | F10: 0 | G10: 0 | H10: 8570 | I10: 136002.73
A11: Sep-18 | B11: 2840 | C11: 37394.78 | D11: 4388 | E11: 85624.29 | F11: 0 | G11: 0 | H11: 7228 | I11: 123019.07
A12: Oct-18 | B12: 2958 | C12: 35876.15 | D12: 4572 | E12: 85078.91 | F12: 0 | G12: 0 | H12: 7530 | I12: 120955.06
A13: Nov-18 | B13: 2921 | C13: 40772.97 | D13: 4214 | E13: 82928.38 | F13: 0 | G13: 0 | H13: 7135 | I13: 123701.35
A14: Dec-18 | B14: 3626 | C14: 56467.11 | D14: 5903 | E14: 123701.67 | F14: 0 | G14: 0 | H14: 9529 | I14: 180168.78
A15: Jan-19 | B15: 4416 | C15: 55223.13 | D15: 6164 | E15: 109125.49 | F15: 0 | G15: 0 | H15: 10580 | I15: 164348.62
A16: Feb-19 | B16: 3556 | C16: 40132.83 | D16: 4826 | E16: 82490.67 | F16: 0 | G16: 0 | H16: 8382 | I16: 122623.5
A17: $ indicates as on February 28, 2018
A18: Source: BSE, NSE and MSEI.

Sheet 14
A1: Table 14: Ratings Assigned for Long-term Corporate Debt Securities (Maturity ≥ 1 year)
A2: Grade | B2: Investment Grade | J2: Non-Investment Grade | L2: Total
B3: Highest Safety (AAA) | D3: High Safety (AA) | F3: Adequate Safety (A) | H3: Moderate Safety (BBB)
A4: Period | B4: No. of issue | C4: Amount (`crore) | D4: No. of issue | E4: Amount (` crore) | F4: No. of issue | G4: Amount (` crore) | H4: No. of issue | I4: Amount (` crore) | J4: No. of issue | K4: Amount (` crore) | L4: No. of issue | M4: Amount (` crore)
A5: 2017-18 | B5: 280 | C5: 1596761.1 | D5: 538 | E5: 408841.17 | F5: 322 | G5: 104834 | H5: 216 | I5: 16271.32 | J5: 88 | K5: 10928.98 | L5: 1444 | M5: 2137636.5
A6: 2018-19$ | B6: =SUM(B7:B17) -> 240 | C6: =SUM(C7:C17) -> 1270384.8 | D6: =SUM(D7:D17) -> 347 | E6: =SUM(E7:E17) -> 286488.45 | F6: =SUM(F7:F17) -> 306 | G6: =SUM(G7:G17) -> 93148.92 | H6: =SUM(H7:H17) -> 207 | I6: =SUM(I7:I17) -> 19156.626 | ... M6: =SUM(M7:M17) -> 1680617.4
A7: Apr-18 | B7: 21 | C7: 85560.55 | D7: 22 | E7: 16730 | F7: 13 | G7: 7273.57 | H7: 9 | I7: 1837.03 | J7: 3 | K7: 1496.41 | L7: 68 | M7: 112897.56
A8: May-18 | B8: 15 | C8: 89278.02 | D8: 22 | E8: 8175 | F8: 16 | G8: 3913.14 | H8: 11 | I8: 1455.11 | J8: 2 | K8: 151 | L8: 66 | M8: 102972.27
A9: Jun-18 | B9: 12 | C9: 35060.97 | D9: 32 | E9: 29036.61 | F9: 28 | G9: 8958.55 | H9: 15 | I9: 2349.19 | J9: 7 | K9: 664.43 | L9: 94 | M9: 76069.75
A10: Jul-18 | B10: 21 | C10: 74224.46 | D10: 29 | E10: 33412.13 | F10: 24 | G10: 3184.32 | H10: 14 | I10: 1432.026 | J10: 3 | K10: 42.76 | L10: 91 | M10: 112295.7
A11: Aug-18 | B11: 23 | C11: 150168.39 | D11: 41 | E11: 44267.69 | F11: 31 | G11: 5276.04 | H11: 18 | I11: 1549.69 | J11: 5 | K11: 4729.1 | L11: 118 | M11: 205990.91
A12: Sep-18 | B12: 19 | C12: 44744.61 | D12: 34 | E12: 16583.67 | F12: 25 | G12: 4558.79 | H12: 19 | I12: 1307.91 | J12: 3 | K12: 580 | L12: 100 | M12: 67774.98
A13: Oct-18 | B13: 24 | C13: 228957.98 | D13: 25 | E13: 32123.03 | F13: 14 | G13: 2177.16 | H13: 19 | I13: 492.77 | J13: 1 | K13: 28 | L13: 83 | M13: 263778.94
A14: Nov-18 | B14: 17 | C14: 34811.13 | D14: 44 | E14: 35696.02 | F14: 21 | G14: 7363.66 | H14: 18 | I14: 1231.1 | J14: 5 | K14: 225.66 | L14: 105 | M14: 79327.57
A15: Dec-18 | B15: 33 | C15: 201626.46 | D15: 34 | E15: 34743.62 | F15: 26 | G15: 5800.35 | H15: 20 | I15: 696.74 | J15: 4 | K15: 457 | L15: 117 | M15: 243324.17
A16: Jan-19 | B16: 26 | C16: 74616.84 | D16: 34 | E16: 18764.15 | F16: 80 | G16: 36700.69 | H16: 43 | I16: 6252.83 | J16: 10 | K16: 2694.2 | L16: 193 | M16: 139028.71
A17: Feb-19 | B17: 29 | C17: 251335.39 | D17: 30 | E17: 16956.53 | F17: 28 | G17: 7942.65 | H17: 21 | I17: 552.23 | J17: 3 | K17: 370 | L17: 111 | M17: 277156.8
A18: $ indicates as on February 28,2019
A19: Source: Credit Rating Agencies.

Sheet 15
A1: Table 15: Review of Accepted Ratings of Corporate Debt Securities (Maturity ≥ 1 year)
A2: Grade | B2: Upgraded | D2: Downgraded | F2: Reaffirmed | H2: Rating Watch | J2: Withdrawn/ Suspended | L2: Total
A3: Period | B3: No. of issue | C3: Amount (`crore) | D3: No. of issue | E3: Amount (`crore) | F3: No. of issue | G3: Amount (`crore) | H3: No. of issue | I3: Amount (`crore) | J3: No. of issue | K3: Amount (`crore) | L3: No. of issue | M3: Amount (`crore)
A4: 2017-18 | B4: 360 | C4: 154861.12 | D4: 331 | E4: 303486.87 | F4: 3591 | G4: 10772518 | H4: 134 | I4: 202450.83 | J4: 894 | K4: 249959.15 | L4: 5310 | M4: 11683276
A5: 2018-19$ | B5: =SUM(B6:B16) -> 650 | C5: =SUM(C6:C16) -> 245768.09 | D5: =SUM(D6:D16) -> 780 | E5: =SUM(E6:E16) -> 782291.3 | F5: =SUM(F6:F16) -> 4980 | G5: =SUM(G6:G16) -> 9999879.1 | H5: =SUM(H6:H16) -> 443 | I5: =SUM(I6:I16) -> 1070982.5 | ... M5: =SUM(M6:M16) -> 12526638
A6: Apr-18 | B6: 28 | C6: 19680.55 | D6: 7 | E6: 683.21 | F6: 310 | G6: 523390.07 | H6: 3 | I6: 2351 | J6: 66 | K6: 30074.17 | L6: 414 | M6: 576179
A7: May-18 | B7: 36 | C7: 8241.89 | D7: 65 | E7: 58224.05 | F7: 369 | G7: 629541.83 | H7: 11 | I7: 7050 | J7: 82 | K7: 16243.84 | L7: 563 | M7: 719301.61
A8: Jun-18 | B8: 122 | C8: 24678.66 | D8: 31 | E8: 27659.57 | F8: 604 | G8: 852387.89 | H8: 3 | I8: 7235 | J8: 101 | K8: 11516.43 | L8: 861 | M8: 923477.55
A9: Jul-18 | B9: 24 | C9: 3101.28 | D9: 52 | E9: 33374.91 | F9: 569 | G9: 694334.55 | H9: 22 | I9: 13707.45 | J9: 116 | K9: 45149.74 | L9: 783 | M9: 789667.93
A10: Aug-18 | B10: 155 | C10: 114544.94 | D10: 63 | E10: 39757.59 | F10: 520 | G10: 756647.31 | H10: 17 | I10: 17147 | J10: 115 | K10: 75942.13 | L10: 870 | M10: 1004039
A11: Sep-18 | B11: 49 | C11: 16439.61 | D11: 149 | E11: 116232.35 | F11: 606 | G11: 1585493.2 | H11: 59 | I11: 67280.51 | J11: 69 | K11: 7939.5 | L11: 932 | M11: 1793385.2
A12: Oct-18 | B12: 83 | C12: 46694.79 | D12: 38 | E12: 16351.23 | F12: 351 | G12: 1166733.7 | H12: 11 | I12: 4195.1 | J12: 59 | K12: 10214.71 | L12: 542 | M12: 1244189.6
A13: Nov-18 | B13: 15 | C13: 1348.16 | D13: 82 | E13: 129966.3 | F13: 451 | G13: 556977.9 | H13: 52 | I13: 54116.8 | J13: 86 | K13: 22903.27 | L13: 686 | M13: 765312.43
A14: Dec-18 | B14: 72 | C14: 5921.18 | D14: 52 | E14: 32465.97 | F14: 476 | G14: 1244178.2 | H14: 44 | I14: 739936 | J14: 85 | K14: 10848.29 | L14: 729 | M14: 2032349.6
A15: Jan-19 | B15: 33 | C15: 2350.75 | D15: 36 | E15: 47927.16 | F15: 309 | G15: 523632.84 | H15: 104 | I15: 79515 | J15: 73 | K15: 22677.48 | L15: 555 | M15: 676103.23
A16: Feb-19 | B16: 33 | C16: 2766.28 | D16: 205 | E16: 279648.96 | F16: 415 | G16: 1466561.6 | H16: 117 | I16: 78448.67 | J16: 84 | K16: 175207.16 | L16: 854 | M16: 2002632.6
A17: $ indicates as on February 28,2019
A18: Source: Credit Rating Agencies.

Sheet 16
A1: Table 16: Distribution of Turnover on Cash Segments of Stock Exchanges (`crore)
A2: Stock Exchanges | B2: 2017-18 | C2: 2018-19$ | D2: Feb-19
A3: BSE | B3: 1082968.2 | C3: 694613.02 | D3: 50655.69
A4: MSEI | B4: 192.76941 | C4: 24.514193 | D4: 5.2180822
A5: NSE | B5: 7234825.7 | C5: 7251779.8 | D5: 639270.41
A6: $ indicates as on February 28, 2018
A7: Source: BSE, NSE and MSEI.

Sheet 17
A1: Table 17: Trends in Cash Segment of BSE
A2: Year / Month | B2: No. of Companies Listed | C2: No. of Companies Permitted* | D2: No. of companies traded | E2: No. of Trading Days | F2: No. of Trades (Lakh) | G2: Traded Quantity (Lakh) | H2: Turnover (` crore) | I2: Average Daily Turnover (` crore) | J2: Average Trade Size (`) | K2: Demat Securities Traded (Lakh) | L2: Demat Turnover (` crore) | M2: Market Capitalisation (` crore) | N2: S&P BSE Sensex
N3: High | O3: Low | P3: Close
A4: 2017-18 | B4: 5619 | C4: 52 | D4: 2794 | E4: 246 | F4: 3585.9 | G4: 771603.31 | H4: 1082968.2 | I4: 4402.3099 | J4: 30200.737 | K4: 771603.31 | L4: 1082968.1 | M4: 14224997 | N4: 36443.98 | O4: 29241.48 | P4: 32968.68
A5: 2018-19$ | B5: 5251 | C5: 36 | D5: 2614 | E5: 229 | F5: 2889.34 | G5: 467062.61 | H5: 694613.02 | I5: 3033.2446 | J5: 24040.543 | K5: 467062.61 | L5: 694612.91 | M5: 14041530 | N5: 38989.65 | O5: 32972.56 | P5: 35867.44
A6: Apr-18 | B6: 5638 | C6: 52 | D6: 2768 | E6: 21 | F6: 233.88 | G6: 47332.62 | H6: 71629.66 | I6: 3410.9362 | J6: 30626.672 | K6: 47332.62 | L6: 71629.66 | M6: 15279535 | N6: 35213.3 | O6: 32972.56 | P6: 35160.36
A7: May-18 | B7: 5450 | C7: 52 | D7: 2755 | E7: 22 | F7: 258.01 | G7: 51335.45 | H7: 75360.5 | I7: 3425.4773 | J7: 29208.364 | K7: 51335.45 | L7: 75360.5 | M7: 14869671 | N7: 35993.53 | O7: 34302.89 | P7: 35322.38
A8: Jun-18 | B8: 5458 | C8: 36 | D8: 2698 | E8: 21 | F8: 191.19 | G8: 41057.9 | H8: 64162.59 | I8: 3055.3614 | J8: 33559.595 | K8: 41057.9 | L8: 64162.58 | M8: 14501942 | N8: 35877.41 | O8: 34784.68 | P8: 35423.48
A9: Jul-18 | B9: 5240 | C9: 36 | D9: 2763 | E9: 22 | F9: 242.84 | G9: 41849.87 | H9: 65168.48 | I9: 2962.2036 | J9: 26835.974 | K9: 41849.87 | L9: 65168.48 | M9: 15314574 | N9: 37644.59 | O9: 35106.57 | P9: 37606.58
A10: Aug-18 | B10: 5233 | C10: 36 | D10: 2823 | E10: 21 | F10: 292 | G10: 45597 | H10: 67896 | I10: 3233 | J10: 23230 | K10: 45597 | L10: 67896 | M10: 15934696 | N10: 38989.65 | O10: 37128.99 | P10: 38645.07
A11: Sep-18 | B11: 5232 | C11: 36 | D11: 2763 | E11: 18 | F11: 297.68 | G11: 38742.96 | H11: 62476.71 | I11: 3470.9283 | J11: 20987.876 | K11: 38742.96 | L11: 62476.7 | M11: 14486402 | N11: 38934.35 | O11: 35985.63 | P11: 36227.14
A12: Oct-18 | B12: 5217 | C12: 36 | D12: 2660 | E12: 21 | F12: 337.3 | G12: 43932.5 | H12: 66384.71 | I12: 3161.1767 | J12: 19681.207 | K12: 43932.5 | L12: 66384.7 | M12: 13845109 | N12: 36616.64 | O12: 33291.58 | P12: 34442.05
A13: Nov-18 | B13: 5216 | C13: 36 | D13: 2719 | E13: 20 | F13: 255.31 | G13: 38075.67 | H13: 59063.84 | I13: 2953.192 | J13: 23134.166 | K13: 38075.67 | L13: 59063.82 | M13: 14288776 | N13: 36389.22 | O13: 34303.38 | P13: 36194.3
A14: Dec-18 | B14: 5232 | C14: 36 | D14: 2756 | E14: 20 | F14: 249.04 | G14: 38058.08 | H14: 50482.91 | I14: 2524.1455 | J14: 20271.005 | K14: 38058.08 | L14: 50482.89 | M14: 14448466 | N14: 36554.99 | O14: 34426.29 | P14: 36068.33
A15: Jan-19 | B15: 5244 | C15: 36 | D15: 2663 | E15: 23 | F15: 274.63 | G15: 38852.44 | H15: 61332.33 | I15: 2666.623 | J15: 22332.713 | K15: 38852.44 | L15: 61332.31 | M15: 14099330 | N15: 36701.03 | O15: 35375.51 | P15: 36256.69
A16: Feb-19 | B16: 5251 | C16: 36 | D16: 2614 | E16: 20 | F16: 257.18 | G16: 42228.53 | H16: 50655.69 | I16: 2532.7845 | J16: 19696.59 | K16: 42228.53 | L16: 50655.67 | M16: 14041530 | N16: 37172.18 | O16: 35287.16 | P16: 35867.44
A17: $ indicates as on February 28,2019
A18: Source: BSE .

Sheet 18
A1: Table 18: Trends in Cash Segment of NSE
A2: Year / Month | B2: No. of Companies Listed | C2: No. of Companies Permitted* | D2: No. of companies traded | E2: No. of Trading Days | F2: No. of Trades (Lakh) | G2: Traded Quantity (Lakh) | H2: Turnover (` crore) | I2: Average Daily Turnover (` crore) | J2: Average Trade Size (`) | K2: Demat Securities Traded (Lakh) | L2: Demat Turnover (` crore) | M2: Market Capitalisation (` crore) | N2: Nifty 50 Index
N3: High | O3: Low | P3: Close
A4: 2017-18 | B4: 1931 | C4: 4 | D4: 1850 | E4: 246 | F4: 24913.765 | G4: 3771836.1 | H4: 7234825.7 | I4: 29409.861 | J4: 29039.471 | K4: 3771836.1 | L4: 7234825.7 | M4: 14044152 | N4: 11172 | O4: 9075 | P4: 10114
A5: 2018-19$ | B5: 1929 | C5: 4 | D5: 1917 | E5: 229 | F5: 26190.121 | G5: 3396913.9 | H5: 7251779.8 | I5: 31667.161 | J5: 27688.989 | K5: 3396913.9 | L5: 7251779.8 | M5: 13871449 | N5: 11760.2 | O5: 10004.55 | P5: 10792.5
A6: Apr-18 | B6: 1952 | C6: 4 | D6: 1817 | E6: 21 | F6: 2176.793 | G6: 298453.35 | H6: 641440.35 | I6: 30544.779 | J6: 29467.221 | K6: 298453.35 | L6: 641440.35 | M6: 15092002 | N6: 10759 | O6: 10111.3 | P6: 10739.35
A7: May-18 | B7: 1941 | C7: 4 | D7: 1820 | E7: 22 | F7: 2467.6265 | G7: 342154.59 | H7: 700012.61 | I7: 31818.755 | J7: 28367.851 | K7: 342154.59 | L7: 700012.61 | M7: 14693260 | N7: 10929.2 | O7: 10417.8 | P7: 10736.15
A8: Jun-18 | B8: 1951 | C8: 4 | D8: 1833 | E8: 21 | F8: 2225.0549 | G8: 280206.37 | H8: 591696.23 | I8: 28176.011 | J8: 26592.433 | K8: 280206.37 | L8: 591696.23 | M8: 14329072 | N8: 10893.25 | O8: 10550.9 | P8: 10714.3
A9: Jul-18 | B9: 1938 | C9: 4 | D9: 1840 | E9: 22 | F9: 2351.817 | G9: 313395.73 | H9: 662867.42 | I9: 30130.337 | J9: 28185.332 | K9: 313395.73 | L9: 662867.42 | M9: 15128449 | N9: 11366 | O9: 10604.65 | P9: 11356.5
A10: Aug-18 | B10: 1916 | C10: 4 | D10: 1841 | E10: 21 | F10: 2408.0901 | G10: 329844.7 | H10: 705869.43 | I10: 33612.83 | J10: 29312.417 | K10: 329844.7 | L10: 705869.43 | M10: 15730918 | N10: 11760.2 | O10: 11234.95 | P10: 11680.5
A11: Sep-18 | B11: 1912 | C11: 4 | D11: 1847 | E11: 18 | F11: 2405.3247 | G11: 303803.53 | H11: 688318.89 | I11: 38239.938 | J11: 28616.465 | K11: 303803.53 | L11: 688318.89 | M11: 14292302 | N11: 11751.8 | O11: 10850.3 | P11: 10930.45
A12: Oct-18 | B12: 1921 | C12: 4 | D12: 1854 | E12: 21 | F12: 2888.8986 | G12: 330715.65 | H12: 745584.25 | I12: 35504.012 | J12: 25808.599 | K12: 330715.65 | L12: 745584.25 | M12: 13693825 | N12: 11035.65 | O12: 10004.55 | P12: 10386.6
A13: Nov-18 | B13: 1922 | C13: 4 | D13: 1850 | E13: 20 | F13: 2304.4386 | G13: 282181.67 | H13: 610913.7 | I13: 30545.685 | J13: 26510.305 | K13: 282181.67 | L13: 610913.7 | M13: 14122535 | N13: 10922.45 | O13: 10341.9 | P13: 10876.75
A14: Dec-18 | B14: 1923 | C14: 4 | D14: 1856 | E14: 20 | F14: 2198.8518 | G14: 287797.21 | H14: 599917.42 | I14: 29995.871 | J14: 27283.213 | K14: 287797.21 | L14: 599917.42 | M14: 14279083 | N14: 10985.15 | O14: 10333.85 | P14: 10862.55
A15: Jan-19 | B15: 1926 | C15: 4 | D15: 1854 | E15: 23 | F15: 2386.5067 | G15: 281350.43 | H15: 665889.12 | I15: 28951.701 | J15: 27902.252 | K15: 281350.43 | L15: 665889.12 | M15: 13916643 | N15: 10987.45 | O15: 10583.65 | P15: 10830.95
A16: Feb-19 | B16: 1929 | C16: 4 | D16: 1859 | E16: 20 | F16: 2376.7194 | G16: 347010.68 | H16: 639270.41 | I16: 31963.52 | J16: 26897.177 | K16: 347010.68 | L16: 639270.41 | M16: 13871449 | N16: 11118.1 | O16: 10585.65 | P16: 10792.5
A17: Source: NSE
A18: $ indicates up to February 28,2019

Sheet 19
A1: Table 19: Trends in Cash Segment of MSEI
A2: Year/Month | B2: No. of Companies Listed | C2: No. of Companies Permitted # | D2: No. of Companies Traded | E2: No. of Trading Days | F2: No. of Trades (Lakh) | G2: Traded Quantity (Lakh) | H2: Turnover (₹ crore) | I2: Average Daily Turnover (₹ crore) | J2: Average Trade Size (`) | K2: Demat Securities Traded (Lakh) | L2: Demat Turnover (₹ crore) | M2: Market Capitalisation (₹ crore) | N2: SX 50 Index
N3: High | O3: Low | P3: Close
A4: 2017-18 | B4: 270 | C4: 1326 | D4: 12 | E4: 246 | F4: 0.02823 | G4: 151.78948 | H4: 192.76941 | I4: 0.78361548 | J4: 682853.02 | K4: 0 | L4: 0 | M4: 13896724 | N4: 21581.92 | O4: 17684.5 | P4: 19686.18
A5: 2018-19$ | B5: 287 | C5: 1311 | D5: 8 | E5: 229 | F5: 0.01563 | G5: 11.42328 | H5: 24.514193 | I5: 0.10704888 | J5: 156840.64 | K5: 11.42317 | L5: 24.508544 | M5: 13687100 | N5: 22872.75 | O5: 19644.59 | P5: 21135.33
A6: Apr-18 | B6: 273 | C6: 1329 | D6: 5 | E6: 21 | F6: 0.00163 | G6: 0.39826 | H6: 1.2880075 | I6: 0.061333691 | J6: 79019 | K6: 0 | L6: 0 | M6: 14855347 | N6: 21070.86 | O6: 19735.82 | P6: 21070.86
A7: May-18 | B7: 277 | C7: 1330 | D7: 4 | E7: 22 | F7: 0.00199 | G7: 0.9141 | H7: 1.8949297 | I7: 0.08613317 | J7: 95222.601 | K7: 0 | L7: 0 | M7: 14469622 | N7: 21084.31 | O7: 20354.57 | P7: 20866.91
A8: Jun-18 | B8: 277 | C8: 1330 | D8: 3 | E8: 21 | F8: 0.00024 | G8: 0.1237 | H8: 0.393194 | I8: 0.018723524 | J8: 163830.83 | K8: 0 | L8: 0 | M8: 14088829 | N8: 21212.67 | O8: 20608.49 | P8: 20874.72
A9: Jul-18 | B9: 277 | C9: 1329 | D9: 3 | E9: 22 | F9: 0.00028 | G9: 0.15975 | H9: 0.4017769 | I9: 0.018262586 | J9: 143491.75 | K9: 0.1598 | L9: 0.4018 | M9: 14873846 | N9: 22078.12 | O9: 20756.42 | P9: 22078.12
A10: Aug-18 | B10: 278 | C10: 1329 | D10: 2 | E10: 21 | F10: 0 | G10: 0.31 | H10: 0.92 | I10: 0.04 | J10: 107218.3 | K10: 0.31 | L10: 0.92 | M10: 15483703 | N10: 22872.75 | O10: 21884.71 | P10: 22759.78
A11: Sep-18 | B11: 282 | C11: 1317 | D11: 2 | E11: 18 | F11: 0.0009 | G11: 0.5395 | H11: 1.1962385 | I11: 0.066457694 | J11: 132915.39 | K11: 0.5395 | L11: 1.1962 | M11: 14072761 | N11: 22605.73 | O11: 21418.2 | P11: 21418.2
A12: Oct-18 | B12: 281 | C12: 1320 | D12: 2 | E12: 21 | F12: 0.00082 | G12: 0.3928 | H12: 0.9920585 | I12: 0.047240881 | J12: 120982.74 | K12: 0.3928 | L12: 0.9920585 | M12: 13489960 | N12: 21585.1 | O12: 19644.59 | P12: 20329.99
A13: Nov-18 | B13: 282 | C13: 1319 | D13: 3 | E13: 20 | F13: 0.00127 | G13: 0.87926 | H13: 1.7222751 | I13: 0.086113755 | J13: 135612.21 | K13: 0.87926 | L13: 1.72 | M13: 13917651 | N13: 21349.05 | O13: 20309.95 | P13: 21349.05
A14: Dec-18 | B14: 282 | C14: 1318 | D14: 2 | E14: 20 | F14: 0.00124 | G14: 0.446 | H14: 1.2421985 | I14: 0.062109925 | J14: 100177.3 | K14: 0.446 | L14: 1.2422 | M14: 14070348 | N14: 21498.26 | O14: 20597.85 | P14: 21273.63
A15: Jan-19 | B15: 284 | C15: 1318 | D15: 6 | E15: 23 | F15: 0.00377 | G15: 4.67015 | H15: 9.2433544 | I15: 0.40188498 | J15: 245181.82 | K15: 4.67015 | L15: 9.2433544 | M15: 13741805 | N15: 21515.91 | O15: 20909.05 | P15: 21284.45
A16: Feb-19 | B16: 287 | C16: 1311 | D16: 4 | E16: 20 | F16: 0.00263 | G16: 2.58796 | H16: 5.2180822 | I16: 0.26090411 | J16: 198406.17 | K16: 2.588 | L16: 5.2181 | M16: 13687100 | N16: 21745.26 | O16: 20799.89 | P16: 21135.33
A17: $ indicates up to February 28,2019
A18: Source: MSEI

Sheet 20
A1: Table 20: City-wise Distribution of Turnover on Cash Segments of BSE and NSE
A2: (Percentage share in Turnover)
A3: S.No | B3: City | C3: BSE | E3: NSE | G3: MSEI
C4: 2017-18 | D4: Feb-19 | E4: 2017-18 | F4: Feb-19 | G4: 2017-18 | H4: Feb-19
A5: 1 | B5: Ahmedabad | C5: 2.9307028 | D5: 2.2956619 | E5: 3.06 | F5: 1.95 | G5: 0 | H5: 0
A6: 2 | B6: Bengaluru | C6: 0.33716712 | D6: 0.84120027 | E6: 4.42 | F6: 3.84 | G6: 0 | H6: 0
A7: 3 | B7: Vadodra | C7: 0.88230549 | D7: 0.95442193 | E7: 0.38 | F7: 0.21 | G7: 0 | H7: 0
A8: 4 | B8: Bhubneshwar | C8: 0.018744452 | D8: 0.019565045 | E8: 0 | F8: 0 | G8: 0 | H8: 0
A9: 5 | B9: Chennai | C9: 1.0669646 | D9: 1.1867363 | E9: 0.9 | F9: 0.73 | G9: 0 | H9: 0
A10: 6 | B10: Ernakulum | C10: 0.11806655 | D10: 0.1041521 | E10: 0.86 | F10: 0.78 | G10: 0 | H10: 0
A11: 7 | B11: Coimbatore | C11: 0.052256386 | D11: 0.048235268 | E11: 0.07 | F11: 0.04 | G11: 0 | H11: 0
A12: 8 | B12: New Delhi | C12: 3.0446179 | D12: 1.4159115 | E12: 6.79 | F12: 7.18 | G12: 4.28 | H12: 39.39
A13: 9 | B13: Guwahati | C13: 0.063264665 | D13: 0.037615883 | E13: 0 | F13: 0 | G13: 0 | H13: 0
A14: 10 | B14: Hyderabad | C14: 0.34063164 | D14: 0.8608159 | E14: 3.51 | F14: 3.17 | G14: 0.07 | H14: 0
A15: 11 | B15: Indore | C15: 0.39403013 | D15: 0.23431157 | E15: 0.53 | F15: 0.36 | G15: 0.24 | H15: 0
A16: 12 | B16: Jaipur | C16: 0.64179047 | D16: 0.52402184 | E16: 0.48 | F16: 0.27 | G16: 0.35 | H16: 0
... A25: 21 | B25: Others | C25: 25.589131 | D25: 34.911506 | E25: 10.26 | F25: 11.33 | G25: 53.24 | H25: 14.97
B26: Total | C26: 100 | D26: 100 | E26: 99.98 | F26: 100 | G26: 100.01 | H26: 100.01
A28: 1. The city-wise distribution of turnover is based on the cities uploaded in the UCC database of the Exchange for clientele trades and members registered office city for proprietary trades.
A29: Source: BSE, NSE and MSEI.

Sheet 21
A1: Table 21: Category-wise Share of Turnover in Cash Segment of BSE
A2: Year / Month | B2: Percentage Share in Turnover
B3: Proprietary | C3: FPIs | D3: Mutual Funds | E3: Banks | F3: Others
A4: 2017-18 | B4: 16.664204 | C4: 15.729893 | D4: 8.2295987 | E4: 0.14340144 | F4: 59.232903
A5: 2018-19$ | B5: 22.860909 | C5: 12.405455 | D5: 8.1818182 | E5: 0.052727273 | F5: 56.498182
A6: Apr-18 | B6: 19.98 | C6: 15.4 | D6: 8.03 | E6: 0.05 | F6: 56.54
A7: May-18 | B7: 21.77 | C7: 15.09 | D7: 9.47 | E7: 0.05 | F7: 53.62
A8: Jun-18 | B8: 18.97 | C8: 18.77 | D8: 8.2 | E8: 0.12 | F8: 53.94
A9: Jul-18 | B9: 20.54 | C9: 15.82 | D9: 7.9 | E9: 0.04 | F9: 55.7
A10: Aug-18 | B10: 22.8 | C10: 10.49 | D10: 7.1 | E10: 0.06 | F10: 59.55
A11: Sep-18 | B11: 24.6 | C11: 12.03 | D11: 7.67 | E11: 0.04 | F11: 55.67
A12: Oct-18 | B12: 26.14 | C12: 9.53 | D12: 8.43 | E12: 0.05 | F12: 55.85
A13: Nov-18 | B13: 22.08 | C13: 13.98 | D13: 9.73 | E13: 0.03 | F13: 54.18
A14: Dec-18 | B14: 26.71 | C14: 8.96 | D14: 5.83 | E14: 0.04 | F14: 58.46
A15: Jan-19 | B15: 23.06 | C15: 8.89 | D15: 11.98 | E15: 0.05 | F15: 56.02
A16: Feb-19 | B16: 24.78 | C16: 7.89 | D16: 5.66 | E16: 0.05 | F16: 61.62
A17: $ indicates as on February 28,2019
A18: Source: BSE.

Sheet 22
A1: Table 22: Category-wise Share of Turnover in Cash Segment of NSE
A2: Year /Month | B2: Percentage Share in Turnover
B3: Proprietary | C3: FPIs | D3: Mutual Funds | E3: Banks | F3: Others
A4: 2017-18 | B4: 17.99 | C4: 16.09 | D4: 7.29 | E4: 0.49 | F4: 58.14
A5: 2018-19$ | B5: 21.59 | C5: 15 | D5: 7.49 | E5: 0.23 | F5: 55.69
A6: Apr-18 | B6: 19.26 | C6: 14.05 | D6: 7.29 | E6: 0.37 | F6: 59.02
A7: May-18 | B7: 20.1 | C7: 16.42 | D7: 7.54 | E7: 0.3 | F7: 55.64
A8: Jun-18 | B8: 20.02 | C8: 17.25 | D8: 8.03 | E8: 0.25 | F8: 54.45
A9: Jul-18 | B9: 22.16 | C9: 13.91 | D9: 7.87 | E9: 0.27 | F9: 55.79
A10: Aug-18 | B10: 21.82 | C10: 13.3 | D10: 7.25 | E10: 0.28 | F10: 57.35
A11: Sep-18 | B11: 22.72 | C11: 16.15 | D11: 7.44 | E11: 0.24 | F11: 53.45
A12: Oct-18 | B12: 22.71 | C12: 15.83 | D12: 8.12 | E12: 0.12 | F12: 53.22
A13: Nov-18 | B13: 21.26 | C13: 15.34 | D13: 7.38 | E13: 0.17 | F13: 55.85
A14: Dec-18 | B14: 22.84 | C14: 13.06 | D14: 7.32 | E14: 0.18 | F14: 56.6
A15: Jan-19 | B15: 22.03 | C15: 14.31 | D15: 6.84 | E15: 0.17 | F15: 56.65
A16: Feb-19 | B16: 22.61 | C16: 15.43 | D16: 7.32 | E16: 0.18 | F16: 54.46
A17: Source: NSE.
A18: $ indicates up to February 28,2019

Sheet 23
A1: Table 23: Category-wise Share of Turnover in Cash Segment of MSEI
A2: Year / Month | B2: Percentage Share in Turnover
B3: Proprietary | C3: FPIs | D3: Mutual Funds | E3: Banks | F3: Others
A4: 2017-18 | B4: 0 | C4: 0 | D4: 0 | E4: 0 | F4: 100
A5: 2018-19$ | B5: 0 | C5: 0 | D5: 0 | E5: 0 | F5: 100
A6: Apr-18 | B6: 0 | C6: 0 | D6: 0 | E6: 0 | F6: 100
A7: May-18 | B7: 0 | C7: 0 | D7: 0 | E7: 0 | F7: 100
A8: Jun-18 | B8: 0 | C8: 0 | D8: 0 | E8: 0 | F8: 100
A9: Jul-18 | B9: 0 | C9: 0 | D9: 0 | E9: 0 | F9: 100
A10: Aug-18 | B10: 0 | C10: 0 | D10: 0 | E10: 0 | F10: 100
A11: Sep-18 | B11: 0 | C11: 0 | D11: 0 | E11: 0 | F11: 100
A12: Oct-18 | B12: 0 | C12: 0 | D12: 0 | E12: 0 | F12: 100
A13: Nov-18 | B13: 0 | C13: 0 | D13: 0 | E13: 0 | F13: 100
A14: Dec-18 | B14: 0 | C14: 0 | D14: 0 | E14: 0 | F14: 100
A15: Jan-19 | B15: 0 | C15: 0 | D15: 0 | E15: 0 | F15: 100
A16: Feb-19 | B16: 0 | C16: 0 | D16: 0 | E16: 0 | F16: 100
A17: $ indicates up to February 28,2019
A18: Source: MSEI.

Sheet 24
A1: Table 24: Component Stocks: S&P BSE Sensex during Feb-19
A2: Sl.No | B2: Name of Security | C2: Issued Capital (` crore) | D2: Free Float Market Capitalisation (` crore) | E2: Weightage (Percent) | F2: Beta | G2: R 2 | H2: Daily Volatility (Percent) | I2: Monthly Return (Percent) | J2: Impact Cost (Percent)
A3: 1 | B3: HDFC BANK | C3: 544.39 | D3: 446947.87 | E3: 12.28 | F3: 0.71 | G3: 0.32 | H3: 0.99 | I3: 0.05 | J3: 0.03
A4: 2 | B4: RELIANCE | C4: 6338.67 | D4: 397773.8 | E4: 10.92 | F4: 1.46 | G4: 0.45 | H4: 1.7 | I4: 0.36 | J4: 0.02
A5: 3 | B5: HDFC | C5: 344.06 | D5: 316366.79 | E5: 8.69 | F5: 1.23 | G5: 0.46 | H5: 1.42 | I5: -4.26 | J5: 0.04
A6: 4 | B6: INFOSYS LTD | C6: 2184.33 | D6: 278927.17 | E6: 7.66 | F6: 0.87 | G6: 0.02 | H6: 4.5 | I6: -2.09 | J6: 0.03
A7: 5 | B7: ITC LTD. | C7: 1225.08 | D7: 235368.54 | E7: 6.46 | F7: 0.93 | G7: 0.33 | H7: 1.28 | I7: -0.93 | J7: 0.04
A8: 6 | B8: ICICI BANK | C8: 1288.66 | D8: 223739.68 | E8: 6.14 | F8: 1.28 | G8: 0.27 | H8: 1.94 | I8: -4.24 | J8: 0.03
A9: 7 | B9: TCS LTD. | C9: 375.24 | D9: 208478.76 | E9: 5.73 | F9: -0.03 | G9: 0 | H9: 4.73 | I9: -1.51 | J9: 0.03
A10: 8 | B10: LARSEN & TOU | C10: 280.52 | D10: 157731.59 | E10: 4.33 | F10: 1 | G10: 0.34 | H10: 1.34 | I10: -1.44 | J10: 0.04
A11: 9 | B11: KOTAK MAH.BK | C11: 954.02 | D11: 143094.9 | E11: 3.93 | F11: 0.99 | G11: 0.25 | H11: 1.57 | I11: -3.26 | J11: 0.04
A12: 10 | B12: AXIS BANK | C12: 514.18 | D12: 125489.49 | E12: 3.45 | F12: 1.21 | G12: 0.26 | H12: 1.85 | I12: -1.88 | J12: 0.03
A13: 11 | B13: HIND UNI LT | C13: 216.46 | D13: 123665.73 | E13: 3.4 | F13: 0.77 | G13: 0.21 | H13: 1.33 | I13: -1.75 | J13: 0.04
A14: 12 | B14: STATE BANK | C14: 892.46 | D14: 101111.12 | E14: 2.78 | F14: 1.36 | G14: 0.32 | H14: 1.89 | I14: -8.04 | J14: 0.03
... A33: 31 | B33: TATAMTRTDVR | C33: 101.7 | D33: 4451.94 | E33: 0.12 | F33: 1.4 | G33: 0.22 | H33: 2.37 | I33: -6.61 | J33: 0.15
A34: 1. Beta & R2 are calculated for the trailing 12 months. Beta measures the degree to which any portfolio of stocks is affected as compared to the effect on the market as a whole.
A35: 2. The coefficient of determination (R2) measures the strength of relationship between two variables the return on a security versus that of the market.
A36: 3. Volatility is the standard deviation of the daily returns for the trailing 12 months.
A37: 4. Impact cost is calculated as the difference between actual buy price and ideal buy price, divided by ideal buy price, multiplied by 100. Hence ideal price is calculated as (best buy + best sell)/2.
A38: 5. The above is calculated for a month for the portfolio size of ` 5 lakh. It is calculated for the current month.
A39: Source: BSE.

Sheet 25
A1: Table 25: Component Stocks: Nifty 50 Index during Feb-19
A2: Sl. No | B2: Name of Security | C2: Issued Capital (`Crore) | D2: Free Float Market Capitalisation (` crore) | E2: Weightage (Percent) | F2: Beta | G2: R 2 | H2: Daily Volatility (Percent) | I2: Monthly Return (Percent) | J2: Impact Cost (Percent)
A3: 1 | B3: HDFC Bank Ltd. | C3: 543.7 | D3: 446176.6 | E3: 10.33 | F3: 0.68 | G3: 0.29 | H3: 0.79 | I3: -0.12 | J3: 0.02
A4: 2 | B4: Reliance Industries Ltd. | C4: 6338.56 | D4: 421366.6 | E4: 9.76 | F4: 1.41 | G4: 0.43 | H4: 1.41 | I4: 0.32 | J4: 0.02
A5: 3 | B5: Housing Development Finance Corporation Ltd. | C5: 343.31 | D5: 303408.82 | E5: 7.03 | F5: 1.21 | G5: 0.44 | H5: 1.15 | I5: -4.22 | J5: 0.02
A6: 4 | B6: Infosys Ltd. | C6: 2184.3 | D6: 279084.41 | E6: 6.46 | F6: 0.65 | G6: 0.12 | H6: 1.26 | I6: -2.03 | J6: 0.02
A7: 5 | B7: I T C Ltd. | C7: 1224.51 | D7: 236617.41 | E7: 5.48 | F7: 0.91 | G7: 0.31 | H7: 0.89 | I7: -0.93 | J7: 0.03
A8: 6 | B8: ICICI Bank Ltd. | C8: 1288.02 | D8: 225500.21 | E8: 5.22 | F8: 1.26 | G8: 0.27 | H8: 1.3 | I8: -3.92 | J8: 0.03
A9: 7 | B9: Tata Consultancy Services Ltd. | C9: 375.24 | D9: 208394.69 | E9: 4.83 | F9: 0.45 | G9: 0.05 | H9: 1.71 | I9: -1.52 | J9: 0.02
A10: 8 | B10: Kotak Mahindra Bank Ltd. | C10: 953.59 | D10: 161952.49 | E10: 3.75 | F10: 0.96 | G10: 0.24 | H10: 1.08 | I10: -3.4 | J10: 0.02
A11: 9 | B11: Larsen & Toubro Ltd. | C11: 280.44 | D11: 159544.06 | E11: 3.69 | F11: 1.01 | G11: 0.35 | H11: 1.2 | I11: -1.62 | J11: 0.03
A12: 10 | B12: Axis Bank Ltd. | C12: 513.98 | D12: 125818.44 | E12: 2.91 | F12: 1.21 | G12: 0.26 | H12: 0.9 | I12: -1.82 | J12: 0.02
A13: 11 | B13: Hindustan Unilever Ltd. | C13: 216.46 | D13: 123769.11 | E13: 2.87 | F13: 0.77 | G13: 0.21 | H13: 0.93 | I13: -1.74 | J13: 0.02
A14: 12 | B14: State Bank of India | C14: 892.46 | D14: 100848.73 | E14: 2.34 | F14: 1.37 | G14: 0.33 | H14: 1.33 | I14: -8.38 | J14: 0.02
... A52: 50 | B52: Hindustan Petroleum Corporation Ltd. | C52: 1523.82 | D52: 16676.94 | E52: 0.39 | F52: 1.43 | G52: 0.13 | H52: 2.1 | I52: -4.35 | J52: 0.03
A53: 1. Beta & R2 are calculated for the the trailing 12 months. Beta measures the degree to which any portfolio of stocks is affected as compared to the effect on the market as a whole.
A54: 2. The coefficient of determination (R2) measures the strength of relationship between two variables the return on a security versus that of the market.
A55: 3. Volatility is the standard deviation of the daily returns for the the trailing 12 months.
A56: 4. Impact cost is calculated as the difference between actual buy price and ideal buy price, divided by ideal buy price, multiplied by 100. Hence ideal price is calculated as (best buy + best sell)/2.
A57: 5. Impact Cost for Nifty 50 is for a portfolio of Rs. 50 Lakhs and is weightage average impact cost.
A58: Source: NSE.

Sheet 26
A1: Table 26: Component Stocks: SX40 Index
A2: S.No. | B2: Name of Security | C2: Issued Capital (₹ crore) | D2: Free Float Market Capitalisation (₹ crore) | E2: Weightage (Percent) | F2: Beta | G2: R2 | H2: Daily Volatility (Percent) | I2: Monthly Return (Percent) | J2: Impact Cost (Percent) *
A3: 1 | B3: HDFCBANK | C3: 544.38955 | D3: 444011.59 | E3: 11.08 | F3: 0.67 | G3: 0.27 | H3: 0.88 | I3: -0.12 | J3: Na
A4: 2 | B4: RELIANCE | C4: 6338.666 | D4: 398928.7 | E4: 9.96 | F4: 1.45 | G4: 0.44 | H4: 1.67 | I4: 0.32 | J4: Na
A5: 3 | B5: HDFC | C5: 344.04356 | D5: 304728.99 | E5: 7.61 | F5: 1.2 | G5: 0.41 | H5: 1.3 | I5: -4.41 | J5: Na
A6: 4 | B6: INFY | C6: 2184.3262 | D6: 278134.91 | E6: 6.94 | F6: 0.76 | G6: 0.15 | H6: 1.37 | I6: -2.08 | J6: Na
A7: 5 | B7: ITC | C7: 1224.6386 | D7: 238033.45 | E7: 5.94 | F7: 0.95 | G7: 0.32 | H7: 1.2 | I7: -0.94 | J7: Na
A8: 6 | B8: ICICIBANK | C8: 1288.528 | D8: 225519.99 | E8: 5.63 | F8: 1.22 | G8: 0.24 | H8: 1.65 | I8: -4.08 | J8: Na
A9: 7 | B9: TCS | C9: 382.85752 | D9: 223144.71 | E9: 5.57 | F9: 0.56 | G9: 0.08 | H9: 1.34 | I9: -1.55 | J9: Na
A10: 8 | B10: LT | C10: 280.4705 | D10: 159009.55 | E10: 3.97 | F10: 1.03 | G10: 0.35 | H10: 1.24 | I10: -1.65 | J10: Na
A11: 9 | B11: KOTAKBANK | C11: 954.017 | D11: 150906.39 | E11: 3.77 | F11: 0.96 | G11: 0.23 | H11: 1.36 | I11: -3.52 | J11: Na
A12: 10 | B12: AXISBANK | C12: 514.08437 | D12: 140069.17 | E12: 3.5 | F12: 1.19 | G12: 0.24 | H12: 1.62 | I12: -1.85 | J12: Na
A13: 11 | B13: HINDUNILVR | C13: 216.46489 | D13: 123059.06 | E13: 3.07 | F13: 0.79 | G13: 0.21 | H13: 0.99 | I13: -1.77 | J13: Na
A14: 12 | B14: SBIN | C14: 892.46115 | D14: 101453.64 | E14: 2.53 | F14: 1.32 | G14: 0.29 | H14: 1.45 | I14: -9.14 | J14: Na
... A42: 40 | B42: ADANIPORTS | C42: 414.19035 | D42: 25439.827 | E42: 0.63 | F42: 1.4 | G42: 0.24 | H42: 3.2 | I42: -3.93 | J42: Na
A44: 1. Market Cap, Beta & R2 as on the last day of the month
A45: 2. Beta & R2 are calculated for the trailing 12 months
A46: 3. Volatility for the current month
A47: 4. *Since there is no trading in the SX40 constituents, the Impact Cost for the given stocks is NIL.
A48: Source: MSEI.

Sheet 27
A1: Table 27: Advances/Declines in Cash Segment of BSE, NSE and MSEI
A2: Year/ Month | B2: BSE | E2: NSE | H2: MSEI
B3: Advances | C3: Declines | D3: Advance/Decline Ratio | E3: Advances | F3: Declines | G3: Advance/Decline Ratio | H3: Advances | I3: Declines | J3: Advance/Decline Ratio
A4: 2017-18 | B4: 703 | C4: 2691 | D4: 0.26124117 | E4: 1202 | F4: 512 | G4: 2.348 | H4: 1 | I4: 8 | J4: 0.13
A5: 2018-19$ | B5: 1173 | C5: 2706 | D5: 0.43348115 | E5: 595 | F5: 1264 | G5: 0.47 | H5: 2 | I5: 4 | J5: 0.5
A6: Apr-18 | B6: 1982 | C6: 1449 | D6: 1.3678399 | E6: 1180 | F6: 659 | G6: 1.79 | H6: 2 | I6: 3 | J6: 0.67
A7: May-18 | B7: 992 | C7: 2448 | D7: 0.40522876 | E7: 486 | F7: 1378 | G7: 0.35 | H7: 0 | I7: 4 | J7: 0
A8: Jun-18 | B8: 779 | C8: 2651 | D8: 0.29 | E8: 361 | F8: 1517 | G8: 0.24 | H8: 0 | I8: 2 | J8: 0
A9: Jul-18 | B9: 842 | C9: 2579 | D9: 0.32648313 | E9: 415 | F9: 1478 | G9: 0.28 | H9: 1 | I9: 2 | J9: 0.5
A10: Aug-18 | B10: 2080 | C10: 1415 | D10: 1.4699647 | E10: 1254 | F10: 637 | G10: 1.97 | H10: 0 | I10: 2 | J10: 0
A11: Sep-18 | B11: 1174 | C11: 2331 | D11: 0.5036465 | E11: 532 | F11: 1361 | G11: 0.39 | H11: 1 | I11: 1 | J11: 1
A12: Oct-18 | B12: 481 | C12: 2973 | D12: 0.16178944 | E12: 159 | F12: 1741 | G12: 0.09 | H12: 1 | I12: 0 | J12: 0
A13: Nov-18 | B13: 1984 | C13: 1457 | D13: 1.3617021 | E13: 1210 | F13: 697 | G13: 1.74 | H13: 1 | I13: 1 | J13: 1
A14: Dec-18 | B14: 1314 | C14: 2095 | D14: 0.62720764 | E14: 741 | F14: 1169 | G14: 0.63 | H14: 1 | I14: 0 | J14: 0
A15: Jan-19 | B15: 1672 | C15: 1219 | D15: 1.3716161 | E15: 789 | F15: 1120 | G15: 0.7 | H15: 1 | I15: 2 | J15: 0.5
A16: Feb-19 | B16: 558 | C16: 2335 | D16: 0.23897216 | E16: 325 | F16: 1588 | G16: 0.2 | H16: 1 | I16: 3 | J16: 0.33
A17: $ indicates as on February 28, 2018
A18: Advance/Decline is calculated based on the average price methodology.
A19: Source: BSE, NSE and MSEI.

Sheet 28
A1: Table 28: Trading Frequency in Cash Segment of BSE, NSE and MSEI
A2: Month | B2: BSE | E2: NSE | H2: MSEI
B3: No. of Companies Listed | C3: No. of Companies Traded | D3: Percent of Traded to Listed | E3: No. of Companies Listed | F3: No. of Companies Traded | G3: Percent of Traded to Listed | H3: No. of Companies Listed | I3: No. of Companies Traded | J3: Percent of Traded to Listed
A4: 2017-18 | B4: 5619 | C4: 2794 | D4: 49.72415 | E4: 1931 | F4: 1850 | G4: 95.805282 | H4: 270 | I4: 12 | J4: 4.4444444
A5: 2018-19$ | B5: 5251 | C5: 2614 | D5: 49.780994 | E5: 1929 | F5: 1917 | G5: 99.377916 | H5: 287 | I5: 8 | J5: 2.7874564
A6: Apr-18 | B6: 5638 | C6: 2768 | D6: 49.095424 | E6: 1952 | F6: 1817 | G6: 93.084016 | H6: 273 | I6: 5 | J6: 1.8315018
A7: May-18 | B7: 5450 | C7: 2755 | D7: 50.550459 | E7: 1941 | F7: 1820 | G7: 93.7661 | H7: 277 | I7: 4 | J7: 1.4440433
A8: Jun-18 | B8: 5458 | C8: 2698 | D8: 49.432026 | E8: 1951 | F8: 1833 | G8: 93.95182 | H8: 277 | I8: 3 | J8: 1.0830325
A9: Jul-18 | B9: 5240 | C9: 2763 | D9: 52.729008 | E9: 1938 | F9: 1840 | G9: 94.94324 | H9: 277 | I9: 3 | J9: 1.0830325
A10: Aug-18 | B10: 5233 | C10: 2823 | D10: 53.946111 | E10: 1916 | F10: 1841 | G10: 96.085595 | H10: 278 | I10: 2 | J10: 0.71942446
A11: Sep-18 | B11: 5232 | C11: 2763 | D11: 52.809633 | E11: 1912 | F11: 1847 | G11: 96.600418 | H11: 282 | I11: 2 | J11: 0.70921986
A12: Oct-18 | B12: 5217 | C12: 2660 | D12: 50.987157 | E12: 1921 | F12: 1854 | G12: 96.512233 | H12: 281 | I12: 2 | J12: 0.71174377
A13: Nov-18 | B13: 5216 | C13: 2719 | D13: 52.128067 | E13: 1922 | F13: 1850 | G13: 96.253902 | H13: 282 | I13: 3 | J13: 1.0638298
A14: Dec-18 | B14: 5232 | C14: 2756 | D14: 52.675841 | E14: 1923 | F14: 1856 | G14: 96.515861 | H14: 282 | I14: 2 | J14: 0.70921986
A15: Jan-19 | B15: 5244 | C15: 2663 | D15: 50.781846 | E15: 1926 | F15: 1854 | G15: 96.261682 | H15: 284 | I15: 6 | J15: 2.1126761
A16: Feb-19 | B16: 5251 | C16: 2614 | D16: 49.780994 | E16: 1929 | F16: 1859 | G16: 96.371177 | H16: 287 | I16: 4 | J16: 1.3937282
A17: $ indicates as on February 28,2019
A18: Source: BSE, NSE and MSEI.

Sheet 29
A1: Table 29: Daily Volatility of Major Indices (percent)
A2: Year / Month | B2: BSE Sensex | C2: BSE 100 | D2: BSE 500 | E2: Nifty 50 | F2: Nifty Next 50 | G2: Nifty 500 | H2: SX40
A3: 2017-18 | B3: 0.62895618 | C3: 0.6405625 | D3: 0.66757021 | E3: 0.62811669 | F3: 0.85157353 | G3: 0.67059787 | H3: 0.61
A4: 2018-19$ | B4: 0.77126826 | C4: 0.79957472 | D4: 0.80741109 | E4: 0.78857445 | F4: 1.0249113 | G4: 0.81026933 | H4: 0.77
A5: Apr-18 | B5: 0.52530155 | C5: 0.55400269 | D5: 0.57040783 | E5: 0.55273867 | F5: 0.71717695 | G5: 0.56593656 | H5: 0.51
A6: May-18 | B6: 0.6229283 | C6: 0.63978356 | D6: 0.64843869 | E6: 0.62695381 | F6: 0.90619295 | G6: 0.62984197 | H6: 0.61
A7: Jun-18 | B7: 0.5718023 | C7: 0.63142488 | D7: 0.70787998 | E7: 0.591008 | F7: 0.922027 | G7: 0.704838 | H7: 0.61
A8: Jul-18 | B8: 0.43503106 | C8: 0.51490879 | D8: 0.59273496 | E8: 0.450786 | F8: 1.033442 | G8: 0.588023 | H8: 0.49
A9: Aug-18 | B9: 0.57 | C9: 0.52 | D9: 0.5 | E9: 0.53057206 | F9: 0.60905243 | G9: 0.49882523 | H9: 0.54
A10: Sep-18 | B10: 0.80192052 | C10: 0.9021091 | D10: 0.91517672 | E10: 0.8111791 | F10: 1.3712431 | G10: 0.88858409 | H10: 0.74
A11: Oct-18 | B11: 1.3835236 | C11: 1.4828015 | D11: 1.4839574 | E11: 1.4352761 | F11: 1.5371641 | G11: 1.4605865 | H11: 1.42
A12: Nov-18 | B12: 0.73225799 | C12: 0.68136122 | D12: 0.62558668 | E12: 0.69818841 | F12: 0.67054525 | G12: 0.61284143 | H12: 0.73
A13: Dec-18 | B13: 0.98 | C13: 0.99 | D13: 0.98 | E13: 0.94618977 | F13: 1.1118054 | G13: 0.96192312 | H13: 0.96
A14: Jan-19 | B14: 0.72240236 | C14: 0.68511412 | D14: 0.64364121 | E14: 0.70031621 | F14: 0.61039543 | G14: 0.62365837 | H14: 0.72
A15: Feb-19 | B15: 0.62378925 | C15: 0.63968296 | D15: 0.61909495 | E15: 0.60709751 | F15: 0.93888965 | G15: 0.59989952 | H15: 0.62
A16: Volatility is calculated as the standard deviation of the natural log of daily returns in indices for the respective period.
A17: $ indicates as on February 28,2019
A18: Source: BSE, MSEI and NSE.

Sheet 30
A1: Table 30: Percentage Share of Top ‘N’ Securities/Members in Turnover of Cash Segment (percent)
A2: Year/ Month | B2: BSE | G2: NSE | L2: MSEI
A3: Top | B3: 5 | C3: 10 | D3: 25 | E3: 50 | F3: 100 | G3: 5 | H3: 10 | I3: 25 | J3: 50 | K3: 100 | L3: 5 | M3: 10 | N3: 25 | O3: 50 | P3: 100
A4: Securities
A5: 2017-18 | B5: 10.6509 | C5: 15.7315 | D5: 26.2105 | E5: 36.85 | F5: 51.7392 | G5: 9.08 | H5: 15.48 | I5: 29.1 | J5: 43.05 | K5: 61.3 | L5: 95.083077 | M5: 99.385843 | N5: 100 | O5: 100 | P5: 100
A6: 2018-19$ | B6: 9.7076 | C6: 16.3386 | D6: 30.7284 | E6: 43.9447 | F6: 59.815 | G6: 11.7 | H6: 20.37 | I6: 36.79 | J6: 52.64 | K6: 70.91 | L6: 99.98 | M6: 100 | N6: 100 | O6: 100 | P6: 100
A7: Apr-18 | B7: 12.2928 | C7: 17.7398 | D7: 29.5265 | E7: 41.9442 | F7: 57.4189 | G7: 11.12 | H7: 18.71 | I7: 33.69 | J7: 48.43 | K7: 66 | L7: 100 | M7: 100 | N7: 100 | O7: 100 | P7: 100
A8: May-18 | B8: 16.0047 | C8: 22.1846 | D8: 34.2137 | E8: 47.3607 | F8: 63.2401 | G8: 10.73 | H8: 17.68 | I8: 33.46 | J8: 50.7 | K8: 69.34 | L8: 100 | M8: 100 | N8: 100 | O8: 100 | P8: 100
A9: Jun-18 | B9: 14.418 | C9: 21.3154 | D9: 34.8804 | E9: 48.6846 | F9: 64.0908 | G9: 11.87 | H9: 19.81 | I9: 35.57 | J9: 51.85 | K9: 69.66 | L9: 100 | M9: 100 | N9: 100 | O9: 100 | P9: 100
A10: Jul-18 | B10: 11.193544 | C10: 17.8572 | D10: 31.3214 | E10: 45.3931 | F10: 62.7058 | G10: 11.77 | H10: 19.76 | I10: 36.05 | J10: 53.32 | K10: 71.63 | L10: 100 | M10: 100 | N10: 100 | O10: 100 | P10: 100
A11: Aug-18 | B11: 9.7655 | C11: 16.3696 | D11: 30.0143 | E11: 43.5059 | F11: 58.9964 | G11: 11.8 | H11: 19.29 | I11: 34.7 | J11: 50.06 | K11: 68.72 | L11: 100 | M11: 100 | N11: 100 | O11: 100 | P11: 100
A12: Sep-18 | B12: 12.5556 | C12: 20.3031 | D12: 33.5522 | E12: 48.4415 | F12: 63.6731 | G12: 14.53 | H12: 23.48 | I12: 40.86 | J12: 56.55 | K12: 73.8 | L12: 100 | M12: 100 | N12: 100 | O12: 100 | P12: 100
A13: Oct-18 | B13: 13.9226 | C13: 23.0265 | D13: 38.7791 | E13: 53.6237 | F13: 69.4366 | G13: 15.69 | H13: 26.3 | I13: 44.3 | J13: 59.47 | K13: 77.27 | L13: 100 | M13: 100 | N13: 100 | O13: 100 | P13: 100
A14: Nov-18 | B14: 14.1482 | C14: 22.8212 | D14: 39.0928 | E14: 52.9224 | F14: 69.3301 | G14: 14.04 | H14: 23.66 | I14: 41.31 | J14: 57.7 | K14: 76.08 | L14: 100 | M14: 100 | N14: 100 | O14: 100 | P14: 100
A15: Dec-18 | B15: 13.0364 | C15: 20.7815 | D15: 36.414 | E15: 50.5001 | F15: 66.5382 | G15: 13.88 | H15: 23.03 | I15: 39.67 | J15: 56.21 | K15: 75.47 | L15: 100 | M15: 100 | N15: 100 | O15: 100 | P15: 100
A16: Jan-19 | B16: 13.8971 | C16: 22.7814 | D16: 40.7137 | E16: 54.135 | F16: 68.7304 | G16: 15.58 | H16: 25.65 | I16: 44.31 | J16: 59.28 | K16: 76.83 | L16: 100 | M16: 100 | N16: 100 | O16: 100 | P16: 100
A17: Feb-19 | B17: 14.7561 | C17: 22.8641 | D17: 38.6842 | E17: 53.5403 | F17: 68.639 | G17: 14.56 | H17: 23.12 | I17: 42.42 | J17: 58.73 | K17: 76.95 | L17: 100 | M17: 100 | N17: 100 | O17: 100 | P17: 100
A18: Members
A19: 2017-18 | B19: 21.16 | C19: 33.31 | D19: 55.24 | E19: 70.51 | F19: 82.76 | G19: 19.75 | H19: 30.91 | I19: 51.52 | J19: 68.45 | K19: 82.01 | L19: 98.021428 | M19: 99.910061 | N19: 100 | O19: 100 | P19: 100
A20: 2018-19$ | B20: 24.61 | C20: 39.21 | D20: 60.42 | E20: 73.02 | F20: 84.3 | G20: 22.42 | H20: 34.31 | I20: 54.59 | J20: 72.29 | K20: 85.66 | L20: 99.22 | M20: 100 | N20: 100 | O20: 100 | P20: 100
A21: Apr-18 | B21: 21.3 | C21: 35.75 | D21: 56.43 | E21: 69.87 | F21: 82.75 | G21: 21.68 | H21: 34 | I21: 53.56 | J21: 69.45 | K21: 83.74 | L21: 100 | M21: 100 | N21: 100 | O21: 100 | P21: 100
A22: May-18 | B22: 22.52 | C22: 36.07 | D22: 58.22 | E22: 72.16 | F22: 83.89 | G22: 20.99 | H22: 32.5 | I22: 53.74 | J22: 70.68 | K22: 84.75 | L22: 100 | M22: 100 | N22: 100 | O22: 100 | P22: 100
A23: Jun-18 | B23: 24.45 | C23: 37.88 | D23: 60.4 | E23: 73.42 | F23: 84.53 | G23: 20.98 | H23: 31.59 | I23: 53.71 | J23: 71.01 | K23: 84.83 | L23: 100 | M23: 100 | N23: 100 | O23: 100 | P23: 100
A24: Jul-18 | B24: 24.59 | C24: 38.53 | D24: 62.3 | E24: 74.86 | F24: 85.14 | G24: 22.48 | H24: 33.98 | I24: 54.11 | J24: 71.53 | K24: 85.43 | L24: 100 | M24: 100 | N24: 100 | O24: 100 | P24: 100
A25: Aug-18 | B25: 24.99 | C25: 39.36 | D25: 60.58 | E25: 72.87 | F25: 83.58 | G25: 22.39 | H25: 34.47 | I25: 54.08 | J25: 71.55 | K25: 84.95 | L25: 100 | M25: 100 | N25: 100 | O25: 100 | P25: 100
A26: Sep-18 | B26: 35.19 | C26: 48.65 | D26: 68.51 | E26: 79.22 | F26: 87.85 | G26: 22.18 | H26: 34.76 | I26: 56.02 | J26: 73.83 | K26: 86.6 | L26: 100 | M26: 100 | N26: 100 | O26: 100 | P26: 100
A27: Oct-18 | B27: 30.33 | C27: 45.74 | D27: 67.58 | E27: 78.18 | F27: 86.79 | G27: 22.75 | H27: 35.36 | I27: 56.27 | J27: 74.04 | K27: 87.22 | L27: 100 | M27: 100 | N27: 100 | O27: 100 | P27: 100
A28: Nov-18 | B28: 29.75 | C28: 43.72 | D28: 64.68 | E28: 76.63 | F28: 86.58 | G28: 23.19 | H28: 35.4 | I28: 55.99 | J28: 73.78 | K28: 86.45 | L28: 100 | M28: 100 | N28: 100 | O28: 100 | P28: 100
A29: Dec-18 | B29: 30.99 | C29: 45.28 | D29: 64.3 | E29: 75.92 | F29: 85.57 | G29: 25.39 | H29: 38.2 | I29: 56.99 | J29: 74.2 | K29: 86.7 | L29: 100 | M29: 100 | N29: 100 | O29: 100 | P29: 100
A30: Jan-19 | B30: 28.14 | C30: 43.11 | D30: 63.62 | E30: 75.51 | F30: 85.09 | G30: 24.78 | H30: 36.44 | I30: 56.42 | J30: 74.01 | K30: 86.5 | L30: 100 | M30: 100 | N30: 100 | O30: 100 | P30: 100
A31: Feb-19 | B31: 30.89 | C31: 48.68 | D31: 67.83 | E31: 77.84 | F31: 86.26 | G31: 24.11 | H31: 36.15 | I31: 56.76 | J31: 74.96 | K31: 87.23 | L31: 100 | M31: 100 | N31: 100 | O31: 100 | P31: 100
A32: $ indicates as on February 28,2019
A33: 1. Data for Top N scrips has been compiled for all markets except Auction market & Retail Debt Market and includes series EQ, BE,BT, BL and IL.
A34: Source: BSE, NSE and MSEI.

Sheet 31
A1: Table 31: Settlement Statistics for Cash Segment of BSE
A2: Year / Month | B2: No. of Trades(Lakh) | C2: Traded Quantity (Lakh) | D2: Delivered Quantity (Lakh) | E2: Percent of Delivered Quantity to Traded Quantity | F2: Turnover (` crore) | G2: Delivered Value (` crore) | H2: Percent of Delivered Value to Total Turnover | I2: Delivered Quantity in Demat Mode (Lakh) | J2: Percent of Demat Delivered Quantity to Total Delivered Quantity | K2: Delivered Value in Demat Mode (` crore) | L2: Percent of Demat Delivered Value to Total Delivered Value | M2: Short Delivery (Auctioned quantity) (Lakh) | N2: Percent of Short Delivery to Delivery Quantity | O2: Funds Pay-in (` crore) | P2: Securities Pay-in (` crore) | Q2: Settlement Guarantee Fund (`crore)
A3: 2017-18 | B3: 3585.825 | C3: 771564 | D3: 308291.03 | E3: 39.786919 | F3: 1082968.2 | G3: 395999.29 | H3: 36.43034 | I3: 307998.3 | J3: 99.891064 | K3: 395846 | L3: 99.946962 | M3: 624.55445 | N3: 0.20111173 | O3: 150247.04 | P3: 308291.03 | Q3: 192.27
A4: 2018-19$ | B4: 2889.3352 | C4: 467066 | D4: 173348.31 | E4: 36.975224 | F4: 694612.69 | G4: 221180.1 | H4: 31.612917 | I4: 173050.44 | J4: 99.811815 | K4: 221179.61 | L4: 99.993636 | M4: 422.24007 | N4: 0.22819441 | O4: 92100.414 | P4: 172734.75 | Q4: 205.82
A5: Apr-18 | B5: 233.87 | C5: 47331 | D5: 20197.59 | E5: 42.673068 | F5: 71629.66 | G5: 26176.786 | H5: 36.544619 | I5: 20197.59 | J5: 99.99 | K5: 26176.774 | L5: 99.99 | M5: 37.66553 | N5: 0.18648527 | O5: 11283.395 | P5: 20197.59 | Q5: 193.4
A6: May-18 | B6: 258.01628 | C6: 51333 | D6: 20552.438 | E6: 40.037477 | F6: 75360.5 | G6: 24720.487 | H6: 32.802977 | I6: 20552.438 | J6: 99.99 | K6: 24720.452 | L6: 99.99 | M6: 41.71 | N6: 0.2 | O6: 10687.196 | P6: 20552.438 | Q6: 194.65
A7: Jun-18 | B7: 191.17866 | C7: 41060 | D7: 16823.908 | E7: 40.97396 | F7: 64162.59 | G7: 25439.471 | H7: 39.648448 | I7: 16823.905 | J7: 99.99 | K7: 25439.431 | L7: 99.99 | M7: 45.00381 | N7: 0.2 | O7: 11203.598 | P7: 16823.908 | Q7: 195.86
A8: Jul-18 | B8: 242.83 | C8: 41852 | D8: 16416.385 | E8: 39.224853 | F8: 65168.48 | G8: 22564.465 | H8: 34.624814 | I8: 16367.017 | J8: 99.699273 | K8: 22564.423 | L8: 99.99 | M8: 49.36804 | N8: 0.2 | O8: 7788.497 | P8: 16416.385 | Q8: 197.1
A9: Aug-18 | B9: 292 | C9: 45597 | D9: 16677 | E9: 36.6 | F9: 67896 | G9: 21673 | H9: 31.9 | I9: 16641 | J9: 99.8 | K9: 21673 | L9: 100 | M9: 36.7 | N9: 0.2 | O9: 8022.42 | P9: 16677.49 | Q9: 198
A10: Sep-18 | B10: 297.69 | C10: 38742 | D10: 12866.714 | E10: 33.21128 | F10: 62476.71 | G10: 17771.125 | H10: 28.444399 | I10: 12839.387 | J10: 99.787614 | K10: 17770.992 | L10: 99.99 | M10: 27.32715 | N10: 0.21283843 | O10: 7103.2562 | P10: 12866.714 | Q10: 199.51
A11: Oct-18 | B11: 337.3 | C11: 43930 | D11: 13624.226 | E11: 31.013489 | F11: 66384.71 | G11: 17968.005 | H11: 27.066481 | I11: 13589.709 | J11: 99.74665 | K11: 17967.852 | L11: 99.99 | M11: 34.51437 | N11: 0.25397432 | O11: 8200.093 | P11: 13624.226 | Q11: 200.75
A12: Nov-18 | B12: 255.31027 | C12: 38077 | D12: 13214.227 | E12: 34.70396 | F12: 59063.84 | G12: 19645.852 | H12: 33.262063 | I12: 13190.034 | J12: 99.816915 | K12: 19645.852 | L12: 100 | M12: 24.19332 | N12: 0.18342122 | O12: 8400.776 | P12: 13214 | Q12: 201.98
A13: Dec-18 | B13: 249.07 | C13: 38061 | D13: 14037.03 | E13: 36.88 | F13: 50482.91 | G13: 13424.54 | H13: 26.59 | I13: 14013.38 | J13: 99.83 | K13: 13424.54 | L13: 100 | M13: 23.65 | N13: 0.17 | O13: 5438.8 | P13: 14037 | Q13: 203.28
A14: Jan-19 | B14: 274.6 | C14: 38852 | D14: 14128.8 | E14: 36.365695 | F14: 61332 | G14: 17263 | H14: 28.146808 | I14: 14095.2 | J14: 99.762188 | K14: 17263 | L14: 100 | M14: 33.6 | N14: 0.23837902 | O14: 6891 | P14: 14129 | Q14: 204.53
A15: Feb-19 | B15: 257.2 | C15: 42231 | D15: 14809.498 | E15: 35.067837 | F15: 50655.69 | G15: 14533.205 | H15: 28.690173 | I15: 14740.947 | J15: 99.537112 | K15: 14533.205 | L15: 100 | M15: 68.55134 | N15: 0.46504028 | O15: 7081.3812 | P15: 14196 | Q15: 205.82
A16: $ indicates as on February 28,2019
A17: Source: BSE.

Sheet 32
A1: Table 32: Settlement Statistics for Cash Segment of NSE
A2: Year / Month | B2: No. of Trades(Lakh) | C2: Traded Quantity (Lakh) | D2: Delivered Quantity (Lakh) | E2: Percent of Delivered Quantity to Traded Quantity | F2: Turnover (` crore) | G2: Delivered Value (` crore) | H2: Percent of Delivered Value to Total Turnover | I2: Delivered Quantity in Demat Mode (Lakh) | J2: Percent of Demat Delivered Quantity to Total Delivered Quantity | K2: Delivered Value in Demat Mode (` crore) | L2: Percent of Demat Delivered Value to Total Delivered Value | M2: Short Delivery (Auctioned quantity) (Lakh) | N2: Percent of Short Delivery to Delivery Quantity | O2: Funds Pay-in (` crore) | P2: Securities Pay-in (` crore) | Q2: Settlement Guarantee Fund (`crore)
A3: 2017-18 | B3: 24800.641 | C3: 3710851.7 | D3: 952812.13 | E3: 25.676373 | F3: 7198787 | G3: 2019893.3 | H3: 28.058801 | I3: 951307.86 | J3: 100 | K3: 2018374.8 | L3: 100 | M3: 1504.2681 | N3: 0.15812632 | O3: 509415.17 | P3: 2019893.3 | Q3: 224.59
A4: 2018-19$ | B4: 26139.796 | C4: 3331612.8 | D4: 761377.64 | E4: 22.853125 | F4: 7232114.9 | G4: 1771952.5 | H4: 24.501166 | I4: 760359.23 | J4: 100 | K4: 1770739.9 | L4: 100 | M4: 1018.4019 | N4: 0.13393694 | O4: 477981.63 | P4: 1771952.5 | Q4: 268.67
A5: Apr-18 | B5: 2091.9331 | C5: 285047.89 | D5: 68755.397 | E5: 24.120647 | F5: 611743.01 | G5: 162383.76 | H5: 26.54444 | I5: 68661.863 | J5: 100 | K5: 162274.33 | L5: 100 | M5: 93.53462 | N5: 0.13603968 | O5: 39790.5 | P5: 162383.76 | Q5: 234.74
A6: May-18 | B6: 2516.6105 | C6: 337019.65 | D6: 74791.657 | E6: 22.192076 | F6: 713497.52 | G6: 181517.31 | H6: 25.440496 | I6: 74680.476 | J6: 100 | K6: 181406.2 | L6: 100 | M6: 111.18066 | N6: 0.14887514 | O6: 46574.98 | P6: 181517.31 | Q6: 244.12
A7: Jun-18 | B7: 2264.94 | C7: 284355.01 | D7: 67803.935 | E7: 23.84 | F7: 612853.34 | G7: 167170.23 | H7: 27.28 | I7: 67690.4 | J7: 100 | K7: 167072.69 | L7: 100 | M7: 113.53 | N7: 0.17 | O7: 46530.21 | P7: 167170.23 | Q7: 247.37
A8: Jul-18 | B8: 2335.9821 | C8: 301754.09 | D8: 72846.148 | E8: 24.140898 | F8: 660330.65 | G8: 168312.96 | H8: 25.489195 | I8: 72755.537 | J8: 100 | K8: 168201.78 | L8: 100 | M8: 90.6104 | N8: 0.1245409 | O8: 41899.58 | P8: 168312.96 | Q8: 250.14
A9: Aug-18 | B9: 2385.8871 | C9: 318996.96 | D9: 67313.94 | E9: 21.10175 | F9: 687997.79 | G9: 164691.19 | H9: 23.93775 | I9: 67212.05 | J9: 100 | K9: 164590.08 | L9: 100 | M9: 101.88997 | N9: 0.1515948 | O9: 38165.31 | P9: 164691.19 | Q9: 252.23
A10: Sep-18 | B10: 2337.34 | C10: 294001.06 | D10: 63774.87 | E10: 21.692056 | F10: 683237.09 | G10: 164549.18 | H10: 24.083761 | I10: 63686.22 | J10: 100 | K10: 164450.75 | L10: 100 | M10: 88.65689 | N10: 0.13901539 | O10: 44990.417 | P10: 164549.18 | Q10: 253.23
A11: Oct-18 | B11: 2915.9512 | C11: 331328.21 | D11: 73057.434 | E11: 22.049868 | F11: 757984.96 | G11: 180012.39 | H11: 23.748808 | I11: 72976.559 | J11: 100 | K11: 179895.61 | L11: 100 | M11: 80.87454 | N11: 0.11082263 | O11: 53537.09 | P11: 180012.39 | Q11: 256.22
A12: Nov-18 | B12: 2305.602 | C12: 274964.75 | D12: 61598.032 | E12: 22.402156 | F12: 598236.37 | G12: 140142.73 | H12: 23.42598 | I12: 61533.702 | J12: 100 | K12: 140081.01 | L12: 100 | M12: 64.33069 | N12: 0.10454546 | O12: 39138.84 | P12: 140142.73 | Q12: 258.73
A13: Dec-18 | B13: 2301.8103 | C13: 299885.03 | D13: 73133.803 | E13: 24.38728 | F13: 635303.83 | G13: 147710.95 | H13: 23.250443 | I13: 73048.47 | J13: 100 | K13: 147513.71 | L13: 100 | M13: 85.33255 | N13: 0.11681634 | O13: 39421.4 | P13: 147710.95 | Q13: 261.36
A14: Jan-19 | B14: 2287.8984 | C14: 267820.95 | D14: 59430.083 | E14: 22.19023 | F14: 634124.53 | G14: 140250.58 | H14: 22.117198 | I14: 59341.485 | J14: 100 | K14: 140158.96 | L14: 100 | M14: 88.59813 | N14: 0.1493022 | O14: 38529.99 | P14: 140250.58 | Q14: 263.84
A15: Feb-19 | B15: 2395.8344 | C15: 336439.21 | D15: 78872.332 | E15: 23.443264 | F15: 636805.83 | G15: 155211.17 | H15: 24.37339 | I15: 78772.469 | J15: 100 | K15: 155094.83 | L15: 100 | M15: 99.86365 | N15: 0.12677481 | O15: 49403.31 | P15: 155211.17 | Q15: 268.67
A16: $ indicates as on February 28,2019
A17: Source: NSE.

Sheet 33
A1: Table 33: Settlement Statistics for Cash Segment of MSEI
A2: Month Sorting | B2: No. of Trades(Lakh) | C2: Traded Quantity (Lakh) | D2: Delivered Quantity (Lakh) | E2: Percent of Delivered Quantity to Traded Quantity | F2: Turnover (₹ crore) | G2: Delivered Value (₹ crore) | H2: Percent of Delivered Value to Total Turnover | I2: Delivered Quantity in Demat Mode (Lakh) | J2: Percent of Demat Delivered Quantity to Total Delivered Quantity | K2: Delivered Value in Demat Mode (₹ crore) | L2: Percent of Demat Delivered Value to Total Delivered Value | M2: Funds Pay-in (₹ crore) | N2: Securities Pay-in (₹ crore) | O2: Settlement Guarantee Fund(₹ crore)
A3: 2017-18 | B3: 0.02823 | C3: 151.78948 | D3: 28.12238 | E3: 18.527226 | F3: 192.76668 | G3: 43.622502 | H3: 22.62969 | I3: 28.12238 | J3: 100 | K3: 43.622502 | L3: 100 | M3: 43.626682 | N3: 43.622502 | O3: 0.32
A4: 2018-19$ | B4: 0.01567 | C4: 11.42328 | D4: 11.42328 | E4: 100 | F4: 24.514194 | G4: 24.514194 | H4: 100 | I4: 11.42328 | J4: 100 | K4: 24.514194 | L4: 100 | M4: 24.514194 | N4: 24.514194 | O4: 0.32
A5: Apr-18 | B5: 0.00163 | C5: 0.39826 | D5: 0.39826 | E5: 100 | F5: 1.2880075 | G5: 1.2880075 | H5: 100 | I5: 0.39826 | J5: 100 | K5: 1.2880075 | L5: 100 | M5: 1.2880075 | N5: 1.2880075 | O5: 0.32
A6: May-18 | B6: 0.002 | C6: 0.9141 | D6: 0.9141 | E6: 100 | F6: 1.8949297 | G6: 1.8949297 | H6: 100 | I6: 0.9141 | J6: 100 | K6: 1.8949297 | L6: 100 | M6: 1.8949297 | N6: 1.8949297 | O6: 0.32
A7: Jun-18 | B7: 0.0002 | C7: 0.1237 | D7: 0.1237 | E7: 100 | F7: 0.3932 | G7: 0.3932 | H7: 100 | I7: 0.1237 | J7: 100 | K7: 0.3932 | L7: 100 | M7: 0.3932 | N7: 0.3932 | O7: 0.32
A8: Jul-18 | B8: 0.0003 | C8: 0.1598 | D8: 0.1598 | E8: 100 | F8: 0.4018 | G8: 0.4018 | H8: 100 | I8: 0.1598 | J8: 100 | K8: 0.4018 | L8: 100 | M8: 0.4018 | N8: 0.4018 | O8: 0.32
A9: Aug-18 | B9: 0.00086 | C9: 0.3118 | D9: 0.3118 | E9: 100 | F9: 0.9221 | G9: 0.9221 | H9: 100 | I9: 0.3118 | J9: 100 | K9: 0.9221 | L9: 100 | M9: 0.9221 | N9: 0.9221 | O9: 0.32
A10: Sep-18 | B10: 0.0009 | C10: 0.5395 | D10: 0.5395 | E10: 100 | F10: 1.1962385 | G10: 1.1962385 | H10: 100 | I10: 0.5395 | J10: 100 | K10: 1.1962385 | L10: 100 | M10: 1.1962385 | N10: 1.1962385 | O10: 0.32
A11: Oct-18 | B11: 0.00082 | C11: 0.3928 | D11: 0.3928 | E11: 100 | F11: 0.9920585 | G11: 0.9920585 | H11: 100 | I11: 0.3928 | J11: 100 | K11: 0.9920585 | L11: 100 | M11: 0.9920585 | N11: 0.9920585 | O11: 0.32
A12: Nov-18 | B12: 0.0013 | C12: 0.87926 | D12: 0.87926 | E12: 100 | F12: 1.7222751 | G12: 1.7222751 | H12: 100 | I12: 0.87926 | J12: 100 | K12: 1.7222751 | L12: 100 | M12: 1.7222751 | N12: 1.7222751 | O12: 0.32
A13: Dec-18 | B13: 0.00124 | C13: 0.446 | D13: 0.446 | E13: 100 | F13: 1.2422 | G13: 1.2422 | H13: 100 | I13: 0.446 | J13: 100 | K13: 1.2422 | L13: 100 | M13: 1.2422 | N13: 1.2422 | O13: 0.32
A14: Jan-19 | B14: 0.00377 | C14: 4.67015 | D14: 4.67015 | E14: 100 | F14: 9.2433544 | G14: 9.2433544 | H14: 100 | I14: 4.67015 | J14: 100 | K14: 9.2433544 | L14: 100 | M14: 9.2433544 | N14: 9.2433544 | O14: 0.32
A15: Feb-19 | B15: 0.00263 | C15: 2.58796 | D15: 2.58796 | E15: 100 | F15: 5.2180822 | G15: 5.2180822 | H15: 100 | I15: 2.58796 | J15: 100 | K15: 5.2180822 | L15: 100 | M15: 5.2180822 | N15: 5.2180822 | O15: 0.32
A16: $ indicates as on February 28, 2019
A17: Source: MSEI.

Sheet 34
A1: Table 34: Trends in Equity Derivatives Segment at BSE (Turnover in Notional Value)
A2: Year/ Month | B2: No. of Trading Days | C2: Index Futures | E2: Stock Futures | G2: Index Options | K2: Stock Options | O2: Total | Q2: Open Interest at the end of Month
G3: Call | I3: Put | K3: Call | M3: Put
C4: No. of Contracts | D4: Turnover (` crore) | E4: No. of Contracts | F4: Turnover (` crore) | G4: No. of Contracts | H4: Turnover (` crore) | I4: No. of Contracts | J4: Turnover (` crore) | K4: No. of Contracts | L4: Turnover (` crore) | M4: No. of Contracts | N4: Turnover (` crore) | O4: No. of Contracts | P4: Turnover (` crore) | Q4: No. of contracts | R4: Turnover (` crore)
A5: 2017-18 | B5: 246 | C5: 44117 | D5: 3217.5382 | E5: 467 | F5: 36.725538 | G5: 82 | H5: 5.920746 | I5: 32 | J5: 2.2844629 | K5: 3 | L5: 0.17922 | M5: 0 | N5: 0 | O5: 44701 | P5: 3262.6482 | Q5: 2 | R5: 0.12
A6: 2018-19$ | B6: 229 | C6: 379 | D6: 33.550222 | E6: 179 | F6: 11.238145 | G6: 0 | H6: 0 | I6: 0 | J6: 0 | K6: 2 | L6: 0.07568 | M6: 0 | N6: 0 | O6: 560 | P6: 44.864046 | Q6: 3 | R6: 0.21
A7: Apr-18 | B7: 21 | C7: 20 | D7: 1.7020806 | E7: 39 | F7: 2.5485902 | G7: 0 | H7: 0 | I7: 0 | J7: 0 | K7: 0 | L7: 0 | M7: 0 | N7: 0 | O7: 59 | P7: 4.2506708 | Q7: 2 | R7: 0.13
A8: May-18 | B8: 22 | C8: 6 | D8: 0.52782562 | E8: 33 | F8: 2.0079963 | G8: 0 | H8: 0 | I8: 0 | J8: 0 | K8: 2 | L8: 0.07568 | M8: 0 | N8: 0 | O8: 41 | P8: 2.6115019 | Q8: 4 | R8: 0.23
A9: Jun-18 | B9: 21 | C9: 331 | D9: 29.302817 | E9: 21 | F9: 1.2498841 | G9: 0 | H9: 0 | I9: 0 | J9: 0 | K9: 0 | L9: 0 | M9: 0 | N9: 0 | O9: 352 | P9: 30.552702 | Q9: 11 | R9: 0.90134249
A10: Jul-18 | B10: 22 | C10: 20 | D10: 1.8381006 | E10: 22 | F10: 1.3421004 | G10: 0 | H10: 0 | I10: 0 | J10: 0 | K10: 0 | L10: 0 | M10: 0 | N10: 0 | O10: 42 | P10: 3.180201 | Q10: 3 | R10: 0.17589258
A11: Aug-18 | B11: 21 | C11: 0 | D11: 0 | E11: 16 | F11: 1.0051319 | G11: 0 | H11: 0 | I11: 0 | J11: 0 | K11: 0 | L11: 0 | M11: 0 | N11: 0 | O11: 16 | P11: 1.0051319 | Q11: 3 | R11: 0.20286813
A12: Sep-18 | B12: 18 | C12: 0 | D12: 0 | E12: 14 | F12: 0.93372739 | G12: 0 | H12: 0 | I12: 0 | J12: 0 | K12: 0 | L12: 0 | M12: 0 | N12: 0 | O12: 14 | P12: 0.93372739 | Q12: 3 | R12: 0.18461427
A13: Oct-18 | B13: 21 | C13: 0 | D13: 0 | E13: 5 | F13: 0.28684624 | G13: 0 | H13: 0 | I13: 0 | J13: 0 | K13: 0 | L13: 0 | M13: 0 | N13: 0 | O13: 5 | P13: 0.28684624 | Q13: 2 | R13: 0.12
A14: Nov-18 | B14: 20 | C14: 0 | D14: 0 | E14: 4 | F14: 0.2465433 | G14: 0 | H14: 0 | I14: 0 | J14: 0 | K14: 0 | L14: 0 | M14: 0 | N14: 0 | O14: 4 | P14: 0.2465433 | Q14: 2 | R14: 0.12
A15: Dec-18 | B15: 20 | C15: 0 | D15: 0 | E15: 9 | F15: 0.5509133 | G15: 0 | H15: 0 | I15: 0 | J15: 0 | K15: 0 | L15: 0 | M15: 0 | N15: 0 | O15: 9 | P15: 0.5509133 | Q15: 3 | R15: 0.18
A16: Jan-19 | B16: 23 | C16: 2 | D16: 0.1793975 | E16: 5 | F16: 0.28869165 | G16: 0 | H16: 0 | I16: 0 | J16: 0 | K16: 0 | L16: 0 | M16: 0 | N16: 0 | O16: 7 | P16: 0.46808915 | Q16: 2 | R16: 0.1184723
A17: Feb-19 | B17: 20 | C17: 0 | D17: 0 | E17: 11 | F17: 0.77771986 | G17: 0 | H17: 0 | I17: 0 | J17: 0 | K17: 0 | L17: 0 | M17: 0 | N17: 0 | O17: 11 | P17: 0.77771986 | Q17: 3 | R17: 0.21
A18: $ indicates as on February 28,2019
A19: 1. Notional Turnover = (Strike Price + Premium) * Quantity.
A20: Source: BSE.

Sheet 35
A1: Table 35: Trends in Equity Derivatives Segment at NSE (Turnover in Notional Value)
A2: Year/ Month | B2: No. of Trading Days | C2: Index Futures | E2: Stock Futures | G2: Index Options | K2: Stock Options | O2: Total | Q2: Open Interest at the end of Month
G3: Call | I3: Put | K3: Call | M3: Put
C4: No. of Contracts | D4: Turnover (` crore) | E4: No. of Contracts | F4: Turnover (` crore) | G4: No. of Contracts | H4: Turnover (` crore) | I4: No. of Contracts | J4: Turnover (` crore) | K4: No. of Contracts | L4: Turnover (` crore) | M4: No. of Contracts | N4: Turnover (` crore) | O4: No. of Contracts | P4: Turnover (` crore) | Q4: No. of Contracts | R4: Turnover (` crore)
A5: 2017-18 | B5: 246 | C5: 57674584 | D5: 4810454.4 | E5: 214758366 | F5: 15597520 | G5: 783312918 | H5: 71028905 | I5: 731721304 | J5: 63892971 | K5: 86282094 | L5: 6728006.9 | M5: 40129282 | N5: 2927001.6 | O5: 1913878548 | P5: 1.6498486e+08 | Q5: 3800266 | R5: 274930.59
A6: 2018-19$ | B6: 229 | C6: 63855305 | D6: 5139810 | E6: 235978261 | F6: 14946168 | G6: 1234405083 | H6: 97504024 | I6: 1123759943 | J6: 86652929 | K6: 112791717 | L6: 7816176.5 | M6: 58357171 | N6: 3748290.4 | O6: 2829147480 | P6: 2.158074e+08 | Q6: 3534643 | R6: 232143.54
A7: Apr-18 | B7: 21 | C7: 4993824 | D7: 433691.27 | E7: 19971346 | F7: 1431956.8 | G7: 69599045 | H7: 6570818.4 | I7: 67963276 | J7: 6169967.6 | K7: 9224410 | L7: 711977.43 | M7: 4247393 | N7: 301815.94 | O7: 175999294 | P7: 15620227 | Q7: 4567264 | R7: 351290.32
A8: May-18 | B8: 22 | C8: 4991448 | D8: 446740.89 | E8: 21801493 | F8: 1430486.5 | G8: 86598523 | H8: 8491735.7 | I8: 82860071 | J8: 7927461.4 | K8: 9968877 | L8: 712976.87 | M8: 5105748 | N8: 332671.51 | O8: 211326160 | P8: 19342073 | Q8: 3796577 | R8: 285599.44
A9: Jun-18 | B9: 21 | C9: 5182508 | D9: 468591.04 | E9: 20044920 | F9: 1317353.4 | G9: 84577639 | H9: 8445192.9 | I9: 76522830 | J9: 7441947.8 | K9: 8967595 | L9: 651758.49 | M9: 4212883 | N9: 285772.96 | O9: 199508375 | P9: 18610617 | Q9: 3992821 | R9: 300615.84
A10: Jul-18 | B10: 22 | C10: 4672793 | D10: 429456.79 | E10: 21816111 | F10: 1476882.4 | G10: 77931556 | H10: 7947392.4 | I10: 76059866 | J10: 7553894.1 | K10: 11475161 | L10: 870430.05 | M10: 5324918 | N10: 379021.05 | O10: 197280405 | P10: 18657077 | Q10: 4353922 | R10: 350440.9
A11: Aug-18 | B11: 21 | C11: 4086103 | D11: 394229.14 | E11: 21581854 | F11: 1544987.2 | G11: 80237798 | H11: 8626841.1 | I11: 78161817 | J11: 8184551.3 | K11: 11369088 | L11: 901552.54 | M11: 5249072 | N11: 393971 | O11: 200685732 | P11: 20046132 | Q11: 4152480 | R11: 341915.26
A12: Sep-18 | B12: 18 | C12: 5832447 | D12: 540039.54 | E12: 21640734 | F12: 1464394.1 | G12: 104142054 | H12: 10662247 | I12: 87133996 | J12: 8675527.5 | K12: 9897504 | L12: 753661.15 | M12: 5036142 | N12: 362771.89 | O12: 233682877 | P12: 22458641 | Q12: 3859031 | R12: 284743.02
A13: Oct-18 | B13: 21 | C13: 8230210 | D13: 667269.87 | E13: 24929740 | F13: 1488064.9 | G13: 123060526 | H13: 10742713 | I13: 101343656 | J13: 8520364.1 | K13: 9592185 | L13: 664312.25 | M13: 5482238 | N13: 350545.59 | O13: 272638555 | P13: 22433270 | Q13: 5134553 | R13: 317298.02
A14: Nov-18 | B14: 20 | C14: 6717256 | D14: 441854.54 | E14: 21315096 | F14: 1187157.3 | G14: 144476482 | H14: 8216768.4 | I14: 138321044 | J14: 7702237.2 | K14: 9868483 | L14: 576187.5 | M14: 5323461 | N14: 290333.37 | O14: 326021822 | P14: 18414538 | Q14: 4337096 | R14: 276558.73
A15: Dec-18 | B15: 20 | C15: 6343194 | D15: 432193.7 | E15: 20474282 | F15: 1170839.2 | G15: 150063428 | H15: 8858652.9 | I15: 136335130 | J15: 7864301.9 | K15: 9523131 | L15: 576930.38 | M15: 4865999 | N15: 280844.69 | O15: 327605164 | P15: 19183763 | Q15: 4422992 | R15: 290864.55
A16: Jan-19 | B16: 23 | C16: 6852010 | D16: 472303.34 | E16: 21835896 | F16: 1277385.5 | G16: 173612999 | H16: 10316456 | I16: 152121040 | J16: 8887078.3 | K16: 11934197 | L16: 738289.89 | M16: 6738236 | N16: 393322.65 | O16: 373094378 | P16: 22084835 | Q16: 3705986 | R16: 243146.45
A17: Feb-19 | B17: 20 | C17: 5953512 | D17: 413439.91 | E17: 20566789 | F17: 1156660.7 | G17: 140105033 | H17: 8625206.1 | I17: 126937217 | J17: 7725598.2 | K17: 10971086 | L17: 658099.93 | M17: 6771081 | N17: 377219.79 | O17: 311304718 | P17: 18956225 | Q17: 3534643 | R17: 232143.54
A18: $ indicates as on February 28,2019
A19: 1. Notional Turnover = (Strike Price + Premium) * Quantity.
A20: Source: NSE.

Sheet 36
A1: Table 36: Settlement Statistics in Equity Derivatives Segment at BSE and NSE (` crore)
A2: Year/ Month | B2: BSE | H2: NSE
B3: Index/Stock Futures | D3: Index/Stock Options | F3: Total | G3: Settlement Gurantee Fund | H3: Index/Stock Futures | J3: Index/Stock Options | L3: Total | M3: Settlement Gurantee Fund
B4: MTM Settlement | C4: Final Settlement | D4: Premium Settlement | E4: Exercise Settlement | H4: MTM Settlement | I4: Final Settlement | J4: Premium Settlement | K4: Exercise Settlement
A5: 2017-18 | B5: 10.68 | C5: 0.34 | D5: 0.06 | E5: 0 | F5: 11.08 | G5: 17.89 | H5: 115457.08 | I5: 2212.95 | J5: 18941.51 | K5: 3210.19 | L5: 139821.73 | M5: 1617.45
A6: 2018-19$ | B6: 0.83 | C6: 0.05 | D6: 0 | E6: 0 | F6: 0.88 | G6: 19.32 | H6: 128486.91 | I6: 2546.54 | J6: 17138.84 | K6: 2304.68 | L6: 150476.97 | M6: 1882.93
A7: Apr-18 | B7: 0.12 | C7: 0.02 | D7: 0 | E7: 0 | F7: 0.14 | G7: 17.98 | H7: 9426.5 | I7: 160.96 | J7: 1453.52 | K7: 144.61 | L7: 11185.59 | M7: 0
A8: May-18 | B8: 0.13 | C8: 0 | D8: 0 | E8: 0 | F8: 0.13 | G8: 18.09 | H8: 12422.3 | I8: 373.97 | J8: 1275.35 | K8: 208.78 | L8: 14280.4 | M8: 1663.79
A9: Jun-18 | B9: 0.13 | C9: 0.02 | D9: 0 | E9: 0 | F9: 0.15 | G9: 18.2 | H9: 11243.01 | I9: 299.4 | J9: 1645.06 | K9: 394.04 | L9: 13581.51 | M9: 1692.85
A10: Jul-18 | B10: 0.11 | C10: 0 | D10: 0 | E10: 0 | F10: 0.11 | G10: 18.31 | H10: 12392.17 | I10: 161.07 | J10: 1323.05 | K10: 124.62 | L10: 14000.91 | M10: 1708.07
A11: Aug-18 | B11: 0.05 | C11: 0 | D11: 0 | E11: 0 | F11: 0.05 | G11: 18.42 | H11: 9001.41 | I11: 108.61 | J11: 1187.6 | K11: 133.41 | L11: 10431.03 | M11: 1730.54
A12: Sep-18 | B12: 0.07 | C12: 0 | D12: 0 | E12: 0 | F12: 0 | G12: 0.07 | H12: 16643.84 | I12: 347.61 | J12: 1857.61 | K12: 264.74 | L12: 19113.8 | M12: 1735.74
A13: Oct-18 | B13: 0.14 | C13: 0 | D13: 0 | E13: 0 | F13: 0 | G13: 0.14 | H13: 19279.05 | I13: 359.46 | J13: 2456.09 | K13: 272.48 | L13: 22367.08 | M13: 1780.09
A14: Nov-18 | B14: 0.03 | C14: 0 | D14: 0 | E14: 0 | F14: 0.03 | G14: 18.82 | H14: 8535.87 | I14: 296 | J14: 1202.97 | K14: 156.78 | L14: 10191.62 | M14: 1805.85
A15: Dec-18 | B15: 0.03 | C15: 0.01 | D15: 0 | E15: 0 | F15: 0.04 | G15: 18.93 | H15: 10940.52 | I15: 88.1 | J15: 2041.47 | K15: 382.72 | L15: 13452.81 | M15: 1838.78
A16: Jan-19 | B16: 0.05 | C16: 0 | D16: 0 | E16: 0 | F16: 0.05 | G16: 19.15 | H16: 8867.9 | I16: 278.25 | J16: 1469.83 | K16: 116.48 | L16: 10732.46 | M16: 1873.3
A17: Feb-19 | B17: 0.04 | C17: 0 | D17: 0 | E17: 0 | F17: 0.04 | G17: 19.32 | H17: 9734.34 | I17: 73.11 | J17: 1226.29 | K17: 106.02 | L17: 11139.76 | M17: 1882.93
A18: $ indicates as on February 28,2019
A19: Source: BSE and NSE

Sheet 37
A1: Table 37: Category-wise Share of Turnover & Open Interest in Equity Derivative Segment of BSE
A2: Year/Month | B2: Percentage Share in Turnover | G2: Percentage Share in Open Interest
B3: Pro | C3: FII | D3: Mutual Funds | E3: Banks | F3: Others | G3: Pro | H3: FII | I3: Mutual Funds | J3: Banks | K3: Others
A4: 2017-18 | B4: 90.616431 | C4: 1.5461211 | D4: 0 | E4: 0 | F4: 7.8374479 | G4: 0 | H4: 0 | I4: 0 | J4: 0 | K4: 100
A5: 2018-19$ | B5: 74.68 | C5: 0 | D5: 0 | E5: 0 | F5: 25.32 | G5: 0 | H5: 0 | I5: 0 | J5: 0 | K5: 100
A6: Apr-18 | B6: 44.71 | C6: 0 | D6: 0 | E6: 0 | F6: 55.29 | G6: 0 | H6: 0 | I6: 0 | J6: 0 | K6: 100
A7: May-18 | B7: 21.11 | C7: 0 | D7: 0 | E7: 0 | F7: 78.89 | G7: 0 | H7: 0 | I7: 0 | J7: 0 | K7: 100
A8: Jun-18 | B8: 95.33 | C8: 0 | D8: 0 | E8: 0 | F8: 4.67 | G8: 78.6016 | H8: 0 | I8: 0 | J8: 0 | K8: 21.3984
A9: Jul-18 | B9: 55 | C9: 0 | D9: 0 | E9: 0 | F9: 45 | G9: 0 | H9: 0 | I9: 0 | J9: 0 | K9: 100
A10: Aug-18 | B10: 0 | C10: 0 | D10: 0 | E10: 0 | F10: 100 | G10: 0 | H10: 0 | I10: 0 | J10: 0 | K10: 100
A11: Sep-18 | B11: 0 | C11: 0 | D11: 0 | E11: 0 | F11: 100 | G11: 0 | H11: 0 | I11: 0 | J11: 0 | K11: 100
A12: Oct-18 | B12: 0 | C12: 0 | D12: 0 | E12: 0 | F12: 100 | G12: 0 | H12: 0 | I12: 0 | J12: 0 | K12: 100
A13: Nov-18 | B13: 0 | C13: 0 | D13: 0 | E13: 0 | F13: 100 | G13: 0 | H13: 0 | I13: 0 | J13: 0 | K13: 100
A14: Dec-18 | B14: 0 | C14: 0 | D14: 0 | E14: 0 | F14: 100 | G14: 0 | H14: 0 | I14: 0 | J14: 0 | K14: 100
A15: Jan-19 | B15: 38.33 | C15: 0 | D15: 0 | E15: 0 | F15: 61.67 | G15: 0 | H15: 0 | I15: 0 | J15: 0 | K15: 100
A16: Feb-19 | B16: 0 | C16: 0 | D16: 0 | E16: 0 | F16: 100 | G16: 0 | H16: 0 | I16: 0 | J16: 0 | K16: 100
A17: $ indicates as on February 28,2019
A18: Source: BSE.

Sheet 38
A1: Table 38: Category-wise Share of Turnover & Open Interest in Equity Derivative Segment of NSE
A2: Year/Month | B2: Percentage Share in Turnover | G2: Percentage Share in Open Interest
B3: Pro | C3: FPIs | D3: Mutual Funds | E3: Banks | F3: Others | G3: Pro | H3: FPIs | I3: Mutual Funds | J3: Banks | K3: Others
A4: 2017-18 | B4: 42.34 | C4: 11.44 | D4: 0.46 | E4: 0 | F4: 45.76 | G4: 11.149433 | H4: 24.377642 | I4: 14.032153 | J4: 0 | K4: 50.440772
A5: 2018-19$ | B5: 38.16 | C5: 13.14 | D5: 0.42 | E5: 0 | F5: 48.28 | G5: 12.94 | H5: 30.93 | I5: 15.81 | J5: 0 | K5: 40.33
A6: Apr-18 | B6: 42.38 | C6: 12.67 | D6: 0.51 | E6: 0 | F6: 44.43 | G6: 12.7 | H6: 22.2 | I6: 12.97 | J6: 0 | K6: 52.13
A7: May-18 | B7: 42.58 | C7: 12.6 | D7: 0.41 | E7: 0 | F7: 44.41 | G7: 11.42 | H7: 24.74 | I7: 15.58 | J7: 0 | K7: 48.25
A8: Jun-18 | B8: 42.75 | C8: 11.72 | D8: 0.42 | E8: 0 | F8: 45.11 | G8: 13.01 | H8: 24.95 | I8: 13.96 | J8: 0 | K8: 48.08
A9: Jul-18 | B9: 41.02 | C9: 11.23 | D9: 0.44 | E9: 0 | F9: 47.31 | G9: 13.71 | H9: 23.01 | I9: 13.64 | J9: 0 | K9: 49.63
A10: Aug-18 | B10: 39.08 | C10: 11.64 | D10: 0.45 | E10: 0 | F10: 48.84 | G10: 13 | H10: 24.23 | I10: 14.52 | J10: 0 | K10: 48.25
A11: Sep-18 | B11: 35.41 | C11: 14.09 | D11: 0.36 | E11: 0 | F11: 50.14 | G11: 13.48 | H11: 27.34 | I11: 15.5 | J11: 0 | K11: 43.68
A12: Oct-18 | B12: 34.9 | C12: 15.26 | D12: 0.42 | E12: 0 | F12: 49.42 | G12: 16.41 | H12: 26.5 | I12: 13.31 | J12: 0 | K12: 43.77
A13: Nov-18 | B13: 35.11 | C13: 12.91 | D13: 0.46 | E13: 0 | F13: 51.52 | G13: 13.46 | H13: 28.49 | I13: 15.17 | J13: 0 | K13: 42.88
A14: Dec-18 | B14: 35.3 | C14: 13.12 | D14: 0.43 | E14: 0 | F14: 51.15 | G14: 15.23 | H14: 24.6 | I14: 13.56 | J14: 0 | K14: 46.61
A15: Jan-19 | B15: 35.76 | C15: 12.9 | D15: 0.36 | E15: 0 | F15: 50.99 | G15: 11.86 | H15: 31.79 | I15: 15.94 | J15: 0 | K15: 40.42
A16: Feb-19 | B16: 35.45 | C16: 16.46 | D16: 0.41 | E16: 0 | F16: 47.68 | G16: 12.94 | H16: 30.93 | I16: 15.81 | J16: 0 | K16: 40.33
A17: Source: NSE.
A18: $ indicates as on February 28,2019

Sheet 39
A1: Table 39: Instrument-wise Turnover in Index Derivatives at BSE
A2: Turnover (in Percentage)
A3: Year/Month | B3: BSE 30 SENSEX | C3: BSE SENSEX 50 | D3: BSE BANKEX | E3: BSE OIL & GAS INDEX | F3: BSE TECK INDEX | G3: BSE100 | H3: HANG SENG Index Futures | I3: MICEX Index Futures | J3: FTSE/JSE Top 40 Futures | K3: IBOVESPA Futures
A4: 2017-18 | B4: 0.04125657 | C4: 99.958743 | D4: 0 | E4: 0 | F4: 0 | G4: 5.8662e-05 | H4: 0 | I4: 0 | J4: 0 | K4: 0
A5: 2018-19$ | B5: 100 | C5: 0 | D5: 0 | E5: 0 | F5: 0 | G5: 0 | H5: 0 | I5: 0 | J5: 0 | K5: 0
A6: Apr-18 | B6: 100 | C6: 0 | D6: 0 | E6: 0 | F6: 0 | G6: 0 | H6: 0 | I6: 0 | J6: 0 | K6: 0
A7: May-18 | B7: 100 | C7: 0 | D7: 0 | E7: 0 | F7: 0 | G7: 0 | H7: 0 | I7: 0 | J7: 0 | K7: 0
A8: Jun-18 | B8: 100 | C8: 0 | D8: 0 | E8: 0 | F8: 0 | G8: 0 | H8: 0 | I8: 0 | J8: 0 | K8: 0
A9: Jul-18 | B9: 100 | C9: 0 | D9: 0 | E9: 0 | F9: 0 | G9: 0 | H9: 0 | I9: 0 | J9: 0 | K9: 0
A10: Aug-18 | B10: 0 | C10: 0 | D10: 0 | E10: 0 | F10: 0 | G10: 0 | H10: 0 | I10: 0 | J10: 0 | K10: 0
A11: Sep-18 | B11: 0 | C11: 0 | D11: 0 | E11: 0 | F11: 0 | G11: 0 | H11: 0 | I11: 0 | J11: 0 | K11: 0
A12: Oct-18 | B12: 0 | C12: 0 | D12: 0 | E12: 0 | F12: 0 | G12: 0 | H12: 0 | I12: 0 | J12: 0 | K12: 0
A13: Nov-18 | B13: 0 | C13: 0 | D13: 0 | E13: 0 | F13: 0 | G13: 0 | H13: 0 | I13: 0 | J13: 0 | K13: 0
A14: Dec-18 | B14: 100 | C14: 0 | D14: 0 | E14: 0 | F14: 0 | G14: 0 | H14: 0 | I14: 0 | J14: 0 | K14: 0
A15: Jan-19 | B15: 100 | C15: 0 | D15: 0 | E15: 0 | F15: 0 | G15: 0 | H15: 0 | I15: 0 | J15: 0 | K15: 0
A16: Feb-19 | B16: 0 | C16: 0 | D16: 0 | E16: 0 | F16: 0 | G16: 0 | H16: 0 | I16: 0 | J16: 0 | K16: 0
A17: $ indicates as on February 28,2019
A18: Source: BSE.

Sheet 40
A1: Table 40: Instrument-wise Turnover in Index Derivatives at NSE
A2: Turnover (in Percentage)
A3: Year/Month | B3: NIFTY | C3: NIFTYIT | D3: BANKNIFTY | E3: NIFTYMID50 | F3: NIFTYPSE | G3: NIFTYINFRA | H3: FTSE100 | I3: S&P500 | J3: DJIA | K3: India VIX | L3: NIFTYCPSE
A4: 2017-18 | B4: 35.72 | C4: 0 | D4: 64.27 | E4: 0 | F4: 0 | G4: 0 | H4: 0 | I4: 0 | J4: 0 | K4: 0 | L4: 0
A5: 2018-19$ | B5: 25.428784 | C5: 0.00386939 | D5: 74.564517 | E5: 0.002828893 | F5: 1e-06 | G5: 0 | H5: 8.5e-08 | I5: 0 | J5: 0 | K5: 0 | L5: 4.01e-07
A6: Apr-18 | B6: 30.25 | C6: 0.01 | D6: 69.73 | E6: 0 | F6: 0 | G6: 0 | H6: 0 | I6: 0 | J6: 0 | K6: 0 | L6: 0
A7: May-18 | B7: 26.34 | C7: 0 | D7: 73.65 | E7: 0 | F7: 0 | G7: 0 | H7: 0 | I7: 0 | J7: 0 | K7: 0 | L7: 0
A8: Jun-18 | B8: 25.33762 | C8: 0.003423759 | D8: 74.655378 | E8: 0.003576979 | F8: 8.98e-07 | G8: 0 | H8: 0 | I8: 0 | J8: 0 | K8: 0 | L8: 0
A9: Jul-18 | B9: 23.626187 | C9: 0.00328918 | D9: 76.366885 | E9: 0.00363814 | F9: 0 | G9: 0 | H9: 0 | I9: 0 | J9: 0 | K9: 0 | L9: 0
A10: Aug-18 | B10: 19.68685 | C10: 0.002105226 | D10: 80.307406 | E10: 0.003637454 | F10: 0 | G10: 0 | H10: 0 | I10: 0 | J10: 0 | K10: 0 | L10: 1.033e-06
A11: Sep-18 | B11: 23.448892 | C11: 0.004053896 | D11: 76.543182 | E11: 0.003871085 | F11: 0 | G11: 0 | H11: 7.4e-07 | I11: 0 | J11: 0 | K11: 0 | L11: 0
A12: Oct-18 | B12: 27.197965 | C12: 0.003540508 | D12: 72.794701 | E12: 0.003792443 | F12: 0 | G12: 0 | H12: 0 | I12: 0 | J12: 0 | K12: 0 | L12: 1.675e-06
A13: Nov-18 | B13: 22.620128 | C13: 0.003584514 | D13: 77.371458 | E13: 0.004829343 | F13: 0 | G13: 0 | H13: 0 | I13: 0 | J13: 0 | K13: 0 | L13: 0
A14: Dec-18 | B14: 25.050778 | C14: 0.003413049 | D14: 74.945801 | E14: 7.328e-06 | F14: 0 | G14: 0 | H14: 0 | I14: 0 | J14: 0 | K14: 0 | L14: 0
A15: Jan-19 | B15: 22.947571 | C15: 0.003631231 | D15: 77.048798 | E15: 0 | F15: 0 | G15: 0 | H15: 0 | I15: 0 | J15: 0 | K15: 0 | L15: 0
A16: Feb-19 | B16: 34.698539 | C16: 0.004023414 | D16: 65.297438 | E16: 0 | F16: 0 | G16: 0 | H16: 0 | I16: 0 | J16: 0 | K16: 0 | L16: 0
A17: $ indicates as on February 28,2019
A18: Source: NSE.

Sheet 41
A1: Table 41: Trends in Currency Derivatives Segment at BSE
A2: Year/ Month | B2: No. of Trading Days | C2: Currency Futures | E2: Currency Options | I2: Total | K2: Open Interest at the end of the Month
E3: Call | G3: Put
C4: No. of Contracts | D4: Turnover (` crore) | E4: No. of Contracts | F4: Turnover (` crore) | G4: No. of Contracts | H4: Turnover (` crore) | I4: No. of Contracts | J4: Turnover (` crore) | K4: No. of Contracts | L4: Value (` crore)
A5: 2017-18 | B5: 242 | C5: 307657074 | D5: 1993289.7 | E5: 129411173 | F5: 849930.62 | G5: 253165612 | H5: 1593210.2 | I5: 690233859 | J5: 4436430.4 | K5: 902208 | L5: 5918.9469
A6: 2018-19$ | B6: 224 | C6: 425717719 | D6: 2989443 | E6: 212204514 | F6: 1508314.8 | G6: 334899144 | H6: 2297496.9 | I6: 972821377 | J6: 6795254.7 | K6: 711999 | L6: 5073.9667
A7: Apr-18 | B7: 19 | C7: 30952221 | D7: 204764.54 | E7: 18771032 | F7: 125269.73 | G7: 27736861 | H7: 179927.31 | I7: 77460114 | J7: 509961.57 | K7: 1201971 | L7: 8074.2158
A8: May-18 | B8: 22 | C8: 42674267 | D8: 289561.42 | E8: 28817134 | F8: 198632.12 | G8: 36317492 | H8: 240274.92 | I8: 107808893 | J8: 728468.46 | K8: 1380015 | L8: 9320.8139
A9: Jun-18 | B9: 21 | C9: 45978940 | D9: 312995.48 | E9: 25069692 | F9: 173561.36 | G9: 34044225 | H9: 227128.28 | I9: 105092857 | J9: 713685.13 | K9: 1287083 | L9: 8836.3755
A10: Jul-18 | B10: 22 | C10: 37207835 | D10: 256366.2 | E10: 17349707 | F10: 121756.05 | G10: 39749432 | H10: 267057.88 | I10: 94306974 | J10: 645180.14 | K10: 924938 | L10: 6356.2837
A11: Aug-18 | B11: 20 | C11: 41814396 | D11: 291775.96 | E11: 24071134 | F11: 170569.88 | G11: 35916282 | H11: 245811.6 | I11: 101801812 | J11: 708157.43 | K11: 1378737 | L11: 9792.1349
A12: Sep-18 | B12: 18 | C12: 45790152 | D12: 331536.24 | E12: 8111593 | F12: 59602.895 | G12: 40847488 | H12: 288910.44 | I12: 94749233 | J12: 680049.57 | K12: 1030557 | L12: 7491.7922
A13: Oct-18 | B13: 21 | C13: 41294429 | D13: 304896.83 | E13: 13882510 | F13: 103956.57 | G13: 32048698 | H13: 232441.76 | I13: 87225637 | J13: 641295.16 | K13: 894213 | L13: 6622.43
A14: Nov-18 | B14: 19 | C14: 34950057 | D14: 251263.86 | E14: 24757257 | F14: 182441.9 | G14: 19758755 | H14: 140040.51 | I14: 79466069 | J14: 573746.27 | K14: 795267 | L14: 5547.27
A15: Dec-18 | B15: 20 | C15: 38917915 | D15: 275968.98 | E15: 16496565 | F15: 119518.99 | G15: 17303077 | H15: 120185.1 | I15: 72717557 | J15: 515673.06 | K15: 830342 | L15: 5797.04
A16: Jan-19 | B16: 23 | C16: 34030550 | D16: 241184.02 | E16: 18699832 | F16: 135593.12 | G16: 27704227 | H16: 191426.03 | I16: 80434609 | J16: 568203.17 | K16: 740780 | L16: 5272.4777
A17: Feb-19 | B17: 19 | C17: 32106957 | D17: 229129.46 | E17: 16178058 | F17: 117412.16 | G17: 23472607 | H17: 164293.09 | I17: 71757622 | J17: 510834.71 | K17: 711999 | L17: 5073.9667
A18: $ indicates as on February 28,2019
A19: Source: BSE

Sheet 42
A1: Table 42: Trends in Currency Derivatives Segment at NSE
A2: Year/ Month | B2: No. of Trading Days | C2: Currency Futures | E2: Currency Options | I2: Total | K2: Open Interest at the end of Month
C3: No. of Contracts | D3: Turnover (` crore) | E3: Call | G3: Put | I3: No. of Contracts | J3: Turnover (` crore) | K3: No. of Contracts | L3: Value (` crore)
E4: No. of Contracts | F4: Turnover (` crore) | G4: No. of Contracts | H4: Turnover (` crore)
A5: 2017-18 | B5: 242 | C5: 390433137 | D5: 2595685.7 | E5: 207170787 | F5: 1351047.5 | G5: 167359805 | H5: 1081769 | I5: 764963729 | J5: 5028502.2 | K5: 3847220 | L5: 25725.673
A6: 2018-19$ | B6: 224 | C6: 594750080 | D6: 4263577 | E6: 242576369 | F6: 1722179.5 | G6: 245123794 | H6: 1717259 | I6: 1082450243 | J6: 7703015.6 | K6: 4441072 | L6: 31909.216
A7: Apr-18 | B7: 19 | C7: 43614222 | D7: 297368.38 | E7: 15388108 | F7: 102162.38 | G7: 15704990 | H7: 103126.42 | I7: 74707320 | J7: 502657.18 | K7: 5105855 | L7: 34603.989
A8: May-18 | B8: 22 | C8: 58034086 | D8: 403383.58 | E8: 19588790 | F8: 133768.59 | G8: 22622791 | H8: 152299.41 | I8: 100245667 | J8: 689451.58 | K8: 4745561 | L8: 32363.68
A9: Jun-18 | B9: 21 | C9: 51556491 | D9: 360161.73 | E9: 18636606 | F9: 127840.4 | G9: 18373357 | H9: 124386.49 | I9: 88566454 | J9: 612388.62 | K9: 5201656 | L9: 36030.472
A10: Jul-18 | B10: 22 | C10: 45194719 | D10: 319727.24 | E10: 17383943 | F10: 120678.01 | G10: 17278419 | H10: 118460.71 | I10: 79857081 | J10: 558865.96 | K10: 3932469 | L10: 27346.28
A11: Aug-18 | B11: 20 | C11: 56747406 | D11: 403910.91 | E11: 25304617 | F11: 178287.61 | G11: 23992540 | H11: 166682.98 | I11: 106044563 | J11: 748881.51 | K11: 6350909 | L11: 45582.842
A12: Sep-18 | B12: 18 | C12: 70515824 | D12: 517416.66 | E12: 28808093 | F12: 210264.08 | G12: 32382684 | H12: 232260.12 | I12: 131706601 | J12: 959940.86 | K12: 5176690 | L12: 37923.701
A13: Oct-18 | B13: 21 | C13: 64356584 | D13: 481103.67 | E13: 18372683 | F13: 136852.38 | G13: 21798564 | H13: 159572.46 | I13: 104527831 | J13: 777528.51 | K13: 4165346 | L13: 31097.817
A14: Nov-18 | B14: 19 | C14: 47368479 | D14: 345891.96 | E14: 24396081 | F14: 177532.6 | G14: 21962805 | H14: 158235.73 | I14: 93727365 | J14: 681660.29 | K14: 3682475 | L14: 25870.621
A15: Dec-18 | B15: 20 | C15: 53424447 | D15: 383122.75 | E15: 26179268 | F15: 187370.06 | G15: 24262860 | H15: 171311.15 | I15: 103866575 | J15: 741803.96 | K15: 3750066 | L15: 26361.685
A16: Jan-19 | B16: 23 | C16: 55668608 | D16: 401107.62 | E16: 24068286 | F16: 171884.95 | G16: 25036281 | H16: 176490.02 | I16: 104773175 | J16: 749482.59 | K16: 3824404 | L16: 27499.51
A17: Feb-19 | B17: 19 | C17: 48269214 | D17: 350382.51 | E17: 24449894 | F17: 175538.48 | G17: 21708503 | H17: 154433.5 | I17: 94427611 | J17: 680354.49 | K17: 4441072 | L17: 31909.216
A18: 1. Trading Value :- For Futures, Value of contract = Traded Qty*Traded Price. 2. For Options, Value of contract = Traded Qty*(Strike Price+Traded Premium)
A19: $ indicates as on February 28,2019
A20: Source: NSE.

Sheet 43
A1: Table 43: Trends in Currency Derivatives Segment at MSEI
A2: Year/ Month | B2: No. of Trading Days | C2: Currency Futures | E2: Currency Options | I2: Total | K2: Open Interest at the end of Month
C3: No. of Contracts | D3: Turnover (` crore) | E3: Call | G3: Put | I3: No. of Contracts | J3: Turnover (` crore) | K3: No. of Contracts | L3: Value (` crore)
E4: No. of Contracts | F4: Turnover (` crore) | G4: No. of Contracts | H4: Turnover (` crore)
A5: 2017-18 | B5: 242 | C5: 15393172 | D5: 99722.314 | E5: 1387661 | F5: 9059.1398 | G5: 1068854 | H5: 6951.327 | I5: 17849687 | J5: 115732.78 | K5: 95637 | L5: 628.49921
A6: 2018-19$ | B6: 224 | C6: 5197728 | D6: 36068.757 | E6: 526310 | F6: 3726.8073 | G6: 669307 | H6: 4742.153 | I6: 6393345 | J6: 44537.717 | K6: 17038 | L6: 125.58599
A7: Apr-18 | B7: 19 | C7: 802159 | D7: 5319.2364 | E7: 112894 | F7: 750.84314 | G7: 76747 | H7: 500.88062 | I7: 991800 | J7: 6570.9601 | K7: 82927 | L7: 558.39804
A8: May-18 | B8: 22 | C8: 969230 | D8: 6574.3143 | E8: 30754 | F8: 210.15391 | G8: 66366 | H8: 452.52458 | I8: 1066350 | J8: 7236.9928 | K8: 50799 | L8: 345.68943
A9: Jun-18 | B9: 21 | C9: 703647 | D9: 4843.3185 | E9: 12526 | F9: 85.718977 | G9: 47953 | H9: 328.12731 | I9: 764126 | J9: 5257.1648 | K9: 35923 | L9: 248.57173
A10: Jul-18 | B10: 22 | C10: 1143174 | D10: 7905.8325 | E10: 32206 | F10: 223.12148 | G10: 38039 | H10: 265.31956 | I10: 1213419 | J10: 8394.2735 | K10: 31871 | L10: 221.31518
A11: Aug-18 | B11: 20 | C11: 475217 | D11: 3342.13 | E11: 19391 | F11: 135.68 | G11: 40930 | H11: 288.96 | I11: 535538 | J11: 3766.77 | K11: 36644 | L11: 261.88
A12: Sep-18 | B12: 18 | C12: 450547 | D12: 3283.8225 | E12: 21706 | F12: 157.37263 | G12: 74689 | H12: 550.16743 | I12: 546942 | J12: 3991.3626 | K12: 17023 | L12: 124.86731
A13: Oct-18 | B13: 21 | C13: 214773 | D13: 1614.4937 | E13: 63597 | F13: 472.22849 | G13: 110119 | H13: 813.67053 | I13: 388489 | J13: 2900.3927 | K13: 17476 | L13: 132.13047
A14: Nov-18 | B14: 19 | C14: 128066 | D14: 945.62911 | E14: 84580 | F14: 611.50264 | G14: 68624 | H14: 493.64339 | I14: 281270 | J14: 2050.7751 | K14: 11906 | L14: 83.63016
A15: Dec-18 | B15: 20 | C15: 93021 | D15: 667.22274 | E15: 51448 | F15: 374.43917 | G15: 34706 | H15: 249.20524 | I15: 179175 | J15: 1290.8672 | K15: 13970 | L15: 99.166469
A16: Jan-19 | B16: 23 | C16: 94303 | D16: 678.81171 | E16: 73571 | F16: 529.01256 | G16: 48926 | H16: 349.01743 | I16: 216800 | J16: 1556.8417 | K16: 13546 | L16: 99.172168
A17: Feb-19 | B17: 19 | C17: 123591 | D17: 893.94902 | E17: 23637 | F17: 176.72935 | G17: 62208 | H17: 450.63538 | I17: 209436 | J17: 1521.3138 | K17: 17038 | L17: 125.58599
A18: $ indicates as on February 28,2019
A19: Source: MSEI

Sheet 44
A1: Table 44: Settlement Statistics of Currency Derivatives Segment (` crore)
A2: Year/ Month | B2: BSE | F2: Total | G2: NSE | K2: Total | L2: MSEI | P2: Total
B3: Currency Futures | D3: Currency Options | G3: Currency Futures | I3: Currency Options | L3: Currency Futures | N3: Currency Options
B4: MTM Settlement | C4: Final Settlement | D4: Premium Settlement | E4: Exercise Settlement | G4: MTM Settlement | H4: Final Settlement | I4: Premium Settlement | J4: Exercise Settlement | L4: MTM Settlement | M4: Final Settlement | N4: Premium Settlement | O4: Exercise Settlement
A5: 2017-18 | B5: 3227.51 | C5: 104.85 | D5: 2681.5 | E5: 174.81 | F5: 6188.67 | G5: 3570.0747 | H5: 118.59464 | I5: 948.73255 | J5: 391.98226 | K5: 5029.3842 | L5: 321.64 | M5: 13.38 | N5: 21.25 | O5: 16.26 | P5: 372.53
A6: 2018-19$ | B6: 5623.67 | C6: 189.56 | D6: 3327.96 | E6: 145.43 | F6: 9286.62 | G6: 7890.1058 | H6: 289.17754 | I6: 1166.2916 | J6: 584.07626 | K6: 9929.6512 | L6: 121.28275 | M6: 6.75936 | N6: 0.55571825 | O6: 0.68199744 | P6: 129.27983
A7: Apr-18 | B7: 322.23 | C7: 29.06 | D7: 199.52 | E7: 11.89 | F7: 562.7 | G7: 404.78531 | H7: 59.002073 | I7: 69.355563 | J7: 40.149632 | K7: 573.29258 | L7: 20.03 | M7: 1.98 | N7: 0.11 | O7: 0.31 | P7: 22.43
A8: May-18 | B8: 800.07 | C8: 55.96 | D8: 305.45 | E8: 10.63 | F8: 1172.11 | G8: 997.53043 | H8: 89.251836 | I8: 88.315348 | J8: 62.568464 | K8: 1237.6661 | L8: 32.93 | M8: 2.64 | N8: 0.07 | O8: 0.13 | P8: 35.77
A9: Jun-18 | B9: 508.38 | C9: 23.82 | D9: 321 | E9: 11.58 | F9: 864.78 | G9: 754.42386 | H9: 49.76034 | I9: 80.044044 | J9: 57.173141 | K9: 941.40139 | L9: 10.84 | M9: 0.46 | N9: 0.04 | O9: 0.03 | P9: 11.37
A10: Jul-18 | B10: 345.71 | C10: 5.05 | D10: 221.87 | E10: 4.21 | F10: 576.84 | G10: 498.96861 | H10: 4.3749745 | I10: 78.874698 | J10: 22.692806 | K10: 604.91109 | L10: 8.86 | M10: 0.25 | N10: 0.06 | O10: 0 | P10: 9.17
A11: Aug-18 | B11: 966.56 | C11: 61.88 | D11: 562.24 | E11: 48.08 | F11: 1638.76 | G11: 634.87094 | H11: 47.43282 | I11: 110.75714 | J11: 56.791506 | K11: 849.8524 | L11: 7.57 | M11: 1.07 | N11: 0.1 | O11: 0.08 | P11: 8.82
A12: Sep-18 | B12: 685.57 | C12: 5.76 | D12: 365.8 | E12: 24.17 | F12: 1081.3 | G12: 1416.9842 | H12: 5.1058309 | I12: 150.55131 | J12: 82.973717 | K12: 1655.615 | L12: 15.02 | M12: 0.04 | N12: 0.05 | O12: 0.09 | P12: 15.2
A13: Oct-18 | B13: 606.39 | C13: 5.78 | D13: 414.76 | E13: 9.93 | F13: 1036.86 | G13: 1106.069 | H13: 4.1425155 | I13: 123.00491 | J13: 41.500148 | K13: 1274.7166 | L13: 5.69 | M13: 0.01 | N13: 0.047453 | O13: 0.01 | P13: 5.757453
A14: Nov-18 | B14: 571.7 | C14: 7.21 | D14: 377.34 | E14: 27.38 | F14: 983.63 | G14: 638.17381 | H14: 4.8196269 | I14: 149.75747 | J14: 136.15358 | K14: 928.90449 | L14: 7.4 | M14: 0.023 | N14: 0.031558 | O14: 0.0284 | P14: 7.482958
A15: Dec-18 | B15: 580.17 | C15: 18.47 | D15: 313.82 | E15: 12.31 | F15: 924.77 | G15: 572.0686 | H15: 14.201362 | I15: 137.38567 | J15: 30.047445 | K15: 753.70308 | L15: 6.28 | M15: 0.19656 | N15: 0.0042 | O15: 0 | P15: 6.48076
A16: Jan-19 | B16: 407.44 | C16: 2.8 | D16: 298.94 | E16: 6.1 | F16: 715.28 | G16: 439.43686 | H16: 1.7020151 | I16: 103.57586 | J16: 31.386414 | K16: 576.10116 | L16: 3.74 | M16: 0.02 | N16: 0.04 | O16: 0.003 | P16: 3.803
A17: Feb-19 | B17: 312.73 | C17: 4.71 | D17: 228.34 | E17: 3.19 | F17: 548.97 | G17: 426.79422 | H17: 9.3841434 | I17: 74.669617 | J17: 22.639409 | K17: 533.48739 | L17: 2.925 | M17: 0.0698 | N17: 0.00150725 | O17: 0.00059744 | P17: 2.9969047
A18: $ indicates as on February 28,2019
A19: Source: BSE, NSE and MSEI.

Sheet 45
A1: Table 45: Instrument-wise Turnover in Currency Derivative Segment of BSE
A2: Year/Month | B2: Turnover (` crore) | I2: Open Interest as on last day of the month (in lots)
B3: USDINR | C3: EURINR | D3: GBPINR | E3: JPYINR | F3: EURUSD | G3: GBPUSD | H3: USDJPY | I3: USDINR | J3: EURINR | K3: GBPINR | L3: JPYINR | M3: EURUSD | N3: GBPUSD | O3: USDJPY
A4: 2017-2018 | B4: 4403388.1 | C4: 10491.21 | D4: 10781.62 | E4: 1726.47 | F4: 5148.12 | G4: 4719.51 | H4: 175.36 | I4: 871702 | J4: 22950 | K4: 5696 | L4: 1860 | M4: 1994 | N4: 3967 | O4: 3
A5: 2018-19 | B5: 6780040.6 | C5: 5252.8312 | D5: 4664.2394 | E5: 1275.6587 | F5: 2712.9962 | G5: 1275.2541 | H5: 33.1141 | I5: 708430 | J5: 1032 | K5: 1846 | L5: 691 | M5: 0 | N5: 0 | O5: 0
A6: Apr-18 | B6: 505815.14 | C6: 1723.5059 | D6: 667.5933 | E6: 65.5509 | F6: 836.7694 | G6: 826.8413 | H6: 26.1731 | I6: 1172762 | J6: 21756 | K6: 6699 | L6: 754 | M6: 2334 | N6: 3325 | O6: 429
A7: May-18 | B7: 724688.08 | C7: 1181.77 | D7: 765.13 | E7: 67.18 | F7: 1517.89 | G7: 241.74 | H7: 6.69 | I7: 1372211 | J7: 2938 | K7: 4164 | L7: 702 | M7: 3231 | N7: 450 | O7: 24
A8: Jun-18 | B8: 712251.33 | C8: 453.5 | D8: 440.13 | E8: 93.45 | F8: 312.31 | G8: 134.15 | H8: 0.26 | I8: 1280120 | J8: 2299 | K8: 3809 | L8: 855 | M8: 60 | N8: 10 | O8: 0
A9: Jul-18 | B9: 644204.79 | C9: 341.21 | D9: 452.14 | E9: 72.7 | F9: 40.98 | G9: 68.32 | H9: 0 | I9: 917659 | J9: 2825 | K9: 3713 | L9: 707 | M9: 12 | N9: 22
A10: Aug-18 | B10: 707320.92 | C10: 313.56 | D10: 266.28 | E10: 248.9 | F10: 4.29 | G10: 3.48 | H10: 0 | I10: 1362719 | J10: 6386 | K10: 4502 | L10: 5085 | M10: 15 | N10: 30 | O10: 0
A11: Sep-18 | B11: 679315.29 | C11: 244.81915 | D11: 426.20257 | E11: 62.056103 | F11: 0.52337672 | G11: 0.68272695 | H11: 0 | I11: 1021346 | J11: 4466 | K11: 4611 | L11: 112 | M11: 20 | N11: 2 | O11: 0
A12: Oct-18 | B12: 640681.91 | C12: 182.63486 | D12: 384.02175 | E12: 46.359502 | F12: 0.21189305 | G12: 0.019413912 | H12: 0 | I12: 889470 | J12: 2039 | K12: 2134 | L12: 570 | M12: 0 | N12: 0 | O12: 0
A13: Nov-18 | B13: 572947.75 | C13: 234.66967 | D13: 469.50797 | E13: 94.335503 | F13: 0 | G13: 0 | H13: 0 | I13: 787973 | J13: 5500 | K13: 1370 | L13: 424 | M13: 0 | N13: 0 | O13: 0
A14: Dec-18 | B14: 515111.71 | C14: 143.73 | D14: 307.86 | E14: 109.77 | F14: 0 | G14: 0 | H14: 0 | I14: 827968 | J14: 947 | K14: 743 | L14: 684 | M14: 0 | N14: 0 | O14: 0
A15: Jan-19 | B15: 567264.74 | C15: 290.8773 | D15: 275.4545 | E15: 372.0515 | F15: 0.0161 | G15: 0.0276 | H15: 0 | I15: 726324 | J15: 9299 | K15: 1262 | L15: 3895 | M15: 0 | N15: 0 | O15: 0
A16: Feb-19 | B16: 510438.92 | C16: 142.56074 | D16: 209.91797 | E16: 43.307551 | F16: 0 | G16: 0 | H16: 0 | I16: 708430 | J16: 1032 | K16: 1846 | L16: 691 | M16: 0 | N16: 0 | O16: 0
A17: 1. USDINR includes Futures and options both other currencys have only futures till February 26, 2018.
A18: 2. All Products include both Futures & options from February 27, 2018 onwards.
A19: 3. EURUSD, GBPUSD, USDJPY wer launched in Feb 2018
A20: $ indicates as on February 28,2019
A21: Source: BSE

Sheet 46
A1: Table 46: Instrument-wise Turnover in Currency Derivatives of NSE
A2: Year/Month | B2: Turnover ( ` crore) | I2: Open Interest as on last day of the month ( in lots)
B3: USDINR | C3: EURINR | D3: GBPINR | E3: JPYINR | F3: EURUSD | G3: GBPUSD | H3: USDJPY | I3: USDINR | J3: EURINR | K3: GBPINR | L3: JPYINR | M3: EURUSD | N3: GBPUSD | O3: USDJPY
A4: 2017-18 | B4: 4612668.2 | C4: 161598.73 | D4: 194484.71 | E4: 46310.03 | F4: 43775.688 | G4: 42495.632 | H4: 36992.214 | I4: 3503144 | J4: 182368 | K4: 98106 | L4: 34923 | M4: 15886 | N4: 11570 | O4: 1223
A5: 2018-19$ | B5: 7202747.2 | C5: 165575.16 | D5: 205148.98 | E5: 55165.831 | F5: 41526.616 | G5: 31665.993 | H5: 1185.7678 | I5: 4220790 | J5: 63485 | K5: 85230 | L5: 36283 | M5: 31233 | N5: 3826 | O5: 225
A6: Apr-18 | B6: 457294.48 | C6: 14873.312 | D6: 20143.857 | E6: 3936.2091 | F6: 2960.415 | G6: 3203.1246 | H6: 245.77931 | I6: 4824550 | J6: 147077 | K6: 81673 | L6: 27074 | M6: 15759 | N6: 7322 | O6: 2400
A7: May-18 | B7: 631556.1 | C7: 18960.308 | D7: 20211.804 | E7: 4062.5619 | F7: 10942.008 | G7: 3511.3835 | H7: 207.42066 | I7: 4522147 | J7: 105700 | K7: 50420 | L7: 31384 | M7: 31172 | N7: 2990 | O7: 1748
A8: Jun-18 | B8: 556743.35 | C8: 17893.986 | D8: 20172.906 | E8: 5562.1592 | F8: 7859.9329 | G8: 3968.2222 | H8: 188.07187 | I8: 4961108 | J8: 112949 | K8: 47584 | L8: 37332 | M8: 33279 | N8: 8026 | O8: 1378
A9: Jul-18 | B9: 506418.69 | C9: 16841.309 | D9: 21026.967 | E9: 5716.188 | F9: 4185.4096 | G9: 4490.1344 | H9: 187.26068 | I9: 3684852 | J9: 125558 | K9: 53196 | L9: 35667 | M9: 27068 | N9: 4482 | O9: 1646
A10: Aug-18 | B10: 698841.78 | C10: 17925.436 | D10: 18041.729 | E10: 6485.2389 | F10: 3868.475 | G10: 3593.2577 | H10: 125.5876 | I10: 5996455 | J10: 174436 | K10: 71402 | L10: 64390 | M10: 25465 | N10: 17659 | O10: 1102
A11: Sep-18 | B11: 915275.39 | C11: 16015.352 | D11: 16408.705 | E11: 5677.0604 | F11: 3216.0991 | G11: 3297.976 | H11: 50.277777 | I11: 4954025 | J11: 113994 | K11: 46874 | L11: 32357 | M11: 25039 | N11: 4034 | O11: 367
A12: Oct-18 | B12: 735417.74 | C12: 15625.984 | D12: 15992.89 | E12: 4962.0828 | F12: 3104.9459 | G12: 2397.7051 | H12: 27.161642 | I12: 3962595 | J12: 98443 | K12: 38857 | L12: 34164 | M12: 27433 | N12: 3649 | O12: 205
A13: Nov-18 | B13: 645879.39 | C13: 11666.892 | D13: 16958.368 | E13: 3521.1617 | F13: 1463.8594 | G13: 2140.714 | H13: 29.898967 | I13: 3513292 | J13: 73612 | K13: 35961 | L13: 25794 | M13: 28894 | N13: 4643 | O13: 279
A14: Dec-18 | B14: 708035.38 | C14: 11525.26 | D14: 15287.875 | E14: 4107.5237 | F14: 1416.8349 | G14: 1392.5944 | H14: 38.488997 | I14: 3602162 | J14: 57285 | K14: 27736 | L14: 30879 | M14: 28086 | N14: 3166 | O14: 752
A15: Jan-19 | B15: 703691.19 | C15: 14038.628 | D15: 21351.363 | E15: 6912.2316 | F15: 1481.3518 | G15: 1949.0005 | H15: 58.826699 | I15: 3588739 | J15: 86410 | K15: 59962 | L15: 53047 | M15: 31097 | N15: 4485 | O15: 664
A16: Feb-19 | B16: 643593.71 | C16: 10208.695 | D16: 19552.515 | E16: 4223.4136 | F16: 1027.2845 | G16: 1721.8801 | H16: 26.993583 | I16: 4220790 | J16: 63485 | K16: 85230 | L16: 36283 | M16: 31233 | N16: 3826 | O16: 225
A17: 1. Cross Currency was introduced wef Feb 27, 2018
A18: 2. Options contracts on EURINR,GBPINR,JPYINR were introduced wef Feb 27, 2018
A19: $ indicates as on February 28,2019
A20: Source: NSE.

Sheet 47
A1: Table 47: Instrument-wise Turnover in Currency Derivative Segment of MSEI
A2: Year/Month | B2: Turnover (` crore) | F2: Open Interest as on last day of the month (in lots)
B3: USDINR | C3: EURINR | D3: GBPINR | E3: JPYINR | F3: USDINR | G3: EURINR | H3: GBPINR | I3: JPYINR
A4: 2017-18 | B4: 113894.66 | C4: 709.2593 | D4: 942.47782 | E4: 186.38497 | F4: 93395 | G4: 1292 | H4: 906 | I4: 44
A5: 2018-19$ | B5: 43034.752 | C5: 547.86455 | D5: 932.67809 | E5: 20.79593 | F5: 15098 | G5: 58 | H5: 1866 | I5: 16
A6: Apr-18 | B6: 6474.7276 | C6: 30.447038 | D6: 63.302846 | E6: 2.4825932 | F6: 81339 | G6: 666 | H6: 869 | I6: 53
A7: May-18 | B7: 7131.3881 | C7: 58.711927 | D7: 44.624411 | E7: 2.268332 | F7: 49725 | G7: 309 | H7: 716 | I7: 49
A8: Jun-18 | B8: 5023.1932 | C8: 96.384553 | D8: 132.78992 | E8: 4.7971367 | F8: 35087 | G8: 164 | H8: 642 | I8: 30
A9: Jul-18 | B9: 8204.5266 | C9: 68.97959 | D9: 119.30727 | E9: 1.4601122 | F9: 30990 | G9: 196 | H9: 666 | I9: 19
A10: Aug-18 | B10: 3611.54 | C10: 58.7 | D10: 95.17 | E10: 1.37 | F10: 35992 | G10: 420 | H10: 207 | I10: 25
A11: Sep-18 | B11: 3875.5163 | C11: 58.985829 | D11: 55.511549 | E11: 1.3488975 | F11: 16479 | G11: 262 | H11: 274 | I11: 8
A12: Oct-18 | B12: 2751.6784 | C12: 38.819265 | D12: 108.25012 | E12: 1.6449015 | F12: 16232 | G12: 123 | H12: 1117 | I12: 4
A13: Nov-18 | B13: 1924.4182 | C13: 32.599251 | D13: 92.644183 | E13: 1.113484 | F13: 11648 | G13: 61 | H13: 182 | I13: 15
A14: Dec-18 | B14: 1175.257 | C14: 44.353555 | D14: 68.599885 | E14: 1.030345 | F14: 13142 | G14: 306 | H14: 500 | I14: 22
A15: Jan-19 | B15: 1478.7378 | C15: 17.332912 | D15: 58.909116 | E15: 1.8618445 | F15: 12304 | G15: 85 | H15: 1100 | I15: 57
A16: Feb-19 | B16: 1383.7722 | C16: 42.554454 | D16: 93.57077 | E16: 1.4163292 | F16: 15098 | G16: 58 | H16: 1866 | I16: 16
A17: $ indicates as on February 28,2019
A18: Data includes Notional Value for Options
A19: Excludes data of Interest Rate Futures
A20: Source: MSEI

Sheet 48
A1: Table 48: Maturity-wise Turnover in Currency Derivative Segment of BSE (` crore)
A2: Year/Month | B2: Currency Futures | F2: Currency Options
B3: 1 Month | C3: 2 Month | D3: 3 Month | E3: > 3 Months | F3: 1 Month | G3: 2 Month | H3: 3 Month | I3: > 3 Months
A4: 2017-18 | B4: 1780792.3 | C4: 257394.98 | D4: 14923.935 | E4: 3215.2645 | F4: 2121666.7 | G4: 242715.17 | H4: 4734.7311 | I4: 938.817
A5: 2018-19$ | B5: 2632813.9 | C5: 320351.54 | D5: 8309.8879 | E5: 1587.534 | F5: 3421476.5 | G5: 301592.83 | H5: 1132.1236 | I5: 127.1642
A6: Apr-18 | B6: 172464.05 | C6: 29834.333 | D6: 737.9049 | E6: 38.4668 | F6: 268708.34 | G6: 36303.749 | H6: 178.2041 | I6: 6.7463
A7: May-18 | B7: 248017.25 | C7: 39004.463 | D7: 694.3888 | E7: 78.9955 | F7: 382200.44 | G7: 56483.561 | H7: 178.6556 | I7: 44.3955
A8: Jun-18 | B8: 266768.28 | C8: 44853.971 | D8: 922.3214 | E8: 53.287 | F8: 335804.79 | G8: 64566.97 | H8: 257.62 | I8: 11.1637
A9: Jul-18 | B9: 229620.37 | C9: 25172.678 | D9: 683.7712 | E9: 889.3872 | F9: 354707.27 | G9: 34055.645 | H9: 44.4543 | I9: 6.5679
A10: Aug-18 | B10: 255467.19 | C10: 30913.91 | D10: 575.41 | E10: 72.26 | F10: 360701.72 | G10: 27711.85 | H10: 98.97 | I10: 6.07
A11: Sep-18 | B11: 297641.8 | C11: 29632.89 | D11: 580.88 | E11: 51.27 | F11: 328172.6 | G11: 12874.15 | H11: 303.96 | I11: 46.98
A12: Oct-18 | B12: 273134.18 | C12: 27408.23 | D12: 894.67 | E12: 96.19 | F12: 313674.63 | G12: 18228.41 | H12: 39.55 | I12: 0
A13: Nov-18 | B13: 222269.13 | C13: 25297.427 | D13: 906.5348 | E13: 38.9995 | F13: 300532.76 | G13: 17649.139 | H13: 19.0444 | I13: 1.1125
A14: Dec-18 | B14: 249354.26 | C14: 22482.781 | D14: 683.5989 | E14: 62.9629 | F14: 225382.44 | G14: 7120.8534 | H14: 4.4075 | I14: 4.1231
A15: Jan-19 | B15: 215598.91 | C15: 21778.308 | D15: 888.2864 | E15: 25.9418 | F15: 308670.45 | G15: 11972.345 | H15: 5.4315 | I15: 0
A16: Feb-19 | B16: 202478.48 | C16: 23972.556 | D16: 742.1288 | E16: 179.7764 | F16: 242921.06 | G16: 14626.153 | H16: 1.8241 | I16: 0
A17: $ indicates as on February 28,2019
A18: Source: BSE

Sheet 49
A1: Table 49: Maturity-wise Turnover in Currency Derivative Segment of NSE (` crore)
A2: Year/Month | B2: Currency Future | F2: Currency Options
B3: 1 Month | C3: 2 Month | D3: 3 Month | E3: > 3 Months | F3: 1 Month | G3: 2 Month | H3: 3 Month | I3: > 3 Months
A4: 2017-18 | B4: 2053700.4 | C4: 465857.95 | D4: 52348.625 | E4: 23778.695 | F4: 2029429 | G4: 379758.38 | H4: 19693.138 | I4: 3935.9502
A5: 2018-19$ | B5: 3416537.3 | C5: 753518.34 | D5: 61996.559 | E5: 31524.833 | F5: 2476222.3 | G5: 476153.34 | H5: 182971.58 | I5: 304091.32
A6: Apr-18 | B6: 225500.08 | C6: 64372.783 | D6: 4922.144 | E6: 2573.3732 | F6: 163688.51 | G6: 39873.741 | H6: 1705.8362 | I6: 20.713539
A7: May-18 | B7: 320285.61 | C7: 73421.956 | D7: 5731.439 | E7: 3944.5798 | F7: 251117.02 | G7: 34680.897 | H7: 251.28388 | I7: 18.797507
A8: Jun-18 | B8: 278639.82 | C8: 73587.922 | D8: 5137.1571 | E8: 2796.8274 | F8: 225437.77 | G8: 26213.716 | H8: 574.61722 | I8: 0.790063
A9: Jul-18 | B9: 257945.99 | C9: 55684.415 | D9: 3810.9854 | E9: 2285.8535 | F9: 210792.78 | G9: 28330.338 | H9: 15.598645 | I9: 0
A10: Aug-18 | B10: 314425.96 | C10: 79776.33 | D10: 6308.037 | E10: 3400.5831 | F10: 310832.46 | G10: 34024.753 | H10: 113.37046 | I10: 0.013912
A11: Sep-18 | B11: 417092.81 | C11: 89357.549 | D11: 6966.1671 | E11: 4000.1395 | F11: 407356.31 | G11: 34894.757 | H11: 228.18929 | I11: 44.940802
A12: Oct-18 | B12: 396623.46 | C12: 75209.23 | D12: 7001.8757 | E12: 2269.1088 | F12: 269942.1 | G12: 25706.179 | H12: 773.3052 | I12: 3.259424
A13: Nov-18 | B13: 284669.85 | C13: 54716.973 | D13: 4269.4356 | E13: 2235.6958 | F13: 309703.63 | G13: 26011.233 | H13: 53.466822 | I13: 0
A14: Dec-18 | B14: 313406.08 | C14: 61383.135 | D14: 4699.9082 | E14: 3633.6268 | F14: 92930.452 | G14: 108381.6 | H14: 66223.711 | I14: 91145.443
A15: Jan-19 | B15: 329735.19 | C15: 61921.338 | D15: 7341.6404 | E15: 2109.4435 | F15: 110415.24 | G15: 63704.536 | H15: 55971.795 | I15: 118283.4
A16: Feb-19 | B16: 278212.44 | C16: 64086.705 | D16: 5807.7691 | E16: 2275.6015 | F16: 124006.02 | G16: 54331.585 | H16: 57060.406 | I16: 94573.964
A17: $ indicates as on February 28,2019
A18: Source: NSE.

Sheet 50
A1: Table 50: Maturity-wise Turnover in Currency Derivative Segment of MSEI (` crore)
A2: Year/Month | B2: Currency Future | F2: Currency Options
B3: 1 Month | C3: 2 Month | D3: 3 Month | E3: > 3 Months | F3: 1 Month | G3: 2 Month | H3: 3 Month | I3: > 3 Months
A4: 2017-18 | B4: 79306.76 | C4: 18863.523 | D4: 1531.6327 | E4: 20.399033 | F4: 12055.742 | G4: 3071.173 | H4: 582.826 | I4: 300.72625
A5: 2018-19$ | B5: 31247.814 | C5: 4746.686 | D5: 51.311287 | E5: 22.945404 | F5: 5231.6184 | G5: 3060.9514 | H5: 176.3905 | I5: 0
A6: Apr-18 | B6: 4265.5222 | C6: 1049.7477 | D6: 3.5726245 | E6: 0.3939 | F6: 821.24082 | G6: 254.09244 | H6: 176.3905 | I6: 0
A7: May-18 | B7: 5520.1396 | C7: 1023.7223 | D7: 24.312977 | E7: 6.139426 | F7: 102.39644 | G7: 560.28205 | H7: 0 | I7: 0
A8: Jun-18 | B8: 4004.28 | C8: 822.23 | D8: 12.98 | E8: 3.83 | F8: 46.87 | G8: 366.98 | H8: 0 | I8: 0
A9: Jul-18 | B9: 7547.3075 | C9: 358.47645 | D9: 0.02079375 | E9: 0.0277675 | F9: 124.11167 | G9: 364.32937 | H9: 0 | I9: 0
A10: Aug-18 | B10: 2875.24 | C10: 447.76 | D10: 8.57 | E10: 10.56 | F10: 214.28 | G10: 210.37 | H10: 0 | I10: 0
A11: Sep-18 | B11: 3000.8617 | C11: 280.1801 | D11: 0.81045925 | E11: 1.97023 | F11: 394.61845 | G11: 312.9216 | H11: 0 | I11: 0
A12: Oct-18 | B12: 1393.2188 | C12: 220.94704 | D12: 0.30547 | E12: 0.022367 | F12: 921.46059 | G12: 364.43843 | H12: 0 | I12: 0
A13: Nov-18 | B13: 789.65556 | C13: 155.61805 | D13: 0.3555 | E13: 0 | F13: 789.95193 | G13: 315.1941 | H13: 0 | I13: 0
A14: Dec-18 | B14: 535.36405 | C14: 131.5551 | D14: 0.30359 | E14: 0 | F14: 483.14551 | G14: 140.4989 | H14: 0 | I14: 0
A15: Jan-19 | B15: 526.00668 | C15: 152.74104 | D15: 0.06399 | E15: 0 | F15: 706.1849 | G15: 171.84509 | H15: 0 | I15: 0
A16: Feb-19 | B16: 790.22067 | C16: 103.70679 | D16: 0.02156 | E16: 0 | F16: 627.36473 | G16: 0 | H16: 0 | I16: 0
A17: $ indicates as on February 28,2019
A18: Source: MSEI

Sheet 51
A1: Table 51: Trading Statistics of Interest Rate Futures at BSE, NSE and MSEI
A2: Year/ Month | B2: No. of Trading Days | C2: BSE | G2: NSE | K2: MSEI
C3: Interest Rate Futures | E3: Open Interest at the end of | G3: Interest Rate Futures | I3: Open Interest at the end of | K3: Interest RateFutures | M3: Open Interest at the end of
C4: No. of Contracts | D4: Traded Value (` crore) | E4: No. of Contracts | F4: Traded Value (` crore) | G4: No. of Contracts | H4: Traded Value (` crore) | I4: No. of Contracts | J4: Value (` crore) | K4: No. of Contracts | L4: Traded Value (` crore) | M4: No. of Contracts | N4: Value (` crore)
A5: 2017-18 | B5: 242 | C5: 11345215 | D5: 223880.89 | E5: 336 | F5: 6.3927 | G5: 16186719 | H5: 321208.12 | I5: 41032 | J5: 781.14212 | K5: 10648 | L5: 218.54813 | M5: 0 | N5: 0
A6: 2018-19$ | B6: 224 | C6: 5137863 | D6: 96709.032 | E6: 24303 | F6: 471.38095 | G6: 12130665 | H6: 232978.39 | I6: 83872 | J6: 1625.2341 | K6: 0 | L6: 0 | M6: 0 | N6: 0
A7: Apr-18 | B7: 19 | C7: 477406 | D7: 8979.4697 | E7: 460 | F7: 8.572376 | G7: 1435453 | H7: 27039.273 | I7: 63757 | J7: 1189.7054 | K7: 0 | L7: 0 | M7: 0 | N7: 0
A8: May-18 | B8: 22 | C8: 426520 | D8: 7943.6572 | E8: 4400 | F8: 82.04348 | G8: 648029 | H8: 12087.967 | I8: 46859 | J8: 874.84106 | K8: 0 | L8: 0 | M8: 0 | N8: 0
A9: Jun-18 | B9: 21 | C9: 353456 | D9: 6561.954 | E9: 8237 | F9: 151.8998 | G9: 459649 | H9: 8623.8255 | I9: 40027 | J9: 754.71892 | K9: 0 | L9: 0 | M9: 0 | N9: 0
A10: Jul-18 | B10: 22 | C10: 588862 | D10: 11056.946 | E10: 9586 | F10: 182.55718 | G10: 729014 | H10: 13944.554 | I10: 78883 | J10: 1510.6961 | K10: 0 | L10: 0 | M10: 0 | N10: 0
A11: Aug-18 | B11: 20 | C11: 565212 | D11: 10591.939 | E11: 10025 | F11: 184.02538 | G11: 964141 | H11: 18422.714 | I11: 93108 | J11: 1765.1697 | K11: 0 | L11: 0 | M11: 0 | N11: 0
A12: Sep-18 | B12: 18 | C12: 403384 | D12: 7489.95 | E12: 1941 | F12: 36.652912 | G12: 1028618 | H12: 19345.564 | I12: 51510 | J12: 972.14823 | K12: 0 | L12: 0 | M12: 0 | N12: 0
A13: Oct-18 | B13: 21 | C13: 489616 | D13: 9223.2 | E13: 12828 | F13: 245.2162 | G13: 1190063 | H13: 22604.788 | I13: 71700 | J13: 1369.6851 | K13: 0 | L13: 0 | M13: 0 | N13: 0
A14: Nov-18 | B14: 19 | C14: 324647 | D14: 6156.8183 | E14: 8621 | F14: 167.53465 | G14: 1052294 | H14: 20286.93 | I14: 69143 | J14: 1342.2731 | K14: 0 | L14: 0 | M14: 0 | N14: 0
A15: Dec-18 | B15: 20 | C15: 219779 | D15: 4245.4411 | E15: 24576 | F15: 480.146 | G15: 1986662 | H15: 39136.416 | I15: 79625 | J15: 1571.9966 | K15: 0 | L15: 0 | M15: 0 | N15: 0
A16: Jan-19 | B16: 23 | C16: 480065 | D16: 9129.2566 | E16: 15056 | F16: 294.707 | G16: 1438254 | H16: 28146.945 | I16: 68815 | J16: 1347.8794 | K16: 0 | L16: 0 | M16: 0 | N16: 0
A17: Feb-19 | B17: 19 | C17: 808916 | D17: 15330.4 | E17: 24303 | F17: 471.38095 | G17: 1198488 | H17: 23339.418 | I17: 83872 | J17: 1625.2341 | K17: 0 | L17: 0 | M17: 0 | N17: 0
A18: $ indicates as on February 28,2019
A19: Source: BSE, NSE and MSEI

Sheet 52
A1: Table 52: Settlement Statistics in Interest Rate Futures at BSE, NSE and MSEI (` crore)
A2: Year/ Month | B2: BSE | D2: NSE | F2: MSEI
B3: MTM Settlement | C3: Physical Delivery Settlement | D3: MTM Settlement | E3: Physical Delivery Settlement | F3: MTM Settlement | G3: Physical Delivery Settlement
A4: 2017-18 | B4: 377.62849 | C4: 14.766768 | D4: 786.15609 | E4: 26.764484 | F4: 0.0504 | G4: 0
A5: 2018-19$ | B5: 241.69012 | C5: 11.41287 | D5: 585.81723 | E5: 12.944533 | F5: 0.0504 | G5: 0
A6: Apr-18 | B6: 16.23 | C6: 0.24 | D6: 66.713457 | E6: 0.76758968 | F6: 0 | G6: 0
A7: May-18 | B7: 11.584563 | C7: 1.12124 | D7: 50.558771 | E7: 2.2892792 | F7: 0 | G7: 0
A8: Jun-18 | B8: 10.922114 | C8: 0.66827 | D8: 28.173412 | E8: 1.019115 | F8: 0 | G8: 0
A9: Jul-18 | B9: 15.718727 | C9: 0.537477 | D9: 34.566626 | E9: 1.0004758 | F9: 0 | G9: 0
A10: Aug-18 | B10: 14.152948 | C10: 0.104844 | D10: 44.860393 | E10: 0.37230096 | F10: 0 | G10: 0
A11: Sep-18 | B11: 16.805185 | C11: 0.55408 | D11: 54.62772 | E11: 1.662287 | F11: 0 | G11: 0
A12: Oct-18 | B12: 12.571749 | C12: 0.259753 | D12: 57.408569 | E12: 0.6671934 | F12: 0 | G12: 0
A13: Nov-18 | B13: 16.735815 | C13: 1.449173 | D13: 44.911328 | E13: 2.0025684 | F13: 0 | G13: 0
A14: Dec-18 | B14: 29.15771 | C14: 0.513495 | D14: 79.386109 | E14: 0.52690762 | F14: 0 | G14: 0
A15: Jan-19 | B15: 35.987583 | C15: 1.940089 | D15: 62.196082 | E15: 1.2890964 | F15: 0 | G15: 0
A16: Feb-19 | B16: 61.819564 | C16: 4.024923 | D16: 62.414768 | E16: 1.3477194 | F16: 0 | G16: 0
A17: $ indicates as on February 28,2019
A18: Source: NSE, BSE and MSEI

Sheet 53
A1: Table 53: Trends in Foreign Portfolio Investment
A2: Year/Month | B2: Gross Purchase (` crore) | C2: Gross Sales (` crores) | D2: Net Investment (` crores) | E2: Net Investment (US' $ mn.) | F2: Cumulative Net Investment (US $ mn.)
A3: 2017-18 | B3: 1728359.5 | C3: 1583678.8 | D3: 144680.77 | E3: 22465.57 | F3: 253652.92
A4: 2018-2019$ | B4: 1440588.2 | C4: 1528270 | D4: -87681.85 | E4: -12531.52 | F4: 241121.4
A5: Apr-18 | B5: 134718.56 | C5: 150280.04 | D5: -15561.48 | E5: -2352.68 | F5: 251300.24
A6: May-18 | B6: 127492.24 | C6: 157267.82 | D6: -29775.58 | E6: -4409.97 | F6: 246890.27
A7: Jun-18 | B7: 145149.57 | C7: 160944.54 | D7: -15794.97 | E7: -2322.18 | F7: 244568.09
A8: Jul-18 | B8: 128610.93 | C8: 126346.99 | D8: 2263.94 | E8: 329.85 | F8: 244897.94
A9: Aug-18 | B9: 119546.48 | C9: 114400.94 | D9: 5145.54 | E9: 762.47 | F9: 245660.41
A10: Sep-18 | B10: 131050.1 | C10: 152084.64 | D10: -21034.54 | E10: -2906.71 | F10: 242753.7
A11: Oct-18 | B11: 134506.68 | C11: 173412.36 | D11: -38905.68 | E11: -5281.19 | F11: 237472.51
A12: Nov-18 | B12: 128220.7 | C12: 116625.64 | D12: 11595.06 | E12: 1609.5 | F12: 239082.01
A13: Dec-18 | B13: 129514.11 | C13: 121624.92 | D13: 7889.19 | E13: 1129 | F13: 240211.01
A14: Jan-19 | B14: 122075.46 | C14: 127631.68 | D14: -5556.22 | E14: -787 | F14: 239424.01
A15: Feb-19 | B15: 139703.34 | C15: 127650.45 | D15: 12052.89 | E15: 1697.39 | F15: 241121.4
A16: Source: NSDL, CDSL
A17: $ indicates up to February 28,2019

Sheet 54
A1: Table 54: Notional Value of Offshore Derivative Instruments (ODIs) compared to Assets Under Custody (AUC) of FPIs/Deemed FPIs (` crore)
A2: Year/ Month | B2: Notional value of ODIs on Equity, Debt & Derivatives | C2: Notional value of ODIs on Equity & Debt excluding Derivatives | D2: Assets Under Custody of FPIs/Deemed FPIs | E2: Notional value of ODIs on Equity, Debt & Derivatives as % of Assets Under Custody of FPIs/Deemed FPIs | F2: Notional value of ODIs on Equity & Debt excluding Derivatives as % of Assets Under Custody of FPIs/Deemed FPIs
A3: 2017-18 | B3: 106403 | C3: 102726 | D3: 3148349 | E3: 3.4 | F3: 3.3
A4: 2018-19$ | B4: 73428 | C4: 73319 | D4: 30,89,602 | E4: 2.4 | F4: 2.4
A5: Apr-18 | B5: 100245 | C5: 99595 | D5: 3319175 | E5: 3 | F5: 3
A6: May-18 | B6: 93497 | C6: 89974 | D6: 3177685 | E6: 2.9 | F6: 2.8
A7: Jun-18 | B7: 83688 | C7: 80279 | D7: 3188252 | E7: 2.6 | F7: 2.5
A8: Jul-18 | B8: 80341 | C8: 76769 | D8: 3334518 | E8: 2.4 | F8: 2.3
A9: Aug-18 | B9: 84647 | C9: 80882 | D9: 3431511 | E9: 2.5 | F9: 2.4
A10: Sep-18 | B10: 79548 | C10: 75641 | D10: 3138334 | E10: 2.5 | F10: 2.4
A11: Oct-18 | B11: 66587 | C11: 65147 | D11: 2982324 | E11: 2.2 | F11: 2.2
A12: Nov-18 | B12: 79247 | C12: 78015 | D12: 3108886 | E12: 2.5 | F12: 2.5
A13: Dec-18 | B13: 79513 | C13: 78558 | D13: 3138205 | E13: 2.5 | F13: 2.5
A14: Jan-19 | B14: 75693 | C14: 74866 | D14: 3090508 | E14: 2.4 | F14: 2.4
A15: Feb-19 | B15: 73428 | C15: 73319 | D15: 30,89,602 | E15: 2.4 | F15: 2.4
A16: 1. Figures are compiled based on reports submitted by FPIs/deemed FPIs issuing ODIs. 2. Column 4 Figures are compiled on the basis of reports submitted by custodians & does not includes positions taken by FPIs/deemed FPIs in derivatives. 3. The total value of ODIs excludes the unhedged positions & portfolio hedging positions taken by the FPIs/deemed FPIs issuing ODIs.
A17: $ indicates up to February 28,2019
A18: Source: SEBI.

Sheet 55
A1: Table 55: Assets under the Custody of Custodians
A2: Type of Client | B2: FPIs | D2: Foreign Depositories | F2: FDI Investments | H2: Foreign Venture Capital Investments | J2: OCBs | L2: NRIs | N2: Mutual Funds | P2: Corporates | R2: Banks | T2: Insurance Companies | V2: Local Pension Funds | X2: Financial Institutions | Z2: Others | AB2: Total
B3: No. | C3: Amount (` crore) | D3: No. | E3: Amount (`crore) | F3: No. | G3: Amount (`crore) | H3: No. | I3: Amount (`crore) | J3: No. | K3: Amount (`crore) | L3: No. | M3: Amount (`crore) | N3: No. | O3: Amount (`crore) | P3: No. | Q3: Amount (`crore) | R3: No. | S3: Amount (`crore) | T3: No. | U3: Amount (`crore) | V3: No. | W3: Amount (`crore) | X3: No. | Y3: Amount (`crore) | Z3: No. | AA3: Amount (`crore) | AB3: No. | AC3: Amount (`crore)
A4: 2017-18 | B4: 9326 | C4: 3148349.1 | D4: 64 | E4: 295547.79 | F4: 1651 | G4: 733301.51 | H4: 188 | I4: 31419.8 | J4: 23 | K4: 2424.31 | L4: 415 | M4: 3249.11 | N4: 1541 | O4: 1978171.3 | P4: 459 | Q4: 87064.84 | R4: 114 | S4: 352781.54 | T4: 856 | U4: 1578986.8 | V4: 120 | W4: 332925.09 | X4: 27 | Y4: 109009.14 | Z4: 15580 | AA4: 662457.84 | AB4: 30364 | AC4: 9315688.1
A5: 2018-19$ | B5: 9541 | C5: 3089601.8 | D5: 64 | E5: 325403.37 | F5: 1842 | G5: 784803.12 | H5: 198 | I5: 37062.57 | J5: 24 | K5: 1210.93 | L5: 536 | M5: 3204.01 | N5: 1760 | O5: 2183721.6 | P5: 494 | Q5: 87835.79 | R5: 117 | S5: 336197.18 | T5: 772 | U5: 1649797.3 | V5: 120 | W5: 414257.96 | X5: 25 | Y5: 57995.94 | Z5: 18962 | AA5: 755417.1 | AB5: 34455 | AC5: 9726508.7
A6: Apr-18 | B6: 9349 | C6: 3319175.1 | D6: 64 | E6: 308800.9 | F6: 1669 | G6: 775454.44 | H6: 191 | I6: 31842.35 | J6: 23 | K6: 2618.65 | L6: 427 | M6: 3438.26 | N6: 1515 | O6: 2146009.7 | P6: 456 | Q6: 91500.63 | R6: 115 | S6: 380738.39 | T6: 857 | U6: 1642074 | V6: 120 | W6: 339999.29 | X6: 27 | Y6: 118420.16 | Z6: 15883 | AA6: 689143.47 | AB6: 30696 | AC6: 9849215.3
A7: May-18 | B7: 9333 | C7: 3177684.6 | D7: 64 | E7: 312863.48 | F7: 1672 | G7: 770218.53 | H7: 191 | I7: 138558.64 | J7: 23 | K7: 2668.31 | L7: 440 | M7: 3333.06 | N7: 1580 | O7: 2111430.8 | P7: 464 | Q7: 88886.44 | R7: 115 | S7: 381097.86 | T7: 857 | U7: 1609844.2 | V7: 120 | W7: 344887.12 | X7: 27 | Y7: 115740.77 | Z7: 16190 | AA7: 693734.91 | AB7: 31076 | AC7: 9750948.7
A8: Jun-18 | B8: 9347 | C8: 3188252.1 | D8: 64 | E8: 309592.13 | F8: 1690 | G8: 766045.58 | H8: 191 | I8: 30493.257 | J8: 23 | K8: 2634.02 | L8: 448 | M8: 3260.74 | N8: 1633 | O8: 2072703.9 | P8: 468 | Q8: 88657.06 | R8: 116 | S8: 349157.24 | T8: 859 | U8: 1610771 | V8: 120 | W8: 352534.73 | X8: 27 | Y8: 107443.48 | Z8: 16566 | AA8: 692213.93 | AB8: 31552 | AC8: 9573759.2
A9: Jul-18 | B9: 9356 | C9: 3334518.6 | D9: 64 | E9: 322500.25 | F9: 1689 | G9: 808673.55 | H9: 191 | I9: 30528.38 | J9: 23 | K9: 2312.91 | L9: 459 | M9: 3400.27 | N9: 1647 | O9: 2207951 | P9: 465 | Q9: 90761.83 | R9: 116 | S9: 365212.58 | T9: 863 | U9: 1673735.4 | V9: 120 | W9: 358241.89 | X9: 25 | Y9: 64494.08 | Z9: 16692 | AA9: 701946.6 | AB9: 31710 | AC9: 9964277.2
A10: Aug-18 | B10: 9375 | C10: 3431511.1 | D10: 64 | E10: 339837.62 | F10: 1699 | G10: 848766.12 | H10: 193 | I10: 31153.82 | J10: 23 | K10: 2056.85 | L10: 478 | M10: 3527.42 | N10: 1671 | O10: 2239800.2 | P10: 470 | Q10: 91898.59 | R10: 118 | S10: 369399.71 | T10: 865 | U10: 1723166 | V10: 120 | W10: 366199.32 | X10: 25 | Y10: 70176.24 | Z10: 17264 | AA10: 719663.44 | AB10: 32365 | AC10: 10237156
A11: Sep-18 | B11: 9382 | C11: 3138333.9 | D11: 64 | E11: 324869.57 | F11: 1714 | G11: 753575.56 | H11: 193 | I11: 31290.02 | J11: 23 | K11: 1825.5 | L11: 485 | M11: 3205.65 | N11: 1671 | O11: 2049229.9 | P11: 477 | Q11: 91616.4 | R11: 118 | S11: 343971.63 | T11: 871 | U11: 1640476.6 | V11: 120 | W11: 371562.34 | X11: 25 | Y11: 65535.15 | Z11: 17441 | AA11: 690463.23 | AB11: 32584 | AC11: 9505955.4
A12: OCT-18 | B12: 9408 | C12: 2982324.3 | D12: 64 | E12: 313508.23 | F12: 1722 | G12: 755553.45 | H12: 193 | I12: 33329.9 | J12: 23 | K12: 1797.3 | L12: 517 | M12: 3110.65 | N12: 1677 | O12: 2074606.4 | P12: 479 | Q12: 90299.78 | R12: 119 | S12: 355589.63 | T12: 823 | U12: 1605831.4 | V12: 120 | W12: 378002.27 | X12: 25 | Y12: 63074.5 | Z12: 17840 | AA12: 697079.79 | AB12: 33010 | AC12: 9354107.6
A13: Nov-18 | B13: 9444 | C13: 3108885.6 | D13: 64 | E13: 326243.47 | F13: 1751 | G13: 803953.65 | H13: 197 | I13: 33693.29 | J13: 24 | K13: 1956.11 | L13: 517 | M13: 3256.67 | N13: 1682 | O13: 2129233.7 | P13: 477 | Q13: 90699.5 | R13: 119 | S13: 338536.09 | T13: 811 | U13: 1637650.1 | V13: 120 | W13: 385062.23 | X13: 25 | Y13: 65218.85 | Z13: 18035 | AA13: 716618.69 | AB13: 33266 | AC13: 9641007.9
A14: DEC-18 | B14: 9492 | C14: 3138204.9 | D14: 64 | E14: 325175.14 | F14: 1788 | G14: 818430.91 | H14: 196 | I14: 36815.05 | J14: 24 | K14: 1960.49 | L14: 518 | M14: 3353.92 | N14: 1713 | O14: 2144981.4 | P14: 479 | Q14: 91237.86 | R14: 118 | S14: 336972.02 | T14: 771 | U14: 1655213.9 | V14: 120 | W14: 394058.22 | X14: 25 | Y14: 65266.18 | Z14: 18368 | AA14: 738926.4 | AB14: 33676 | AC14: 9750596.4
A15: JAN-19 | B15: 9546 | C15: 3090507.6 | D15: 64 | E15: 329951.22 | F15: 1816 | G15: 783831.11 | H15: 197 | I15: 36740.34 | J15: 24 | K15: 1792.18 | L15: 530 | M15: 3137.45 | N15: 1736 | O15: 2193231.6 | P15: 486 | Q15: 90119.86 | R15: 117 | S15: 343035.26 | T15: 773 | U15: 1651975.3 | V15: 120 | W15: 406735.15 | X15: 25 | Y15: 68114.9 | Z15: 18745 | AA15: 749913.72 | AB15: 34179 | AC15: 9749085.7
A16: FEB-19 | B16: 9541 | C16: 3089601.8 | D16: 64 | E16: 325403.37 | F16: 1842 | G16: 784803.12 | H16: 198 | I16: 37062.57 | J16: 24 | K16: 1210.93 | L16: 536 | M16: 3204.01 | N16: 1760 | O16: 2183721.6 | P16: 494 | Q16: 87835.79 | R16: 117 | S16: 336197.18 | T16: 772 | U16: 1649797.3 | V16: 120 | W16: 414257.96 | X16: 25 | Y16: 57995.94 | Z16: 18962 | AA16: 755417.1 | AB16: 34455 | AC16: 9726508.7
A17: 1. With the commencement of FPI Regime from June 1, 2014, the erstwhile FIIs, Sub Accounts and QFIs are merged into a new investor class termed as .Foreign Portfolio Investors (FPIs)..
A18: 2. "Others" include Portfolio manager, partnership firm, trusts, depository receipts, AIFs, FCCB, HUFs, Brokers etc.
A19: $ indicates as on February 28,2019
A20: Source: Custodians.

Sheet 56
A1: Table 56: Trends in Resource Mobilization by Mutual Funds (` crore)
A2: Year / Month | B2: Gross Mobilisation | E2: Redemption | H2: Net Inflow/ Outflow | K2: Assets at the End of Period
B3: Pvt. Sector | C3: Public Sector | D3: Total | E3: Pvt. Sector | F3: Public Sector | G3: Total | H3: Pvt. Sector | I3: Public Sector | J3: Total
A4: 2017-18 | B4: 17382189 | C4: 3616463 | D4: 20998652 | E4: 17153718 | F4: 3573137.2 | G4: 20726855 | H4: 228470.8 | I4: 43325.8 | J4: 271796.6 | K4: 2136035.8
A5: 2018-19$ | B5: 17949304 | C5: 4168385.8 | D5: 22117689 | E5: 17889737 | F5: 4265384.3 | G5: 22155122 | H5: 59566.34 | I5: 72491.872 | J5: 132058.21 | K5: 2316403.5
A6: Apr-18 | B6: 1416279.8 | C6: 302048.59 | D6: 1718328.4 | E6: 1312070.3 | F6: 268829.37 | G6: 1580899.7 | H6: 104209.42 | I6: 33219.223 | J6: 137428.64 | K6: 2325505.2
A7: May-18 | B7: 1580004.1 | C7: 358422.45 | D7: 1938426.5 | E7: 1626220.7 | F7: 362206.83 | G7: 1988427.5 | H7: -46216.614 | I7: -3784.3742 | J7: -50000.988 | K7: 2259578.3
A8: Jun-18 | B8: 1687434.8 | C8: 381015.27 | D8: 2068450.1 | E8: 1651020.5 | F8: 370954.26 | G8: 2021974.8 | H8: 36414.259 | I8: 10061.008 | J8: 46475.267 | K8: 2286400.5
A9: Jul-18 | B9: 1799448.5 | C9: 401957.65 | D9: 2201406.2 | E9: 1835653.3 | F9: 398380.98 | G9: 2234034.2 | H9: -36204.718 | I9: 3576.6722 | J9: -32628.046 | K9: 2305538.2
A10: Aug-18 | B10: 1622019.8 | C10: 357759.55 | D10: 1979779.3 | E10: 1481851.3 | F10: 323279.1 | G10: 1805130.4 | H10: 140168.51 | I10: 34480.448 | J10: 174648.95 | K10: 2520429.8
A11: Sep-18 | B11: 1361955.5 | C11: 331024.75 | D11: 1692980.2 | E11: 1560352.4 | F11: 362787.03 | G11: 1923139.4 | H11: -198396.9 | I11: -31762.275 | J11: -230159.17 | K11: 2204422.7
A12: Oct-18 | B12: 1757449.3 | C12: 575530.09 | D12: 2332979.4 | E12: 1738122.8 | F12: 559326.71 | G12: 2297449.5 | H12: 19326.502 | I12: 16203.37 | J12: 35529.873 | K12: 2223559.9
A13: Nov-18 | B13: 1588398.3 | C13: 351181.9 | D13: 1939580.2 | E13: 1462592.8 | F13: 334628.94 | G13: 1797221.7 | H13: 125805.55 | I13: 16552.951 | J13: 142358.51 | K13: 2403134.4
A14: Dec-18 | B14: 1656191.1 | C14: 385549.94 | D14: 2041741 | E14: 1764970.2 | F14: 413721.33 | G14: 2178691.6 | H14: -108779.17 | I14: -28171.394 | J14: -136950.56 | K14: 2285911.7
A15: Jan-19 | B15: 1942529.6 | C15: 480153.78 | D15: 2422683.4 | E15: 1899862.5 | F15: 457382.28 | G15: 2357244.8 | H15: 42667.149 | I15: 22771.493 | J15: 65438.642 | K15: 2337118
A16: Feb-19 | B16: 1537592.9 | C16: 243741.81 | D16: 1781334.7 | E16: 1557020.5 | F16: 413887.45 | G16: 1970908 | H16: -19427.652 | I16: -655.25004 | J16: -20082.902 | K16: 2316403.5
A17: $ indicates as on February 28,2019
A18: Source: SEBI.
H20: =B15-E15 -> 42667.149 | I20: =C15-F15 -> 22771.493 | J20: =D15-G15 -> 65438.642
H21: =B16-E16 -> -19427.652 | I21: =C16-F16 -> -170145.64 | J21: =D16-G16 -> -189573.29
A24: Jan-19 | B24: 1942529.6 | C24: 480153.78 | D24: 2422683.4 | E24: 1899862.5 | F24: 457382.28 | G24: 2357244.8 | H24: 42667.149 | I24: 22771.493 | J24: 65438.642 | K24: 2337118
A25: Feb-19 | B25: 1537592.9 | C25: 243741.81 | D25: 1781334.7 | E25: 1557020.5 | F25: 413887.45 | G25: 1970908 | H25: -19427.652 | I25: -655.25004 | J25: -20082.902 | K25: 2316403.5
A27: April 1, 2018 to February 28, 2019 | B27: 17949304 | C27: 1642501.1 | D27: 2525884.7 | E27: 22117689 | F27: 17889737 | G27: 1803410.7 | H27: 2461973.6 | I27: 22155122 | J27: 59566.34 | K27: 8580.825 | L27: 63911.048 | M27: 132058.21 | N27: 1853375 | O27: 148119.7 | P27: 314908.75 | Q27: 2316403.5
A28: 1April - 31 Jan 2019 | B28: 16411711 | C28: 1642501.1 | D28: 2282142.9 | E28: 20336355 | F28: 16332717 | G28: 1630328.9 | H28: 2221167.9 | I28: 20184214 | J28: 78993.992 | K28: 12172.181 | L28: 60974.942 | M28: 152141.11 | N28: 1873337.2 | O28: 151674.84 | P28: 312105.89 | Q28: 2337118
B30: =B27-B28 -> 1537592.9 | C30: =C27-C28 -> 0 | D30: =D27-D28 -> 243741.81 | E30: =E27-E28 -> 1781334.7 | F30: =F27-F28 -> 1557020.5 | G30: =G27-G28 -> 173081.74 | H30: =H27-H28 -> 240805.7 | I30: =I27-I28 -> 1970908 | ... Q30: =Q27-Q28 -> -20714.491

Sheet 57
A1: Table 57: Type-wise Resource Mobilisation by Mutual Funds: Open-ended and Close-ended (` crore)
A2: Scheme | B2: 2017-18 | E2: 2018-19$ | H2: Feb-19 | K2: Assets at the end of period
B3: Sale | C3: Purchase | D3: Net | E3: Sale | F3: Purchase | G3: Net | H3: Sale | I3: Purchase | J3: Net
A4: Open-ended | B4: 20652260 | C4: 20922379 | D4: 270118.29 | E4: 22085317 | F4: 22212829 | G4: 127511.59 | H4: 1968684.7 | I4: 4368126 | J4: -20319.171 | K4: 2113266.1
A5: Close-ended | B5: 71872.777 | C5: 73963.334 | D5: 2090.5575 | E5: 63560.495 | F5: 70358.195 | G5: 6797.6999 | H5: 1177.6498 | I5: 2353.1092 | J5: 1175.4594 | K5: 200701.7
A6: Interval | B6: 2722.1551 | C6: 2309.9037 | D6: -412.25135 | E6: 6243.6171 | F6: 3992.5423 | G6: -2251.0748 | H6: 1045.643 | I6: 106.4531 | J6: -939.18986 | K6: 2435.7189
A7: Total | B7: 20726855 | C7: 20998652 | D7: 271796.6 | E7: 22155122 | F7: 22287180 | G7: 132058.21 | H7: 1970908 | I7: 4370585.6 | J7: -20082.902 | K7: 2316403.5
A8: $ indicates as on February 28,2019
A9: Source: SEBI.
G13: Scheme | H13: February 2019* | K13: Net Assets as on February 28, 2019*
H14: Sale | I14: Purchase | J14: Net
B16: =H16-H29 -> 1968684.7 | C16: =I16-I29 -> 4368126 | D16: =J16-J29 -> -20319.171 | E16: =K16 -> 2113266.1 | G16: Open Ended | H16: 22085317 | I16: 22212829 | J16: 127511.59 | K16: 2113266.1
B17: =H17-H30 -> 1177.6498 | C17: =I17-I30 -> 2353.1092 | D17: =J17-J30 -> 1175.4594 | E17: =K17 -> 200701.7 | G17: Close Ended | H17: 63560.495 | I17: 70358.195 | J17: 6797.6999 | K17: 200701.7
B18: =H18-H31 -> 1045.643 | C18: =I18-I31 -> 106.4531 | D18: =J18-J31 -> -939.18986 | E18: =K18 -> 2435.7189 | G18: Interval | H18: 6243.6171 | I18: 3992.5423 | J18: -2251.0748 | K18: 2435.7189
B19: =H19-H32 -> 1970908 | C19: =I19-I32 -> 4370585.6 | D19: =J19-J32 -> -20082.902 | E19: =K19 -> 2316403.5 | G19: Total | H19: 22155122 | I19: 22287180 | J19: 132058.21 | K19: 2316403.5
G21: * Notes :
D26: February 2019* | E26: January 2019* | G26: Scheme | H26: January 2019* | K26: Net Assets as on Jan 31, 2019*
D27: =I16-H16 -> 127511.59 | E27: =I29-H29 -> -2271929.8 | H27: Sale | I27: Purchase | J27: Net
D28: =I17-H17 -> 6797.6999 | E28: =I30-H30 -> 5622.2406
D29: =I18-H18 -> -2251.0748 | E29: =I31-H31 -> -1311.8849 | G29: Open Ended | H29: 20116633 | I29: 17844703 | J29: 147830.76 | K29: 2134855.8
D30: =I19-H19 -> 132058.21 | E30: =I32-H32 -> -2267619.4 | G30: Close Ended | H30: 62382.846 | I30: 68005.086 | J30: 5622.2406 | K30: 198887.61
G31: Interval | H31: 5197.9742 | I31: 3886.0892 | J31: -1311.8849 | K31: 3374.5395
G32: Total | H32: 20184214 | I32: 17916594 | J32: 152141.11 | K32: 2337118
G34: * Notes :

Sheet 58
A1: Table 58: Scheme-wise Resource Mobilisation and Assets under Management by Mutual Funds (`crore)
A2: Type | B2: 2017-2018 | F2: 2018-19$ | J2: FEB-19
B3: Sale | C3: Purchase | D3: Net | E3: Assests at the end | F3: Sale | G3: Purchase | H3: Net | I3: Assests at the end | J3: Sale | K3: Purchase | L3: Net
A4: A. Income/Debt Oriented Schemes(i+ii+iii+iv+v) | B4: 20432029 | C4: 20420305 | D4: -11724.547 | E4: 1134949.7 | F4: 21892952 | G4: 21882082 | H4: -10870.09 | I4: 1194439 | J4: 1940348.2 | K4: 1911476.9 | L4: -28871.307
A5: i. Liquid/Money Market | B5: 19505850 | C5: 19502914 | D5: -2936.2578 | E5: 335524.82 | F5: 21267312 | G5: 21394748 | H5: 127436.03 | I5: 487980.19 | J5: 1900741 | K5: 1876231.3 | L5: -24509.697
A6: ii. Gilt | B6: 11254.743 | C6: 7977.3016 | D6: -3277.4417 | E6: 11404.162 | F6: 5241.5919 | G6: 1763.1539 | H6: -3478.438 | I6: 7934.5079 | J6: 263.24469 | K6: 115.71419 | L6: -147.53051
A7: iii. Debt (other than assured return) | B7: 914924.13 | C7: 909073.28 | D7: -5850.8476 | E7: 785552.94 | F7: 620398.71 | G7: 485418.03 | H7: -134980.68 | I7: 695779.97 | J7: 39343.963 | K7: 35129.885 | L7: -4214.0788
A8: iv. Debt (assured return) | B8: 0 | C8: 0 | D8: 0 | E8: 0 | F8: 0 | G8: 0 | H8: 0 | I8: 0 | J8: 0 | K8: 0 | L8: 0
A9: v. Infrastructure Development | B9: 0 | C9: 340 | D9: 340 | E9: 2467.7894 | F9: 0 | G9: 153 | H9: 153 | I9: 2744.303 | J9: 0 | K9: 0 | L9: 0
A10: B. Growth/Equity Oriented Schemes (i+ii) | B10: 229382.46 | C10: 400451.36 | D10: 171068.9 | E10: 749789.73 | F10: 172125.59 | G10: 272337.38 | H10: 100211.78 | I10: 829182.02 | J10: 14513.055 | K10: 19151.967 | L10: 4638.9122
A11: i. ELSS | B11: 7976.0731 | C11: 22291.474 | D11: 14315.401 | E11: 80582.994 | F11: 6722.9589 | G11: 16752.101 | H11: 10029.142 | I11: 87219.523 | J11: 563.93832 | K11: 1738.2516 | L11: 1174.3132
A12: ii. Others | B12: 221406.39 | C12: 378159.89 | D12: 156753.5 | E12: 669206.74 | F12: 165402.64 | G12: 255585.28 | H12: 90182.641 | I12: 741962.5 | J12: 13949.117 | K12: 17413.715 | L12: 3464.599
A13: C. Balanced Schemes | B13: 29568.58 | C13: 119325.96 | D13: 89757.38 | E13: 172151.25 | F13: 38649.081 | G13: 48694.897 | H13: 10045.816 | I13: 175608.01 | J13: 3664.2249 | K13: 2587.0192 | L13: -1077.2058
A14: D. Exchange Traded Fund (i+ii) | B14: 35248.693 | C14: 58371.767 | D14: 23123.074 | E14: 77694.062 | F14: 51073.022 | G14: 83510.109 | H14: 32437.087 | I14: 118117.01 | J14: 12355.407 | K14: 17576.806 | L14: 5221.3996
A15: i. Gold ETFs | B15: 865.88554 | C15: 31.458122 | D15: -834.42742 | E15: 4806.0582 | F15: 492.72528 | G15: 118.7197 | H15: -374.00557 | I15: 4736.5081 | J15: 32.690814 | K15: 19.263699 | L15: -13.427115
... A18: Total (A+B+C+D+E) | B18: 20726855 | C18: 20998652 | D18: 271796.6 | E18: 2136035.8 | F18: 22155122 | G18: 22287180 | H18: 132058.21 | I18: 2316403.5 | J18: 1970908 | K18: 1950825.1 | L18: -20082.902
A19: $ indicates as on February 28,2019
A20: Source: SEBI.

Sheet 59
A1: Table 59: Number of Schemes and Folios by Investment Objective
A2: Type | B2: 2017-18 | J2: 2018-19$
B3: No. of Schemes | F3: No. of Folios | J3: No. of Schemes | N3: No. of Folios
B4: Open | C4: Closed | D4: Interval | E4: Total | F4: Open | G4: Closed | H4: Interval | I4: Total | J4: Open | K4: Closed | L4: Interval | M4: Total | N4: Open | O4: Closed | P4: Interval | Q4: Total
A5: A. Income/Debt Oriented Schemes(i+ii+iii+iv+v) | B5: 343 | C5: 983 | D5: 31 | E5: 1357 | F5: 9504514 | G5: 1237976 | H5: 5592 | I5: 10748082 | J5: 332 | K5: 956 | L5: 27 | M5: 1315 | N5: 10342035 | O5: 1246251 | P5: 4708 | Q5: 11592994
A6: i. Liquid/Money Market | B6: 52 | C6: 0 | D6: 0 | E6: 52 | F6: 1095226 | G6: 0 | H6: 0 | I6: 1095226 | J6: 61 | K6: 0 | L6: 0 | M6: 61 | N6: 1649410 | O6: 0 | P6: 0 | Q6: 1649410
A7: ii. Gilt | B7: 38 | C7: 0 | D7: 0 | E7: 38 | F7: 75553 | G7: 0 | H7: 0 | I7: 75553 | J7: 27 | K7: 0 | L7: 0 | M7: 27 | N7: 70742 | O7: 0 | P7: 0 | Q7: 70742
A8: iii. Debt (other than assured return) | B8: 253 | C8: 974 | D8: 31 | E8: 1258 | F8: 8333735 | G8: 1237891 | H8: 5592 | I8: 9577218 | J8: 244 | K8: 946 | L8: 27 | M8: 1217 | N8: 8621883 | O8: 1246154 | P8: 4708 | Q8: 9872745
A9: iv. Debt (assured return) | B9: 0 | C9: 0 | D9: 0 | E9: 0 | F9: 0 | G9: 0 | H9: 0 | I9: 0 | J9: 0 | K9: 0 | L9: 0 | M9: 0 | N9: 0 | O9: 0 | P9: 0 | Q9: 0
A10: v. Infrastructure Development | B10: 0 | C10: 9 | D10: 0 | E10: 9 | F10: 0 | G10: 85 | H10: 0 | I10: 85 | J10: 0 | K10: 10 | L10: 0 | M10: 10 | N10: 0 | O10: 97 | P10: 0 | Q10: 97
A11: B. Growth/Equity Oriented Schemes (i+ii) | B11: 370 | C11: 144 | D11: 0 | E11: 514 | F11: 51633997 | G11: 1900988 | H11: 0 | I11: 53534985 | J11: 415 | K11: 135 | L11: 1 | M11: 551 | N11: 60499599 | O11: 1814186 | P11: 12017 | Q11: 62325802
A12: i. ELSS | B12: 44 | C12: 28 | D12: 0 | E12: 72 | F12: 9781472 | G12: 633215 | H12: 0 | I12: 10414687 | J12: 43 | K12: 28 | L12: 0 | M12: 71 | N12: 11106665 | O12: 513793 | P12: 0 | Q12: 11620458
A13: ii. Others | B13: 326 | C13: 116 | D13: 0 | E13: 442 | F13: 41852525 | G13: 1267773 | H13: 0 | I13: 43120298 | J13: 372 | K13: 107 | L13: 1 | M13: 480 | N13: 49392934 | O13: 1300393 | P13: 12017 | Q13: 50705344
A14: C. Balanced Schemes | B14: 31 | C14: 0 | D14: 0 | E14: 31 | F14: 5889085 | G14: 0 | H14: 0 | I14: 5889085 | J14: 28 | K14: 0 | L14: 0 | M14: 28 | N14: 6416340 | O14: 0 | P14: 0 | Q14: 6416340
A15: D. Exchange Traded Fund (i+ii) | J15: 77 | K15: 0 | L15: 0 | M15: 77 | N15: 1332952 | O15: 0 | P15: 0 | Q15: 1332952
A16: D. Exchange Traded Funds (i+ii) | B16: 68 | C16: 0 | D16: 0 | E16: 68 | F16: 1081290 | G16: 0 | H16: 0 | I16: 1081290
A17: i. Gold ETFs | B17: 12 | C17: 0 | D17: 0 | E17: 12 | F17: 329343 | G17: 0 | H17: 0 | I17: 329343 | J17: 12 | K17: 0 | L17: 0 | M17: 12 | N17: 318808 | O17: 0 | P17: 0 | Q17: 318808
A18: ii. Other ETFs | B18: 56 | C18: 0 | D18: 0 | E18: 56 | F18: 751947 | G18: 0 | H18: 0 | I18: 751947 | J18: 65 | K18: 0 | L18: 0 | M18: 65 | N18: 1014144 | O18: 0 | P18: 0 | Q18: 1014144
A19: E. Fund of Funds Investing Overseas | B19: 28 | C19: 0 | D19: 0 | E19: 28 | F19: 93859 | G19: 0 | H19: 0 | I19: 93859 | J19: 29 | K19: 0 | L19: 0 | M19: 29 | N19: 124676 | O19: 0 | P19: 0 | Q19: 124676
A20: Total (A+B+C+D+E) | B20: 840 | C20: 1127 | D20: 31 | E20: 1998 | F20: 68202745 | G20: 3138964 | H20: 5592 | I20: 71347301 | J20: 881 | K20: 1091 | L20: 28 | M20: 2000 | N20: 78715602 | O20: 3060437 | P20: 16725 | Q20: 81792764
A21: Data for No. of Schemes also includes serial plans.
A22: $ indicates as on February 28,2019
A23: Source: SEBI.

Sheet 60
A1: Table 60: Trends in Transactions on Stock Exchanges by Mutual Funds (`crore)
A2: Year/ Month | B2: Equity | E2: Debt | H2: Total
B3: Gross Purchases | C3: Gross Sales | D3: Net Purchases /Sales | E3: Gross Purchases | F3: Gross Sales | G3: Net Purchases /Sales | H3: Gross Purchases | I3: Gross Sales | J3: Net purchases /Sale
A4: 2017-18 | B4: 667008.82 | C4: 525239.54 | D4: 141769.28 | E4: 1825231 | F4: 1454515 | G4: 370715.95 | H4: 2492239.8 | I4: 1979754.5 | J4: 512485.23
A5: 2018-19$ | B5: =SUM(B6:B16) -> 652126.65 | C5: =SUM(C6:C16) -> 556582.96 | D5: =SUM(D6:D16) -> 95543.69 | E5: =SUM(E6:E16) -> 1956065.6 | F5: =SUM(F6:F16) -> 1641181.6 | G5: =SUM(G6:G16) -> 343055.16 | H5: =SUM(H6:H16) -> 2608192.3 | I5: =SUM(I6:I16) -> 2197764.5 | J5: =SUM(J6:J16) -> 438598.85
A6: Apr-18 | B6: 57598.19 | C6: 46304.73 | D6: 11293.46 | E6: 171450.16 | F6: 151285.34 | G6: 20164.82 | H6: 229048.35 | I6: 197590.07 | J6: 31458.28
A7: May-18 | B7: 68739.62 | C7: 55120.8 | D7: 13618.82 | E7: 174469.22 | F7: 188554.77 | G7: 14085.55 | H7: 243208.84 | I7: 243675.57 | J7: 27704.37
A8: Jun-18 | B8: 57543.15 | C8: 48100.59 | D8: 9442.56 | E8: 185365.02 | F8: 144950.09 | G8: 40414.93 | H8: 242908.17 | I8: 193050.68 | J8: 49857.49
A9: Jul-18 | B9: 59897.02 | C9: 55977.87 | D9: 3919.15 | E9: 142717.37 | F9: 146352.58 | G9: -3635.21 | H9: 202614.39 | I9: 202330.45 | J9: 283.94
A10: Aug-18 | B10: 57455.32 | C10: 53360.79 | D10: 4094.53 | E10: 161151.51 | F10: 125407.15 | G10: 35744.36 | H10: 218606.83 | I10: 178767.94 | J10: 39838.89
A11: Sep-18 | B11: 61772.13 | C11: 50133.95 | D11: 11638.18 | E11: 170019.25 | F11: 151332.77 | G11: 18686.48 | H11: 231791.38 | I11: 201466.72 | J11: 30324.66
A12: Oct-18 | B12: 78340.33 | C12: 54293.01 | D12: 24047.32 | E12: 144356.66 | F12: 116992.15 | G12: 27364.51 | H12: 222696.99 | I12: 171285.16 | J12: 51411.83
A13: Nov-18 | B13: 53828.26 | C13: 48591.78 | D13: 5236.48 | E13: 180633.86 | F13: 129241.29 | G13: 51392.57 | H13: 234462.12 | I13: 177833.07 | J13: 56629.05
A14: Dec-18 | B14: 48199.59 | C14: 45280.62 | D14: 2918.97 | E14: 241205.45 | F14: 175970.45 | G14: 65235 | H14: 289405.04 | I14: 221251.07 | J14: 68153.97
A15: Jan-19 | B15: 57222.37 | C15: 50061.76 | D15: 7160.61 | E15: 220033 | F15: 172881.06 | G15: 47151.94 | H15: 277255.37 | I15: 222942.82 | J15: 54312.55
A16: Feb-19 | B16: 51530.67 | C16: 49357.06 | D16: 2173.61 | E16: 164664.14 | F16: 138213.93 | G16: 26450.21 | H16: 216194.81 | I16: 187570.99 | J16: 28623.82
A17: $ indicates up to February 28,2019
A18: Source: SEBI

Sheet 61
A1: Table 61: Assets Under Management by Portfolio Managers
A2: Year / Month | B2: 2017-18 | C2: 2017-18 | D2: 2017-18 | E2: 2018-19$ | F2: 2018-19$ | G2: 2018-19$
A3: Particulars | B3: Discretionary | C3: Non-Discretionary | D3: Advisory | E3: Discretionary | F3: Non-Discretionary | G3: Advisory
A4: No. of Clients | B4: 113776 | C4: 5427 | D4: 2158 | E4: 136586 | F4: 6729 | G4: 3998
A5: AUM (` crore)
A6: Listed Equity | B6: 102587.34 | C6: 15278.95 | D6: 225131.32 | E6: 100608.91 | F6: 17743.99 | G6: 171266.86
A7: Unlisted Equity | B7: 479.87 | C7: 127.54 | D7: 0 | E7: 575.2 | F7: 77.84
A8: Plain Debt | B8: 1018735.8 | C8: 63135.72 | D8: 0 | E8: 1144568 | F8: 74074.77
A9: Structured Debt | B9: 386.37 | C9: 440.42 | D9: 0 | E9: 645.82 | F9: 460.07
A10: Equity Derivatives | B10: 825.32 | C10: -3.14 | D10: 0 | E10: 483.68 | F10: -2.15
A11: Mutual Funds | B11: 11643.02 | C11: 9844.29 | D11: 0 | E11: 13776.08 | F11: 13611.91
A12: Others | B12: 17465.29 | C12: 973.07 | D12: 0 | E12: 15572.11 | F12: 1257.57
A13: Total | B13: 1152123 | C13: 89796.85 | D13: 225131.32 | E13: 1276229.8 | F13: 107224
A14: 1. *Value of Assets for which Advisory Services are being given.2.�#Of the above AUM�Rs. 1115282.78 Crore�is contributed by funds from EPFO/PFs.3. The above data is based on the monthly reports received from portfolio managers.
A15: $ indicates as on February 28,2019
A16: Source: SEBI.

Sheet 62
A1: Table 62: Progress Report of NSDL & CDSL as on end of Feb-19 (Listed Companies)
A2: Parameter | B2: Unit | C2: NSDL | H2: CDSL
C3: Feb-19 | D3: Jan-19 | E3: Feb-18 | F3: % Change during the year | G3: % Change during the month | H3: Feb-19 | I3: Jan-19 | J3: Feb-18 | K3: % Change during the year | L3: % Change during the month
A4: Number of companies signed up to make their shares available for dematerialization | B4: Number | C4: 6136 | D4: 6126 | E4: 5889 | F4: 4.1942605 | G4: 0.16323866 | H4: 6886 | I4: 6876 | J4: 6682 | K4: 3.05 | L4: 0.15 | N4: Number of companies signed up to make their shares available for dematerialization
A5: Number of Depository Participants (registered) | B5: Number | C5: 277 | D5: 276 | E5: 276 | F5: 0.36231884 | G5: 0.36231884 | H5: 595 | I5: 592 | J5: 592 | K5: 0.51 | L5: 0.51 | N5: Number of Depository Participants (registered)
A6: Number of Stock Exchanges (connected) | B6: Number | C6: 3 | D6: 3 | E6: 3 | F6: 0 | G6: 0 | H6: 3 | I6: 3 | J6: 3 | K6: 0 | L6: 0 | N6: Number of Stock Exchanges (connected)
A7: Number of Investors Accounts | B7: Lakh | C7: 184.08648 | D7: 182.77974 | E7: 169.93616 | F7: 8.3268446 | G7: 0.71492606 | H7: 169.71 | I7: 167.25 | J7: 144.16 | K7: 17.72 | L7: 1.47 | N7: Number of Investors Accounts
A8: Quantity of Shares dematerialized | B8: Crore | C8: 52810.217 | D8: 52576.752 | E8: 48368.554 | F8: 9.1829564 | G8: 0.44404609 | H8: 17690.39 | I8: 17633.87 | J8: 14388.71 | K8: 22.95 | L8: 0.32 | N8: Quantity of Shares dematerialized
A9: Value of Shares dematerialized | B9: Crore | C9: 12236295 | D9: 12268632 | E9: 12695644 | F9: -3.6181612 | G9: -0.26357436 | H9: 1639025.8 | I9: 1721837.7 | J9: 1922156.3 | K9: -14.72 | L9: -4.81 | N9: Value of Shares dematerialized
A10: Quantity of Securities dematerialized # | B10: Crore | C10: 56762.077 | D10: 56315.719 | E10: 51618.016 | F10: 9.9656317 | G10: 0.79259945 | H10: 19243.59 | I10: 19394.01 | J10: 15453.57 | K10: 24.53 | L10: -0.78 | N10: Quantity of Securities dematerialized #
A11: Value of Securities dematerialized # | B11: Crore | C11: 14942504 | D11: 14953464 | E11: 15214039 | F11: -1.7847653 | G11: -0.073293911 | H11: 1753530.6 | I11: 1840459.1 | J11: 2014431.4 | K11: -12.95 | L11: -4.72 | N11: Value of Securities dematerialized #
A12: Quantity of shares settled during the month | B12: Crore | C12: 1093.946 | D12: 902.94401 | E12: 1051.6212 | F12: 4.0247182 | G12: 21.153252 | H12: 501.66 | I12: 432.34 | J12: 1397.5 | K12: -64.1 | L12: 16.03 | N12: Quantity of shares settled during the month
A13: Average Quantity of shares settled daily (quantity of shares settled during the month (divided by 30)) | B13: Crore | C13: 57.576107 | D13: 39.258435 | E13: 55.348486 | F13: 4.0247182 | G13: 46.659199 | H13: 16.18 | I13: 13.95 | J13: 45.08 | K13: -64.1 | L13: 16 | N13: Average Quantity of shares settled daily (quantity of shares settled during the month (divided by 30))
A14: Value of shares settled during the month in dematerialized form | B14: Crore | C14: 289333.79 | D14: 216447.15 | E14: 258408.88 | F14: 11.967431 | G14: 33.674102 | H14: 51174.43 | I14: 47859.72 | J14: 108182.6 | K14: -52.7 | L14: 6.93 | N14: Value of shares settled during the month in dematerialized form
A15: Average Value of shares settled daily (value of shares settled during the month (divided by 30)) | B15: Crore | C15: 15228.094 | D15: 9410.7458 | E15: 13600.467 | F15: 11.967431 | G15: 61.816018 | H15: 1650.79 | I15: 1543.86 | J15: 3489.76 | K15: -52.7 | L15: 6.93 | N15: Average Value of shares settled daily (value of shares settled during the month (divided by 30))
... A17: The ratio of dematerialized equity shares to the total outstanding shares market value | B17: Percent | C17: 87.142635 | D17: 87.132317 | E17: 85.769302 | F17: 1.6011944 | G17: 0.011842111 | H17: 11.59 | I17: 11.77 | J17: 13.21 | K17: -12.26 | L17: -1.51 | N17: The ratio of dematerialized equity shares to the total outstanding shares (market value)
A18: 1. Shares includes only equity shares. 2. Securities include common equity shares, preference shares, debenture, MF units, etc. 3. No. of days taken for calculating Daily Average is 30 days instead of Actual settlement days. 4. Quantity and value of shares mentioned are single sided. 5. #Source for listed securities information: Issuer/ NSE/BSE.
A19: Source: NSDL and CDSL.

Sheet 63
A1: Table 63: Progress of Dematerialisation at NSDL and CDSL (Listed and Unlisted Companies)
A2: Year/ Month | B2: NSDL | G2: CDSL
B3: Companies Live | C3: DPs Live | D3: DPs Locations | E3: Demat Quantity (million securities) | F3: Demat Value (` crore) | G3: Companies Live | H3: DPs Live | I3: DPs Locations | J3: Demat Quantity (million securities) | K3: Demat Value (` crore)
A4: 2017-18 | B4: 19865 | C4: 276 | D4: 30385 | E4: 1506339 | F4: 17220167 | G4: 10628 | H4: 593 | I4: 17473 | J4: 283805 | K4: 1983981
A5: 2018-19$ | B5: 24510 | C5: 277 | D5: 30764 | E5: 1790175.7 | F5: 17579017 | G5: 12110 | H5: 595 | I5: 19312 | J5: 350133.73 | K5: 1944171.6
A6: Apr-18 | B6: 20089 | C6: 277 | D6: 30439 | E6: 1532784.6 | F6: 18187157 | G6: 10761 | H6: 601 | I6: 17454 | J6: 298670.46 | K6: 2121782.2
A7: May-18 | B7: 20282 | C7: 277 | D7: 30563 | E7: 1549218.5 | F7: 17570560 | G7: 10892 | H7: 602 | I7: 19172 | J7: 300622.23 | K7: 2069038.3
A8: Jun-18 | B8: 20462 | C8: 275 | D8: 30512 | E8: 1576579.9 | F8: 17586566 | G8: 10992 | H8: 597 | I8: 19176 | J8: 305639 | K8: 1995128
A9: Jul-18 | B9: 20648 | C9: 275 | D9: 30560 | E9: 1566791.5 | F9: 18447742 | G9: 11088 | H9: 596 | I9: 19154 | J9: 307852 | K9: 2095750
A10: Aug-18 | B10: 20809 | C10: 276 | D10: 30562 | E10: 1557558 | F10: 18964147 | G10: 11174 | H10: 595 | I10: 19189 | J10: 311080 | K10: 2168984
A11: Sep-18 | B11: 20942 | C11: 276 | D11: 30729 | E11: 1583551.9 | F11: 176330.15 | G11: 11237 | H11: 595 | I11: 19221 | J11: 310691.96 | K11: 1950935.8
A12: Oct-18 | B12: 21392 | C12: 274 | D12: 30797 | E12: 1601695.6 | F12: 1705.5665 | G12: 11362 | H12: 593 | I12: 19277 | J12: 321519.11 | K12: 1909449.3
A13: Nov-18 | B13: 22018 | C13: 273 | D13: 30761 | E13: 1622142 | F13: 1758.5679 | G13: 11539 | H13: 592 | I13: 19288 | J13: 329296.12 | K13: 1928099.1
A14: Dec-18 | B14: 22897 | C14: 276 | D14: 30738 | E14: 1676903.2 | F14: 17812044 | G14: 11800 | H14: 592 | I14: 19267 | J14: 340758.56 | K14: 2022692.6
A15: Jan-19 | B15: 23837 | C15: 276 | D15: 30739 | E15: 1754160.2 | F15: 17584348 | G15: 12110 | H15: 595 | I15: 19312 | J15: 350133.73 | K15: 1944171.6
A16: Feb-19 | B16: 24510 | C16: 277 | D16: 30764 | E16: 1790175.7 | F16: 17579017
A17: 1. For CDSL, the current and historical data of Companies Live has been revised to exclude MF schemes count. 2. The Companies Live figure includes only the number of mutual fund companies and not the mutual fund schemes. 3. DPs Locations represents the total live (main DPs and branch DPs as well as non-live (back office connected collection centres).
A18: * Includes Nine Participants which are under closure/termination process and SEBI registration is not yet cancelled/suspended
A19: Source: NSDL and CDSL.

Sheet 64
A1: Table 64: Depository Statistics
A2: Particulars | B2: Unit | C2: Debt | E2: Equity | G2: Others | I2: Total
C3: Listed | D3: Unlisted | E3: Listed | F3: Unlisted | G3: Listed | H3: Unlisted | I3: Listed | J3: Unlisted
A4: NSDL
A5: No.of issuers debt/Companies(equity) | B5: (numbers) | C5: 711 | D5: 1801 | E5: 6136 | F5: 15163 | G5: 69 | H5: 4496 | I5: 6916 | J5: 21460
A6: No.of Active Instruments | B6: (numbers) | C6: 10806 | D6: 6183 | E6: 12453 | F6: 15817 | G6: 8404 | H6: 32259 | I6: 31663 | J6: 54259
A7: Demat Quantity | B7: (lakhs) | C7: 114886.86 | D7: 421294.28 | E7: 5281021.7 | F7: 8224657.9 | G7: 280299.15 | H7: 3579596.8 | I7: 5676207.7 | J7: 12225549
A8: Demat Value | B8: (Rs.Crore) | C8: 2535413.9 | D8: 489451.88 | E8: 12236295 | F8: 834986.7 | G8: 170795.09 | H8: 1312074 | I8: 14942504 | J8: 2636512.6
A9: Quantity settled during the month | B9: (Lakh) | C9: 13787.573 | D9: 16896.183 | E9: 109394.6 | F9: 114.05328 | G9: 6980.4834 | H9: 628.2869 | I9: 130162.66 | J9: 17638.523
A10: Value Settled during the month | B10: (Rs.Crores) | C10: 319954.23 | D10: 22203.146 | E10: 289333.79 | F10: 326.33084 | G10: 3168.6637 | H10: 169.96252 | I10: 612456.68 | J10: 22699.439
A11: CDSL
A12: No. of Issuers (Debt) / Companies (Equity) | B12: (numbers) | C12: 559 | D12: 373 | E12: 6886 | F12: 4188 | G12: 2456 | H12: 521 | I12: 9901 | J12: 5082
A13: No. of Active Instruments | B13: (numbers) | C13: 8365 | D13: 1878 | E13: 7003 | F13: 4393 | G13: 19159 | H13: 1817 | I13: 34527 | J13: 8088
A14: Demat Quantity | B14: (lakh) | C14: 3567.31 | D14: 98168.61 | E14: 1769038.6 | F14: 1305127.1 | G14: 151753.02 | H14: 173682.66 | I14: 1924358.9 | J14: 1576978.4
A15: Demat Value | B15: (Rs.crore) | C15: 60645.05 | D15: 32377.69 | E15: 1639025.8 | F15: 132154.85 | G15: 53859.65 | H15: 26108.57 | I15: 1753530.6 | J15: 190641.11
A16: Quantity settled during the month | B16: (lakh) | C16: 45.73 | D16: 0 | E16: 50166.48 | F16: 0 | G16: 10158.04 | H16: 0 | I16: 60370.25 | J16: 0
A17: Value Settled during the month | B17: (Rs.crore) | C17: 1318.17 | D17: 0 | E17: 51174.43 | F17: 0 | G17: 7408.33 | H17: 0 | I17: 59900.93 | J17: 0
A18: The categories included in Others are Preference Shares, Mutual Fund Units, Warrants, PTCs, Treasury Bills, CPs, CDs and Government Securities.
A19: Source: NSDL and CDSL.

Sheet 65
A1: Table 65: Number of commodities permitted and traded at exchanges
A2: Exchanges | B2: Particulars | C2: Futures | H2: Options
C3: Agriculture | D3: Metals other than bullion | E3: Bullion | F3: Energy | G3: Gems and Stones | H3: Agriculture | I3: Metals other than bullion | J3: Bullion | K3: Energy
A4: NCDEX | B4: Permitted for trading | C4: 19 | D4: 2 | E4: 1 | F4: 1 | G4: 0 | H4: 5 | I4: 0 | J4: 0 | K4: 0
B5: Contracts floated | C5: 19 | D5: 0 | E5: 0 | F5: 0 | G5: 0 | H5: 5 | I5: 0 | J5: 0 | K5: 0
B6: Traded | C6: 15 | D6: 0 | E6: 0 | F6: 0 | G6: 0 | H6: 5 | I6: 0 | J6: 0 | K6: 0
A7: MCX | B7: Permitted for trading | C7: 8 | D7: 6 | E7: 3 | F7: 2 | G7: 0 | H7: 0 | I7: 2 | J7: 2 | K7: 1
B8: Contracts floated | C8: 8 | D8: 6 | E8: 2 | F8: 2 | G8: 0 | H8: 0 | I8: 1 | J8: 2 | K8: 1
B9: Traded | C9: 4 | D9: 5 | E9: 2 | F9: 2 | G9: 0 | H9: 0 | I9: 1 | J9: 2 | K9: 1
A10: ICEX | B10: Permitted for trading | C10: 11 | D10: 1 | E10: 0 | F10: 0 | G10: 1 | H10: 0 | I10: 0 | J10: 0 | K10: 0
B11: Contracts floated | C11: 11 | D11: 1 | E11: 0 | F11: 0 | G11: 1 | H11: 0 | I11: 0 | J11: 0 | K11: 0
B12: Traded | C12: 1 | D12: 1 | E12: 0 | F12: 0 | G12: 1 | H12: 0 | I12: 0 | J12: 0 | K12: 0
A13: BSE | B13: Permitted for trading | C13: 3 | D13: 1 | E13: 2 | F13: 1 | G13: 0 | H13: 0 | I13: 0 | J13: 0 | K13: 0
B14: Contracts floated | C14: 3 | D14: 1 | E14: 2 | F14: 1 | G14: 0 | H14: 0 | I14: 0 | J14: 0 | K14: 0
B15: Traded | C15: 3 | D15: 0 | E15: 2 | F15: 0 | G15: 0 | H15: 0 | I15: 0 | J15: 0 | K15: 0
A16: NSE | B16: Permitted for trading | C16: 0 | D16: 1 | E16: 2 | F16: 1 | G16: 0 | H16: 0 | I16: 0 | J16: 0 | K16: 0
B17: Contracts floated | C17: 0 | D17: 0 | E17: 2 | F17: 0 | G17: 0 | H17: 0 | I17: 0 | J17: 0 | K17: 0
B18: Traded | C18: 0 | D18: 0 | E18: 2 | F18: 0 | G18: 0 | H18: 0 | I18: 0 | J18: 0 | K18: 0
A19: Source: NCDEX, MCX, ICEX, BSE and NSE

Sheet 66
A1: Table 66: Trends in commodity indices
A2: Year/ Month | B2: MCX Comdex | F2: NCDEX Dhaanya
B3: Open | C3: High | D3: Low | E3: Close | F3: Open | G3: High | H3: Low | I3: Close
A4: 2017-18 | B4: 3244.07 | C4: 3729.64 | D4: 2966.02 | E4: 3662.7 | F4: 3107.24 | G4: 3205.12 | H4: 2794.83 | I4: 3036.86
A5: 2018-19$ | B5: 3662.99 | C5: =LARGE(C6:C26,1) -> 4171.56 | D5: =SMALL(D6:D30,1) -> 3311.89 | E5: =E16 -> 3752.04 | F5: 3051.23 | G5: =LARGE(G6:G26,1) -> 3589.79 | H5: =SMALL(H6:H30,1) -> 2838.4 | I5: =I16 -> 3268.22
A6: 43191 | B6: 3662.99 | C6: 3887.58 | D6: 3613.55 | E6: 3789.4 | F6: 3051.23 | G6: 3110.84 | H6: 2881.06 | I6: 2898.52
A7: 43222 | B7: 3791.8 | C7: 3964.29 | D7: 3761.67 | E7: 3860.6 | F7: 2899.04 | G7: 3013.64 | H7: 2862.52 | I7: 2876.57
A8: 43254 | B8: 3859.43 | C8: 3954.26 | D8: 3795.96 | E8: 3933.05 | F8: 2883.01 | G8: 3001.49 | H8: 2838.4 | I8: 2981.37
A9: 43285 | B9: 3932.33 | C9: 3938.24 | D9: 3722.08 | E9: 3793.01 | F9: 2989.54 | G9: 3274.25 | H9: 2989.54 | I9: 3265.13
A10: 43317 | B10: 3792.28 | C10: 3892.41 | D10: 3698.71 | E10: 3859.13 | F10: 3268.66 | G10: 3297.36 | H10: 3035.96 | I10: 3117.78
A11: 43349 | B11: 3858.42 | C11: 4022.09 | D11: 3820.7 | E11: 4009.9 | F11: 3132.06 | G11: 3190.19 | H11: 3106.06 | I11: 3167.53
A12: 43379 | B12: 4009.24 | C12: 4171.56 | D12: 3907.93 | E12: 3912.77 | F12: 3199.07 | G12: 3368.51 | H12: 3168.79 | I12: 3349.02
A13: 43405 | B13: 3913.32 | C13: 3916.26 | D13: 3480.63 | E13: 3510.69 | F13: 3362.35 | G13: 3589.79 | H13: 3329.33 | I13: 3384.58
A14: 43436 | B14: 3512.27 | C14: 3663.99 | D14: 3311.89 | E14: 3334.68 | F14: 3381.89 | G14: 3426.74 | H14: 3212.68 | I14: 3321.74
A15: 43468 | B15: 3336.35 | C15: 3695.65 | D15: 3322.71 | E15: 3671.65 | F15: 3340.26 | G15: 3422.04 | H15: 3325.28 | I15: 3391.29
A16: 43500 | B16: 3670.83 | C16: 3781.35 | D16: 3582.27 | E16: 3752.04 | F16: 3395.11 | G16: 3398.98 | H16: 3264.85 | I16: 3268.22
A17: $ indicates as on February 28, 2019
A18: Source: MCX and NCDEX

Sheet 67
A1: Table 67: Trends in commodity derivatives at MCX
A2: FUTURES
A3: Year/ Month | B3: No.of Trading days | C3: Agriculture | F3: Metals | I3: Bullion | L3: Energy | O3: Total | Q3: Open interest at the end of the period
C4: Volume ('000 tonnes) | D4: No. of contracts traded | E4: Turnover (₹ crore) | F4: Volume ('000 tonnes) | G4: No. of contracts traded | H4: Turnover (₹ crore) | I4: Volume ('000 tonnes) | J4: No. of contracts traded | K4: Turnover (₹ crore) | L4: Volume ('000 tonnes)* | M4: No. of contracts traded | N4: Turnover (₹ crore) | O4: No. of contracts traded | P4: Turnover (₹ crore) | Q4: No. of contracts | R4: Value (₹ crore)
A5: 2017-18 | B5: 254 | C5: 11648.45 | D5: 2317338 | E5: 114082 | F5: 95153 | G5: 68133042 | H5: 2112532 | I5: 164 | J5: 27840060 | K5: 1363703 | L5: 574029 | M5: 107634572 | N5: 1792678 | O5: 205925012 | P5: 5382996 | Q5: 300172 | R5: 11204.53
A6: 2018-19$ | B6: =SUM(B7:B17) -> 236 | C6: =SUM(C7:C17) -> 8725.5655 | D6: =SUM(D7:D17) -> 1647637 | E6: =SUM(E7:E17) -> 91526.039 | F6: =SUM(F7:F17) -> 102874.46 | G6: =SUM(G7:G17) -> 72609744 | H6: =SUM(H7:H17) -> 2328428.4 | I6: =SUM(I7:I17) -> 155.57613 | ... P6: =SUM(P7:P17) -> 6013960.3 | Q6: =Q17 -> 257544 | R6: =R17 -> 14376.11
A7: 43191 | B7: 21 | C7: 681.3872 | D7: 135772 | E7: 7382.075 | F7: 10995.024 | G7: 7867869 | H7: 253029.94 | I7: 15.435436 | J7: 2673160 | K7: 125840.43 | L7: 50265.02 | M7: 9663715 | N7: 175610.71 | O7: =M7+J7+G7+D7 -> 20340516 | P7: =N7+K7+H7+E7 -> 561863.15 | Q7: 272419 | R7: 10252.263
A8: 43222 | B8: 23 | C8: 856.49571 | D8: 155130 | E8: 8621.0232 | F8: 8950.3651 | G8: 6394869 | H8: 214667.65 | I8: 12.383255 | J8: 2253461 | K8: 122585.99 | L8: 46250.698 | M8: 8895210 | N8: 177009.7 | O8: =M8+J8+G8+D8 -> 17698670 | P8: =N8+K8+H8+E8 -> 522884.36 | Q8: 247940 | R8: 9719.0456
A9: 43254 | B9: 21 | C9: 886.41457 | D9: 175959 | E9: 9715.8885 | F9: 8167.2401 | G9: 6121070 | H9: 212443.22 | I9: 14.222909 | J9: 2357607 | K9: 110300.49 | L9: 44502.368 | M9: 8569510 | N9: 166191.54 | O9: =M9+J9+G9+D9 -> 17224146 | P9: =N9+K9+H9+E9 -> 498651.14 | Q9: 298803 | R9: 11252.64
A10: 43285 | B10: 22 | C10: 771.97491 | D10: 160034 | E10: 9145.5648 | F10: 10913.254 | G10: 7272721 | H10: 238764.26 | I10: 11.516053 | J10: 1962672 | K10: 99642.058 | L10: 44769.445 | M10: 8301841 | N10: 171692.95 | O10: =M10+J10+G10+D10 -> 17697268 | P10: =N10+K10+H10+E10 -> 519244.83 | Q10: 300324 | R10: 11624.484
A11: 43317 | B11: 22 | C11: 680.41465 | D11: 130026 | E11: 7635.2631 | F11: 10505.019 | G11: 7287437 | H11: 229026.26 | I11: 16.539244 | J11: 2450524 | K11: 115911.34 | L11: 41038.601 | M11: 8179663 | N11: 158522.47 | O11: =M11+J11+G11+D11 -> 18047650 | P11: =N11+K11+H11+E11 -> 511095.34 | Q11: 337203 | R11: 12937.86
A12: 43349 | B12: 20 | C12: 644.88197 | D12: 126410 | E12: 7423.7061 | F12: 10275.787 | G12: 7038163 | H12: 225426.85 | I12: 15.594591 | J12: 2505658 | K12: 134224.13 | L12: 43708.061 | M12: 8617984 | N12: 180485.21 | O12: =M12+J12+G12+D12 -> 18288215 | P12: =N12+K12+H12+E12 -> 547559.89 | Q12: 293647 | R12: 12632.031
A13: 43380 | B13: 22 | C13: 713.76738 | D13: 135899 | E13: 7922.7077 | F13: 10507.374 | G13: 7274845 | H13: 242104.49 | I13: 15.778854 | J13: 2716283 | K13: 137468.71 | L13: 47470.92 | M13: 10202221 | N13: 222820.32 | O13: =M13+J13+G13+D13 -> 20329248 | P13: =N13+K13+H13+E13 -> 610316.23 | Q13: 326788 | R13: 14618.349
A14: 43405 | B14: 22 | C14: 880.84588 | D14: 146737 | E14: 8040.6244 | F14: 7868.6852 | G14: 5781903 | H14: 176376.6 | I14: 15.451758 | J14: 2404522 | K14: 122191.63 | L14: 58249.488 | M14: 13204283 | N14: 261805.17 | O14: =M14+J14+G14+D14 -> 21537445 | P14: =N14+K14+H14+E14 -> 568414.02 | Q14: 328316 | R14: 12267.827
A15: 43436 | B15: 20 | C15: 973.94296 | D15: 173622 | E15: 9155.3992 | F15: 7145.4594 | G15: 5228208 | H15: 155530.52 | I15: 12.463302 | J15: 2255493 | K15: 117881.04 | L15: 75804.095 | M15: 15931498 | N15: 242020.19 | O15: 23588821 | P15: 524587.14 | Q15: 325197 | R15: 13161.637
A16: 43468 | B16: 23 | C16: 842.58994 | D16: 157073 | E16: 8419.2547 | F16: 9397.7367 | G16: 6500061 | H16: 195705.3 | I16: 13.373667 | J16: 2526183 | K16: 144350.73 | L16: 81981.645 | M16: 17407316 | N16: 260414.53 | O16: 26590633 | P16: 608889.81 | Q16: 261376 | R16: 14907.61
A17: 43500 | B17: 20 | C17: 792.85031 | D17: 150975 | E17: 8064.5327 | F17: 8148.5166 | G17: 5842598 | H17: 185353.34 | I17: 12.817058 | J17: 2271899 | K17: 131567.12 | L17: 69132.38 | M17: 14091322 | N17: 215469.37 | O17: 22356794 | P17: 540454.38 | Q17: 257544 | R17: 14376.11
A18: OPTIONS
A19: Year / Month | B19: No.of Trading days | C19: Metals | G19: Bullion | K19: Energy | O19: Total | Q19: Open interest at the end of the period
C20: Call Options | E20: Put Options | G20: Call Options | I20: Put Options | K20: Call Options | M20: Put Options | O20: No. of contracts | P20: Turnover (₹ crore) | Q20: No. of contracts | R20: Notional Value (₹ crore)
C21: No. of contracts | D21: Turnover (₹ crore) | E21: No. of contracts | F21: Turnover (₹ crore) | G21: No. of contracts | H21: Turnover (₹ crore) | I21: No. of contracts | J21: Turnover (₹ crore) | K21: No. of contracts | L21: Turnover (₹ crore) | M21: No. of contracts | N21: Turnover (₹ crore)
A22: 2017-18 | B22: 116 | C22: Na | D22: Na | E22: Na | F22: Na | G22: 23207 | H22: 6955 | I22: 11545 | J22: 3399 | K22: Na | L22: Na | M22: Na | N22: Na | O22: =G22+I22 -> 34752 | P22: =H22+J22 -> 10354 | Q22: 298 | R22: 92
A23: 2018-19$ | B23: =SUM(B24:B34) -> 236 | C23: =SUM(C24:C34) -> 64814 | D23: =SUM(D24:D34) -> 3413.9713 | E23: =SUM(E24:E34) -> 49304 | F23: =SUM(F24:F34) -> 2414.2785 | G23: =SUM(G24:G34) -> 246719 | H23: =SUM(H24:H34) -> 69983.596 | I23: =SUM(I24:I34) -> 196713 | ... P23: =SUM(P24:P34) -> 168293.47 | Q23: =Q34 -> 9204 | R23: =R34 -> 1270.5655
A24: 43191 | B24: 21 | C24: 0 | D24: 0 | E24: 0 | F24: 0 | G24: 4584 | H24: 1533.95 | I24: 3534 | J24: 1106.47 | K24: 0 | L24: 0 | M24: 0 | N24: 0 | O24: 8388 | P24: =H24+J24 -> 2640.42 | Q24: 1650 | R24: 517.56
A25: 43221 | B25: 23 | C25: 3575 | D25: 169.95 | E25: 2777 | F25: 130.75 | G25: 26483 | H25: 8134.59 | I25: 22435 | J25: 6916.01 | K25: 17615 | L25: 861.47 | M25: 13660 | N25: 657.54 | O25: =G25+I25+C25+E25+K25+M25 -> 86545 | P25: =H25+J25+D25+F25+L25+N25 -> 16870.31 | Q25: 5677 | R25: 528.7
A26: 43252 | B26: 21 | C26: 12624 | D26: 681.89 | E26: 9217 | F26: 448.87 | G26: 24430 | H26: 6551.92 | I26: 20714 | J26: 5617.14 | K26: 31403 | L26: 1464.8 | M26: 26661 | N26: 1223.12 | O26: =G26+I26+C26+E26+K26+M26 -> 125049 | P26: =H26+J26+D26+F26+L26+N26 -> 15987.74 | Q26: 10748 | R26: 1389.4
A27: 43282 | B27: 22 | C27: 9967 | D27: 611.25 | E27: 3844 | F27: 203.52 | G27: 29249 | H27: 8447.3 | I27: 25159 | J27: 7394.52 | K27: 26313 | L27: 1313.15 | M27: 35238 | N27: 1702.25 | O27: =G27+I27+C27+E27+K27+M27 -> 129770 | P27: =H27+J27+D27+F27+L27+N27 -> 19671.99 | Q27: 5971 | R27: 535.57
A28: 43313 | B28: 22 | C28: 10066 | D28: 487.48 | E28: 5386 | F28: 249.66 | G28: 17000 | H28: 4150.34 | I28: 12647 | J28: 3416.64 | K28: 30747 | L28: 1486.43 | M28: 26732 | N28: 1250.83 | O28: =G28+I28+C28+E28+K28+M28 -> 102578 | P28: =H28+J28+D28+F28+L28+N28 -> 11041.38 | Q28: 5735 | R28: 657.73
A29: 43344 | B29: 20 | C29: 3053 | D29: 172.47193 | E29: 4308 | F29: 215.48277 | G29: 83236 | H29: 25124.148 | I29: 59085 | J29: 17949.004 | K29: 28034 | L29: 1445.2013 | M29: 34418 | N29: 1717.8269 | O29: =G29+I29+C29+E29+K29+M29 -> 212134 | P29: =H29+J29+D29+F29+L29+N29 -> 46624.135 | Q29: 6441 | R29: 528.00232
A30: 43380 | B30: 22 | C30: 4312 | D30: 223.8 | E30: 5332 | F30: 265.19 | G30: 20488 | H30: 5973.91 | I30: 16640 | J30: 5051.42 | K30: 39583 | L30: 2141.4 | M30: 37645 | N30: 1989.11 | O30: =G30+I30+C30+E30+K30+M30 -> 124000 | P30: =H30+J30+D30+F30+L30+N30 -> 15644.83 | Q30: 7666 | R30: 903.96
A31: 43405 | B31: 22 | C31: 5460 | D31: 259.68746 | E31: 5173 | F31: 241.76314 | G31: 14307 | H31: 3315.2145 | I31: 7228 | J31: 1779.0653 | K31: 67680 | L31: 2915.99 | M31: 41202 | N31: 1723 | O31: =G31+I31+C31+E31+K31+M31 -> 141050 | P31: =H31+J31+D31+F31+L31+N31 -> 10234.72 | Q31: 8862 | R31: 675.52
A32: 43436 | B32: 20 | C32: 3743 | D32: 185.48787 | E32: 2885 | F32: 140.62683 | G32: 8483 | H32: 2296.985 | I32: 9156 | J32: 2648.1092 | K32: 77534 | L32: 2921.917 | M32: 44777 | N32: 1620.779 | O32: 146578 | P32: 9813.9139 | Q32: 13117 | R32: 1132.95
A33: 43468 | B33: 23 | C33: 5748 | D33: 276.76 | E33: 3692 | F33: 175.6 | G33: 9323 | H33: 2220.88 | I33: 10589 | J33: 2947.47 | K33: 67738 | L33: 2531.4 | M33: 65512 | N33: 2320.62 | O33: 162602 | P33: 10472.72 | Q33: 9625 | R33: 736.74
A34: 43500 | B34: 20 | C34: 6266 | D34: 345.194 | E34: 6690 | F34: 342.8158 | G34: 9136 | H34: 2234.359 | I34: 9526 | J34: 2606.7807 | K34: 48063 | L34: 1935.36 | M34: 47265 | N34: 1826.8 | O34: 126946 | P34: 9291.3095 | Q34: 9204 | R34: 1270.5655
A35: ='66'!A17 -> $ indicates as on February 28, 2019
A36: Natural Gas volume is in Trillion BTU and is not included in volume ('000 tonnes) of energy contracts.
A37: Source: MCX
B42: following is not for publications (verifications):
B43: annual total of TO | D43: Agir | E43: non-agri | F43: Total | H43: futures | I43: options | J43: total | K43: match
B45: Monthly totals of TO | D45: =E6+'68'!E6+'69'!E5+'68'!I6+'68'!K6 -> 604953.37 | E45: =P23+H6+K6+N6+'69'!K5+'69'!H5+'70'!P4+'71'!E5 -> 6140445.7 | F45: =D45+E45 -> 6745399.1 | H45: =P6+'68'!E6+'69'!M5+'70'!P4+'71'!E5 -> 6576936.9 | I45: =P23+'68'!I6+'68'!K6 -> 168462.2 | J45: =H45+I45 -> 6745399.1 | K45: =F45=J45 -> TRUE | M45: ='73'!D28+'73'!D40+'74'!D21+'74'!D28+'75'!D16+'75'!D26+'75'!D35+0.51 -> 6745400.3
B46: 43191 | D46: =E7+'68'!E7+'69'!E6+'68'!I7+'68'!K7 -> 50188.155 | E46: =P24+H7+K7+N7+'69'!K6 -> 557600.76 | F46: =D46+E46 -> 607788.91 | H46: =P7+'68'!E7+'69'!M6 -> 605127.23 | I46: =P24+'68'!I7+'68'!K7 -> 2661.68 | J46: =H46+I46 -> 607788.91 | K46: =F46=J46 -> TRUE
B47: 43221 | D47: =E8+'68'!E8+'69'!E7+'68'!I8+'68'!K8 -> 53494.711 | E47: =P25+H8+K8+N8+'69'!K7 -> 531496.07 | F47: =D47+E47 -> 584990.78 | H47: =P8+'68'!E8+'69'!M7 -> 568107.17 | I47: =P25+'68'!I8+'68'!K8 -> 16883.61 | J47: =H47+I47 -> 584990.78 | K47: =F47=J47 -> TRUE
B48: 43252 | D48: =E9+'68'!E9+'69'!E8+'68'!I9+'68'!K9 -> 54011.815 | E48: =P26+H9+K9+N9+'69'!K8 -> 505217.87 | F48: =D48+E48 -> 559229.69 | H48: =P9+'68'!E9+'69'!M8 -> 543225.36 | I48: =P26+'68'!I9+'68'!K9 -> 16004.33 | J48: =H48+I48 -> 559229.69 | K48: =F48=J48 -> TRUE
B49: 43282 | D49: =E10+'68'!E10+'69'!E9+'68'!I10+'68'!K10 -> 72925.607 | E49: =P27+H10+K10+N10+'69'!K9 -> 530236.35 | F49: =D49+E49 -> 603161.96 | H49: =P10+'68'!E10+'69'!M9 -> 583474.4 | I49: =P27+'68'!I10+'68'!K10 -> 19687.56 | J49: =H49+I49 -> 603161.96 | K49: =F49=J49 -> TRUE
B50: 43313 | D50: =E11+'68'!E11+'69'!E10+'68'!I11+'68'!K11 -> 67565.12 | E50: =P28+H11+K11+N11+'69'!K10+'69'!H10 -> 514933.94 | F50: =D50+E50 -> 582499.06 | H50: =P11+'68'!E11+'69'!M10 -> 571445.63 | I50: =P28+'68'!I11+'68'!K11 -> 11053.43 | J50: =H50+I50 -> 582499.06 | K50: =F50=J50 -> TRUE
B51: 43344 | D51: =E12+'68'!E12+'69'!E11+'68'!I12+'68'!K12 -> 46857.934 | E51: =P29+H12+K12+N12+'69'!K11+'69'!H11+'70'!P4+'71'!E5 -> 619084.4 | F51: =D51+E51 -> 665942.34 | H51: =P12+'68'!E12+'69'!M11+'70'!P4+'71'!E5 -> 619305.01 | I51: =P29+'68'!I12+'68'!K12 -> 46637.325 | J51: =H51+I51 -> 665942.34 | K51: =F51=J51 -> TRUE
B52: 43380 | D52: =E13+'68'!E13+'69'!E12+'68'!I13+'68'!K13 -> 62124.014 | E52: =P30+H13+K13+N13+'69'!K12+'69'!H12+'70'!P5+'71'!E6 -> 627389.33 | F52: =D52+E52 -> 689513.34 | H52: =P13+'68'!E13+'69'!M12+'70'!P5+'71'!E6 -> 673827.53 | I52: =P30+'68'!I13+'68'!K13 -> 15685.81 | J52: =H52+I52 -> 689513.34 | K52: =F52=J52 -> TRUE
B53: 43405 | D53: =E14+'68'!E14+'69'!E13+'68'!I14+'68'!K14 -> 65485.593 | E53: =P31+H14+K14+N14+'69'!K13+'69'!H13+'70'!P6+'71'!E7 -> 580956 | F53: =D53+E53 -> 646441.6 | H53: =P14+'68'!E14+'69'!M13+'70'!P6+'71'!E7 -> 636186.97 | I53: =P31+'68'!I14+'68'!K14 -> 10254.63 | J53: =H53+I53 -> 646441.6 | K53: =F53=J53 -> TRUE

Sheet 68
A1: Table 68: Trends in commodity derivatives at NCDEX
A2: Year/ Month | B2: No.of Trading days | C2: FUTURES | H2: OPTIONS
C3: Volume ('000 tonnes) | D3: No. of contracts traded | E3: Turnover (₹ crore) | F3: Open interest at the end of the period | H3: Call options | J3: Put options | L3: Open interest at the end of the period
F4: No. of Contracts | G4: Value (₹ crore) | H4: No. of contracts | I4: Turnover (₹ crore) | J4: No. of contracts | K4: Turnover (₹ crore) | L4: No. of contracts | M4: Notional Value (₹ crore)
A5: 2017-18 | B5: 248 | C5: 133172 | D5: 15187625 | E5: 589497 | F5: 135902 | G5: 5099.96 | H5: 5169 | I5: 233.66 | J5: 1440 | K5: 64.65 | L5: 569 | M5: 25.32
A6: 2018-19$ | B6: =SUM(B7:B17) -> 229 | C6: =SUM(C7:C17) -> 112887.65 | D6: =SUM(D7:D17) -> 13094931 | E6: =SUM(E7:E17) -> 498725.17 | F6: =F17 -> 148375 | G6: =G17 -> 5257.82 | H6: =SUM(H7:H17) -> 3530 | I6: =SUM(I7:I17) -> 154.77 | J6: =SUM(J7:J17) -> 328 | K6: =SUM(K7:K17) -> 13.96 | L6: =L17 -> 41 | M6: =M17 -> 1.78
A7: 43191 | B7: 21 | C7: 9906.961 | D7: 1080591 | E7: 39618.826 | F7: 151062 | G7: 5180.63 | H7: 401 | I7: 17.38 | J7: 95 | K7: 3.88 | L7: 78 | M7: 3.31
A8: 43222 | B8: 22 | C8: 10347.104 | D8: 1124310 | E8: 41737.886 | F8: 132329 | G8: 4692.6 | H8: 315 | I8: 12.5 | J8: 20 | K8: 0.8 | L8: 32 | M8: 1.24
A9: 43254 | B9: 21 | C9: 10948.555 | D9: 1184196 | E9: 41893.866 | F9: 125671 | G9: 4629.28 | H9: 413 | I9: 15.88 | J9: 18 | K9: 0.71 | L9: 145 | M9: 6
A10: 43285 | B10: 22 | C10: 14388.817 | D10: 1565853 | E10: 61323.26 | F10: 119819 | G10: 4913.88 | H10: 360 | I10: 15.25 | J10: 8 | K10: 0.32 | L10: 155 | M10: 6.91
A11: 43317 | B11: 21 | C11: 12897.352 | D11: 1431248 | E11: 58371.163 | F11: 109058 | G11: 4425.59 | H11: 243 | I11: 10.96 | J11: 24 | K11: 1.09 | L11: 256 | M11: 11.53
A12: 43349 | B12: 18 | C12: 8241.862 | D12: 922621 | E12: 38248.203 | F12: 106059 | G12: 4414.45 | H12: 287 | I12: 12.8 | J12: 9 | K12: 0.39 | L12: 109 | M12: 4.92
A13: 43380 | B13: 21 | C13: 11217.004 | D13: 1419259 | E13: 54025.149 | F13: 126089 | G13: 5539.36 | H13: 814 | I13: 37.21 | J13: 86 | K13: 3.77 | L13: 86.5 | M13: 4.2
A14: 43405 | B14: 20 | C14: 11567.297 | D14: 1478815 | E14: 57347.978 | F14: 122788 | G14: 5165.91 | H14: 374 | I14: 18.02 | J14: 41 | K14: 1.89 | L14: 33 | M14: 1.77
A15: 43436 | B15: 20 | C15: 7587.112 | D15: 961336 | E15: 35475.967 | F15: 120973 | G15: 4997.43 | H15: 94 | I15: 4.6 | J15: 10 | K15: 0.42 | L15: 2 | M15: 0.89
A16: 43468 | B16: 23 | C16: 9294.648 | D16: 1121343 | E16: 41595.64 | F16: 131282 | G16: 5496.11 | H16: 128 | I16: 5.72 | J16: 8 | K16: 0.32 | L16: 10 | M16: 0.45
A17: 43500 | B17: 20 | C17: 6490.94 | D17: 805359 | E17: 29087.23 | F17: 148375 | G17: 5257.82 | H17: 101 | I17: 4.45 | J17: 9 | K17: 0.37 | L17: 41 | M17: 1.78
A18: ='66'!A17 -> $ indicates as on February 28, 2019
A19: Source: NCDEX

Sheet 69
A1: Table 69: Trends in commodity derivatives at ICEX
A2: Year/ Month | B2: No.of Trading days | C2: Agriculture Futures | F2: Metals Futures | I2: Gems and Stones Futures | L2: Total | N2: Open interest at the end of the period
C3: Volume ('000 tonnes) | D3: No. of contracts traded | E3: Turnover (₹ crore) | F3: Volume ('000 tonnes) | G3: No. of contracts traded | H3: Turnover (₹ crore) | I3: Volume (in cents) | J3: No. of contracts traded | K3: Turnover (₹ crore) | L3: No. of contracts traded | M3: Turnover (₹ crore) | N3: No. of contracts | O3: Value (₹ crore)
A4: 2017-18 | B4: 246 | C4: 7512 | D4: 1653274 | E4: 34591 | F4: NA | G4: NA | H4: NA | I4: 7362673 | J4: 7362673 | K4: 2158 | L4: =SUM(J4,G4,D4) -> 9015947 | M4: =SUM(K4,H4,E4) -> 36749 | N4: 42771 | O4: 58.654043
A5: 2018-19$ | B5: =SUM(B6:B16) -> 236 | C5: =SUM(C6:C16) -> 3177.8932 | D5: =SUM(D6:D16) -> 665581 | E5: =SUM(E6:E16) -> 14533.434 | F5: =SUM(F6:F16) -> 844.17 | G5: =SUM(G6:G16) -> 98678 | H5: =SUM(H6:H16) -> 3485.4997 | I5: =SUM(I6:I16) -> 43165533 | ... M5: =SUM(M6:M16) -> 32858.501 | N5: =N16 -> 157090 | O5: =O16 -> 91.09
A6: 43191 | B6: 21 | C6: 688.82163 | D6: 179598 | E6: 3165.9945 | F6: NA | G6: NA | H6: NA | I6: 1764149 | J6: 1764149 | K6: 479.26 | L6: 1943747 | M6: =E6+K6 -> 3645.2545 | N6: 64616 | O6: 58.016364
A7: 43222 | B7: 23 | C7: 685.49515 | D7: 166702 | E7: 3122.5015 | F7: NA | G7: NA | H7: NA | I7: 1252759 | J7: 1252759 | K7: 362.4169 | L7: 1419461 | M7: =E7+K7 -> 3484.9184 | N7: 44701 | O7: 55.18191
A8: 43254 | B8: 21 | C8: 552.4161 | D8: 118634 | E8: 2385.4703 | F8: NA | G8: NA | H8: NA | I8: 1010150 | J8: 1010150 | K8: 294.87927 | L8: 1128784 | M8: =E8+K8 -> 2680.3495 | N8: 41951 | O8: 39.937001
A9: 43285 | B9: 22 | C9: 556.22928 | D9: 79255 | E9: 2441.2125 | F9: NA | G9: NA | H9: NA | I9: 1529890 | J9: 1529890 | K9: 465.09 | L9: 1609145 | M9: =E9+K9 -> 2906.3025 | N9: 63875 | O9: 35.555507
A10: 43317 | B10: 22 | C10: 362.67805 | D10: 39115 | E10: 1546.6437 | F10: 30.78 | G10: 3078 | H10: 118.04 | I10: 1068842 | J10: 1068842 | K10: 314.44 | L10: 1111035 | M10: =E10+K10+H10 -> 1979.1237 | N10: 56449 | O10: 26.897642
A11: 43349 | B11: 20 | C11: 266.973 | D11: 31266 | E11: 1172.8346 | F11: 159.6 | G11: 15960 | H11: 613.23 | I11: 1012245 | J11: 1012245 | K11: 317.91 | L11: 1059471 | M11: =E11+K11+H11 -> 2103.9746 | N11: 48875 | O11: 32.4203
A12: 43380 | B12: 22 | C12: 20.111 | D12: 6233 | E12: 135.1769 | F12: 183.85 | G12: 18385 | H12: 661.73573 | I12: 2677357 | J12: 2677357 | K12: 943.67369 | L12: 2701975 | M12: =E12+K12+H12 -> 1740.5863 | N12: 32859 | O12: 22.37
A13: 43411 | B13: 22 | C13: 6.589 | D13: 6175 | E13: 77.08 | F13: 127.46 | G13: 12746 | H13: 447.384 | I13: 5138963 | J13: 5138963 | K13: 1834.427 | L13: 5157884 | M13: =E13+K13+H13 -> 2358.891 | N13: 9537 | O13: 19.46
A14: 43442 | B14: 20 | C14: 10.072 | D14: 10072 | E14: 126.75 | F14: 150.63 | G14: 15063 | H14: 508.41 | I14: 6662853 | J14: 6662853 | K14: 2356.4 | L14: 6687988 | M14: 2991.56 | N14: 32498 | O14: 38.84
A15: 43474 | B15: 23 | C15: 13.508 | D15: 13508 | E15: 169.87 | F15: 15.85 | G15: 15853 | H15: 525.6 | I15: 8345922 | J15: 8345922 | K15: 2939.57 | L15: 8375283 | M15: 3635.04 | N15: 113812 | O15: 64.18
A16: 43506 | B16: 20 | C16: 15 | D16: 15023 | E16: 189.9 | F16: 176 | G16: 17593 | H16: 611.1 | I16: 12702403 | J16: 12702403 | K16: 4531.5001 | L16: 12735019 | M16: 5332.5001 | N16: 157090 | O16: 91.09
A17: ='66'!A17 -> $ indicates as on February 28, 2019
A18: i. Contract size for all diamond futures contract at ICEX is one cent.
A19: ii. Futures trading in steel long contracts commenced from 28th Aug. 2018.
A20: iii. Consequent upon merger of NMCE with ICEX, all contracts of NMCE are transferred to ICEX w.e.f September 24, 2018. The trading data of NMCE is added to agri. segment of ICEX.
A21: Source: ICEX

Sheet 70
A1: Table 70: Trends in commodity derivatives at BSE
A2: Year/ Month | B2: No.of Trading days | C2: Metal Futures | F2: Bullion Futures | I2: Energy Futures | L2: Agriculture | O2: Total | Q2: Open interest at the end of the period
C3: Volume ( tonnes) | D3: No. of contracts traded | E3: Turnover (₹ crore) | F3: Volume ( tonnes) | G3: No. of contracts traded | H3: Turnover (₹ crore) | I3: Volume ( tonnes) | J3: No. of contracts traded | K3: Turnover (₹ crore) | L3: Volume ( tonnes) | M3: No. of contracts traded | N3: Turnover (₹ crore) | O3: No. of contracts traded | P3: Turnover (₹ crore) | Q3: No. of contracts | R3: Value (₹ crore)
A4: 2018-19$ | B4: =SUM(B5:B9) -> 107 | C4: =SUM(C5:C9) -> 0.021 | D4: =SUM(D5:D9) -> 21 | E4: =SUM(E5:E9) -> 0.99 | F4: =SUM(F5:F9) -> 716.921 | G4: =SUM(G5:G9) -> 97170 | H4: =SUM(H5:H9) -> 26555.829 | I4: =SUM(I5:I9) -> 1050.4935 | ... P4: =SUM(P5:P9) -> 28378.724 | Q4: =Q9 -> 1099 | R4: =R9 -> 78.39
A5: 43374 | B5: 22 | C5: 0 | D5: 0 | E5: 0 | F5: 274.212 | G5: 27509 | H5: 7045.08 | I5: =7700/7.33 -> 1050.4775 | J5: 77 | K5: 4.28514 | O5: =D5+G5+J5 -> 27586 | P5: =E5+H5+K5 -> 7049.3651 | Q5: 374 | R5: 58.18
A6: 43405 | B6: 22 | C6: 0.021 | D6: 21 | E6: 0.99 | F6: 179.18 | G6: 26668 | H6: 7227.19 | I6: =(8/1000) -> 0.008 | J6: 0 | K6: 0 | O6: =D6+G6+J6 -> 26689 | P6: =E6+H6+K6 -> 7228.18 | Q6: 899 | R6: 113.35
A7: 43436 | B7: 20 | C7: 0 | D7: 0 | E7: 0 | F7: 109.889 | G7: 14073 | H7: 3754.7995 | I7: =(8/1000) -> 0.008 | J7: 0 | K7: 0 | O7: 14073 | P7: 3754.7995 | Q7: 865 | R7: 133.65
A8: 43468 | B8: 23 | C8: 0 | D8: 0 | E8: 0 | F8: 74 | G8: 21483 | H8: 6538.509 | I8: 0 | J8: 0 | K8: 0 | O8: 21483 | P8: 6538.509 | Q8: 771 | R8: 121.84
A9: 43500 | B9: 20 | C9: 0 | D9: 0 | E9: 0 | F9: 79.64 | G9: 7437 | H9: 1990.25 | I9: 0 | J9: 0 | K9: 0 | L9: 566.42 | M9: 40558 | N9: 1817.62 | O9: 47995 | P9: 3807.87 | Q9: 1099 | R9: 78.39
A10: $ indicates as on February 28, 2019
A11: Conversion factors: OMAN Crude Oil (1 Tonne = 7.33Barrels)
A12: Source: BSE

Sheet 71
A1: Table 71: Trends in commodity derivatives at NSE
A3: Year/ Month | B3: No.of Trading days | C3: Bullion Futures | F3: Open interest at the end of the period
C4: Volume ( tonnes) | D4: No. of contracts traded | E4: Turnover (₹ crore) | F4: No. of contracts | G4: Value (₹ crore)
A5: 2018-19$ | B5: =SUM(B6:B10) -> 99 | C5: =SUM(C6:C10) -> 136.1439 | D5: =SUM(D6:D10) -> 27506 | E5: =SUM(E6:E10) -> 3014.218 | F5: =F10 -> 207 | G5: =G10 -> 19.89
A6: 43374 | B6: 14 | C6: 24.879 | D6: 2881 | E6: 696.19926 | F6: 139 | G6: 29.01
A7: 43405 | B7: 22 | C7: 34.4435 | D7: 3407 | E7: 837.90052 | F7: 338 | G7: 68.21
A8: 43436 | B8: 20 | C8: 38.4803 | D8: 3007 | E8: 532.61176 | F8: 292 | G8: 60.89
A9: 43468 | B9: 23 | C9: 19.8886 | D9: 6163 | E9: 448.81896 | F9: 284 | G9: 36.09
A10: 43500 | B10: 20 | C10: 18.4525 | D10: 12048 | E10: 498.68747 | F10: 207 | G10: 19.89
A11: $ indicates as on February 28, 2019
A12: Source: NSE

Sheet 72
A1: Table 72: Participant-wise percentage share of turnover at MCX, NCDEX, ICEX, BSE and NSE
A2: Year/ Month | B2: MCX | F2: NCDEX | I2: ICEX | M2: BSE | O2: NSE
B3: Agriculture | D3: Non-Agriculture Segment | F3: Agriculture | I3: Agriculture | K3: Non-Agriculture | M3: Non-Agriculture | O3: Non-Agriculture
B4: Proprietary | C4: Client | D4: Proprietary | E4: Client | F4: Proprietary | G4: Client | H4: Hedgers | I4: Proprietary | J4: Client | K4: Proprietary | L4: Client | M4: Proprietary | N4: Client | O4: Proprietary | P4: Client
A5: 2017-18 | B5: 35.440517 | C5: 64.559483 | D5: 20.606491 | E5: 79.393509 | F5: 41.042632 | G5: 58.794851 | H5: 0.16251644 | I5: 2.0745346 | J5: 97.925465 | K5: NA | L5: NA | M5: NA | N5: NA | O5: NA | P5: NA
A6: 2018-19$ | B6: 38.248436 | C6: 61.751564 | D6: 26.895303 | E6: 73.104697 | F6: 43.989223 | G6: 55.660864 | H6: 0.4 | I6: 1.74 | J6: 98.26 | K6: 44.45 | L6: 55.549 | M6: 97.600922 | N6: 2.3990783 | O6: 84.392416 | P6: 15.607584
A7: 43191 | B7: 36.640628 | C7: 63.359372 | D7: 25.799195 | E7: 74.200805 | F7: 41.46474 | G7: 58.313476 | H7: 0.22178459 | I7: 3.7808934 | J7: 96.219107 | K7: 77.623795 | L7: 22.376205 | M7: NA | N7: NA | O7: NA | P7: NA
A8: 43222 | B8: 39.699137 | C8: 60.300863 | D8: 23.42454 | E8: 76.57546 | F8: 41.543462 | G8: 57.954045 | H8: 0.50249263 | I8: 1.2831352 | J8: 98.716865 | K8: 87.272 | L8: 12.72794 | M8: NA | N8: NA | O8: NA | P8: NA
A9: 43254 | B9: 36.64485 | C9: 63.35515 | D9: 24.119344 | E9: 75.880656 | F9: 40.839523 | G9: 58.456153 | H9: 0.70432409 | I9: 0.97375301 | J9: 99.026247 | K9: 88.8 | L9: 11.198 | M9: NA | N9: NA | O9: NA | P9: NA
A10: 43285 | B10: 34.634726 | C10: 65.365274 | D10: 23.958426 | E10: 76.041574 | F10: 42.096345 | G10: 57.666393 | H10: 0.23726223 | I10: 0.53923167 | J10: 99.460768 | K10: 84.086 | L10: 15.913 | M10: NA | N10: NA | O10: NA | P10: NA
A11: 43317 | B11: 35.746453 | C11: 64.253547 | D11: 24.638629 | E11: 75.361371 | F11: 46.468796 | G11: 53.381877 | H11: 0.14932679 | I11: 0.1902669 | J11: 99.809733 | K11: 71.035 | L11: 28.964 | M11: NA | N11: NA | O11: NA | P11: NA
A12: 43349 | B12: 39.742171 | C12: 60.257829 | D12: 25.029793 | E12: 74.970207 | F12: 44.633655 | G12: 55.071884 | H12: 0.29446078 | I12: 0.13218173 | J12: 99.867818 | K12: 56.94096 | L12: 43.05904 | M12: NA | N12: NA | O12: NA | P12: NA
A13: 43374 | B13: 41.375664 | C13: 58.624336 | D13: 27.632407 | E13: 72.367593 | F13: 45.378565 | G13: 54.167547 | H13: 0.45388882 | I13: 14.298 | J13: 85.7018 | K13: 40.319 | L13: 59.68069 | M13: 97.45 | N13: 2.55 | O13: 83.419655 | P13: 16.580345
A14: 43434 | B14: 40.227908 | C14: 59.772092 | D14: 30.488624 | E14: 69.511376 | F14: 46.975663 | G14: 52.751553 | H14: 0.27278471 | I14: 11.98 | J14: 88.02 | K14: 30.75 | L14: 69.25 | M14: 98.55 | N14: 1.45 | O14: 82.748723 | P14: 17.251277
A15: 43435 | B15: 39.911047 | C15: 60.088953 | D15: 32.587843 | E15: 67.412157 | F15: 44.959441 | G15: 54.594706 | H15: 0.44585274 | I15: 13.36 | J15: 86.636 | K15: 27.64 | L15: 72.357 | M15: 97.356937 | N15: 2.6430634 | O15: 93.674234 | P15: 6.3257664
A16: 43467 | B16: 38.259392 | C16: 61.740608 | D16: 30.226113 | E16: 69.773887 | F16: 45.345913 | G16: 54.011736 | H16: 0.64235066 | I16: 23.15 | J16: 76.85 | K16: 36.06 | L16: 63.94 | M16: 96.852541 | N16: 3.1474589 | O16: 84.556728 | P16: 15.443272
A17: 43499 | B17: 36.167833 | C17: 63.832167 | D17: 32.505914 | E17: 67.494086 | F17: 44.973535 | G17: 54.265042 | H17: 0.76142318 | I17: 36.21 | J17: 63.79 | K17: 49.36 | L17: 50.64 | M17: 78.829337 | N17: 21.170663 | O17: 78.451091 | P17: 21.548909
A18: ='66'!A17 -> $ indicates as on February 28, 2019
A19: Conserquent to merger of NMCE with ICEX w.e.f. September 24, 2018, data pertaiing to NMCE are merged with ICEX
A20: Source: MCX, NCDEX, ICEX, BSE and NSE

Sheet 73
A1: Table 73: Commodity-wise monthly turnover and trading volume at MCX
A2: Sr.No | B2: Name of the Commodity | C2: 2018-19$ | E2: 43132 | G2: 43466 | I2: 43497
C3: Volume ('000 tonnes) | D3: Value (₹ crore) | E3: Volume ('000 tonnes) | F3: Value (₹ crore) | G3: Volume ('000 tonnes) | H3: Value (₹ crore) | I3: Volume ('000 tonnes) | J3: Value (₹ crore)
A4: Futures
A5: A | B5: Bullion
A6: 1 | B6: Gold | C6: 2.4577453 | D6: 769162.56 | E6: 0.19587398 | F6: 59507.921 | G6: 0.28802539 | H6: 92678.838 | I6: 0.24317182 | J6: 81086.467
A7: 2 | B7: Silver | C7: 153.11838 | D7: 592801.11 | E7: 13.852875 | F7: 53356.638 | G7: 13.085642 | H7: 51671.889 | I7: 12.573886 | J7: 50480.657
B8: Total for A | C8: =SUM(C6:C7) -> 155.57613 | D8: =SUM(D6:D7) -> 1361963.7 | E8: =SUM(E6:E7) -> 14.048749 | F8: =SUM(F6:F7) -> 112864.56 | G8: =SUM(G6:G7) -> 13.373667 | H8: =SUM(H6:H7) -> 144350.73 | I8: =SUM(I6:I7) -> 12.817058 | J8: =SUM(J6:J7) -> 131567.12
A9: B | B9: Metals other than Bullion
A10: 1 | B10: Aluminium | C10: 18576.54 | D10: 272374.01 | E10: 1530.73 | F10: 21464.113 | G10: 1657.08 | H10: 21874.245 | I10: 1163.858 | J10: 15687.513
A11: 2 | B11: Brass | C11: 5.703 | D11: 202.87955 | E11: Na | F11: Na | G11: Na | H11: Na | I11: Na | J11: Na
A12: 3 | B12: Copper | C12: 12995.403 | D12: 572559.6 | E12: 998.96175 | F12: 45203.828 | G12: 1125.676 | H12: 47120.133 | I12: 916.25875 | J12: 41206.342
A13: 4 | B13: Lead | C13: 24599.316 | D13: 367503.81 | E13: 2173.53 | F13: 36113.279 | G13: 2162.935 | H13: 30719.345 | I13: 1859.985 | J13: 27457.077
A14: 5 | B14: Nickel | C14: 3184.2757 | D14: 291089.11 | E14: 345.874 | F14: 30322.546 | G14: 240.5507 | H14: 19634.729 | I14: 277.1389 | J14: 25105.843
A15: 6 | B15: Zinc | C15: 43513.224 | D15: 824699.02 | E15: 2938.399 | F15: 66527.111 | G15: 4211.495 | H15: 76356.846 | I15: 3931.276 | J15: 75896.569
B16: Total for B | C16: =SUM(C10:C15) -> 102874.46 | D16: =SUM(D10:D15) -> 2328428.4 | E16: =SUM(E10:E15) -> 7987.4947 | F16: =SUM(F10:F15) -> 199630.88 | G16: =SUM(G10:G15) -> 9397.7367 | H16: =SUM(H10:H15) -> 195705.3 | I16: =SUM(I10:I15) -> 8148.5166 | J16: =SUM(J10:J15) -> 185353.34
A17: C | B17: Agricultural commodities
A18: 1 | B18: Cardamom | C18: 1.4977 | D18: 185.39099 | E18: 0.227 | F18: 25.986645 | G18: 0.1623 | H18: 25.743171 | I18: 0.0802 | J18: 12.131378
A19: 2 | B19: Cotton | C19: 3049.9275 | D19: 39077.999 | E19: 407.17975 | F19: 4817.7143 | G19: 322.184 | H19: 3972.9285 | I19: 369.74575 | J19: 4453.7329
A20: 3 | B20: CPO | C20: 5544.27 | D20: 32441.482 | E20: 461.09 | F20: 2683.4349 | G20: 509.93 | H20: 2799.3646 | I20: 415.23 | J20: 2346.3264
A21: 4 | B21: Mentha Oil | C21: 129.79728 | D21: 19820.392 | E21: 12.83724 | F21: 1768.9021 | G21: 10.31364 | H21: 1621.2184 | I21: 7.79436 | J21: 1252.3421
A22: 5 | B22: Rubber | C22: 0.053 | D22: 0.69222 | E22: Na | F22: Na | G22: Na | H22: Na | I22: Na | J22: Na
B23: Total for C | C23: =SUM(C18:C22) -> 8725.5455 | D23: =SUM(D18:D22) -> 91525.956 | E23: =SUM(E18:E22) -> 881.33399 | F23: =SUM(F18:F22) -> 9296.038 | G23: =SUM(G18:G22) -> 842.58994 | H23: =SUM(H18:H22) -> 8419.2547 | I23: =SUM(I18:I22) -> 792.85031 | J23: =SUM(J18:J22) -> 8064.5327
A24: D | B24: Energy
A25: 1 | B25: Crude Oil | C25: 603172.72 | D25: 1896242.3 | E25: 49601.769 | F25: 145769.97 | G25: 81981.645 | H25: 217712.2 | I25: 69132.38 | J25: 198392.76
A26: 2 | B26: Natural Gas (trln. Btu) | C26: 14166.246 | D26: 335799.86 | E26: 1695.9462 | F26: 29503.658 | G26: 1896.6913 | H26: 42702.33 | I26: 891.565 | J26: 17076.617
B27: Total for D* | C27: 603172.72 | D27: 2232042.2 | E27: 49601.769 | F27: 175273.63 | G27: 81981.645 | H27: 260414.53 | I27: 69132.38 | J27: 215469.37
A28: Grand Total (A+B+C+D) | C28: =C27+C23+C16+C8 -> 714928.3 | D28: =D27+D23+D16+D8 -> 6013960.2 | E28: =E27+E23+E16+E8 -> 58484.646 | F28: =F27+F23+F16+F8 -> 497065.11 | G28: =SUM(G8+G16+G23+G27) -> 92235.345 | H28: =H27+H23+H16+H8 -> 608889.81 | I28: =I27+I23+I16+I8 -> 78086.564 | J28: =J27+J23+J16+J8 -> 540454.38
A29: Options
A30: E | B30: Bullion
A31: 1 | B31: Gold | C31: 0.388908 | D31: 120937.25 | E31: 0.001673 | F31: 506.57136 | G31: 0.01385 | H31: 4444.063 | I31: 0.012077 | J31: 4041.4791
A32: 2 | B32: Silver | C32: 1.64382 | D32: 6479.0043 | E32: 0 | F32: 0 | G32: 0.18186 | H32: 724.2834 | I32: 0.19755 | J32: 799.65968
B33: Total of E | C33: =SUM(C31:C32) -> 2.032728 | D33: =SUM(D31:D32) -> 127416.26 | E33: =SUM(E31:E32) -> 0.001673 | F33: =SUM(F31:F32) -> 506.57136 | G33: =SUM(G31:G32) -> 0.19571 | H33: =SUM(H31:H32) -> 5168.3464 | I33: =SUM(I31:I32) -> 0.209627 | J33: =SUM(J31:J32) -> 4841.1388
A34: F | B34: Metals
A35: 1 | B35: Copper | C35: 100.745 | D35: 4545.6858 | E35: 0 | F35: 0 | G35: 8.513 | H35: 367.41404 | I35: 10.95 | J35: 492.16834
A36: 2 | B36: Zinc | C36: 66.865 | D36: 1282.5522 | E36: 0 | F36: 0 | G36: 4.635 | H36: 84.950095 | I36: 10.03 | J36: 195.84142
B37: Total of F | C37: =SUM(C35:C36) -> 167.61 | D37: =SUM(D35:D36) -> 5828.2379 | E37: 0 | F37: 0 | G37: =SUM(G35:G36) -> 13.148 | H37: =SUM(H35:H36) -> 452.36414 | I37: =SUM(I35:I36) -> 20.98 | J37: =SUM(J35:J36) -> 688.00976
A38: G | B38: Energy
A39: 1 | B39: Crude Oil | C39: 11020.737 | D39: 35048.998 | E39: 0 | F39: 0 | G39: 1817.8718 | H39: 4852.0203 | I39: 1300.5184 | J39: 3762.1566
A40: Grand Total (E+F+G) | C40: =SUM(C33+C37+C39) -> 11190.38 | D40: =SUM(D33+D37+D39) -> 168293.49 | E40: =SUM(E33) -> 0.001673 | F40: =SUM(F33) -> 506.57136 | G40: =SUM(G33+G37+G39) -> 1831.2155 | H40: =SUM(H33+H37+H39) -> 10472.731 | I40: =SUM(I33+I37+I39) -> 1321.7081 | J40: =SUM(J33+J37+J39) -> 9291.3052
A41: ='66'!A17 -> $ indicates as on February 28, 2019
A42: Natural Gas volume is in trillion BTU and is not included in total volume.
A43: Turnover of options contract is notional value.
